Workbook

Sheet README
B1: MH Robotics — Seed + TIPS IR Financial Model (Draft v5, 2026-10)
B3: 목적: Seed · TIPS IR 덱의 모든 사업 수치를 하나의 수식 모델로 관리. 단위는 별도 표기가 없으면 만원 (KRW 10,000). 억원 = 만원 / 10,000.
B4: 주의: 실적 · 계약 · 고객 · Partner 데이터 없음. 모든 수치는 FACT / DERIVED / ASSUMPTION / TARGET Tag로 구분.
B6: Color code
B7: 파란 글자 = 입력값 (Inputs, Inputs_Yearly, Budget_24M 팀 · 지출 표에서만 수정) · 검은 글자 = 수식 · 녹색 글자 = 다른 Sheet 참조 · 노란 바탕 = 핵심 가정 (WTP · BOM · Volume)
B8: Tag
B9: FACT = 공식 통계 · 공개자료 확인값 · DERIVED = FACT 또는 가정으로 계산한 값 · ASSUMPTION = 현재 사업가설 · TARGET = 24개월 · 이후 목표
B10: Sheets
B11: Inputs: 단일값 가정 (시나리오별 Conservative / Base / Upside 열)
B12: Inputs_Yearly: 연도별 가정 (Volume, BOM, Interface 표준부품 사용률, 인원 · 지출 등). Y1~Y2 지출 = Budget_24M 팀 · 지출 계획과 같은 값
B13: FM_Conservative / FM_Base / FM_Upside: 5개년 Bottom-up 손익 (INSTALL · OPERATE · EXPAND 매출층, 채널 3종)
B14: Scenario_Summary: 3개 시나리오 요약 (억원)
... B23: 재현: python3 MH/source/model.py → python3 MH/source/xlsx_model.py (LibreOffice 재계산 후 check_xlsx.py로 model.py와 교차검증)

Sheet Scenario_Summary
A1: Scenario Summary (억원 · 세대 · 대)
A2: 각 셀은 FM Sheet 참조. 억원 = 만원 / 10,000. Upside는 가격 인상 없이 Partner·표준화·설치원가·Installed Base로 차이.
A4: Conservative | B4: 단위 | C4: Y1 | D4: Y2 | E4: Y3 | F4: Y4 | G4: Y5
A5: 매출 | B5: 억원 | C5: =FM_Conservative!$C$42/10000 -> 0 | D5: =FM_Conservative!$D$42/10000 -> 0.14508 | E5: =FM_Conservative!$E$42/10000 -> 3.609345 | F5: =FM_Conservative!$F$42/10000 -> 15.328645 | G5: =FM_Conservative!$G$42/10000 -> 33.985163
A6: 매출총이익 | B6: 억원 | C6: =FM_Conservative!$C$60/10000 -> 0 | D6: =FM_Conservative!$D$60/10000 -> -0.34295685 | E6: =FM_Conservative!$E$60/10000 -> 0.1148028 | F6: =FM_Conservative!$F$60/10000 -> 0.94692397 | G6: =FM_Conservative!$G$60/10000 -> 4.4150543
A7: 매출총이익률 | B7: % | C7: =FM_Conservative!$C$61 -> 0 | D7: =FM_Conservative!$D$61 -> -2.3639154 | E7: =FM_Conservative!$E$61 -> 0.031807101 | F7: =FM_Conservative!$F$61 -> 0.061774798 | G7: =FM_Conservative!$G$61 -> 0.12991123
A8: Contribution | B8: 억원 | C8: =FM_Conservative!$C$66/10000 -> 0 | D8: =FM_Conservative!$D$66/10000 -> -0.39695685 | E8: =FM_Conservative!$E$66/10000 -> -0.4164972 | F8: =FM_Conservative!$F$66/10000 -> -1.098076 | G8: =FM_Conservative!$G$66/10000 -> -0.02324566
A9: Opex | B9: 억원 | C9: =FM_Conservative!$C$69/10000 -> 9.216775 | D9: =FM_Conservative!$D$69/10000 -> 13.8166 | E9: =FM_Conservative!$E$69/10000 -> 30.5 | F9: =FM_Conservative!$F$69/10000 -> 43.9 | G9: =FM_Conservative!$G$69/10000 -> 56.7
A10: 영업이익 (근사) | B10: 억원 | C10: =FM_Conservative!$C$70/10000 -> -9.216775 | D10: =FM_Conservative!$D$70/10000 -> -14.213557 | E10: =FM_Conservative!$E$70/10000 -> -30.916497 | F10: =FM_Conservative!$F$70/10000 -> -44.998076 | G10: =FM_Conservative!$G$70/10000 -> -56.723246
A11: 누적 현금흐름 | B11: 억원 | C11: =FM_Conservative!$C$72/10000 -> -9.216775 | D11: =FM_Conservative!$D$72/10000 -> -23.560445 | E11: =FM_Conservative!$E$72/10000 -> -55.274209 | F11: =FM_Conservative!$F$72/10000 -> -100.09549 | G11: =FM_Conservative!$G$72/10000 -> -156.64195
A12: 설치 세대 (Remodeling + Retrofit + New-build) | B12: 세대 | C12: =FM_Conservative!$C$9 -> 0 | D12: =FM_Conservative!$D$9 -> 3 | E12: =FM_Conservative!$E$9 -> 30 | F12: =FM_Conservative!$F$9 -> 105 | G12: =FM_Conservative!$G$9 -> 230
A13: Robot 설치 | B13: 대 | C13: =FM_Conservative!$C$14 -> 0 | D13: =FM_Conservative!$D$14 -> 3 | E13: =FM_Conservative!$E$14 -> 22.5 | F13: =FM_Conservative!$F$14 -> 81.625 | G13: =FM_Conservative!$G$14 -> 184.04375
A14: Installed Robot (기말) | B14: 대 | C14: =FM_Conservative!$C$28 -> 0 | D14: =FM_Conservative!$D$28 -> 3 | E14: =FM_Conservative!$E$28 -> 25.5 | F14: =FM_Conservative!$F$28 -> 107.125 | G14: =FM_Conservative!$G$28 -> 291.16875
A15: 신축 Backlog | B15: 세대 | C15: =FM_Conservative!$C$29 -> 0 | D15: =FM_Conservative!$D$29 -> 0 | E15: =FM_Conservative!$E$29 -> 0 | F15: =FM_Conservative!$F$29 -> 48 | G15: =FM_Conservative!$G$29 -> 144
A16: OPERATE + EXPAND 비중 | B16: % | C16: =FM_Conservative!$C$78 -> 0 | D16: =FM_Conservative!$D$78 -> 0.14205955 | E16: =FM_Conservative!$E$78 -> 0.05474539 | F16: =FM_Conservative!$F$78 -> 0.039029195 | G16: =FM_Conservative!$G$78 -> 0.041439204
A18: Base | B18: 단위 | C18: Y1 | D18: Y2 | E18: Y3 | F18: Y4 | G18: Y5
A19: 매출 | B19: 억원 | C19: =FM_Base!$C$42/10000 -> 0 | D19: =FM_Base!$D$42/10000 -> 0.260511 | E19: =FM_Base!$E$42/10000 -> 7.4234195 | F19: =FM_Base!$F$42/10000 -> 35.918587 | G19: =FM_Base!$G$42/10000 -> 91.490638
A20: 매출총이익 | B20: 억원 | C20: =FM_Base!$C$60/10000 -> 0 | D20: =FM_Base!$D$60/10000 -> -0.21031785 | E20: =FM_Base!$E$60/10000 -> 1.7258479 | F20: =FM_Base!$F$60/10000 -> 10.248569 | G20: =FM_Base!$G$60/10000 -> 32.044477
A21: 매출총이익률 | B21: % | C21: =FM_Base!$C$61 -> 0 | D21: =FM_Base!$D$61 -> -0.8073281 | E21: =FM_Base!$E$61 -> 0.23248692 | F21: =FM_Base!$F$61 -> 0.28532772 | G21: =FM_Base!$G$61 -> 0.3502487
A22: Contribution | B22: 억원 | C22: =FM_Base!$C$66/10000 -> 0 | D22: =FM_Base!$D$66/10000 -> -0.25531785 | E22: =FM_Base!$E$66/10000 -> 0.71894793 | F22: =FM_Base!$F$66/10000 -> 6.4267186 | G22: =FM_Base!$G$66/10000 -> 23.069177
A23: Opex | B23: 억원 | C23: =FM_Base!$C$69/10000 -> 9.216775 | D23: =FM_Base!$D$69/10000 -> 13.8166 | E23: =FM_Base!$E$69/10000 -> 30.5 | F23: =FM_Base!$F$69/10000 -> 43.9 | G23: =FM_Base!$G$69/10000 -> 56.7
A24: 영업이익 (근사) | B24: 억원 | C24: =FM_Base!$C$70/10000 -> -9.216775 | D24: =FM_Base!$D$70/10000 -> -14.071918 | E24: =FM_Base!$E$70/10000 -> -29.781052 | F24: =FM_Base!$F$70/10000 -> -37.473281 | G24: =FM_Base!$G$70/10000 -> -33.630823
A25: 누적 현금흐름 | B25: 억원 | C25: =FM_Base!$C$72/10000 -> -9.216775 | D25: =FM_Base!$D$72/10000 -> -23.413865 | E25: =FM_Base!$E$72/10000 -> -54.548278 | F25: =FM_Base!$F$72/10000 -> -91.742539 | G25: =FM_Base!$G$72/10000 -> -125.09434
A26: 설치 세대 (Remodeling + Retrofit + New-build) | B26: 세대 | C26: =FM_Base!$C$9 -> 0 | D26: =FM_Base!$D$9 -> 3 | E26: =FM_Base!$E$9 -> 50 | F26: =FM_Base!$F$9 -> 200 | G26: =FM_Base!$G$9 -> 560
A27: Robot 설치 | B27: 대 | C27: =FM_Base!$C$14 -> 0 | D27: =FM_Base!$D$14 -> 3 | E27: =FM_Base!$E$14 -> 42.5 | F27: =FM_Base!$F$14 -> 173.75 | G27: =FM_Base!$G$14 -> 443.375
A28: Installed Robot (기말) | B28: 대 | C28: =FM_Base!$C$28 -> 0 | D28: =FM_Base!$D$28 -> 3 | E28: =FM_Base!$E$28 -> 45.5 | F28: =FM_Base!$F$28 -> 219.25 | G28: =FM_Base!$G$28 -> 662.625
A29: 신축 Backlog | B29: 세대 | C29: =FM_Base!$C$29 -> 0 | D29: =FM_Base!$D$29 -> 0 | E29: =FM_Base!$E$29 -> 80 | F29: =FM_Base!$F$29 -> 240 | G29: =FM_Base!$G$29 -> 400
A30: OPERATE + EXPAND 비중 | B30: % | C30: =FM_Base!$C$78 -> 0 | D30: =FM_Base!$D$78 -> 0.094280088 | E30: =FM_Base!$E$78 -> 0.053973711 | F30: =FM_Base!$F$78 -> 0.039046553 | G30: =FM_Base!$G$78 -> 0.041225868
A32: Upside | B32: 단위 | C32: Y1 | D32: Y2 | E32: Y3 | F32: Y4 | G32: Y5
A33: 매출 | B33: 억원 | C33: =FM_Upside!$C$42/10000 -> 0 | D33: =FM_Upside!$D$42/10000 -> 0.307701 | E33: =FM_Upside!$E$42/10000 -> 9.6346287 | F33: =FM_Upside!$F$42/10000 -> 55.237647 | G33: =FM_Upside!$G$42/10000 -> 154.77567
A34: 매출총이익 | B34: 억원 | C34: =FM_Upside!$C$60/10000 -> 0 | D34: =FM_Upside!$D$60/10000 -> -0.14501076 | E34: =FM_Upside!$E$60/10000 -> 2.7281883 | F34: =FM_Upside!$F$60/10000 -> 18.549148 | G34: =FM_Upside!$G$60/10000 -> 63.360874
A35: 매출총이익률 | B35: % | C35: =FM_Upside!$C$61 -> 0 | D35: =FM_Upside!$D$61 -> -0.47127166 | E35: =FM_Upside!$E$61 -> 0.28316486 | F35: =FM_Upside!$F$61 -> 0.33580626 | G35: =FM_Upside!$G$61 -> 0.4093723
A36: Contribution | B36: 억원 | C36: =FM_Upside!$C$66/10000 -> 0 | D36: =FM_Upside!$D$66/10000 -> -0.18701076 | E36: =FM_Upside!$E$66/10000 -> 1.3563733 | F36: =FM_Upside!$F$66/10000 -> 13.100638 | G36: =FM_Upside!$G$66/10000 -> 50.043774
A37: Opex | B37: 억원 | C37: =FM_Upside!$C$69/10000 -> 9.216775 | D37: =FM_Upside!$D$69/10000 -> 13.8166 | E37: =FM_Upside!$E$69/10000 -> 30.5 | F37: =FM_Upside!$F$69/10000 -> 43.9 | G37: =FM_Upside!$G$69/10000 -> 56.7
A38: 영업이익 (근사) | B38: 억원 | C38: =FM_Upside!$C$70/10000 -> -9.216775 | D38: =FM_Upside!$D$70/10000 -> -14.003611 | E38: =FM_Upside!$E$70/10000 -> -29.143627 | F38: =FM_Upside!$F$70/10000 -> -30.799362 | G38: =FM_Upside!$G$70/10000 -> -6.6562262
A39: 누적 현금흐름 | B39: 억원 | C39: =FM_Upside!$C$72/10000 -> -9.216775 | D39: =FM_Upside!$D$72/10000 -> -23.340617 | E39: =FM_Upside!$E$72/10000 -> -54.130179 | F39: =FM_Upside!$F$72/10000 -> -84.597251 | G39: =FM_Upside!$G$72/10000 -> -90.921187
A40: 설치 세대 (Remodeling + Retrofit + New-build) | B40: 세대 | C40: =FM_Upside!$C$9 -> 0 | D40: =FM_Upside!$D$9 -> 3 | E40: =FM_Upside!$E$9 -> 65 | F40: =FM_Upside!$F$9 -> 310 | G40: =FM_Upside!$G$9 -> 982
A41: Robot 설치 | B41: 대 | C41: =FM_Upside!$C$14 -> 0 | D41: =FM_Upside!$D$14 -> 3 | E41: =FM_Upside!$E$14 -> 55.25 | F41: =FM_Upside!$F$14 -> 269.17 | G41: =FM_Upside!$G$14 -> 753.1696
A42: Installed Robot (기말) | B42: 대 | C42: =FM_Upside!$C$28 -> 0 | D42: =FM_Upside!$D$28 -> 3 | E42: =FM_Upside!$E$28 -> 58.25 | F42: =FM_Upside!$F$28 -> 327.42 | G42: =FM_Upside!$G$28 -> 1080.5896
A43: 신축 Backlog | B43: 세대 | C43: =FM_Upside!$C$29 -> 0 | D43: =FM_Upside!$D$29 -> 0 | E43: =FM_Upside!$E$29 -> 192 | F43: =FM_Upside!$F$29 -> 480 | G43: =FM_Upside!$G$29 -> 672
A44: OPERATE + EXPAND 비중 | B44: % | C44: =FM_Upside!$C$78 -> 0 | D44: =FM_Upside!$D$78 -> 0.079820995 | E44: =FM_Upside!$E$78 -> 0.052420676 | F44: =FM_Upside!$F$78 -> 0.035731039 | G44: =FM_Upside!$G$78 -> 0.038339675

Sheet Inputs
A1: Inputs — 단일값 가정 (만원 기준)
A3: Key | B3: 항목 | C3: 단위 | D3: Conservative | E3: Base | F3: Upside | G3: Tag | H3: Source / Note
A4: MARKET
A5: m_housing_total | B5: 총주택 (2025.11.1 기준) | C5: 천호 | D5: 20181 | E5: 20181 | F5: 20181 | G5: FACT | H5: 국가데이터처, 2025 인구주택총조사 등록센서스 결과 (2026.7.28 발표)
A6: m_apt_share | B6: 아파트 비중 (총주택 대비) | C6: % | D6: 0.658 | E6: 0.658 | F6: 0.658 | G6: FACT | H6: 국가데이터처, 2025 인구주택총조사
A7: m_house_20y_share | B7: 준공 20년 이상 주택 비중 | C7: % | D7: 0.56 | E7: 0.56 | F7: 0.56 | G7: FACT | H7: 국가데이터처, 2025 인구주택총조사
A8: m_house_30y_share | B8: 준공 30년 이상 주택 비중 | C8: % | D8: 0.306 | E8: 0.306 | F8: 0.306 | G8: FACT | H8: 국가데이터처, 2025 인구주택총조사
A9: m_apt_2023 | B9: 아파트 수 (2023) | C9: 천호 | D9: 12630 | E9: 12630 | F9: 12630 | G9: FACT | H9: 통계청, 2023 주택총조사 (보도 인용)
A10: m_apt_20y_2023 | B10: 준공 20년 이상 아파트 (2023) | C10: 천호 | D10: 6390 | E10: 6390 | F10: 6390 | G10: FACT | H10: 통계청, 2023 주택총조사 (보도 인용)
A11: m_txn_2025 | B11: 주택 매매거래 (2025, 전체 주택) | C11: 천호 | D11: 726 | E11: 726 | F11: 726 | G11: FACT | H11: KB주택시장리뷰 2026.2 (한국부동산원 자료)
A12: m_completion_2025 | B12: 주택 준공 (2025 연간, 전체 주택) | C12: 천호 | D12: 342.4 | E12: 342.4 | F12: 342.4 | G12: FACT | H12: 국토교통부, 2025년 12월 주택통계
A13: m_movein_2025 | B13: 아파트 입주 (2025) | C13: 천호 | D13: 236.3 | E13: 236.3 | F13: 236.3 | G13: FACT | H13: 부동산114 REPS
A14: m_movein_2026e | B14: 아파트 입주 예정 (2026) | C14: 천호 | D14: 183.1 | E14: 183.1 | F14: 183.1 | G14: FACT | H14: 부동산114 REPS (예정 물량)
A15: a_replace_cycle | B15: Kitchen 교체주기 (노후 아파트) | C15: 년 | D15: 22 | E15: 22 | F15: 22 | G15: ASSUMPTION | H15: 교차검증용 가정. 견적 · 인터뷰로 검증
A16: a_txn_apt_share | B16: 매매거래 중 아파트 비중 | C16: % | D16: 0.7 | E16: 0.7 | F16: 0.7 | G16: ASSUMPTION | H16: 부동산원 월별 아파트 거래 비중 확인 필요
... A27: a_premium_project | B27: Premium 단지 비중 (신축) | C27: % | D27: 0.15 | E27: 0.15 | F27: 0.15 | G27: ASSUMPTION | H27: 브랜드 · 분양가 기준 정의 필요
A28: VALUE
A29: f_helper_rate | B29: 가사서비스 시간당 요금 (플랫폼 4시간 59,900~64,900원) | C29: 만원/h | D29: 1.5 | E29: 1.5 | F29: 1.5 | G29: FACT | H29: 가사서비스 플랫폼 공개 요금 (2025, 보도 · 앱 정보)
A30: a_cleanup_min | B30: 식사 후 정리 시간 (식기 이동 · 식세기 · 수납, 일) | C30: 분/일 | D30: 40 | E30: 40 | F30: 40 | G30: ASSUMPTION | H30: Time-diary(n=30)로 검증
A31: a_auto_share | B31: CLEAN 자동화 가능 비중 | C31: % | D31: 0.6 | E31: 0.6 | F31: 0.6 | G31: ASSUMPTION | H31: 식기 이동 · 식세기 적재/인출 · 수납만. 행주 · 싱크 세척 제외
A32: fx | B32: 환율 (Benchmark 환산용) | C32: 원/USD | D32: 1400 | E32: 1400 | F32: 1400 | G32: ASSUMPTION | H32: 부품 Benchmark 환산 전용
A33: PRICE
A34: p_rr | B34: Interface · Integration — Remodeling (Robot Home · Rail · 식세기 Interface · Storage Dock) | C34: 만원/세대 | D34: 400 | E34: 450 | F34: 450 | G34: ASSUMPTION | H34: 주방 공사비 위 증분. 시스템에어컨 유상옵션(500~1,000만원) 대비 하단
A35: p_rr_new | B35: Interface Option — New-build (설계 반영, MH 공급가) | C35: 만원/세대 | D35: 200 | E35: 220 | F35: 220 | G35: ASSUMPTION | H35: 건설사 · 가구사 마진 별도. 분양 고객가 약 300만원 가정
A36: p_rt_if | B36: Interface Kit — Retrofit (Compact Mount · Dock · Vision Reference · Drop Zone) | C36: 만원/세대 | D36: 150 | E36: 150 | F36: 150 | G36: ASSUMPTION | H36: 기존 주방 유지. 최소 시공
A37: p_robot | B37: Robot System ASP (Arm · Adaptive Hand · Vision · Safety · Controller) | C37: 만원/대 | D37: 1290 | E37: 1490 | F37: 1490 | G37: ASSUMPTION | H37: Upside는 가격 인상 없음. WTP 검증 대상 1순위
A38: p_comm | B38: Installation · Calibration · Safety Check (Remodeling · New-build) | C38: 만원/대 | D38: 80 | E38: 80 | F38: 80 | G38: ASSUMPTION
A39: p_comm_rt | B39: Installation · Calibration (Retrofit, 현장 Calibration 비중 큼) | C39: 만원/대 | D39: 120 | E39: 120 | F39: 120 | G39: ASSUMPTION
A40: p_rent | B40: Robot Rental 월 요금 (Care Basic · Grip Kit 포함, 60개월) | C40: 만원/월 | D40: 29 | E40: 33 | F40: 33 | G40: ASSUMPTION | H40: 원가 Build-up (감가 · 금융 · Care · Grip · Reserve) + 마진
A41: rent_months | B41: Rental 계약기간 | C41: 개월 | D41: 60 | E41: 60 | F41: 60 | G41: ASSUMPTION
A42: p_care | B42: Care Basic 연 요금 (구매 고객) | C42: 만원/년 | D42: 42 | E42: 48 | F42: 48 | G42: ASSUMPTION | H42: 정기 안전점검 · Calibration · 원격진단 · SW Update · A/S 공임
A43: p_care_plus | B43: Care Plus 연 요금 (Kit 정기교체 포함) | C43: 만원/년 | D43: 72 | E43: 72 | F43: 72 | G43: ASSUMPTION | H43: 옵션 상품. 재무 Base에는 미반영
A44: p_grip | B44: Grip Kit (Finger Pad · Food-contact Tip · Suction Seal) | C44: 만원/Kit | D44: 4.5 | E44: 4.5 | F44: 4.5 | G44: ASSUMPTION | H44: 분기 교체 가정
A45: n_grip | B45: Grip Kit 교체 횟수 | C45: 회/년 | D45: 4 | E45: 4 | F45: 4 | G45: ASSUMPTION | H45: Pad 마모율 · 교체주기 검증 대상 (KPI: Pad 수명)
A46: p_clean | B46: Cleaning Kit (Brush · Wiper · Cleaning Pad) | C46: 만원/Kit | D46: 2.5 | E46: 2.5 | F46: 2.5 | G46: ASSUMPTION
A47: n_clean | B47: Cleaning Kit 교체 횟수 | C47: 회/년 | D47: 4 | E47: 4 | F47: 4 | G47: ASSUMPTION
A48: p_protect | B48: Protection Kit (Sensor Cover · Sleeve · Seal) | C48: 만원/Kit | D48: 4 | E48: 4 | F48: 4 | G48: ASSUMPTION
A49: n_protect | B49: Protection Kit 교체 횟수 | C49: 회/년 | D49: 2 | E49: 2 | F49: 2 | G49: ASSUMPTION
A50: cons_attach | B50: Consumables 구매율 | C50: % | D50: 0.55 | E50: 0.7 | F50: 0.7 | G50: ASSUMPTION
A51: care_attach | B51: Care 가입률 (구매 고객) | C51: % | D51: 0.55 | E51: 0.7 | F51: 0.7 | G51: ASSUMPTION
A52: p_sw | B52: ASSIST Skill Pack (설치 다음 해) | C52: 만원 | D52: 60 | E52: 60 | F52: 60 | G52: ASSUMPTION | H52: ASSIST 기능 (재료 이동 · 투입 보조 등) 출시 전제
A53: sw_attach | B53: ASSIST Skill 구매율 | C53: % | D53: 0.1 | E53: 0.2 | F53: 0.2 | G53: ASSUMPTION
A54: p_tool | B54: Tool · End-effector 추가 (설치 2년 후) | C54: 만원 | D54: 80 | E54: 80 | F54: 80 | G54: ASSUMPTION | H54: FUTURE CONCEPT 제품
A55: tool_attach | B55: Tool 구매율 | C55: % | D55: 0.15 | E55: 0.25 | F55: 0.25 | G55: ASSUMPTION
A56: wholesale | B56: Rental Partner 공급가율 (Robot ASP 대비) | C56: % | D56: 0.88 | E56: 0.88 | F56: 0.88 | G56: ASSUMPTION | H56: Y4부터 Rental Partner가 자산 보유
A57: partner_fee | B57: Rental Partner → MH Care · Grip 서비스료 | C57: 만원/월 | D57: 6 | E57: 6 | F57: 6 | G57: ASSUMPTION
A58: COST
A59: kit_std_cost | B59: Interface Kit 원가 — Remodeling (표준부품 100% 기준) | C59: 만원/세대 | D59: 200 | E59: 200 | F59: 200 | G59: ASSUMPTION | H59: Robot Home (Dock) · Rail Interface · 식세기 상향 하우징 · 전원/통신 · Storage Dock
A60: custom_factor | B60: Custom 부품 원가 배수 | C60: x | D60: 1.6 | E60: 1.6 | F60: 1.6 | G60: ASSUMPTION
A61: design_cost | B61: Site 설계 · 조정 원가 (100% Custom 시) | C61: 만원/세대 | D61: 100 | E61: 100 | F61: 100 | G61: ASSUMPTION
A62: kit_new_cost | B62: Interface Option 원가 — New-build (공장 생산) | C62: 만원/세대 | D62: 145 | E62: 130 | F62: 120 | G62: ASSUMPTION
A63: rt_kit_cost | B63: Interface Kit 원가 — Retrofit | C63: 만원/세대 | D63: 70 | E63: 70 | F63: 70 | G63: ASSUMPTION | H63: Compact Mount · Dock · Vision Reference
A64: logistics | B64: 물류 (세대당) | C64: 만원/세대 | D64: 25 | E64: 25 | F64: 25 | G64: ASSUMPTION
A65: warranty | B65: Warranty Reserve (Robot 매출 대비) | C65: % | D65: 0.05 | E65: 0.04 | F65: 0.035 | G65: ASSUMPTION | H65: 1년 무상 A/S
A66: corrective | B66: 고장 방문 (Failure Rate) | C66: 회/대·년 | D66: 0.9 | E66: 0.6 | F66: 0.5 | G66: ASSUMPTION
A67: corr_cost | B67: 고장 방문 1회 원가 (소부품 포함) | C67: 만원/회 | D67: 18 | E67: 18 | F67: 18 | G67: ASSUMPTION
A68: cloud | B68: Cloud · Software 운영비 | C68: 만원/대·년 | D68: 4 | E68: 4 | F68: 4 | G68: ASSUMPTION
A69: cons_cogs | B69: Consumables 원가율 (물류 포함) | C69: % | D69: 0.4 | E69: 0.35 | F69: 0.32 | G69: ASSUMPTION
A70: sw_cogs | B70: Skill 원가율 | C70: % | D70: 0.1 | E70: 0.1 | F70: 0.1 | G70: ASSUMPTION
A71: tool_cogs | B71: Tool 원가율 | C71: % | D71: 0.45 | E71: 0.45 | F71: 0.45 | G71: ASSUMPTION
A72: partner_margin | B72: Kitchen · Interior · 설치 Partner 수수료 (Partner 경유 판매) | C72: % | D72: 0.12 | E72: 0.1 | F72: 0.09 | G72: ASSUMPTION
A73: cac | B73: 직접판매 획득비용 (상담 · 설계 · Demo) | C73: 만원/세대 | D73: 180 | E73: 150 | F73: 140 | G73: ASSUMPTION
A74: bd_new | B74: 신축 Project 수주비용 (Spec · 견본주택) | C74: 만원/Project | D74: 2000 | E74: 2000 | F74: 2000 | G74: ASSUMPTION
A75: residual | B75: Rental 자산 잔존가치 (60개월 후) | C75: % | D75: 0.15 | E75: 0.15 | F75: 0.15 | G75: ASSUMPTION | H75: Refurbish 재배치
A76: fin_rate | B76: Rental 자산 금융비용 | C76: %/년 | D76: 0.08 | E76: 0.08 | F76: 0.08 | G76: ASSUMPTION | H76: 캐피탈 조달금리 + Spread 가정
A77: payback_hurdle | B77: Rental Partner 요구 Payback | C77: 개월 | D77: 36 | E77: 36 | F77: 36 | G77: ASSUMPTION | H77: 렌탈 · 캐피탈사 협의로 검증
A78: VOLUME
A79: later_attach | B79: Interface 선설치 세대의 연간 Robot 후설치 | C79: %/년 | D79: 0.05 | E79: 0.1 | F79: 0.12 | G79: ASSUMPTION
A80: hh_project | B80: Project당 세대수 | C80: 세대 | D80: 800 | E80: 800 | F80: 800 | G80: ASSUMPTION
A81: option_rate | B81: 신축 Interface Option 선택률 | C81: % | D81: 0.06 | E81: 0.1 | F81: 0.12 | G81: ASSUMPTION
A82: new_attach | B82: 신축 입주 시 Robot Attach | C82: % | D82: 0.15 | E82: 0.25 | F82: 0.3 | G82: ASSUMPTION
A83: FUNDING
A84: tips | B84: TIPS R&D 정부지원금 (일반 트랙 최대) | C84: 만원 | D84: 80000 | E84: 80000 | F84: 80000 | G84: FACT | H84: 중소벤처기업부 공고 제2026-40호 (2026.1.26) 팁스 창업기업 지원계획. 선정 미확정
A85: tips_months | B85: TIPS R&D 기간 (최대) | C85: 개월 | D85: 24 | E85: 24 | F85: 24 | G85: FACT | H85: 공고 제2026-40호
A86: tips_gov_ratio | B86: 정부지원연구개발비 비율 상한 (총 연구개발비 대비) | C86: % | D86: 0.75 | E86: 0.75 | F86: 0.75 | G86: FACT | H86: 공고 제2026-40호 (사본 · 운용사 정리 기준: 정부 75% 이내, 기관부담 25% 이상)
A87: tips_cash_ratio | B87: 기관부담연구개발비 중 현금 최소 비율 | C87: % | D87: 0.1 | E87: 0.1 | F87: 0.1 | G87: FACT | H87: 공고 제2026-40호 (사본 · 운용사 정리 기준)
A88: op_invest_min | B88: TIPS 운영사 선투자 요건 (수도권) | C88: 만원 | D88: 20000 | E88: 20000 | F88: 20000 | G88: FACT | H88: 2026: 수도권 2억원 이상 · 비수도권 1억원 이상
A89: biz_link | B89: 비R&D 연계 (창업사업화 · 해외마케팅) 각 최대 (선정 뒤 별도 신청, 기본안 미반영) | C89: 만원 | D89: 15000 | E89: 15000 | F89: 15000 | G89: FACT | H89: 공고 제2026-40호: 각 10개월 최대 1.5억원, 합산 3억원, 정부 70% 이내

Sheet Inputs_Yearly
A1: Inputs_Yearly — 연도별 가정
A3: Key | B3: 항목 | C3: 단위 | D3: Scenario | E3: Y1 | F3: Y2 | G3: Y3 | H3: Y4 | I3: Y5 | J3: Tag | K3: Source / Note
A4: realization | B4: 가격 실현율 (Y2 Pilot 할인) | C4: % | D4: Conservative | E4: 1 | F4: 0.3 | G4: 1 | H4: 1 | I4: 1 | J4: ASSUMPTION | K4: Pilot은 할인 유료
A5: realization | B5: 가격 실현율 (Y2 Pilot 할인) | C5: % | D5: Base | E5: 1 | F5: 0.5 | G5: 1 | H5: 1 | I5: 1 | J5: ASSUMPTION | K5: Pilot은 할인 유료
A6: realization | B6: 가격 실현율 (Y2 Pilot 할인) | C6: % | D6: Upside | E6: 1 | F6: 0.6 | G6: 1 | H6: 1 | I6: 1 | J6: ASSUMPTION | K6: Pilot은 할인 유료
A8: smr | B8: Interface 표준부품 사용률 | C8: % | D8: Conservative | E8: 0.4 | F8: 0.45 | G8: 0.55 | H8: 0.62 | I8: 0.65 | J8: TARGET | K8: M24 65% 이상 목표 (M18 60% 미만이면 Interface 설계 재검토)
A9: smr | B9: Interface 표준부품 사용률 | C9: % | D9: Base | E9: 0.4 | F9: 0.5 | G9: 0.65 | H9: 0.75 | I9: 0.8 | J9: TARGET | K9: M24 65% 이상 목표 (M18 60% 미만이면 Interface 설계 재검토)
A10: smr | B10: Interface 표준부품 사용률 | C10: % | D10: Upside | E10: 0.4 | F10: 0.55 | G10: 0.7 | H10: 0.8 | I10: 0.85 | J10: TARGET | K10: M24 65% 이상 목표 (M18 60% 미만이면 Interface 설계 재검토)
A12: bom | B12: Robot System BOM (Adaptive Hand 포함) | C12: 만원/대 | D12: Conservative | E12: 1680 | F12: 1580 | G12: 1330 | H12: 1210 | I12: 1100 | J12: ASSUMPTION | K12: BOM 구성 Benchmark 기반 (부록). 수량 · 국산화 · 자체 Hand 원가 하락 가정
A13: bom | B13: Robot System BOM (Adaptive Hand 포함) | C13: 만원/대 | D13: Base | E13: 1680 | F13: 1520 | G13: 1180 | H13: 1030 | I13: 915 | J13: ASSUMPTION | K13: BOM 구성 Benchmark 기반 (부록). 수량 · 국산화 · 자체 Hand 원가 하락 가정
A14: bom | B14: Robot System BOM (Adaptive Hand 포함) | C14: 만원/대 | D14: Upside | E14: 1680 | F14: 1460 | G14: 1100 | H14: 950 | I14: 820 | J14: ASSUMPTION | K14: BOM 구성 Benchmark 기반 (부록). 수량 · 국산화 · 자체 Hand 원가 하락 가정
A16: comm_cost | B16: Installation · Calibration 원가 — Remodeling · New-build (MH 인력) | C16: 만원/대 | D16: Conservative | E16: 120 | F16: 100 | G16: 75 | H16: 62 | I16: 55 | J16: ASSUMPTION | K16: Calibration 시간 KPI와 연동
A17: comm_cost | B17: Installation · Calibration 원가 — Remodeling · New-build (MH 인력) | C17: 만원/대 | D17: Base | E17: 120 | F17: 90 | G17: 60 | H17: 45 | I17: 38 | J17: ASSUMPTION | K17: Calibration 시간 KPI와 연동
A18: comm_cost | B18: Installation · Calibration 원가 — Remodeling · New-build (MH 인력) | C18: 만원/대 | D18: Upside | E18: 120 | F18: 85 | G18: 52 | H18: 38 | I18: 30 | J18: ASSUMPTION | K18: Calibration 시간 KPI와 연동
... A46: attach | B46: Robot Attach Rate (Remodeling, 설치 시점) | C46: % | D46: Upside | E46: 1 | F46: 1 | G46: 0.85 | H46: 0.85 | I46: 0.85 | J46: ASSUMPTION | K46: 나머지는 Interface 선설치 (Robot 후설치)
A48: rental_share | B48: Rental 선택 비중 | C48: % | D48: Conservative | E48: 0 | F48: 0.3 | G48: 0.3 | H48: 0.35 | I48: 0.35 | J48: ASSUMPTION
A49: rental_share | B49: Rental 선택 비중 | C49: % | D49: Base | E49: 0 | F49: 0.3 | G49: 0.3 | H49: 0.4 | I49: 0.4 | J49: ASSUMPTION
A50: rental_share | B50: Rental 선택 비중 | C50: % | D50: Upside | E50: 0 | F50: 0.3 | G50: 0.3 | H50: 0.45 | I50: 0.45 | J50: ASSUMPTION
A52: partner_rental | B52: Rental 자산 보유 주체 (0 = MH Pilot, 1 = Rental Partner) | C52: flag | D52: Conservative | E52: 0 | F52: 0 | G52: 0 | H52: 1 | I52: 1 | J52: ASSUMPTION
A53: partner_rental | B53: Rental 자산 보유 주체 (0 = MH Pilot, 1 = Rental Partner) | C53: flag | D53: Base | E53: 0 | F53: 0 | G53: 0 | H53: 1 | I53: 1 | J53: ASSUMPTION
A54: partner_rental | B54: Rental 자산 보유 주체 (0 = MH Pilot, 1 = Rental Partner) | C54: flag | D54: Upside | E54: 0 | F54: 0 | G54: 0 | H54: 1 | I54: 1 | J54: ASSUMPTION
A56: projects | B56: 신축 Interface Option 계약 Project | C56: 개 | D56: Conservative | E56: 0 | F56: 0 | G56: 0 | H56: 1 | I56: 2 | J56: TARGET | K56: 계약 2년 후 입주 · 설치
A57: projects | B57: 신축 Interface Option 계약 Project | C57: 개 | D57: Base | E57: 0 | F57: 0 | G57: 1 | H57: 2 | I57: 3 | J57: TARGET | K57: 계약 2년 후 입주 · 설치
A58: projects | B58: 신축 Interface Option 계약 Project | C58: 개 | D58: Upside | E58: 0 | F58: 0 | G58: 2 | H58: 3 | I58: 4 | J58: TARGET | K58: 계약 2년 후 입주 · 설치
A60: fte | B60: 평균 인원 (FTE) | C60: 명 | D60: Conservative | E60: 7.0416667 | F60: 12.75 | G60: 20 | H60: 32 | I60: 42 | J60: ASSUMPTION | K60: Y1~Y2 = 팀 계획 (Budget_24M, Founder 2 + 신규 채용) · Y3부터 Series A 전제
A61: fte | B61: 평균 인원 (FTE) | C61: 명 | D61: Base | E61: 7.0416667 | F61: 12.75 | G61: 20 | H61: 32 | I61: 42 | J61: ASSUMPTION | K61: Y1~Y2 = 팀 계획 (Budget_24M, Founder 2 + 신규 채용) · Y3부터 Series A 전제
A62: fte | B62: 평균 인원 (FTE) | C62: 명 | D62: Upside | E62: 7.0416667 | F62: 12.75 | G62: 20 | H62: 32 | I62: 42 | J62: ASSUMPTION | K62: Y1~Y2 = 팀 계획 (Budget_24M, Founder 2 + 신규 채용) · Y3부터 Series A 전제
A64: loaded | B64: 인당 연 인건비 (4대보험 · 퇴직급여 포함, 평균) | C64: 만원/년 | D64: Conservative | E64: 7927.8107 | F64: 7611.7647 | G64: 8500 | H64: 8500 | I64: 8500 | J64: ASSUMPTION | K64: Y1~Y2 = 팀 계획 가중평균 · Y3~ 평균 연봉 약 7,100만원 × 1.2
A65: loaded | B65: 인당 연 인건비 (4대보험 · 퇴직급여 포함, 평균) | C65: 만원/년 | D65: Base | E65: 7927.8107 | F65: 7611.7647 | G65: 8500 | H65: 8500 | I65: 8500 | J65: ASSUMPTION | K65: Y1~Y2 = 팀 계획 가중평균 · Y3~ 평균 연봉 약 7,100만원 × 1.2
A66: loaded | B66: 인당 연 인건비 (4대보험 · 퇴직급여 포함, 평균) | C66: 만원/년 | D66: Upside | E66: 7927.8107 | F66: 7611.7647 | G66: 8500 | H66: 8500 | I66: 8500 | J66: ASSUMPTION | K66: Y1~Y2 = 팀 계획 가중평균 · Y3~ 평균 연봉 약 7,100만원 × 1.2
A68: robot_hw | B68: Robot Hardware (R&D 로봇 셀) | C68: 만원 | D68: Conservative | E68: 4800 | F68: 1600 | G68: 12000 | H68: 14000 | I68: 16000 | J68: ASSUMPTION
A69: robot_hw | B69: Robot Hardware (R&D 로봇 셀) | C69: 만원 | D69: Base | E69: 4800 | F69: 1600 | G69: 12000 | H69: 14000 | I69: 16000 | J69: ASSUMPTION
A70: robot_hw | B70: Robot Hardware (R&D 로봇 셀) | C70: 만원 | D70: Upside | E70: 4800 | F70: 1600 | G70: 12000 | H70: 14000 | I70: 16000 | J70: ASSUMPTION
A72: hand_proto | B72: Hand Prototype (비교군 · 자체 Hand v1~v3) | C72: 만원 | D72: Conservative | E72: 6000 | F72: 4000 | G72: 10000 | H72: 12000 | I72: 14000 | J72: ASSUMPTION
A73: hand_proto | B73: Hand Prototype (비교군 · 자체 Hand v1~v3) | C73: 만원 | D73: Base | E73: 6000 | F73: 4000 | G73: 10000 | H73: 12000 | I73: 14000 | J73: ASSUMPTION
A74: hand_proto | B74: Hand Prototype (비교군 · 자체 Hand v1~v3) | C74: 만원 | D74: Upside | E74: 6000 | F74: 4000 | G74: 10000 | H74: 12000 | I74: 14000 | J74: ASSUMPTION
A76: mockup | B76: Kitchen Mock-up (실물 크기 3종) | C76: 만원 | D76: Conservative | E76: 5000 | F76: 2500 | G76: 8000 | H76: 9000 | I76: 10000 | J76: ASSUMPTION
A77: mockup | B77: Kitchen Mock-up (실물 크기 3종) | C77: 만원 | D77: Base | E77: 5000 | F77: 2500 | G77: 8000 | H77: 9000 | I77: 10000 | J77: ASSUMPTION
A78: mockup | B78: Kitchen Mock-up (실물 크기 3종) | C78: 만원 | D78: Upside | E78: 5000 | F78: 2500 | G78: 8000 | H78: 9000 | I78: 10000 | J78: ASSUMPTION
A80: swdata | B80: Software · Data (GPU · Cloud · Annotation) | C80: 만원 | D80: Conservative | E80: 2500 | F80: 3000 | G80: 10000 | H80: 15000 | I80: 20000 | J80: ASSUMPTION
A81: swdata | B81: Software · Data (GPU · Cloud · Annotation) | C81: 만원 | D81: Base | E81: 2500 | F81: 3000 | G81: 10000 | H81: 15000 | I81: 20000 | J81: ASSUMPTION
A82: swdata | B82: Software · Data (GPU · Cloud · Annotation) | C82: 만원 | D82: Upside | E82: 2500 | F82: 3000 | G82: 10000 | H82: 15000 | I82: 20000 | J82: ASSUMPTION
... A90: custval | B90: Customer Validation · Partner · Marketing | C90: 만원 | D90: Upside | E90: 2000 | F90: 4000 | G90: 30000 | H90: 50000 | I90: 70000 | J90: ASSUMPTION
A92: cert | B92: Safety · Certification | C92: 만원 | D92: Conservative | E92: 1500 | F92: 4500 | G92: 15000 | H92: 6000 | I92: 5000 | J92: ASSUMPTION | K92: Y3 본인증
A93: cert | B93: Safety · Certification | C93: 만원 | D93: Base | E93: 1500 | F93: 4500 | G93: 15000 | H93: 6000 | I93: 5000 | J93: ASSUMPTION | K93: Y3 본인증
A94: cert | B94: Safety · Certification | C94: 만원 | D94: Upside | E94: 1500 | F94: 4500 | G94: 15000 | H94: 6000 | I94: 5000 | J94: ASSUMPTION | K94: Y3 본인증
A96: ip | B96: IP (선행기술조사 · 출원) | C96: 만원 | D96: Conservative | E96: 1500 | F96: 3000 | G96: 5000 | H96: 4000 | I96: 5000 | J96: ASSUMPTION
A97: ip | B97: IP (선행기술조사 · 출원) | C97: 만원 | D97: Base | E97: 1500 | F97: 3000 | G97: 5000 | H97: 4000 | I97: 5000 | J97: ASSUMPTION
A98: ip | B98: IP (선행기술조사 · 출원) | C98: 만원 | D98: Upside | E98: 1500 | F98: 3000 | G98: 5000 | H98: 4000 | I98: 5000 | J98: ASSUMPTION
A100: space | B100: Space (실험실 · 목업 공간) | C100: 만원 | D100: Conservative | E100: 4800 | F100: 4800 | G100: 10000 | H100: 12000 | I100: 15000 | J100: ASSUMPTION
A101: space | B101: Space (실험실 · 목업 공간) | C101: 만원 | D101: Base | E101: 4800 | F101: 4800 | G101: 10000 | H101: 12000 | I101: 15000 | J101: ASSUMPTION
A102: space | B102: Space (실험실 · 목업 공간) | C102: 만원 | D102: Upside | E102: 4800 | F102: 4800 | G102: 10000 | H102: 12000 | I102: 15000 | J102: ASSUMPTION
A104: ga | B104: Operating · G&A (법무 · 회계 · 보험 · 사무) | C104: 만원 | D104: Conservative | E104: 4000 | F104: 5000 | G104: 30000 | H104: 40000 | I104: 50000 | J104: ASSUMPTION
A105: ga | B105: Operating · G&A (법무 · 회계 · 보험 · 사무) | C105: 만원 | D105: Base | E105: 4000 | F105: 5000 | G105: 30000 | H105: 40000 | I105: 50000 | J105: ASSUMPTION
A106: ga | B106: Operating · G&A (법무 · 회계 · 보험 · 사무) | C106: 만원 | D106: Upside | E106: 4000 | F106: 5000 | G106: 30000 | H106: 40000 | I106: 50000 | J106: ASSUMPTION
A108: contingency | B108: 예비비 (인건비 외 지출의 10%, Y1~Y2) | C108: 만원 | D108: Conservative | E108: 3210 | F108: 3590 | G108: 0 | H108: 0 | I108: 0 | J108: DERIVED | K108: 24개월 계획의 하드웨어 · 일정 Risk 대비
A109: contingency | B109: 예비비 (인건비 외 지출의 10%, Y1~Y2) | C109: 만원 | D109: Base | E109: 3210 | F109: 3590 | G109: 0 | H109: 0 | I109: 0 | J109: DERIVED | K109: 24개월 계획의 하드웨어 · 일정 Risk 대비
A110: contingency | B110: 예비비 (인건비 외 지출의 10%, Y1~Y2) | C110: 만원 | D110: Upside | E110: 3210 | F110: 3590 | G110: 0 | H110: 0 | I110: 0 | J110: DERIVED | K110: 24개월 계획의 하드웨어 · 일정 Risk 대비
A112: rnd_allow | B112: 연구수당 (TIPS 과제 현금 인건비 × 5%) | C112: 만원 | D112: Conservative | E112: 1032.75 | F112: 1626 | G112: 0 | H112: 0 | I112: 0 | J112: DERIVED | K112: TIPS 선정 시
A113: rnd_allow | B113: 연구수당 (TIPS 과제 현금 인건비 × 5%) | C113: 만원 | D113: Base | E113: 1032.75 | F113: 1626 | G113: 0 | H113: 0 | I113: 0 | J113: DERIVED | K113: TIPS 선정 시
A114: rnd_allow | B114: 연구수당 (TIPS 과제 현금 인건비 × 5%) | C114: 만원 | D114: Upside | E114: 1032.75 | F114: 1626 | G114: 0 | H114: 0 | I114: 0 | J114: DERIVED | K114: TIPS 선정 시

Sheet FM_Conservative
A1: 5-Year Bottom-up Model — Conservative (만원)
A2: 모든 입력은 Inputs / Inputs_Yearly의 Conservative 열·행을 참조 (녹색). 영업이익은 이자·세금 제외 근사.
A3: 항목 | B3: 단위 | C3: Y1 | D3: Y2 | E3: Y3 | F3: Y4 | G3: Y5 | H3: 5Y 합계
A4: VOLUME
A5: Remodeling — MH 직접 판매 | B5: 세대 | C5: =Inputs_Yearly!$E$32 -> 0 | D5: =Inputs_Yearly!$F$32 -> 3 | E5: =Inputs_Yearly!$G$32 -> 20 | F5: =Inputs_Yearly!$H$32 -> 35 | G5: =Inputs_Yearly!$I$32 -> 40 | H5: =SUM(C5:G5) -> 98
A6: Remodeling — Partner 경유 | B6: 세대 | C6: =Inputs_Yearly!$E$36 -> 0 | D6: =Inputs_Yearly!$F$36 -> 0 | E6: =Inputs_Yearly!$G$36 -> 10 | F6: =Inputs_Yearly!$H$36 -> 60 | G6: =Inputs_Yearly!$I$36 -> 150 | H6: =SUM(C6:G6) -> 220
A7: Existing Kitchen Retrofit | B7: 세대 | C7: =Inputs_Yearly!$E$40 -> 0 | D7: =Inputs_Yearly!$F$40 -> 0 | E7: =Inputs_Yearly!$G$40 -> 0 | F7: =Inputs_Yearly!$H$40 -> 10 | G7: =Inputs_Yearly!$I$40 -> 40 | H7: =SUM(C7:G7) -> 50
A8: New-build Interface Option 입주 (계약 2년 후) | B8: 세대 | C8: =0 -> 0 | D8: =0 -> 0 | E8: =Inputs_Yearly!$E$56*Inputs!$D$80*Inputs!$D$81 -> 0 | F8: =Inputs_Yearly!$F$56*Inputs!$D$80*Inputs!$D$81 -> 0 | G8: =Inputs_Yearly!$G$56*Inputs!$D$80*Inputs!$D$81 -> 0 | H8: =SUM(C8:G8) -> 0
A9: 설치 세대 합계 | B9: 세대 | C9: =C5+C6+C8+C7 -> 0 | D9: =D5+D6+D8+D7 -> 3 | E9: =E5+E6+E8+E7 -> 30 | F9: =F5+F6+F8+F7 -> 105 | G9: =G5+G6+G8+G7 -> 230 | H9: =SUM(C9:G9) -> 368
A10: Robot Attach Rate (Remodeling) | B10: % | C10: =Inputs_Yearly!$E$44 -> 1 | D10: =Inputs_Yearly!$F$44 -> 1 | E10: =Inputs_Yearly!$G$44 -> 0.75 | F10: =Inputs_Yearly!$H$44 -> 0.75 | G10: =Inputs_Yearly!$I$44 -> 0.75
A11: Interface 선설치 세대 Robot 후설치 | B11: 대 | C11: =0*Inputs!$D$79 -> 0 | D11: =C21*Inputs!$D$79 -> 0 | E11: =D21*Inputs!$D$79 -> 0 | F11: =E21*Inputs!$D$79 -> 0.375 | G11: =F21*Inputs!$D$79 -> 1.54375 | H11: =SUM(C11:G11) -> 1.91875
A12: Robot 설치 — Remodeling | B12: 대 | C12: =(C5+C6)*C10 -> 0 | D12: =(D5+D6)*D10 -> 3 | E12: =(E5+E6)*E10 -> 22.5 | F12: =(F5+F6)*F10 -> 71.25 | G12: =(G5+G6)*G10 -> 142.5 | H12: =SUM(C12:G12) -> 239.25
A13: Robot 설치 — New-build 입주 | B13: 대 | C13: =C8*Inputs!$D$82 -> 0 | D13: =D8*Inputs!$D$82 -> 0 | E13: =E8*Inputs!$D$82 -> 0 | F13: =F8*Inputs!$D$82 -> 0 | G13: =G8*Inputs!$D$82 -> 0 | H13: =SUM(C13:G13) -> 0
A14: Robot 설치 합계 (Retrofit 포함) | B14: 대 | C14: =C12+C13+C11+C7 -> 0 | D14: =D12+D13+D11+D7 -> 3 | E14: =E12+E13+E11+E7 -> 22.5 | F14: =F12+F13+F11+F7 -> 81.625 | G14: =G12+G13+G11+G7 -> 184.04375 | H14: =SUM(C14:G14) -> 291.16875
A15: Rental 비중 | B15: % | C15: =Inputs_Yearly!$E$48 -> 0 | D15: =Inputs_Yearly!$F$48 -> 0.3 | E15: =Inputs_Yearly!$G$48 -> 0.3 | F15: =Inputs_Yearly!$H$48 -> 0.35 | G15: =Inputs_Yearly!$I$48 -> 0.35
A16: Rental Partner 보유 Flag | B16: flag | C16: =Inputs_Yearly!$E$52 -> 0 | D16: =Inputs_Yearly!$F$52 -> 0 | E16: =Inputs_Yearly!$G$52 -> 0 | F16: =Inputs_Yearly!$H$52 -> 1 | G16: =Inputs_Yearly!$I$52 -> 1
A17: Rental 설치 | B17: 대 | C17: =C14*C15 -> 0 | D17: =D14*D15 -> 0.9 | E17: =E14*E15 -> 6.75 | F17: =F14*F15 -> 28.56875 | G17: =G14*G15 -> 64.415312 | H17: =SUM(C17:G17) -> 100.63406
A18: 구매 설치 | B18: 대 | C18: =C14-C17 -> 0 | D18: =D14-D17 -> 2.1 | E18: =E14-E17 -> 15.75 | F18: =F14-F17 -> 53.05625 | G18: =G14-G17 -> 119.62844 | H18: =SUM(C18:G18) -> 190.53469
A19: Rental — MH 보유 (Pilot) | B19: 대 | C19: =C17*(1-C16) -> 0 | D19: =D17*(1-D16) -> 0.9 | E19: =E17*(1-E16) -> 6.75 | F19: =F17*(1-F16) -> 0 | G19: =G17*(1-G16) -> 0 | H19: =SUM(C19:G19) -> 7.65
A20: Rental — Partner 보유 | B20: 대 | C20: =C17*C16 -> 0 | D20: =D17*D16 -> 0 | E20: =E17*E16 -> 0 | F20: =F17*F16 -> 28.56875 | G20: =G17*G16 -> 64.415312 | H20: =SUM(C20:G20) -> 92.984062
A21: Interface 선설치 (Robot 미설치) 누적 | B21: 세대 | C21: =0+(C5+C6)*(1-C10)+C8*(1-Inputs!$D$82)-C11 -> 0 | D21: =C21+(D5+D6)*(1-D10)+D8*(1-Inputs!$D$82)-D11 -> 0 | E21: =D21+(E5+E6)*(1-E10)+E8*(1-Inputs!$D$82)-E11 -> 7.5 | F21: =E21+(F5+F6)*(1-F10)+F8*(1-Inputs!$D$82)-F11 -> 30.875 | G21: =F21+(G5+G6)*(1-G10)+G8*(1-Inputs!$D$82)-G11 -> 76.83125
A22: 구매 Robot 누적 (기말) | B22: 대 | C22: =0+C18 -> 0 | D22: =C22+D18 -> 2.1 | E22: =D22+E18 -> 17.85 | F22: =E22+F18 -> 70.90625 | G22: =F22+G18 -> 190.53469
A23: 구매 Robot 평균 가동 | B23: 대 | C23: =0+C18/2 -> 0 | D23: =C22+D18/2 -> 1.05 | E23: =D22+E18/2 -> 9.975 | F23: =E22+F18/2 -> 44.378125 | G23: =F22+G18/2 -> 130.72047
A24: MH Rental 누적 (기말) | B24: 대 | C24: =0+C19 -> 0 | D24: =C24+D19 -> 0.9 | E24: =D24+E19 -> 7.65 | F24: =E24+F19 -> 7.65 | G24: =F24+G19 -> 7.65
A25: MH Rental 평균 가동 | B25: 대 | C25: =0+C19/2 -> 0 | D25: =C24+D19/2 -> 0.45 | E25: =D24+E19/2 -> 4.275 | F25: =E24+F19/2 -> 7.65 | G25: =F24+G19/2 -> 7.65
A26: Partner Rental 누적 (기말) | B26: 대 | C26: =0+C20 -> 0 | D26: =C26+D20 -> 0 | E26: =D26+E20 -> 0 | F26: =E26+F20 -> 28.56875 | G26: =F26+G20 -> 92.984062
A27: Partner Rental 평균 가동 | B27: 대 | C27: =0+C20/2 -> 0 | D27: =C26+D20/2 -> 0 | E27: =D26+E20/2 -> 0 | F27: =E26+F20/2 -> 14.284375 | G27: =F26+G20/2 -> 60.776406
A28: Installed Robot (기말) | B28: 대 | C28: =C22+C24+C26 -> 0 | D28: =D22+D24+D26 -> 3 | E28: =E22+E24+E26 -> 25.5 | F28: =F22+F24+F26 -> 107.125 | G28: =G22+G24+G26 -> 291.16875
A29: 신축 계약 Backlog (미설치 세대) | B29: 세대 | C29: =Inputs_Yearly!$E$56*Inputs!$D$80*Inputs!$D$81 -> 0 | D29: =(Inputs_Yearly!$F$56+Inputs_Yearly!$E$56)*Inputs!$D$80*Inputs!$D$81 -> 0 | E29: =(Inputs_Yearly!$G$56+Inputs_Yearly!$F$56)*Inputs!$D$80*Inputs!$D$81 -> 0 | F29: =(Inputs_Yearly!$H$56+Inputs_Yearly!$G$56)*Inputs!$D$80*Inputs!$D$81 -> 48 | G29: =(Inputs_Yearly!$I$56+Inputs_Yearly!$H$56)*Inputs!$D$80*Inputs!$D$81 -> 144
A30: REVENUE (만원) — INSTALL / OPERATE / EXPAND
A31: 가격 실현율 | B31: % | C31: =Inputs_Yearly!$E$4 -> 1 | D31: =Inputs_Yearly!$F$4 -> 0.3 | E31: =Inputs_Yearly!$G$4 -> 1 | F31: =Inputs_Yearly!$H$4 -> 1 | G31: =Inputs_Yearly!$I$4 -> 1
A32: Consumables 연 List (구매 고객) | B32: 만원/대 | C32: =Inputs!$D$44*Inputs!$D$45+Inputs!$D$46*Inputs!$D$47+Inputs!$D$48*Inputs!$D$49 -> 36 | D32: =Inputs!$D$44*Inputs!$D$45+Inputs!$D$46*Inputs!$D$47+Inputs!$D$48*Inputs!$D$49 -> 36 | E32: =Inputs!$D$44*Inputs!$D$45+Inputs!$D$46*Inputs!$D$47+Inputs!$D$48*Inputs!$D$49 -> 36 | F32: =Inputs!$D$44*Inputs!$D$45+Inputs!$D$46*Inputs!$D$47+Inputs!$D$48*Inputs!$D$49 -> 36 | G32: =Inputs!$D$44*Inputs!$D$45+Inputs!$D$46*Inputs!$D$47+Inputs!$D$48*Inputs!$D$49 -> 36
A33: Consumables 연 List (Rental, Grip 제외) | B33: 만원/대 | C33: =Inputs!$D$46*Inputs!$D$47+Inputs!$D$48*Inputs!$D$49 -> 18 | D33: =Inputs!$D$46*Inputs!$D$47+Inputs!$D$48*Inputs!$D$49 -> 18 | E33: =Inputs!$D$46*Inputs!$D$47+Inputs!$D$48*Inputs!$D$49 -> 18 | F33: =Inputs!$D$46*Inputs!$D$47+Inputs!$D$48*Inputs!$D$49 -> 18 | G33: =Inputs!$D$46*Inputs!$D$47+Inputs!$D$48*Inputs!$D$49 -> 18
A34: Grip Kit 연 List | B34: 만원/대 | C34: =Inputs!$D$44*Inputs!$D$45 -> 18 | D34: =Inputs!$D$44*Inputs!$D$45 -> 18 | E34: =Inputs!$D$44*Inputs!$D$45 -> 18 | F34: =Inputs!$D$44*Inputs!$D$45 -> 18 | G34: =Inputs!$D$44*Inputs!$D$45 -> 18
A35: INSTALL. Interface · Integration | B35: 만원 | C35: =(C5+C6)*Inputs!$D$34*C31+C8*Inputs!$D$35+C7*Inputs!$D$36*C31 -> 0 | D35: =(D5+D6)*Inputs!$D$34*D31+D8*Inputs!$D$35+D7*Inputs!$D$36*D31 -> 360 | E35: =(E5+E6)*Inputs!$D$34*E31+E8*Inputs!$D$35+E7*Inputs!$D$36*E31 -> 12000 | F35: =(F5+F6)*Inputs!$D$34*F31+F8*Inputs!$D$35+F7*Inputs!$D$36*F31 -> 39500 | G35: =(G5+G6)*Inputs!$D$34*G31+G8*Inputs!$D$35+G7*Inputs!$D$36*G31 -> 82000 | H35: =SUM(C35:G35) -> 133860
A36: INSTALL. Installation · Calibration | B36: 만원 | C36: =(C14-C7)*Inputs!$D$38*C31+C7*Inputs!$D$39*C31 -> 0 | D36: =(D14-D7)*Inputs!$D$38*D31+D7*Inputs!$D$39*D31 -> 72 | E36: =(E14-E7)*Inputs!$D$38*E31+E7*Inputs!$D$39*E31 -> 1800 | F36: =(F14-F7)*Inputs!$D$38*F31+F7*Inputs!$D$39*F31 -> 6930 | G36: =(G14-G7)*Inputs!$D$38*G31+G7*Inputs!$D$39*G31 -> 16323.5 | H36: =SUM(C36:G36) -> 25125.5
A37: INSTALL. Robot System (구매 + Rental Partner 공급) | B37: 만원 | C37: =C18*Inputs!$D$37*C31+C20*Inputs!$D$37*Inputs!$D$56 -> 0 | D37: =D18*Inputs!$D$37*D31+D20*Inputs!$D$37*Inputs!$D$56 -> 812.7 | E37: =E18*Inputs!$D$37*E31+E20*Inputs!$D$37*Inputs!$D$56 -> 20317.5 | F37: =F18*Inputs!$D$37*F31+F20*Inputs!$D$37*Inputs!$D$56 -> 100873.81 | G37: =G18*Inputs!$D$37*G31+G20*Inputs!$D$37*Inputs!$D$56 -> 227444.95 | H37: =SUM(C37:G37) -> 349448.95
A38: OPERATE. Rental (MH 보유) | B38: 만원 | C38: =C25*Inputs!$D$40*12 -> 0 | D38: =D25*Inputs!$D$40*12 -> 156.6 | E38: =E25*Inputs!$D$40*12 -> 1487.7 | F38: =F25*Inputs!$D$40*12 -> 2662.2 | G38: =G25*Inputs!$D$40*12 -> 2662.2 | H38: =SUM(C38:G38) -> 6968.7
A39: OPERATE. Care (구매 고객 + Partner 서비스료) | B39: 만원 | C39: =C23*Inputs!$D$51*Inputs!$D$42+C27*Inputs!$D$57*12 -> 0 | D39: =D23*Inputs!$D$51*Inputs!$D$42+D27*Inputs!$D$57*12 -> 24.255 | E39: =E23*Inputs!$D$51*Inputs!$D$42+E27*Inputs!$D$57*12 -> 230.4225 | F39: =F23*Inputs!$D$51*Inputs!$D$42+F27*Inputs!$D$57*12 -> 2053.6097 | G39: =G23*Inputs!$D$51*Inputs!$D$42+G27*Inputs!$D$57*12 -> 7395.5441 | H39: =SUM(C39:G39) -> 9703.8313
A40: OPERATE. Consumables | B40: 만원 | C40: =C23*Inputs!$D$50*C32+(C25+C27)*Inputs!$D$50*C33 -> 0 | D40: =D23*Inputs!$D$50*D32+(D25+D27)*Inputs!$D$50*D33 -> 25.245 | E40: =E23*Inputs!$D$50*E32+(E25+E27)*Inputs!$D$50*E33 -> 239.8275 | F40: =F23*Inputs!$D$50*F32+(F25+F27)*Inputs!$D$50*F33 -> 1095.8372 | G40: =G23*Inputs!$D$50*G32+(G25+G27)*Inputs!$D$50*G33 -> 3265.6867 | H40: =SUM(C40:G40) -> 4626.5964
A41: EXPAND. Skill + Tool | B41: 만원 | C41: =0*Inputs!$D$53*Inputs!$D$52+0*Inputs!$D$55*Inputs!$D$54 -> 0 | D41: =C14*Inputs!$D$53*Inputs!$D$52+0*Inputs!$D$55*Inputs!$D$54 -> 0 | E41: =D14*Inputs!$D$53*Inputs!$D$52+C14*Inputs!$D$55*Inputs!$D$54 -> 18 | F41: =E14*Inputs!$D$53*Inputs!$D$52+D14*Inputs!$D$55*Inputs!$D$54 -> 171 | G41: =F14*Inputs!$D$53*Inputs!$D$52+E14*Inputs!$D$55*Inputs!$D$54 -> 759.75 | H41: =SUM(C41:G41) -> 948.75
A42: 매출 합계 | B42: 만원 | C42: =SUM(C35:C41) -> 0 | D42: =SUM(D35:D41) -> 1450.8 | E42: =SUM(E35:E41) -> 36093.45 | F42: =SUM(F35:F41) -> 153286.45 | G42: =SUM(G35:G41) -> 339851.63 | H42: =SUM(C42:G42) -> 530682.33
A43: COGS (만원)
A44: Interface 표준부품 사용률 | B44: % | C44: =Inputs_Yearly!$E$8 -> 0.4 | D44: =Inputs_Yearly!$F$8 -> 0.45 | E44: =Inputs_Yearly!$G$8 -> 0.55 | F44: =Inputs_Yearly!$H$8 -> 0.62 | G44: =Inputs_Yearly!$I$8 -> 0.65
A45: Interface Kit 원가/세대 (Remodeling) | B45: 만원 | C45: =Inputs!$D$59*(C44+Inputs!$D$60*(1-C44))+Inputs!$D$61*(1-C44) -> 332 | D45: =Inputs!$D$59*(D44+Inputs!$D$60*(1-D44))+Inputs!$D$61*(1-D44) -> 321 | E45: =Inputs!$D$59*(E44+Inputs!$D$60*(1-E44))+Inputs!$D$61*(1-E44) -> 299 | F45: =Inputs!$D$59*(F44+Inputs!$D$60*(1-F44))+Inputs!$D$61*(1-F44) -> 283.6 | G45: =Inputs!$D$59*(G44+Inputs!$D$60*(1-G44))+Inputs!$D$61*(1-G44) -> 277
A46: Robot BOM/대 | B46: 만원 | C46: =Inputs_Yearly!$E$12 -> 1680 | D46: =Inputs_Yearly!$F$12 -> 1580 | E46: =Inputs_Yearly!$G$12 -> 1330 | F46: =Inputs_Yearly!$H$12 -> 1210 | G46: =Inputs_Yearly!$I$12 -> 1100
A47: Care 원가/대·년 | B47: 만원 | C47: =Inputs_Yearly!$E$24*Inputs_Yearly!$E$28+Inputs!$D$66*Inputs!$D$67+Inputs!$D$68 -> 50.2 | D47: =Inputs_Yearly!$F$24*Inputs_Yearly!$F$28+Inputs!$D$66*Inputs!$D$67+Inputs!$D$68 -> 48.2 | E47: =Inputs_Yearly!$G$24*Inputs_Yearly!$G$28+Inputs!$D$66*Inputs!$D$67+Inputs!$D$68 -> 45.2 | F47: =Inputs_Yearly!$H$24*Inputs_Yearly!$H$28+Inputs!$D$66*Inputs!$D$67+Inputs!$D$68 -> 42.2 | G47: =Inputs_Yearly!$I$24*Inputs_Yearly!$I$28+Inputs!$D$66*Inputs!$D$67+Inputs!$D$68 -> 40.2
A48: Interface 원가 (3개 채널) | B48: 만원 | C48: =(C5+C6)*C45+C8*Inputs!$D$62+C7*Inputs!$D$63 -> 0 | D48: =(D5+D6)*D45+D8*Inputs!$D$62+D7*Inputs!$D$63 -> 963 | E48: =(E5+E6)*E45+E8*Inputs!$D$62+E7*Inputs!$D$63 -> 8970 | F48: =(F5+F6)*F45+F8*Inputs!$D$62+F7*Inputs!$D$63 -> 27642 | G48: =(G5+G6)*G45+G8*Inputs!$D$62+G7*Inputs!$D$63 -> 55430 | H48: =SUM(C48:G48) -> 93005
A49: 물류 | B49: 만원 | C49: =(C5+C6+C8+C7)*Inputs!$D$64 -> 0 | D49: =(D5+D6+D8+D7)*Inputs!$D$64 -> 75 | E49: =(E5+E6+E8+E7)*Inputs!$D$64 -> 750 | F49: =(F5+F6+F8+F7)*Inputs!$D$64 -> 2625 | G49: =(G5+G6+G8+G7)*Inputs!$D$64 -> 5750 | H49: =SUM(C49:G49) -> 9200
A50: Robot BOM (판매분) | B50: 만원 | C50: =(C18+C20)*C46 -> 0 | D50: =(D18+D20)*D46 -> 3318 | E50: =(E18+E20)*E46 -> 20947.5 | F50: =(F18+F20)*F46 -> 98766.25 | G50: =(G18+G20)*G46 -> 202448.12 | H50: =SUM(C50:G50) -> 325479.88
A51: Installation · Calibration 원가 | B51: 만원 | C51: =(C14-C7)*Inputs_Yearly!$E$16+C7*Inputs_Yearly!$E$20 -> 0 | D51: =(D14-D7)*Inputs_Yearly!$F$16+D7*Inputs_Yearly!$F$20 -> 300 | E51: =(E14-E7)*Inputs_Yearly!$G$16+E7*Inputs_Yearly!$G$20 -> 1687.5 | F51: =(F14-F7)*Inputs_Yearly!$H$16+F7*Inputs_Yearly!$H$20 -> 5390.75 | G51: =(G14-G7)*Inputs_Yearly!$I$16+G7*Inputs_Yearly!$I$20 -> 11322.406 | H51: =SUM(C51:G51) -> 18700.656
A52: Warranty Reserve | B52: 만원 | C52: =Inputs!$D$65*C37 -> 0 | D52: =Inputs!$D$65*D37 -> 40.635 | E52: =Inputs!$D$65*E37 -> 1015.875 | F52: =Inputs!$D$65*F37 -> 5043.6904 | G52: =Inputs!$D$65*G37 -> 11372.247 | H52: =SUM(C52:G52) -> 17472.448
A53: Rental 자산 취득 (MH 보유) | B53: 만원 | C53: =C19*C46 -> 0 | D53: =D19*D46 -> 1422 | E53: =E19*E46 -> 8977.5 | F53: =F19*F46 -> 0 | G53: =G19*G46 -> 0 | H53: =SUM(C53:G53) -> 10399.5
A54: Rental 자산 누적 취득 | B54: 만원 | C54: =0+C53 -> 0 | D54: =C54+D53 -> 1422 | E54: =D54+E53 -> 10399.5 | F54: =E54+F53 -> 10399.5 | G54: =F54+G53 -> 10399.5
A55: Rental 자산 감가상각 | B55: 만원 | C55: =0*(1-Inputs!$D$75)/5+C53*(1-Inputs!$D$75)/5*0.5 -> 0 | D55: =C54*(1-Inputs!$D$75)/5+D53*(1-Inputs!$D$75)/5*0.5 -> 120.87 | E55: =D54*(1-Inputs!$D$75)/5+E53*(1-Inputs!$D$75)/5*0.5 -> 1004.8275 | F55: =E54*(1-Inputs!$D$75)/5+F53*(1-Inputs!$D$75)/5*0.5 -> 1767.915 | G55: =F54*(1-Inputs!$D$75)/5+G53*(1-Inputs!$D$75)/5*0.5 -> 1767.915 | H55: =SUM(C55:G55) -> 4661.5275
A56: Care Service 원가 | B56: 만원 | C56: =(C23*Inputs!$D$51+C25+C27)*C47 -> 0 | D56: =(D23*Inputs!$D$51+D25+D27)*D47 -> 49.5255 | E56: =(E23*Inputs!$D$51+E25+E27)*E47 -> 441.2085 | F56: =(F23*Inputs!$D$51+F25+F27)*F47 -> 1955.6469 | G56: =(G23*Inputs!$D$51+G25+G27)*G47 -> 5640.9711 | H56: =SUM(C56:G56) -> 8087.352
A57: Consumables 원가 (Rental Grip 포함) | B57: 만원 | C57: =C40*Inputs!$D$69+(C25+C27)*C34*Inputs!$D$69 -> 0 | D57: =D40*Inputs!$D$69+(D25+D27)*D34*Inputs!$D$69 -> 13.338 | E57: =E40*Inputs!$D$69+(E25+E27)*E34*Inputs!$D$69 -> 126.711 | F57: =F40*Inputs!$D$69+(F25+F27)*F34*Inputs!$D$69 -> 596.26238 | G57: =G40*Inputs!$D$69+(G25+G27)*G34*Inputs!$D$69 -> 1798.9448 | H57: =SUM(C57:G57) -> 2535.2562
A58: Skill · Tool 원가 | B58: 만원 | C58: =0*Inputs!$D$53*Inputs!$D$52*Inputs!$D$70+0*Inputs!$D$55*Inputs!$D$54*Inputs!$D$71 -> 0 | D58: =C14*Inputs!$D$53*Inputs!$D$52*Inputs!$D$70+0*Inputs!$D$55*Inputs!$D$54*Inputs!$D$71 -> 0 | E58: =D14*Inputs!$D$53*Inputs!$D$52*Inputs!$D$70+C14*Inputs!$D$55*Inputs!$D$54*Inputs!$D$71 -> 1.8 | F58: =E14*Inputs!$D$53*Inputs!$D$52*Inputs!$D$70+D14*Inputs!$D$55*Inputs!$D$54*Inputs!$D$71 -> 29.7 | G58: =F14*Inputs!$D$53*Inputs!$D$52*Inputs!$D$70+E14*Inputs!$D$55*Inputs!$D$54*Inputs!$D$71 -> 170.475 | H58: =SUM(C58:G58) -> 201.975
A59: COGS 합계 | B59: 만원 | C59: =C48+C49+C50+C51+C52+C55+C56+C57+C58 -> 0 | D59: =D48+D49+D50+D51+D52+D55+D56+D57+D58 -> 4880.3685 | E59: =E48+E49+E50+E51+E52+E55+E56+E57+E58 -> 34945.422 | F59: =F48+F49+F50+F51+F52+F55+F56+F57+F58 -> 143817.21 | G59: =G48+G49+G50+G51+G52+G55+G56+G57+G58 -> 295701.08 | H59: =SUM(C59:G59) -> 479344.09
A60: 매출총이익 | B60: 만원 | C60: =C42-C59 -> 0 | D60: =D42-D59 -> -3429.5685 | E60: =E42-E59 -> 1148.028 | F60: =F42-F59 -> 9469.2397 | G60: =G42-G59 -> 44150.543 | H60: =SUM(C60:G60) -> 51338.243
A61: 매출총이익률 | B61: % | C61: =IF(C42=0,0,C60/C42) -> 0 | D61: =IF(D42=0,0,D60/D42) -> -2.3639154 | E61: =IF(E42=0,0,E60/E42) -> 0.031807101 | F61: =IF(F42=0,0,F60/F42) -> 0.061774798 | G61: =IF(G42=0,0,G60/G42) -> 0.12991123
A62: CHANNEL · OPEX (만원)
A63: Partner 수수료 (Remodeling Partner · Retrofit) | B63: 만원 | C63: =Inputs!$D$72*(C6*(Inputs!$D$34*C31+C10*(Inputs!$D$37+Inputs!$D$38)*C31)+C7*(Inputs!$D$36+Inputs!$D$37+Inputs!$D$39)*C31) -> 0 | D63: =Inputs!$D$72*(D6*(Inputs!$D$34*D31+D10*(Inputs!$D$37+Inputs!$D$38)*D31)+D7*(Inputs!$D$36+Inputs!$D$37+Inputs!$D$39)*D31) -> 0 | E63: =Inputs!$D$72*(E6*(Inputs!$D$34*E31+E10*(Inputs!$D$37+Inputs!$D$38)*E31)+E7*(Inputs!$D$36+Inputs!$D$37+Inputs!$D$39)*E31) -> 1713 | F63: =Inputs!$D$72*(F6*(Inputs!$D$34*F31+F10*(Inputs!$D$37+Inputs!$D$38)*F31)+F7*(Inputs!$D$36+Inputs!$D$37+Inputs!$D$39)*F31) -> 12150 | G63: =Inputs!$D$72*(G6*(Inputs!$D$34*G31+G10*(Inputs!$D$37+Inputs!$D$38)*G31)+G7*(Inputs!$D$36+Inputs!$D$37+Inputs!$D$39)*G31) -> 33183 | H63: =SUM(C63:G63) -> 47046
A64: 직접판매 획득비용 | B64: 만원 | C64: =C5*Inputs!$D$73 -> 0 | D64: =D5*Inputs!$D$73 -> 540 | E64: =E5*Inputs!$D$73 -> 3600 | F64: =F5*Inputs!$D$73 -> 6300 | G64: =G5*Inputs!$D$73 -> 7200 | H64: =SUM(C64:G64) -> 17640
A65: 신축 Project 수주비용 | B65: 만원 | C65: =Inputs_Yearly!$E$56*Inputs!$D$74 -> 0 | D65: =Inputs_Yearly!$F$56*Inputs!$D$74 -> 0 | E65: =Inputs_Yearly!$G$56*Inputs!$D$74 -> 0 | F65: =Inputs_Yearly!$H$56*Inputs!$D$74 -> 2000 | G65: =Inputs_Yearly!$I$56*Inputs!$D$74 -> 4000 | H65: =SUM(C65:G65) -> 6000
A66: Contribution (매출총이익 − 채널 · 변동 판매비) | B66: 만원 | C66: =C60-C63-C64-C65 -> 0 | D66: =D60-D63-D64-D65 -> -3969.5685 | E66: =E60-E63-E64-E65 -> -4164.972 | F66: =F60-F63-F64-F65 -> -10980.76 | G66: =G60-G63-G64-G65 -> -232.4566 | H66: =SUM(C66:G66) -> -19347.757
A67: 인건비 | B67: 만원 | C67: =Inputs_Yearly!$E$60*Inputs_Yearly!$E$64 -> 55825 | D67: =Inputs_Yearly!$F$60*Inputs_Yearly!$F$64 -> 97050 | E67: =Inputs_Yearly!$G$60*Inputs_Yearly!$G$64 -> 170000 | F67: =Inputs_Yearly!$H$60*Inputs_Yearly!$H$64 -> 272000 | G67: =Inputs_Yearly!$I$60*Inputs_Yearly!$I$64 -> 357000 | H67: =SUM(C67:G67) -> 951875
A68: 기타 운영비 (Robot HW · Hand · Mock-up · SW · Pilot · 고객 · 인증 · IP · 공간 · 관리 · 예비비 · 연구수당) | B68: 만원 | C68: =Inputs_Yearly!$E$68+Inputs_Yearly!$E$72+Inputs_Yearly!$E$76+Inputs_Yearly!$E$80+Inputs_Yearly!$E$84+Inputs_Yearly!$E$88+Inputs_Yearly!$E$92+Inputs_Yearly!$E$96+Inputs_Yearly!$E$100+Inputs_Yearly!$E$104+Inputs_Yearly!$E$108+Inputs_Yearly!$E$112 -> 36342.75 | D68: =Inputs_Yearly!$F$68+Inputs_Yearly!$F$72+Inputs_Yearly!$F$76+Inputs_Yearly!$F$80+Inputs_Yearly!$F$84+Inputs_Yearly!$F$88+Inputs_Yearly!$F$92+Inputs_Yearly!$F$96+Inputs_Yearly!$F$100+Inputs_Yearly!$F$104+Inputs_Yearly!$F$108+Inputs_Yearly!$F$112 -> 41116 | E68: =Inputs_Yearly!$G$68+Inputs_Yearly!$G$72+Inputs_Yearly!$G$76+Inputs_Yearly!$G$80+Inputs_Yearly!$G$84+Inputs_Yearly!$G$88+Inputs_Yearly!$G$92+Inputs_Yearly!$G$96+Inputs_Yearly!$G$100+Inputs_Yearly!$G$104+Inputs_Yearly!$G$108+Inputs_Yearly!$G$112 -> 135000 | F68: =Inputs_Yearly!$H$68+Inputs_Yearly!$H$72+Inputs_Yearly!$H$76+Inputs_Yearly!$H$80+Inputs_Yearly!$H$84+Inputs_Yearly!$H$88+Inputs_Yearly!$H$92+Inputs_Yearly!$H$96+Inputs_Yearly!$H$100+Inputs_Yearly!$H$104+Inputs_Yearly!$H$108+Inputs_Yearly!$H$112 -> 167000 | G68: =Inputs_Yearly!$I$68+Inputs_Yearly!$I$72+Inputs_Yearly!$I$76+Inputs_Yearly!$I$80+Inputs_Yearly!$I$84+Inputs_Yearly!$I$88+Inputs_Yearly!$I$92+Inputs_Yearly!$I$96+Inputs_Yearly!$I$100+Inputs_Yearly!$I$104+Inputs_Yearly!$I$108+Inputs_Yearly!$I$112 -> 210000 | H68: =SUM(C68:G68) -> 589458.75
A69: Opex 합계 | B69: 만원 | C69: =C67+C68 -> 92167.75 | D69: =D67+D68 -> 138166 | E69: =E67+E68 -> 305000 | F69: =F67+F68 -> 439000 | G69: =G67+G68 -> 567000 | H69: =SUM(C69:G69) -> 1541333.8
A70: 영업이익 (근사) | B70: 만원 | C70: =C66-C69 -> -92167.75 | D70: =D66-D69 -> -142135.57 | E70: =E66-E69 -> -309164.97 | F70: =F66-F69 -> -449980.76 | G70: =G66-G69 -> -567232.46 | H70: =SUM(C70:G70) -> -1560681.5
A71: 현금흐름 (영업이익 + 감가 − Rental 자산) | B71: 만원 | C71: =C70+C55-C53 -> -92167.75 | D71: =D70+D55-D53 -> -143436.7 | E71: =E70+E55-E53 -> -317137.64 | F71: =F70+F55-F53 -> -448212.85 | G71: =G70+G55-G53 -> -565464.54 | H71: =SUM(C71:G71) -> -1566419.5
A72: 누적 현금흐름 | B72: 만원 | C72: =0+C71 -> -92167.75 | D72: =C72+D71 -> -235604.45 | E72: =D72+E71 -> -552742.09 | F72: =E72+F71 -> -1000954.9 | G72: =F72+G71 -> -1566419.5
A73: MIX
A74: INSTALL 매출 (Interface + 설치 + Robot) | B74: 만원 | C74: =C35+C36+C37 -> 0 | D74: =D35+D36+D37 -> 1244.7 | E74: =E35+E36+E37 -> 34117.5 | F74: =F35+F36+F37 -> 147303.81 | G74: =G35+G36+G37 -> 325768.45 | H74: =SUM(C74:G74) -> 508434.45
A75: Interface + 설치 매출 | B75: 만원 | C75: =C35+C36 -> 0 | D75: =D35+D36 -> 432 | E75: =E35+E36 -> 13800 | F75: =F35+F36 -> 46430 | G75: =G35+G36 -> 98323.5 | H75: =SUM(C75:G75) -> 158985.5
A76: OPERATE 매출 (Rental + Care + Consumables) | B76: 만원 | C76: =C38+C39+C40 -> 0 | D76: =D38+D39+D40 -> 206.1 | E76: =E38+E39+E40 -> 1957.95 | F76: =F38+F39+F40 -> 5811.6469 | G76: =G38+G39+G40 -> 13323.431 | H76: =SUM(C76:G76) -> 21299.128
A77: EXPAND 매출 (Skill + Tool) | B77: 만원 | C77: =C41 -> 0 | D77: =D41 -> 0 | E77: =E41 -> 18 | F77: =F41 -> 171 | G77: =G41 -> 759.75 | H77: =SUM(C77:G77) -> 948.75
A78: OPERATE + EXPAND 비중 | B78: % | C78: =IF(C42=0,0,(C76+C77)/C42) -> 0 | D78: =IF(D42=0,0,(D76+D77)/D42) -> 0.14205955 | E78: =IF(E42=0,0,(E76+E77)/E42) -> 0.05474539 | F78: =IF(F42=0,0,(F76+F77)/F42) -> 0.039029195 | G78: =IF(G42=0,0,(G76+G77)/G42) -> 0.041439204
A79: Robot + Recurring + Upgrade 비중 | B79: % | C79: =IF(C42=0,0,(C37+C76+C41)/C42) -> 0 | D79: =IF(D42=0,0,(D37+D76+D41)/D42) -> 0.70223325 | E79: =IF(E42=0,0,(E37+E76+E41)/E42) -> 0.61765916 | F79: =IF(F42=0,0,(F37+F76+F41)/F42) -> 0.69710305 | G79: =IF(G42=0,0,(G37+G76+G41)/G42) -> 0.71068698

Sheet FM_Base
A1: 5-Year Bottom-up Model — Base (만원)
A2: 모든 입력은 Inputs / Inputs_Yearly의 Base 열·행을 참조 (녹색). 영업이익은 이자·세금 제외 근사.
A3: 항목 | B3: 단위 | C3: Y1 | D3: Y2 | E3: Y3 | F3: Y4 | G3: Y5 | H3: 5Y 합계
A4: VOLUME
A5: Remodeling — MH 직접 판매 | B5: 세대 | C5: =Inputs_Yearly!$E$33 -> 0 | D5: =Inputs_Yearly!$F$33 -> 3 | E5: =Inputs_Yearly!$G$33 -> 30 | F5: =Inputs_Yearly!$H$33 -> 50 | G5: =Inputs_Yearly!$I$33 -> 60 | H5: =SUM(C5:G5) -> 143
A6: Remodeling — Partner 경유 | B6: 세대 | C6: =Inputs_Yearly!$E$37 -> 0 | D6: =Inputs_Yearly!$F$37 -> 0 | E6: =Inputs_Yearly!$G$37 -> 20 | F6: =Inputs_Yearly!$H$37 -> 130 | G6: =Inputs_Yearly!$I$37 -> 340 | H6: =SUM(C6:G6) -> 490
A7: Existing Kitchen Retrofit | B7: 세대 | C7: =Inputs_Yearly!$E$41 -> 0 | D7: =Inputs_Yearly!$F$41 -> 0 | E7: =Inputs_Yearly!$G$41 -> 0 | F7: =Inputs_Yearly!$H$41 -> 20 | G7: =Inputs_Yearly!$I$41 -> 80 | H7: =SUM(C7:G7) -> 100
A8: New-build Interface Option 입주 (계약 2년 후) | B8: 세대 | C8: =0 -> 0 | D8: =0 -> 0 | E8: =Inputs_Yearly!$E$57*Inputs!$E$80*Inputs!$E$81 -> 0 | F8: =Inputs_Yearly!$F$57*Inputs!$E$80*Inputs!$E$81 -> 0 | G8: =Inputs_Yearly!$G$57*Inputs!$E$80*Inputs!$E$81 -> 80 | H8: =SUM(C8:G8) -> 80
A9: 설치 세대 합계 | B9: 세대 | C9: =C5+C6+C8+C7 -> 0 | D9: =D5+D6+D8+D7 -> 3 | E9: =E5+E6+E8+E7 -> 50 | F9: =F5+F6+F8+F7 -> 200 | G9: =G5+G6+G8+G7 -> 560 | H9: =SUM(C9:G9) -> 813
A10: Robot Attach Rate (Remodeling) | B10: % | C10: =Inputs_Yearly!$E$45 -> 1 | D10: =Inputs_Yearly!$F$45 -> 1 | E10: =Inputs_Yearly!$G$45 -> 0.85 | F10: =Inputs_Yearly!$H$45 -> 0.85 | G10: =Inputs_Yearly!$I$45 -> 0.85
A11: Interface 선설치 세대 Robot 후설치 | B11: 대 | C11: =0*Inputs!$E$79 -> 0 | D11: =C21*Inputs!$E$79 -> 0 | E11: =D21*Inputs!$E$79 -> 0 | F11: =E21*Inputs!$E$79 -> 0.75 | G11: =F21*Inputs!$E$79 -> 3.375 | H11: =SUM(C11:G11) -> 4.125
A12: Robot 설치 — Remodeling | B12: 대 | C12: =(C5+C6)*C10 -> 0 | D12: =(D5+D6)*D10 -> 3 | E12: =(E5+E6)*E10 -> 42.5 | F12: =(F5+F6)*F10 -> 153 | G12: =(G5+G6)*G10 -> 340 | H12: =SUM(C12:G12) -> 538.5
A13: Robot 설치 — New-build 입주 | B13: 대 | C13: =C8*Inputs!$E$82 -> 0 | D13: =D8*Inputs!$E$82 -> 0 | E13: =E8*Inputs!$E$82 -> 0 | F13: =F8*Inputs!$E$82 -> 0 | G13: =G8*Inputs!$E$82 -> 20 | H13: =SUM(C13:G13) -> 20
A14: Robot 설치 합계 (Retrofit 포함) | B14: 대 | C14: =C12+C13+C11+C7 -> 0 | D14: =D12+D13+D11+D7 -> 3 | E14: =E12+E13+E11+E7 -> 42.5 | F14: =F12+F13+F11+F7 -> 173.75 | G14: =G12+G13+G11+G7 -> 443.375 | H14: =SUM(C14:G14) -> 662.625
A15: Rental 비중 | B15: % | C15: =Inputs_Yearly!$E$49 -> 0 | D15: =Inputs_Yearly!$F$49 -> 0.3 | E15: =Inputs_Yearly!$G$49 -> 0.3 | F15: =Inputs_Yearly!$H$49 -> 0.4 | G15: =Inputs_Yearly!$I$49 -> 0.4
A16: Rental Partner 보유 Flag | B16: flag | C16: =Inputs_Yearly!$E$53 -> 0 | D16: =Inputs_Yearly!$F$53 -> 0 | E16: =Inputs_Yearly!$G$53 -> 0 | F16: =Inputs_Yearly!$H$53 -> 1 | G16: =Inputs_Yearly!$I$53 -> 1
A17: Rental 설치 | B17: 대 | C17: =C14*C15 -> 0 | D17: =D14*D15 -> 0.9 | E17: =E14*E15 -> 12.75 | F17: =F14*F15 -> 69.5 | G17: =G14*G15 -> 177.35 | H17: =SUM(C17:G17) -> 260.5
A18: 구매 설치 | B18: 대 | C18: =C14-C17 -> 0 | D18: =D14-D17 -> 2.1 | E18: =E14-E17 -> 29.75 | F18: =F14-F17 -> 104.25 | G18: =G14-G17 -> 266.025 | H18: =SUM(C18:G18) -> 402.125
A19: Rental — MH 보유 (Pilot) | B19: 대 | C19: =C17*(1-C16) -> 0 | D19: =D17*(1-D16) -> 0.9 | E19: =E17*(1-E16) -> 12.75 | F19: =F17*(1-F16) -> 0 | G19: =G17*(1-G16) -> 0 | H19: =SUM(C19:G19) -> 13.65
A20: Rental — Partner 보유 | B20: 대 | C20: =C17*C16 -> 0 | D20: =D17*D16 -> 0 | E20: =E17*E16 -> 0 | F20: =F17*F16 -> 69.5 | G20: =G17*G16 -> 177.35 | H20: =SUM(C20:G20) -> 246.85
A21: Interface 선설치 (Robot 미설치) 누적 | B21: 세대 | C21: =0+(C5+C6)*(1-C10)+C8*(1-Inputs!$E$82)-C11 -> 0 | D21: =C21+(D5+D6)*(1-D10)+D8*(1-Inputs!$E$82)-D11 -> 0 | E21: =D21+(E5+E6)*(1-E10)+E8*(1-Inputs!$E$82)-E11 -> 7.5 | F21: =E21+(F5+F6)*(1-F10)+F8*(1-Inputs!$E$82)-F11 -> 33.75 | G21: =F21+(G5+G6)*(1-G10)+G8*(1-Inputs!$E$82)-G11 -> 150.375
A22: 구매 Robot 누적 (기말) | B22: 대 | C22: =0+C18 -> 0 | D22: =C22+D18 -> 2.1 | E22: =D22+E18 -> 31.85 | F22: =E22+F18 -> 136.1 | G22: =F22+G18 -> 402.125
A23: 구매 Robot 평균 가동 | B23: 대 | C23: =0+C18/2 -> 0 | D23: =C22+D18/2 -> 1.05 | E23: =D22+E18/2 -> 16.975 | F23: =E22+F18/2 -> 83.975 | G23: =F22+G18/2 -> 269.1125
A24: MH Rental 누적 (기말) | B24: 대 | C24: =0+C19 -> 0 | D24: =C24+D19 -> 0.9 | E24: =D24+E19 -> 13.65 | F24: =E24+F19 -> 13.65 | G24: =F24+G19 -> 13.65
A25: MH Rental 평균 가동 | B25: 대 | C25: =0+C19/2 -> 0 | D25: =C24+D19/2 -> 0.45 | E25: =D24+E19/2 -> 7.275 | F25: =E24+F19/2 -> 13.65 | G25: =F24+G19/2 -> 13.65
A26: Partner Rental 누적 (기말) | B26: 대 | C26: =0+C20 -> 0 | D26: =C26+D20 -> 0 | E26: =D26+E20 -> 0 | F26: =E26+F20 -> 69.5 | G26: =F26+G20 -> 246.85
A27: Partner Rental 평균 가동 | B27: 대 | C27: =0+C20/2 -> 0 | D27: =C26+D20/2 -> 0 | E27: =D26+E20/2 -> 0 | F27: =E26+F20/2 -> 34.75 | G27: =F26+G20/2 -> 158.175
A28: Installed Robot (기말) | B28: 대 | C28: =C22+C24+C26 -> 0 | D28: =D22+D24+D26 -> 3 | E28: =E22+E24+E26 -> 45.5 | F28: =F22+F24+F26 -> 219.25 | G28: =G22+G24+G26 -> 662.625
A29: 신축 계약 Backlog (미설치 세대) | B29: 세대 | C29: =Inputs_Yearly!$E$57*Inputs!$E$80*Inputs!$E$81 -> 0 | D29: =(Inputs_Yearly!$F$57+Inputs_Yearly!$E$57)*Inputs!$E$80*Inputs!$E$81 -> 0 | E29: =(Inputs_Yearly!$G$57+Inputs_Yearly!$F$57)*Inputs!$E$80*Inputs!$E$81 -> 80 | F29: =(Inputs_Yearly!$H$57+Inputs_Yearly!$G$57)*Inputs!$E$80*Inputs!$E$81 -> 240 | G29: =(Inputs_Yearly!$I$57+Inputs_Yearly!$H$57)*Inputs!$E$80*Inputs!$E$81 -> 400
A30: REVENUE (만원) — INSTALL / OPERATE / EXPAND
A31: 가격 실현율 | B31: % | C31: =Inputs_Yearly!$E$5 -> 1 | D31: =Inputs_Yearly!$F$5 -> 0.5 | E31: =Inputs_Yearly!$G$5 -> 1 | F31: =Inputs_Yearly!$H$5 -> 1 | G31: =Inputs_Yearly!$I$5 -> 1
A32: Consumables 연 List (구매 고객) | B32: 만원/대 | C32: =Inputs!$E$44*Inputs!$E$45+Inputs!$E$46*Inputs!$E$47+Inputs!$E$48*Inputs!$E$49 -> 36 | D32: =Inputs!$E$44*Inputs!$E$45+Inputs!$E$46*Inputs!$E$47+Inputs!$E$48*Inputs!$E$49 -> 36 | E32: =Inputs!$E$44*Inputs!$E$45+Inputs!$E$46*Inputs!$E$47+Inputs!$E$48*Inputs!$E$49 -> 36 | F32: =Inputs!$E$44*Inputs!$E$45+Inputs!$E$46*Inputs!$E$47+Inputs!$E$48*Inputs!$E$49 -> 36 | G32: =Inputs!$E$44*Inputs!$E$45+Inputs!$E$46*Inputs!$E$47+Inputs!$E$48*Inputs!$E$49 -> 36
A33: Consumables 연 List (Rental, Grip 제외) | B33: 만원/대 | C33: =Inputs!$E$46*Inputs!$E$47+Inputs!$E$48*Inputs!$E$49 -> 18 | D33: =Inputs!$E$46*Inputs!$E$47+Inputs!$E$48*Inputs!$E$49 -> 18 | E33: =Inputs!$E$46*Inputs!$E$47+Inputs!$E$48*Inputs!$E$49 -> 18 | F33: =Inputs!$E$46*Inputs!$E$47+Inputs!$E$48*Inputs!$E$49 -> 18 | G33: =Inputs!$E$46*Inputs!$E$47+Inputs!$E$48*Inputs!$E$49 -> 18
A34: Grip Kit 연 List | B34: 만원/대 | C34: =Inputs!$E$44*Inputs!$E$45 -> 18 | D34: =Inputs!$E$44*Inputs!$E$45 -> 18 | E34: =Inputs!$E$44*Inputs!$E$45 -> 18 | F34: =Inputs!$E$44*Inputs!$E$45 -> 18 | G34: =Inputs!$E$44*Inputs!$E$45 -> 18
A35: INSTALL. Interface · Integration | B35: 만원 | C35: =(C5+C6)*Inputs!$E$34*C31+C8*Inputs!$E$35+C7*Inputs!$E$36*C31 -> 0 | D35: =(D5+D6)*Inputs!$E$34*D31+D8*Inputs!$E$35+D7*Inputs!$E$36*D31 -> 675 | E35: =(E5+E6)*Inputs!$E$34*E31+E8*Inputs!$E$35+E7*Inputs!$E$36*E31 -> 22500 | F35: =(F5+F6)*Inputs!$E$34*F31+F8*Inputs!$E$35+F7*Inputs!$E$36*F31 -> 84000 | G35: =(G5+G6)*Inputs!$E$34*G31+G8*Inputs!$E$35+G7*Inputs!$E$36*G31 -> 209600 | H35: =SUM(C35:G35) -> 316775
A36: INSTALL. Installation · Calibration | B36: 만원 | C36: =(C14-C7)*Inputs!$E$38*C31+C7*Inputs!$E$39*C31 -> 0 | D36: =(D14-D7)*Inputs!$E$38*D31+D7*Inputs!$E$39*D31 -> 120 | E36: =(E14-E7)*Inputs!$E$38*E31+E7*Inputs!$E$39*E31 -> 3400 | F36: =(F14-F7)*Inputs!$E$38*F31+F7*Inputs!$E$39*F31 -> 14700 | G36: =(G14-G7)*Inputs!$E$38*G31+G7*Inputs!$E$39*G31 -> 38670 | H36: =SUM(C36:G36) -> 56890
A37: INSTALL. Robot System (구매 + Rental Partner 공급) | B37: 만원 | C37: =C18*Inputs!$E$37*C31+C20*Inputs!$E$37*Inputs!$E$56 -> 0 | D37: =D18*Inputs!$E$37*D31+D20*Inputs!$E$37*Inputs!$E$56 -> 1564.5 | E37: =E18*Inputs!$E$37*E31+E20*Inputs!$E$37*Inputs!$E$56 -> 44327.5 | F37: =F18*Inputs!$E$37*F31+F20*Inputs!$E$37*Inputs!$E$56 -> 246460.9 | G37: =G18*Inputs!$E$37*G31+G20*Inputs!$E$37*Inputs!$E$56 -> 628918.57 | H37: =SUM(C37:G37) -> 921271.47
A38: OPERATE. Rental (MH 보유) | B38: 만원 | C38: =C25*Inputs!$E$40*12 -> 0 | D38: =D25*Inputs!$E$40*12 -> 178.2 | E38: =E25*Inputs!$E$40*12 -> 2880.9 | F38: =F25*Inputs!$E$40*12 -> 5405.4 | G38: =G25*Inputs!$E$40*12 -> 5405.4 | H38: =SUM(C38:G38) -> 13869.9
A39: OPERATE. Care (구매 고객 + Partner 서비스료) | B39: 만원 | C39: =C23*Inputs!$E$51*Inputs!$E$42+C27*Inputs!$E$57*12 -> 0 | D39: =D23*Inputs!$E$51*Inputs!$E$42+D27*Inputs!$E$57*12 -> 35.28 | E39: =E23*Inputs!$E$51*Inputs!$E$42+E27*Inputs!$E$57*12 -> 570.36 | F39: =F23*Inputs!$E$51*Inputs!$E$42+F27*Inputs!$E$57*12 -> 5323.56 | G39: =G23*Inputs!$E$51*Inputs!$E$42+G27*Inputs!$E$57*12 -> 20430.78 | H39: =SUM(C39:G39) -> 26359.98
A40: OPERATE. Consumables | B40: 만원 | C40: =C23*Inputs!$E$50*C32+(C25+C27)*Inputs!$E$50*C33 -> 0 | D40: =D23*Inputs!$E$50*D32+(D25+D27)*Inputs!$E$50*D33 -> 32.13 | E40: =E23*Inputs!$E$50*E32+(E25+E27)*Inputs!$E$50*E33 -> 519.435 | F40: =F23*Inputs!$E$50*F32+(F25+F27)*Inputs!$E$50*F33 -> 2726.01 | G40: =G23*Inputs!$E$50*G32+(G25+G27)*Inputs!$E$50*G33 -> 8946.63 | H40: =SUM(C40:G40) -> 12224.205
A41: EXPAND. Skill + Tool | B41: 만원 | C41: =0*Inputs!$E$53*Inputs!$E$52+0*Inputs!$E$55*Inputs!$E$54 -> 0 | D41: =C14*Inputs!$E$53*Inputs!$E$52+0*Inputs!$E$55*Inputs!$E$54 -> 0 | E41: =D14*Inputs!$E$53*Inputs!$E$52+C14*Inputs!$E$55*Inputs!$E$54 -> 36 | F41: =E14*Inputs!$E$53*Inputs!$E$52+D14*Inputs!$E$55*Inputs!$E$54 -> 570 | G41: =F14*Inputs!$E$53*Inputs!$E$52+E14*Inputs!$E$55*Inputs!$E$54 -> 2935 | H41: =SUM(C41:G41) -> 3541
A42: 매출 합계 | B42: 만원 | C42: =SUM(C35:C41) -> 0 | D42: =SUM(D35:D41) -> 2605.11 | E42: =SUM(E35:E41) -> 74234.195 | F42: =SUM(F35:F41) -> 359185.87 | G42: =SUM(G35:G41) -> 914906.38 | H42: =SUM(C42:G42) -> 1350931.6
A43: COGS (만원)
A44: Interface 표준부품 사용률 | B44: % | C44: =Inputs_Yearly!$E$9 -> 0.4 | D44: =Inputs_Yearly!$F$9 -> 0.5 | E44: =Inputs_Yearly!$G$9 -> 0.65 | F44: =Inputs_Yearly!$H$9 -> 0.75 | G44: =Inputs_Yearly!$I$9 -> 0.8
A45: Interface Kit 원가/세대 (Remodeling) | B45: 만원 | C45: =Inputs!$E$59*(C44+Inputs!$E$60*(1-C44))+Inputs!$E$61*(1-C44) -> 332 | D45: =Inputs!$E$59*(D44+Inputs!$E$60*(1-D44))+Inputs!$E$61*(1-D44) -> 310 | E45: =Inputs!$E$59*(E44+Inputs!$E$60*(1-E44))+Inputs!$E$61*(1-E44) -> 277 | F45: =Inputs!$E$59*(F44+Inputs!$E$60*(1-F44))+Inputs!$E$61*(1-F44) -> 255 | G45: =Inputs!$E$59*(G44+Inputs!$E$60*(1-G44))+Inputs!$E$61*(1-G44) -> 244
A46: Robot BOM/대 | B46: 만원 | C46: =Inputs_Yearly!$E$13 -> 1680 | D46: =Inputs_Yearly!$F$13 -> 1520 | E46: =Inputs_Yearly!$G$13 -> 1180 | F46: =Inputs_Yearly!$H$13 -> 1030 | G46: =Inputs_Yearly!$I$13 -> 915
A47: Care 원가/대·년 | B47: 만원 | C47: =Inputs_Yearly!$E$25*Inputs_Yearly!$E$29+Inputs!$E$66*Inputs!$E$67+Inputs!$E$68 -> 44.8 | D47: =Inputs_Yearly!$F$25*Inputs_Yearly!$F$29+Inputs!$E$66*Inputs!$E$67+Inputs!$E$68 -> 40.8 | E47: =Inputs_Yearly!$G$25*Inputs_Yearly!$G$29+Inputs!$E$66*Inputs!$E$67+Inputs!$E$68 -> 36.8 | F47: =Inputs_Yearly!$H$25*Inputs_Yearly!$H$29+Inputs!$E$66*Inputs!$E$67+Inputs!$E$68 -> 28.3 | G47: =Inputs_Yearly!$I$25*Inputs_Yearly!$I$29+Inputs!$E$66*Inputs!$E$67+Inputs!$E$68 -> 26.8
A48: Interface 원가 (3개 채널) | B48: 만원 | C48: =(C5+C6)*C45+C8*Inputs!$E$62+C7*Inputs!$E$63 -> 0 | D48: =(D5+D6)*D45+D8*Inputs!$E$62+D7*Inputs!$E$63 -> 930 | E48: =(E5+E6)*E45+E8*Inputs!$E$62+E7*Inputs!$E$63 -> 13850 | F48: =(F5+F6)*F45+F8*Inputs!$E$62+F7*Inputs!$E$63 -> 47300 | G48: =(G5+G6)*G45+G8*Inputs!$E$62+G7*Inputs!$E$63 -> 113600 | H48: =SUM(C48:G48) -> 175680
A49: 물류 | B49: 만원 | C49: =(C5+C6+C8+C7)*Inputs!$E$64 -> 0 | D49: =(D5+D6+D8+D7)*Inputs!$E$64 -> 75 | E49: =(E5+E6+E8+E7)*Inputs!$E$64 -> 1250 | F49: =(F5+F6+F8+F7)*Inputs!$E$64 -> 5000 | G49: =(G5+G6+G8+G7)*Inputs!$E$64 -> 14000 | H49: =SUM(C49:G49) -> 20325
A50: Robot BOM (판매분) | B50: 만원 | C50: =(C18+C20)*C46 -> 0 | D50: =(D18+D20)*D46 -> 3192 | E50: =(E18+E20)*E46 -> 35105 | F50: =(F18+F20)*F46 -> 178962.5 | G50: =(G18+G20)*G46 -> 405688.12 | H50: =SUM(C50:G50) -> 622947.62
A51: Installation · Calibration 원가 | B51: 만원 | C51: =(C14-C7)*Inputs_Yearly!$E$17+C7*Inputs_Yearly!$E$21 -> 0 | D51: =(D14-D7)*Inputs_Yearly!$F$17+D7*Inputs_Yearly!$F$21 -> 270 | E51: =(E14-E7)*Inputs_Yearly!$G$17+E7*Inputs_Yearly!$G$21 -> 2550 | F51: =(F14-F7)*Inputs_Yearly!$H$17+F7*Inputs_Yearly!$H$21 -> 8418.75 | G51: =(G14-G7)*Inputs_Yearly!$I$17+G7*Inputs_Yearly!$I$21 -> 18768.25 | H51: =SUM(C51:G51) -> 30007
A52: Warranty Reserve | B52: 만원 | C52: =Inputs!$E$65*C37 -> 0 | D52: =Inputs!$E$65*D37 -> 62.58 | E52: =Inputs!$E$65*E37 -> 1773.1 | F52: =Inputs!$E$65*F37 -> 9858.436 | G52: =Inputs!$E$65*G37 -> 25156.743 | H52: =SUM(C52:G52) -> 36850.859
A53: Rental 자산 취득 (MH 보유) | B53: 만원 | C53: =C19*C46 -> 0 | D53: =D19*D46 -> 1368 | E53: =E19*E46 -> 15045 | F53: =F19*F46 -> 0 | G53: =G19*G46 -> 0 | H53: =SUM(C53:G53) -> 16413
A54: Rental 자산 누적 취득 | B54: 만원 | C54: =0+C53 -> 0 | D54: =C54+D53 -> 1368 | E54: =D54+E53 -> 16413 | F54: =E54+F53 -> 16413 | G54: =F54+G53 -> 16413
A55: Rental 자산 감가상각 | B55: 만원 | C55: =0*(1-Inputs!$E$75)/5+C53*(1-Inputs!$E$75)/5*0.5 -> 0 | D55: =C54*(1-Inputs!$E$75)/5+D53*(1-Inputs!$E$75)/5*0.5 -> 116.28 | E55: =D54*(1-Inputs!$E$75)/5+E53*(1-Inputs!$E$75)/5*0.5 -> 1511.385 | F55: =E54*(1-Inputs!$E$75)/5+F53*(1-Inputs!$E$75)/5*0.5 -> 2790.21 | G55: =F54*(1-Inputs!$E$75)/5+G53*(1-Inputs!$E$75)/5*0.5 -> 2790.21 | H55: =SUM(C55:G55) -> 7208.085
A56: Care Service 원가 | B56: 만원 | C56: =(C23*Inputs!$E$51+C25+C27)*C47 -> 0 | D56: =(D23*Inputs!$E$51+D25+D27)*D47 -> 48.348 | E56: =(E23*Inputs!$E$51+E25+E27)*E47 -> 704.996 | F56: =(F23*Inputs!$E$51+F25+F27)*F47 -> 3033.2647 | G56: =(G23*Inputs!$E$51+G25+G27)*G47 -> 9653.4605 | H56: =SUM(C56:G56) -> 13440.069
A57: Consumables 원가 (Rental Grip 포함) | B57: 만원 | C57: =C40*Inputs!$E$69+(C25+C27)*C34*Inputs!$E$69 -> 0 | D57: =D40*Inputs!$E$69+(D25+D27)*D34*Inputs!$E$69 -> 14.0805 | E57: =E40*Inputs!$E$69+(E25+E27)*E34*Inputs!$E$69 -> 227.63475 | F57: =F40*Inputs!$E$69+(F25+F27)*F34*Inputs!$E$69 -> 1259.0235 | G57: =G40*Inputs!$E$69+(G25+G27)*G34*Inputs!$E$69 -> 4213.818 | H57: =SUM(C57:G57) -> 5714.5567
A58: Skill · Tool 원가 | B58: 만원 | C58: =0*Inputs!$E$53*Inputs!$E$52*Inputs!$E$70+0*Inputs!$E$55*Inputs!$E$54*Inputs!$E$71 -> 0 | D58: =C14*Inputs!$E$53*Inputs!$E$52*Inputs!$E$70+0*Inputs!$E$55*Inputs!$E$54*Inputs!$E$71 -> 0 | E58: =D14*Inputs!$E$53*Inputs!$E$52*Inputs!$E$70+C14*Inputs!$E$55*Inputs!$E$54*Inputs!$E$71 -> 3.6 | F58: =E14*Inputs!$E$53*Inputs!$E$52*Inputs!$E$70+D14*Inputs!$E$55*Inputs!$E$54*Inputs!$E$71 -> 78 | G58: =F14*Inputs!$E$53*Inputs!$E$52*Inputs!$E$70+E14*Inputs!$E$55*Inputs!$E$54*Inputs!$E$71 -> 591 | H58: =SUM(C58:G58) -> 672.6
A59: COGS 합계 | B59: 만원 | C59: =C48+C49+C50+C51+C52+C55+C56+C57+C58 -> 0 | D59: =D48+D49+D50+D51+D52+D55+D56+D57+D58 -> 4708.2885 | E59: =E48+E49+E50+E51+E52+E55+E56+E57+E58 -> 56975.716 | F59: =F48+F49+F50+F51+F52+F55+F56+F57+F58 -> 256700.18 | G59: =G48+G49+G50+G51+G52+G55+G56+G57+G58 -> 594461.61 | H59: =SUM(C59:G59) -> 912845.79
A60: 매출총이익 | B60: 만원 | C60: =C42-C59 -> 0 | D60: =D42-D59 -> -2103.1785 | E60: =E42-E59 -> 17258.479 | F60: =F42-F59 -> 102485.69 | G60: =G42-G59 -> 320444.77 | H60: =SUM(C60:G60) -> 438085.76
A61: 매출총이익률 | B61: % | C61: =IF(C42=0,0,C60/C42) -> 0 | D61: =IF(D42=0,0,D60/D42) -> -0.8073281 | E61: =IF(E42=0,0,E60/E42) -> 0.23248692 | F61: =IF(F42=0,0,F60/F42) -> 0.28532772 | G61: =IF(G42=0,0,G60/G42) -> 0.3502487
A62: CHANNEL · OPEX (만원)
A63: Partner 수수료 (Remodeling Partner · Retrofit) | B63: 만원 | C63: =Inputs!$E$72*(C6*(Inputs!$E$34*C31+C10*(Inputs!$E$37+Inputs!$E$38)*C31)+C7*(Inputs!$E$36+Inputs!$E$37+Inputs!$E$39)*C31) -> 0 | D63: =Inputs!$E$72*(D6*(Inputs!$E$34*D31+D10*(Inputs!$E$37+Inputs!$E$38)*D31)+D7*(Inputs!$E$36+Inputs!$E$37+Inputs!$E$39)*D31) -> 0 | E63: =Inputs!$E$72*(E6*(Inputs!$E$34*E31+E10*(Inputs!$E$37+Inputs!$E$38)*E31)+E7*(Inputs!$E$36+Inputs!$E$37+Inputs!$E$39)*E31) -> 3569 | F63: =Inputs!$E$72*(F6*(Inputs!$E$34*F31+F10*(Inputs!$E$37+Inputs!$E$38)*F31)+F7*(Inputs!$E$36+Inputs!$E$37+Inputs!$E$39)*F31) -> 26718.5 | G63: =Inputs!$E$72*(G6*(Inputs!$E$34*G31+G10*(Inputs!$E$37+Inputs!$E$38)*G31)+G7*(Inputs!$E$36+Inputs!$E$37+Inputs!$E$39)*G31) -> 74753 | H63: =SUM(C63:G63) -> 105040.5
A64: 직접판매 획득비용 | B64: 만원 | C64: =C5*Inputs!$E$73 -> 0 | D64: =D5*Inputs!$E$73 -> 450 | E64: =E5*Inputs!$E$73 -> 4500 | F64: =F5*Inputs!$E$73 -> 7500 | G64: =G5*Inputs!$E$73 -> 9000 | H64: =SUM(C64:G64) -> 21450
A65: 신축 Project 수주비용 | B65: 만원 | C65: =Inputs_Yearly!$E$57*Inputs!$E$74 -> 0 | D65: =Inputs_Yearly!$F$57*Inputs!$E$74 -> 0 | E65: =Inputs_Yearly!$G$57*Inputs!$E$74 -> 2000 | F65: =Inputs_Yearly!$H$57*Inputs!$E$74 -> 4000 | G65: =Inputs_Yearly!$I$57*Inputs!$E$74 -> 6000 | H65: =SUM(C65:G65) -> 12000
A66: Contribution (매출총이익 − 채널 · 변동 판매비) | B66: 만원 | C66: =C60-C63-C64-C65 -> 0 | D66: =D60-D63-D64-D65 -> -2553.1785 | E66: =E60-E63-E64-E65 -> 7189.4793 | F66: =F60-F63-F64-F65 -> 64267.186 | G66: =G60-G63-G64-G65 -> 230691.77 | H66: =SUM(C66:G66) -> 299595.26
A67: 인건비 | B67: 만원 | C67: =Inputs_Yearly!$E$61*Inputs_Yearly!$E$65 -> 55825 | D67: =Inputs_Yearly!$F$61*Inputs_Yearly!$F$65 -> 97050 | E67: =Inputs_Yearly!$G$61*Inputs_Yearly!$G$65 -> 170000 | F67: =Inputs_Yearly!$H$61*Inputs_Yearly!$H$65 -> 272000 | G67: =Inputs_Yearly!$I$61*Inputs_Yearly!$I$65 -> 357000 | H67: =SUM(C67:G67) -> 951875
A68: 기타 운영비 (Robot HW · Hand · Mock-up · SW · Pilot · 고객 · 인증 · IP · 공간 · 관리 · 예비비 · 연구수당) | B68: 만원 | C68: =Inputs_Yearly!$E$69+Inputs_Yearly!$E$73+Inputs_Yearly!$E$77+Inputs_Yearly!$E$81+Inputs_Yearly!$E$85+Inputs_Yearly!$E$89+Inputs_Yearly!$E$93+Inputs_Yearly!$E$97+Inputs_Yearly!$E$101+Inputs_Yearly!$E$105+Inputs_Yearly!$E$109+Inputs_Yearly!$E$113 -> 36342.75 | D68: =Inputs_Yearly!$F$69+Inputs_Yearly!$F$73+Inputs_Yearly!$F$77+Inputs_Yearly!$F$81+Inputs_Yearly!$F$85+Inputs_Yearly!$F$89+Inputs_Yearly!$F$93+Inputs_Yearly!$F$97+Inputs_Yearly!$F$101+Inputs_Yearly!$F$105+Inputs_Yearly!$F$109+Inputs_Yearly!$F$113 -> 41116 | E68: =Inputs_Yearly!$G$69+Inputs_Yearly!$G$73+Inputs_Yearly!$G$77+Inputs_Yearly!$G$81+Inputs_Yearly!$G$85+Inputs_Yearly!$G$89+Inputs_Yearly!$G$93+Inputs_Yearly!$G$97+Inputs_Yearly!$G$101+Inputs_Yearly!$G$105+Inputs_Yearly!$G$109+Inputs_Yearly!$G$113 -> 135000 | F68: =Inputs_Yearly!$H$69+Inputs_Yearly!$H$73+Inputs_Yearly!$H$77+Inputs_Yearly!$H$81+Inputs_Yearly!$H$85+Inputs_Yearly!$H$89+Inputs_Yearly!$H$93+Inputs_Yearly!$H$97+Inputs_Yearly!$H$101+Inputs_Yearly!$H$105+Inputs_Yearly!$H$109+Inputs_Yearly!$H$113 -> 167000 | G68: =Inputs_Yearly!$I$69+Inputs_Yearly!$I$73+Inputs_Yearly!$I$77+Inputs_Yearly!$I$81+Inputs_Yearly!$I$85+Inputs_Yearly!$I$89+Inputs_Yearly!$I$93+Inputs_Yearly!$I$97+Inputs_Yearly!$I$101+Inputs_Yearly!$I$105+Inputs_Yearly!$I$109+Inputs_Yearly!$I$113 -> 210000 | H68: =SUM(C68:G68) -> 589458.75
A69: Opex 합계 | B69: 만원 | C69: =C67+C68 -> 92167.75 | D69: =D67+D68 -> 138166 | E69: =E67+E68 -> 305000 | F69: =F67+F68 -> 439000 | G69: =G67+G68 -> 567000 | H69: =SUM(C69:G69) -> 1541333.8
A70: 영업이익 (근사) | B70: 만원 | C70: =C66-C69 -> -92167.75 | D70: =D66-D69 -> -140719.18 | E70: =E66-E69 -> -297810.52 | F70: =F66-F69 -> -374732.81 | G70: =G66-G69 -> -336308.23 | H70: =SUM(C70:G70) -> -1241738.5
A71: 현금흐름 (영업이익 + 감가 − Rental 자산) | B71: 만원 | C71: =C70+C55-C53 -> -92167.75 | D71: =D70+D55-D53 -> -141970.9 | E71: =E70+E55-E53 -> -311344.14 | F71: =F70+F55-F53 -> -371942.6 | G71: =G70+G55-G53 -> -333518.02 | H71: =SUM(C71:G71) -> -1250943.4
A72: 누적 현금흐름 | B72: 만원 | C72: =0+C71 -> -92167.75 | D72: =C72+D71 -> -234138.65 | E72: =D72+E71 -> -545482.78 | F72: =E72+F71 -> -917425.39 | G72: =F72+G71 -> -1250943.4
A73: MIX
A74: INSTALL 매출 (Interface + 설치 + Robot) | B74: 만원 | C74: =C35+C36+C37 -> 0 | D74: =D35+D36+D37 -> 2359.5 | E74: =E35+E36+E37 -> 70227.5 | F74: =F35+F36+F37 -> 345160.9 | G74: =G35+G36+G37 -> 877188.57 | H74: =SUM(C74:G74) -> 1294936.5
A75: Interface + 설치 매출 | B75: 만원 | C75: =C35+C36 -> 0 | D75: =D35+D36 -> 795 | E75: =E35+E36 -> 25900 | F75: =F35+F36 -> 98700 | G75: =G35+G36 -> 248270 | H75: =SUM(C75:G75) -> 373665
A76: OPERATE 매출 (Rental + Care + Consumables) | B76: 만원 | C76: =C38+C39+C40 -> 0 | D76: =D38+D39+D40 -> 245.61 | E76: =E38+E39+E40 -> 3970.695 | F76: =F38+F39+F40 -> 13454.97 | G76: =G38+G39+G40 -> 34782.81 | H76: =SUM(C76:G76) -> 52454.085
A77: EXPAND 매출 (Skill + Tool) | B77: 만원 | C77: =C41 -> 0 | D77: =D41 -> 0 | E77: =E41 -> 36 | F77: =F41 -> 570 | G77: =G41 -> 2935 | H77: =SUM(C77:G77) -> 3541
A78: OPERATE + EXPAND 비중 | B78: % | C78: =IF(C42=0,0,(C76+C77)/C42) -> 0 | D78: =IF(D42=0,0,(D76+D77)/D42) -> 0.094280088 | E78: =IF(E42=0,0,(E76+E77)/E42) -> 0.053973711 | F78: =IF(F42=0,0,(F76+F77)/F42) -> 0.039046553 | G78: =IF(G42=0,0,(G76+G77)/G42) -> 0.041225868
A79: Robot + Recurring + Upgrade 비중 | B79: % | C79: =IF(C42=0,0,(C37+C76+C41)/C42) -> 0 | D79: =IF(D42=0,0,(D37+D76+D41)/D42) -> 0.69483054 | E79: =IF(E42=0,0,(E37+E76+E41)/E42) -> 0.65110418 | F79: =IF(F42=0,0,(F37+F76+F41)/F42) -> 0.72521191 | G79: =IF(G42=0,0,(G37+G76+G41)/G42) -> 0.7286389

Sheet FM_Upside
A1: 5-Year Bottom-up Model — Upside (만원)
A2: 모든 입력은 Inputs / Inputs_Yearly의 Upside 열·행을 참조 (녹색). 영업이익은 이자·세금 제외 근사.
A3: 항목 | B3: 단위 | C3: Y1 | D3: Y2 | E3: Y3 | F3: Y4 | G3: Y5 | H3: 5Y 합계
A4: VOLUME
A5: Remodeling — MH 직접 판매 | B5: 세대 | C5: =Inputs_Yearly!$E$34 -> 0 | D5: =Inputs_Yearly!$F$34 -> 3 | E5: =Inputs_Yearly!$G$34 -> 35 | F5: =Inputs_Yearly!$H$34 -> 60 | G5: =Inputs_Yearly!$I$34 -> 70 | H5: =SUM(C5:G5) -> 168
A6: Remodeling — Partner 경유 | B6: 세대 | C6: =Inputs_Yearly!$E$38 -> 0 | D6: =Inputs_Yearly!$F$38 -> 0 | E6: =Inputs_Yearly!$G$38 -> 30 | F6: =Inputs_Yearly!$H$38 -> 220 | G6: =Inputs_Yearly!$I$38 -> 600 | H6: =SUM(C6:G6) -> 850
A7: Existing Kitchen Retrofit | B7: 세대 | C7: =Inputs_Yearly!$E$42 -> 0 | D7: =Inputs_Yearly!$F$42 -> 0 | E7: =Inputs_Yearly!$G$42 -> 0 | F7: =Inputs_Yearly!$H$42 -> 30 | G7: =Inputs_Yearly!$I$42 -> 120 | H7: =SUM(C7:G7) -> 150
A8: New-build Interface Option 입주 (계약 2년 후) | B8: 세대 | C8: =0 -> 0 | D8: =0 -> 0 | E8: =Inputs_Yearly!$E$58*Inputs!$F$80*Inputs!$F$81 -> 0 | F8: =Inputs_Yearly!$F$58*Inputs!$F$80*Inputs!$F$81 -> 0 | G8: =Inputs_Yearly!$G$58*Inputs!$F$80*Inputs!$F$81 -> 192 | H8: =SUM(C8:G8) -> 192
A9: 설치 세대 합계 | B9: 세대 | C9: =C5+C6+C8+C7 -> 0 | D9: =D5+D6+D8+D7 -> 3 | E9: =E5+E6+E8+E7 -> 65 | F9: =F5+F6+F8+F7 -> 310 | G9: =G5+G6+G8+G7 -> 982 | H9: =SUM(C9:G9) -> 1360
A10: Robot Attach Rate (Remodeling) | B10: % | C10: =Inputs_Yearly!$E$46 -> 1 | D10: =Inputs_Yearly!$F$46 -> 1 | E10: =Inputs_Yearly!$G$46 -> 0.85 | F10: =Inputs_Yearly!$H$46 -> 0.85 | G10: =Inputs_Yearly!$I$46 -> 0.85
A11: Interface 선설치 세대 Robot 후설치 | B11: 대 | C11: =0*Inputs!$F$79 -> 0 | D11: =C21*Inputs!$F$79 -> 0 | E11: =D21*Inputs!$F$79 -> 0 | F11: =E21*Inputs!$F$79 -> 1.17 | G11: =F21*Inputs!$F$79 -> 6.0696 | H11: =SUM(C11:G11) -> 7.2396
A12: Robot 설치 — Remodeling | B12: 대 | C12: =(C5+C6)*C10 -> 0 | D12: =(D5+D6)*D10 -> 3 | E12: =(E5+E6)*E10 -> 55.25 | F12: =(F5+F6)*F10 -> 238 | G12: =(G5+G6)*G10 -> 569.5 | H12: =SUM(C12:G12) -> 865.75
A13: Robot 설치 — New-build 입주 | B13: 대 | C13: =C8*Inputs!$F$82 -> 0 | D13: =D8*Inputs!$F$82 -> 0 | E13: =E8*Inputs!$F$82 -> 0 | F13: =F8*Inputs!$F$82 -> 0 | G13: =G8*Inputs!$F$82 -> 57.6 | H13: =SUM(C13:G13) -> 57.6
A14: Robot 설치 합계 (Retrofit 포함) | B14: 대 | C14: =C12+C13+C11+C7 -> 0 | D14: =D12+D13+D11+D7 -> 3 | E14: =E12+E13+E11+E7 -> 55.25 | F14: =F12+F13+F11+F7 -> 269.17 | G14: =G12+G13+G11+G7 -> 753.1696 | H14: =SUM(C14:G14) -> 1080.5896
A15: Rental 비중 | B15: % | C15: =Inputs_Yearly!$E$50 -> 0 | D15: =Inputs_Yearly!$F$50 -> 0.3 | E15: =Inputs_Yearly!$G$50 -> 0.3 | F15: =Inputs_Yearly!$H$50 -> 0.45 | G15: =Inputs_Yearly!$I$50 -> 0.45
A16: Rental Partner 보유 Flag | B16: flag | C16: =Inputs_Yearly!$E$54 -> 0 | D16: =Inputs_Yearly!$F$54 -> 0 | E16: =Inputs_Yearly!$G$54 -> 0 | F16: =Inputs_Yearly!$H$54 -> 1 | G16: =Inputs_Yearly!$I$54 -> 1
A17: Rental 설치 | B17: 대 | C17: =C14*C15 -> 0 | D17: =D14*D15 -> 0.9 | E17: =E14*E15 -> 16.575 | F17: =F14*F15 -> 121.1265 | G17: =G14*G15 -> 338.92632 | H17: =SUM(C17:G17) -> 477.52782
A18: 구매 설치 | B18: 대 | C18: =C14-C17 -> 0 | D18: =D14-D17 -> 2.1 | E18: =E14-E17 -> 38.675 | F18: =F14-F17 -> 148.0435 | G18: =G14-G17 -> 414.24328 | H18: =SUM(C18:G18) -> 603.06178
A19: Rental — MH 보유 (Pilot) | B19: 대 | C19: =C17*(1-C16) -> 0 | D19: =D17*(1-D16) -> 0.9 | E19: =E17*(1-E16) -> 16.575 | F19: =F17*(1-F16) -> 0 | G19: =G17*(1-G16) -> 0 | H19: =SUM(C19:G19) -> 17.475
A20: Rental — Partner 보유 | B20: 대 | C20: =C17*C16 -> 0 | D20: =D17*D16 -> 0 | E20: =E17*E16 -> 0 | F20: =F17*F16 -> 121.1265 | G20: =G17*G16 -> 338.92632 | H20: =SUM(C20:G20) -> 460.05282
A21: Interface 선설치 (Robot 미설치) 누적 | B21: 세대 | C21: =0+(C5+C6)*(1-C10)+C8*(1-Inputs!$F$82)-C11 -> 0 | D21: =C21+(D5+D6)*(1-D10)+D8*(1-Inputs!$F$82)-D11 -> 0 | E21: =D21+(E5+E6)*(1-E10)+E8*(1-Inputs!$F$82)-E11 -> 9.75 | F21: =E21+(F5+F6)*(1-F10)+F8*(1-Inputs!$F$82)-F11 -> 50.58 | G21: =F21+(G5+G6)*(1-G10)+G8*(1-Inputs!$F$82)-G11 -> 279.4104
A22: 구매 Robot 누적 (기말) | B22: 대 | C22: =0+C18 -> 0 | D22: =C22+D18 -> 2.1 | E22: =D22+E18 -> 40.775 | F22: =E22+F18 -> 188.8185 | G22: =F22+G18 -> 603.06178
A23: 구매 Robot 평균 가동 | B23: 대 | C23: =0+C18/2 -> 0 | D23: =C22+D18/2 -> 1.05 | E23: =D22+E18/2 -> 21.4375 | F23: =E22+F18/2 -> 114.79675 | G23: =F22+G18/2 -> 395.94014
A24: MH Rental 누적 (기말) | B24: 대 | C24: =0+C19 -> 0 | D24: =C24+D19 -> 0.9 | E24: =D24+E19 -> 17.475 | F24: =E24+F19 -> 17.475 | G24: =F24+G19 -> 17.475
A25: MH Rental 평균 가동 | B25: 대 | C25: =0+C19/2 -> 0 | D25: =C24+D19/2 -> 0.45 | E25: =D24+E19/2 -> 9.1875 | F25: =E24+F19/2 -> 17.475 | G25: =F24+G19/2 -> 17.475
A26: Partner Rental 누적 (기말) | B26: 대 | C26: =0+C20 -> 0 | D26: =C26+D20 -> 0 | E26: =D26+E20 -> 0 | F26: =E26+F20 -> 121.1265 | G26: =F26+G20 -> 460.05282
A27: Partner Rental 평균 가동 | B27: 대 | C27: =0+C20/2 -> 0 | D27: =C26+D20/2 -> 0 | E27: =D26+E20/2 -> 0 | F27: =E26+F20/2 -> 60.56325 | G27: =F26+G20/2 -> 290.58966
A28: Installed Robot (기말) | B28: 대 | C28: =C22+C24+C26 -> 0 | D28: =D22+D24+D26 -> 3 | E28: =E22+E24+E26 -> 58.25 | F28: =F22+F24+F26 -> 327.42 | G28: =G22+G24+G26 -> 1080.5896
A29: 신축 계약 Backlog (미설치 세대) | B29: 세대 | C29: =Inputs_Yearly!$E$58*Inputs!$F$80*Inputs!$F$81 -> 0 | D29: =(Inputs_Yearly!$F$58+Inputs_Yearly!$E$58)*Inputs!$F$80*Inputs!$F$81 -> 0 | E29: =(Inputs_Yearly!$G$58+Inputs_Yearly!$F$58)*Inputs!$F$80*Inputs!$F$81 -> 192 | F29: =(Inputs_Yearly!$H$58+Inputs_Yearly!$G$58)*Inputs!$F$80*Inputs!$F$81 -> 480 | G29: =(Inputs_Yearly!$I$58+Inputs_Yearly!$H$58)*Inputs!$F$80*Inputs!$F$81 -> 672
A30: REVENUE (만원) — INSTALL / OPERATE / EXPAND
A31: 가격 실현율 | B31: % | C31: =Inputs_Yearly!$E$6 -> 1 | D31: =Inputs_Yearly!$F$6 -> 0.6 | E31: =Inputs_Yearly!$G$6 -> 1 | F31: =Inputs_Yearly!$H$6 -> 1 | G31: =Inputs_Yearly!$I$6 -> 1
A32: Consumables 연 List (구매 고객) | B32: 만원/대 | C32: =Inputs!$F$44*Inputs!$F$45+Inputs!$F$46*Inputs!$F$47+Inputs!$F$48*Inputs!$F$49 -> 36 | D32: =Inputs!$F$44*Inputs!$F$45+Inputs!$F$46*Inputs!$F$47+Inputs!$F$48*Inputs!$F$49 -> 36 | E32: =Inputs!$F$44*Inputs!$F$45+Inputs!$F$46*Inputs!$F$47+Inputs!$F$48*Inputs!$F$49 -> 36 | F32: =Inputs!$F$44*Inputs!$F$45+Inputs!$F$46*Inputs!$F$47+Inputs!$F$48*Inputs!$F$49 -> 36 | G32: =Inputs!$F$44*Inputs!$F$45+Inputs!$F$46*Inputs!$F$47+Inputs!$F$48*Inputs!$F$49 -> 36
A33: Consumables 연 List (Rental, Grip 제외) | B33: 만원/대 | C33: =Inputs!$F$46*Inputs!$F$47+Inputs!$F$48*Inputs!$F$49 -> 18 | D33: =Inputs!$F$46*Inputs!$F$47+Inputs!$F$48*Inputs!$F$49 -> 18 | E33: =Inputs!$F$46*Inputs!$F$47+Inputs!$F$48*Inputs!$F$49 -> 18 | F33: =Inputs!$F$46*Inputs!$F$47+Inputs!$F$48*Inputs!$F$49 -> 18 | G33: =Inputs!$F$46*Inputs!$F$47+Inputs!$F$48*Inputs!$F$49 -> 18
A34: Grip Kit 연 List | B34: 만원/대 | C34: =Inputs!$F$44*Inputs!$F$45 -> 18 | D34: =Inputs!$F$44*Inputs!$F$45 -> 18 | E34: =Inputs!$F$44*Inputs!$F$45 -> 18 | F34: =Inputs!$F$44*Inputs!$F$45 -> 18 | G34: =Inputs!$F$44*Inputs!$F$45 -> 18
A35: INSTALL. Interface · Integration | B35: 만원 | C35: =(C5+C6)*Inputs!$F$34*C31+C8*Inputs!$F$35+C7*Inputs!$F$36*C31 -> 0 | D35: =(D5+D6)*Inputs!$F$34*D31+D8*Inputs!$F$35+D7*Inputs!$F$36*D31 -> 810 | E35: =(E5+E6)*Inputs!$F$34*E31+E8*Inputs!$F$35+E7*Inputs!$F$36*E31 -> 29250 | F35: =(F5+F6)*Inputs!$F$34*F31+F8*Inputs!$F$35+F7*Inputs!$F$36*F31 -> 130500 | G35: =(G5+G6)*Inputs!$F$34*G31+G8*Inputs!$F$35+G7*Inputs!$F$36*G31 -> 361740 | H35: =SUM(C35:G35) -> 522300
A36: INSTALL. Installation · Calibration | B36: 만원 | C36: =(C14-C7)*Inputs!$F$38*C31+C7*Inputs!$F$39*C31 -> 0 | D36: =(D14-D7)*Inputs!$F$38*D31+D7*Inputs!$F$39*D31 -> 144 | E36: =(E14-E7)*Inputs!$F$38*E31+E7*Inputs!$F$39*E31 -> 4420 | F36: =(F14-F7)*Inputs!$F$38*F31+F7*Inputs!$F$39*F31 -> 22733.6 | G36: =(G14-G7)*Inputs!$F$38*G31+G7*Inputs!$F$39*G31 -> 65053.568 | H36: =SUM(C36:G36) -> 92351.168
A37: INSTALL. Robot System (구매 + Rental Partner 공급) | B37: 만원 | C37: =C18*Inputs!$F$37*C31+C20*Inputs!$F$37*Inputs!$F$56 -> 0 | D37: =D18*Inputs!$F$37*D31+D20*Inputs!$F$37*Inputs!$F$56 -> 1877.4 | E37: =E18*Inputs!$F$37*E31+E20*Inputs!$F$37*Inputs!$F$56 -> 57625.75 | F37: =F18*Inputs!$F$37*F31+F20*Inputs!$F$37*Inputs!$F$56 -> 379405.88 | G37: =G18*Inputs!$F$37*G31+G20*Inputs!$F$37*Inputs!$F$56 -> 1061622.7 | H37: =SUM(C37:G37) -> 1500531.7
A38: OPERATE. Rental (MH 보유) | B38: 만원 | C38: =C25*Inputs!$F$40*12 -> 0 | D38: =D25*Inputs!$F$40*12 -> 178.2 | E38: =E25*Inputs!$F$40*12 -> 3638.25 | F38: =F25*Inputs!$F$40*12 -> 6920.1 | G38: =G25*Inputs!$F$40*12 -> 6920.1 | H38: =SUM(C38:G38) -> 17656.65
A39: OPERATE. Care (구매 고객 + Partner 서비스료) | B39: 만원 | C39: =C23*Inputs!$F$51*Inputs!$F$42+C27*Inputs!$F$57*12 -> 0 | D39: =D23*Inputs!$F$51*Inputs!$F$42+D27*Inputs!$F$57*12 -> 35.28 | E39: =E23*Inputs!$F$51*Inputs!$F$42+E27*Inputs!$F$57*12 -> 720.3 | F39: =F23*Inputs!$F$51*Inputs!$F$42+F27*Inputs!$F$57*12 -> 8217.7248 | G39: =G23*Inputs!$F$51*Inputs!$F$42+G27*Inputs!$F$57*12 -> 34226.044 | H39: =SUM(C39:G39) -> 43199.349
A40: OPERATE. Consumables | B40: 만원 | C40: =C23*Inputs!$F$50*C32+(C25+C27)*Inputs!$F$50*C33 -> 0 | D40: =D23*Inputs!$F$50*D32+(D25+D27)*Inputs!$F$50*D33 -> 32.13 | E40: =E23*Inputs!$F$50*E32+(E25+E27)*Inputs!$F$50*E33 -> 655.9875 | F40: =F23*Inputs!$F$50*F32+(F25+F27)*Inputs!$F$50*F33 -> 3876.16 | G40: =G23*Inputs!$F$50*G32+(G25+G27)*Inputs!$F$50*G33 -> 13859.306 | H40: =SUM(C40:G40) -> 18423.584
A41: EXPAND. Skill + Tool | B41: 만원 | C41: =0*Inputs!$F$53*Inputs!$F$52+0*Inputs!$F$55*Inputs!$F$54 -> 0 | D41: =C14*Inputs!$F$53*Inputs!$F$52+0*Inputs!$F$55*Inputs!$F$54 -> 0 | E41: =D14*Inputs!$F$53*Inputs!$F$52+C14*Inputs!$F$55*Inputs!$F$54 -> 36 | F41: =E14*Inputs!$F$53*Inputs!$F$52+D14*Inputs!$F$55*Inputs!$F$54 -> 723 | G41: =F14*Inputs!$F$53*Inputs!$F$52+E14*Inputs!$F$55*Inputs!$F$54 -> 4335.04 | H41: =SUM(C41:G41) -> 5094.04
A42: 매출 합계 | B42: 만원 | C42: =SUM(C35:C41) -> 0 | D42: =SUM(D35:D41) -> 3077.01 | E42: =SUM(E35:E41) -> 96346.288 | F42: =SUM(F35:F41) -> 552376.47 | G42: =SUM(G35:G41) -> 1547756.7 | H42: =SUM(C42:G42) -> 2199556.5
A43: COGS (만원)
A44: Interface 표준부품 사용률 | B44: % | C44: =Inputs_Yearly!$E$10 -> 0.4 | D44: =Inputs_Yearly!$F$10 -> 0.55 | E44: =Inputs_Yearly!$G$10 -> 0.7 | F44: =Inputs_Yearly!$H$10 -> 0.8 | G44: =Inputs_Yearly!$I$10 -> 0.85
A45: Interface Kit 원가/세대 (Remodeling) | B45: 만원 | C45: =Inputs!$F$59*(C44+Inputs!$F$60*(1-C44))+Inputs!$F$61*(1-C44) -> 332 | D45: =Inputs!$F$59*(D44+Inputs!$F$60*(1-D44))+Inputs!$F$61*(1-D44) -> 299 | E45: =Inputs!$F$59*(E44+Inputs!$F$60*(1-E44))+Inputs!$F$61*(1-E44) -> 266 | F45: =Inputs!$F$59*(F44+Inputs!$F$60*(1-F44))+Inputs!$F$61*(1-F44) -> 244 | G45: =Inputs!$F$59*(G44+Inputs!$F$60*(1-G44))+Inputs!$F$61*(1-G44) -> 233
A46: Robot BOM/대 | B46: 만원 | C46: =Inputs_Yearly!$E$14 -> 1680 | D46: =Inputs_Yearly!$F$14 -> 1460 | E46: =Inputs_Yearly!$G$14 -> 1100 | F46: =Inputs_Yearly!$H$14 -> 950 | G46: =Inputs_Yearly!$I$14 -> 820
A47: Care 원가/대·년 | B47: 만원 | C47: =Inputs_Yearly!$E$26*Inputs_Yearly!$E$30+Inputs!$F$66*Inputs!$F$67+Inputs!$F$68 -> 43 | D47: =Inputs_Yearly!$F$26*Inputs_Yearly!$F$30+Inputs!$F$66*Inputs!$F$67+Inputs!$F$68 -> 37 | E47: =Inputs_Yearly!$G$26*Inputs_Yearly!$G$30+Inputs!$F$66*Inputs!$F$67+Inputs!$F$68 -> 28 | F47: =Inputs_Yearly!$H$26*Inputs_Yearly!$H$30+Inputs!$F$66*Inputs!$F$67+Inputs!$F$68 -> 22.6 | G47: =Inputs_Yearly!$I$26*Inputs_Yearly!$I$30+Inputs!$F$66*Inputs!$F$67+Inputs!$F$68 -> 20
A48: Interface 원가 (3개 채널) | B48: 만원 | C48: =(C5+C6)*C45+C8*Inputs!$F$62+C7*Inputs!$F$63 -> 0 | D48: =(D5+D6)*D45+D8*Inputs!$F$62+D7*Inputs!$F$63 -> 897 | E48: =(E5+E6)*E45+E8*Inputs!$F$62+E7*Inputs!$F$63 -> 17290 | F48: =(F5+F6)*F45+F8*Inputs!$F$62+F7*Inputs!$F$63 -> 70420 | G48: =(G5+G6)*G45+G8*Inputs!$F$62+G7*Inputs!$F$63 -> 187550 | H48: =SUM(C48:G48) -> 276157
A49: 물류 | B49: 만원 | C49: =(C5+C6+C8+C7)*Inputs!$F$64 -> 0 | D49: =(D5+D6+D8+D7)*Inputs!$F$64 -> 75 | E49: =(E5+E6+E8+E7)*Inputs!$F$64 -> 1625 | F49: =(F5+F6+F8+F7)*Inputs!$F$64 -> 7750 | G49: =(G5+G6+G8+G7)*Inputs!$F$64 -> 24550 | H49: =SUM(C49:G49) -> 34000
A50: Robot BOM (판매분) | B50: 만원 | C50: =(C18+C20)*C46 -> 0 | D50: =(D18+D20)*D46 -> 3066 | E50: =(E18+E20)*E46 -> 42542.5 | F50: =(F18+F20)*F46 -> 255711.5 | G50: =(G18+G20)*G46 -> 617599.07 | H50: =SUM(C50:G50) -> 918919.07
A51: Installation · Calibration 원가 | B51: 만원 | C51: =(C14-C7)*Inputs_Yearly!$E$18+C7*Inputs_Yearly!$E$22 -> 0 | D51: =(D14-D7)*Inputs_Yearly!$F$18+D7*Inputs_Yearly!$F$22 -> 255 | E51: =(E14-E7)*Inputs_Yearly!$G$18+E7*Inputs_Yearly!$G$22 -> 2873 | F51: =(F14-F7)*Inputs_Yearly!$H$18+F7*Inputs_Yearly!$H$22 -> 11038.46 | G51: =(G14-G7)*Inputs_Yearly!$I$18+G7*Inputs_Yearly!$I$22 -> 25235.088 | H51: =SUM(C51:G51) -> 39401.548
A52: Warranty Reserve | B52: 만원 | C52: =Inputs!$F$65*C37 -> 0 | D52: =Inputs!$F$65*D37 -> 65.709 | E52: =Inputs!$F$65*E37 -> 2016.9012 | F52: =Inputs!$F$65*F37 -> 13279.206 | G52: =Inputs!$F$65*G37 -> 37156.794 | H52: =SUM(C52:G52) -> 52518.61
A53: Rental 자산 취득 (MH 보유) | B53: 만원 | C53: =C19*C46 -> 0 | D53: =D19*D46 -> 1314 | E53: =E19*E46 -> 18232.5 | F53: =F19*F46 -> 0 | G53: =G19*G46 -> 0 | H53: =SUM(C53:G53) -> 19546.5
A54: Rental 자산 누적 취득 | B54: 만원 | C54: =0+C53 -> 0 | D54: =C54+D53 -> 1314 | E54: =D54+E53 -> 19546.5 | F54: =E54+F53 -> 19546.5 | G54: =F54+G53 -> 19546.5
A55: Rental 자산 감가상각 | B55: 만원 | C55: =0*(1-Inputs!$F$75)/5+C53*(1-Inputs!$F$75)/5*0.5 -> 0 | D55: =C54*(1-Inputs!$F$75)/5+D53*(1-Inputs!$F$75)/5*0.5 -> 111.69 | E55: =D54*(1-Inputs!$F$75)/5+E53*(1-Inputs!$F$75)/5*0.5 -> 1773.1425 | F55: =E54*(1-Inputs!$F$75)/5+F53*(1-Inputs!$F$75)/5*0.5 -> 3322.905 | G55: =F54*(1-Inputs!$F$75)/5+G53*(1-Inputs!$F$75)/5*0.5 -> 3322.905 | H55: =SUM(C55:G55) -> 8530.6425
A56: Care Service 원가 | B56: 만원 | C56: =(C23*Inputs!$F$51+C25+C27)*C47 -> 0 | D56: =(D23*Inputs!$F$51+D25+D27)*D47 -> 43.845 | E56: =(E23*Inputs!$F$51+E25+E27)*E47 -> 677.425 | F56: =(F23*Inputs!$F$51+F25+F27)*F47 -> 3579.749 | G56: =(G23*Inputs!$F$51+G25+G27)*G47 -> 11704.455 | H56: =SUM(C56:G56) -> 16005.474
A57: Consumables 원가 (Rental Grip 포함) | B57: 만원 | C57: =C40*Inputs!$F$69+(C25+C27)*C34*Inputs!$F$69 -> 0 | D57: =D40*Inputs!$F$69+(D25+D27)*D34*Inputs!$F$69 -> 12.8736 | E57: =E40*Inputs!$F$69+(E25+E27)*E34*Inputs!$F$69 -> 262.836 | F57: =F40*Inputs!$F$69+(F25+F27)*F34*Inputs!$F$69 -> 1689.8715 | G57: =G40*Inputs!$F$69+(G25+G27)*G34*Inputs!$F$69 -> 6209.4304 | H57: =SUM(C57:G57) -> 8175.0116
A58: Skill · Tool 원가 | B58: 만원 | C58: =0*Inputs!$F$53*Inputs!$F$52*Inputs!$F$70+0*Inputs!$F$55*Inputs!$F$54*Inputs!$F$71 -> 0 | D58: =C14*Inputs!$F$53*Inputs!$F$52*Inputs!$F$70+0*Inputs!$F$55*Inputs!$F$54*Inputs!$F$71 -> 0 | E58: =D14*Inputs!$F$53*Inputs!$F$52*Inputs!$F$70+C14*Inputs!$F$55*Inputs!$F$54*Inputs!$F$71 -> 3.6 | F58: =E14*Inputs!$F$53*Inputs!$F$52*Inputs!$F$70+D14*Inputs!$F$55*Inputs!$F$54*Inputs!$F$71 -> 93.3 | G58: =F14*Inputs!$F$53*Inputs!$F$52*Inputs!$F$70+E14*Inputs!$F$55*Inputs!$F$54*Inputs!$F$71 -> 820.254 | H58: =SUM(C58:G58) -> 917.154
A59: COGS 합계 | B59: 만원 | C59: =C48+C49+C50+C51+C52+C55+C56+C57+C58 -> 0 | D59: =D48+D49+D50+D51+D52+D55+D56+D57+D58 -> 4527.1176 | E59: =E48+E49+E50+E51+E52+E55+E56+E57+E58 -> 69064.405 | F59: =F48+F49+F50+F51+F52+F55+F56+F57+F58 -> 366884.99 | G59: =G48+G49+G50+G51+G52+G55+G56+G57+G58 -> 914148 | H59: =SUM(C59:G59) -> 1354624.5
A60: 매출총이익 | B60: 만원 | C60: =C42-C59 -> 0 | D60: =D42-D59 -> -1450.1076 | E60: =E42-E59 -> 27281.883 | F60: =F42-F59 -> 185491.48 | G60: =G42-G59 -> 633608.74 | H60: =SUM(C60:G60) -> 844931.99
A61: 매출총이익률 | B61: % | C61: =IF(C42=0,0,C60/C42) -> 0 | D61: =IF(D42=0,0,D60/D42) -> -0.47127166 | E61: =IF(E42=0,0,E60/E42) -> 0.28316486 | F61: =IF(F42=0,0,F60/F42) -> 0.33580626 | G61: =IF(G42=0,0,G60/G42) -> 0.4093723
A62: CHANNEL · OPEX (만원)
A63: Partner 수수료 (Remodeling Partner · Retrofit) | B63: 만원 | C63: =Inputs!$F$72*(C6*(Inputs!$F$34*C31+C10*(Inputs!$F$37+Inputs!$F$38)*C31)+C7*(Inputs!$F$36+Inputs!$F$37+Inputs!$F$39)*C31) -> 0 | D63: =Inputs!$F$72*(D6*(Inputs!$F$34*D31+D10*(Inputs!$F$37+Inputs!$F$38)*D31)+D7*(Inputs!$F$36+Inputs!$F$37+Inputs!$F$39)*D31) -> 0 | E63: =Inputs!$F$72*(E6*(Inputs!$F$34*E31+E10*(Inputs!$F$37+Inputs!$F$38)*E31)+E7*(Inputs!$F$36+Inputs!$F$37+Inputs!$F$39)*E31) -> 4818.15 | F63: =Inputs!$F$72*(F6*(Inputs!$F$34*F31+F10*(Inputs!$F$37+Inputs!$F$38)*F31)+F7*(Inputs!$F$36+Inputs!$F$37+Inputs!$F$39)*F31) -> 40085.1 | G63: =Inputs!$F$72*(G6*(Inputs!$F$34*G31+G10*(Inputs!$F$37+Inputs!$F$38)*G31)+G7*(Inputs!$F$36+Inputs!$F$37+Inputs!$F$39)*G31) -> 115371 | H63: =SUM(C63:G63) -> 160274.25
A64: 직접판매 획득비용 | B64: 만원 | C64: =C5*Inputs!$F$73 -> 0 | D64: =D5*Inputs!$F$73 -> 420 | E64: =E5*Inputs!$F$73 -> 4900 | F64: =F5*Inputs!$F$73 -> 8400 | G64: =G5*Inputs!$F$73 -> 9800 | H64: =SUM(C64:G64) -> 23520
A65: 신축 Project 수주비용 | B65: 만원 | C65: =Inputs_Yearly!$E$58*Inputs!$F$74 -> 0 | D65: =Inputs_Yearly!$F$58*Inputs!$F$74 -> 0 | E65: =Inputs_Yearly!$G$58*Inputs!$F$74 -> 4000 | F65: =Inputs_Yearly!$H$58*Inputs!$F$74 -> 6000 | G65: =Inputs_Yearly!$I$58*Inputs!$F$74 -> 8000 | H65: =SUM(C65:G65) -> 18000
A66: Contribution (매출총이익 − 채널 · 변동 판매비) | B66: 만원 | C66: =C60-C63-C64-C65 -> 0 | D66: =D60-D63-D64-D65 -> -1870.1076 | E66: =E60-E63-E64-E65 -> 13563.733 | F66: =F60-F63-F64-F65 -> 131006.38 | G66: =G60-G63-G64-G65 -> 500437.74 | H66: =SUM(C66:G66) -> 643137.74
A67: 인건비 | B67: 만원 | C67: =Inputs_Yearly!$E$62*Inputs_Yearly!$E$66 -> 55825 | D67: =Inputs_Yearly!$F$62*Inputs_Yearly!$F$66 -> 97050 | E67: =Inputs_Yearly!$G$62*Inputs_Yearly!$G$66 -> 170000 | F67: =Inputs_Yearly!$H$62*Inputs_Yearly!$H$66 -> 272000 | G67: =Inputs_Yearly!$I$62*Inputs_Yearly!$I$66 -> 357000 | H67: =SUM(C67:G67) -> 951875
A68: 기타 운영비 (Robot HW · Hand · Mock-up · SW · Pilot · 고객 · 인증 · IP · 공간 · 관리 · 예비비 · 연구수당) | B68: 만원 | C68: =Inputs_Yearly!$E$70+Inputs_Yearly!$E$74+Inputs_Yearly!$E$78+Inputs_Yearly!$E$82+Inputs_Yearly!$E$86+Inputs_Yearly!$E$90+Inputs_Yearly!$E$94+Inputs_Yearly!$E$98+Inputs_Yearly!$E$102+Inputs_Yearly!$E$106+Inputs_Yearly!$E$110+Inputs_Yearly!$E$114 -> 36342.75 | D68: =Inputs_Yearly!$F$70+Inputs_Yearly!$F$74+Inputs_Yearly!$F$78+Inputs_Yearly!$F$82+Inputs_Yearly!$F$86+Inputs_Yearly!$F$90+Inputs_Yearly!$F$94+Inputs_Yearly!$F$98+Inputs_Yearly!$F$102+Inputs_Yearly!$F$106+Inputs_Yearly!$F$110+Inputs_Yearly!$F$114 -> 41116 | E68: =Inputs_Yearly!$G$70+Inputs_Yearly!$G$74+Inputs_Yearly!$G$78+Inputs_Yearly!$G$82+Inputs_Yearly!$G$86+Inputs_Yearly!$G$90+Inputs_Yearly!$G$94+Inputs_Yearly!$G$98+Inputs_Yearly!$G$102+Inputs_Yearly!$G$106+Inputs_Yearly!$G$110+Inputs_Yearly!$G$114 -> 135000 | F68: =Inputs_Yearly!$H$70+Inputs_Yearly!$H$74+Inputs_Yearly!$H$78+Inputs_Yearly!$H$82+Inputs_Yearly!$H$86+Inputs_Yearly!$H$90+Inputs_Yearly!$H$94+Inputs_Yearly!$H$98+Inputs_Yearly!$H$102+Inputs_Yearly!$H$106+Inputs_Yearly!$H$110+Inputs_Yearly!$H$114 -> 167000 | G68: =Inputs_Yearly!$I$70+Inputs_Yearly!$I$74+Inputs_Yearly!$I$78+Inputs_Yearly!$I$82+Inputs_Yearly!$I$86+Inputs_Yearly!$I$90+Inputs_Yearly!$I$94+Inputs_Yearly!$I$98+Inputs_Yearly!$I$102+Inputs_Yearly!$I$106+Inputs_Yearly!$I$110+Inputs_Yearly!$I$114 -> 210000 | H68: =SUM(C68:G68) -> 589458.75
A69: Opex 합계 | B69: 만원 | C69: =C67+C68 -> 92167.75 | D69: =D67+D68 -> 138166 | E69: =E67+E68 -> 305000 | F69: =F67+F68 -> 439000 | G69: =G67+G68 -> 567000 | H69: =SUM(C69:G69) -> 1541333.8
A70: 영업이익 (근사) | B70: 만원 | C70: =C66-C69 -> -92167.75 | D70: =D66-D69 -> -140036.11 | E70: =E66-E69 -> -291436.27 | F70: =F66-F69 -> -307993.62 | G70: =G66-G69 -> -66562.262 | H70: =SUM(C70:G70) -> -898196.01
A71: 현금흐름 (영업이익 + 감가 − Rental 자산) | B71: 만원 | C71: =C70+C55-C53 -> -92167.75 | D71: =D70+D55-D53 -> -141238.42 | E71: =E70+E55-E53 -> -307895.62 | F71: =F70+F55-F53 -> -304670.72 | G71: =G70+G55-G53 -> -63239.357 | H71: =SUM(C71:G71) -> -909211.87
A72: 누적 현금흐름 | B72: 만원 | C72: =0+C71 -> -92167.75 | D72: =C72+D71 -> -233406.17 | E72: =D72+E71 -> -541301.79 | F72: =E72+F71 -> -845972.51 | G72: =F72+G71 -> -909211.87
A73: MIX
A74: INSTALL 매출 (Interface + 설치 + Robot) | B74: 만원 | C74: =C35+C36+C37 -> 0 | D74: =D35+D36+D37 -> 2831.4 | E74: =E35+E36+E37 -> 91295.75 | F74: =F35+F36+F37 -> 532639.48 | G74: =G35+G36+G37 -> 1488416.2 | H74: =SUM(C74:G74) -> 2115182.9
A75: Interface + 설치 매출 | B75: 만원 | C75: =C35+C36 -> 0 | D75: =D35+D36 -> 954 | E75: =E35+E36 -> 33670 | F75: =F35+F36 -> 153233.6 | G75: =G35+G36 -> 426793.57 | H75: =SUM(C75:G75) -> 614651.17
A76: OPERATE 매출 (Rental + Care + Consumables) | B76: 만원 | C76: =C38+C39+C40 -> 0 | D76: =D38+D39+D40 -> 245.61 | E76: =E38+E39+E40 -> 5014.5375 | F76: =F38+F39+F40 -> 19013.985 | G76: =G38+G39+G40 -> 55005.45 | H76: =SUM(C76:G76) -> 79279.583
A77: EXPAND 매출 (Skill + Tool) | B77: 만원 | C77: =C41 -> 0 | D77: =D41 -> 0 | E77: =E41 -> 36 | F77: =F41 -> 723 | G77: =G41 -> 4335.04 | H77: =SUM(C77:G77) -> 5094.04
A78: OPERATE + EXPAND 비중 | B78: % | C78: =IF(C42=0,0,(C76+C77)/C42) -> 0 | D78: =IF(D42=0,0,(D76+D77)/D42) -> 0.079820995 | E78: =IF(E42=0,0,(E76+E77)/E42) -> 0.052420676 | F78: =IF(F42=0,0,(F76+F77)/F42) -> 0.035731039 | G78: =IF(G42=0,0,(G76+G77)/G42) -> 0.038339675
A79: Robot + Recurring + Upgrade 비중 | B79: % | C79: =IF(C42=0,0,(C37+C76+C41)/C42) -> 0 | D79: =IF(D42=0,0,(D37+D76+D41)/D42) -> 0.68995876 | E79: =IF(E42=0,0,(E37+E76+E41)/E42) -> 0.65053142 | F79: =IF(F42=0,0,(F37+F76+F41)/F42) -> 0.72259209 | G79: =IF(G42=0,0,(G37+G76+G41)/G42) -> 0.72425023

Sheet Household
A1: Household Economics — 대표 1세대, 5년, Base (만원)
A2: 기대값 기준 (Skill · Tool은 구매율 반영). 구매 모델은 Care 가입 세대 기준. Y3 / Y5 = 해당 연도의 원가 수준을 5년간 적용. Remodeling = 직접판매 (획득비용), Retrofit = Partner 경유 (수수료), New-build = Project 수주비용 ÷ Option 세대.
A4: 항목 | B4: Remodeling 구매 · Y3 | C4: Remodeling 구매 · Y5 | D4: Remodeling Rental · Y3 | E4: Remodeling Rental · Y5 | F4: Retrofit 구매 · Y3 | G4: New-build 구매 · Y3 | H4: 산식
A5: REVENUE
A6: INSTALL · Interface · Integration | B6: =Inputs!$E$34 -> 450 | C6: =Inputs!$E$34 -> 450 | D6: =Inputs!$E$34 -> 450 | E6: =Inputs!$E$34 -> 450 | F6: =Inputs!$E$36 -> 150 | G6: =Inputs!$E$35 -> 220
A7: INSTALL · Installation · Calibration | B7: =Inputs!$E$38 -> 80 | C7: =Inputs!$E$38 -> 80 | D7: =Inputs!$E$38 -> 80 | E7: =Inputs!$E$38 -> 80 | F7: =Inputs!$E$39 -> 120 | G7: =Inputs!$E$38 -> 80
A8: INSTALL · Robot System (구매) | B8: =Inputs!$E$37 -> 1490 | C8: =Inputs!$E$37 -> 1490 | D8: =0 -> 0 | E8: =0 -> 0 | F8: =Inputs!$E$37 -> 1490 | G8: =Inputs!$E$37 -> 1490
A9: OPERATE · Rental (60개월) | B9: =0 -> 0 | C9: =0 -> 0 | D9: =Inputs!$E$40*Inputs!$E$41 -> 1980 | E9: =Inputs!$E$40*Inputs!$E$41 -> 1980 | F9: =0 -> 0 | G9: =0 -> 0
A10: OPERATE · Care Basic (5년) | B10: =5*Inputs!$E$42 -> 240 | C10: =5*Inputs!$E$42 -> 240 | D10: =0 -> 0 | E10: =0 -> 0 | F10: =5*Inputs!$E$42 -> 240 | G10: =5*Inputs!$E$42 -> 240
A11: OPERATE · Consumables (5년, 구매율 반영) | B11: =5*Inputs!$E$50*(Inputs!$E$44*Inputs!$E$45+Inputs!$E$46*Inputs!$E$47+Inputs!$E$48*Inputs!$E$49) -> 126 | C11: =5*Inputs!$E$50*(Inputs!$E$44*Inputs!$E$45+Inputs!$E$46*Inputs!$E$47+Inputs!$E$48*Inputs!$E$49) -> 126 | D11: =5*Inputs!$E$50*(Inputs!$E$46*Inputs!$E$47+Inputs!$E$48*Inputs!$E$49) -> 63 | E11: =5*Inputs!$E$50*(Inputs!$E$46*Inputs!$E$47+Inputs!$E$48*Inputs!$E$49) -> 63 | F11: =5*Inputs!$E$50*(Inputs!$E$44*Inputs!$E$45+Inputs!$E$46*Inputs!$E$47+Inputs!$E$48*Inputs!$E$49) -> 126 | G11: =5*Inputs!$E$50*(Inputs!$E$44*Inputs!$E$45+Inputs!$E$46*Inputs!$E$47+Inputs!$E$48*Inputs!$E$49) -> 126
A12: EXPAND · ASSIST Skill (기대값) | B12: =Inputs!$E$53*Inputs!$E$52 -> 12 | C12: =Inputs!$E$53*Inputs!$E$52 -> 12 | D12: =Inputs!$E$53*Inputs!$E$52 -> 12 | E12: =Inputs!$E$53*Inputs!$E$52 -> 12 | F12: =Inputs!$E$53*Inputs!$E$52 -> 12 | G12: =Inputs!$E$53*Inputs!$E$52 -> 12
A13: EXPAND · Tool / End-effector (기대값) | B13: =Inputs!$E$55*Inputs!$E$54 -> 20 | C13: =Inputs!$E$55*Inputs!$E$54 -> 20 | D13: =Inputs!$E$55*Inputs!$E$54 -> 20 | E13: =Inputs!$E$55*Inputs!$E$54 -> 20 | F13: =Inputs!$E$55*Inputs!$E$54 -> 20 | G13: =Inputs!$E$55*Inputs!$E$54 -> 20
A14: 5년 매출 | B14: =B6+B7+B8+B9+B10+B11+B12+B13 -> 2418 | C14: =C6+C7+C8+C9+C10+C11+C12+C13 -> 2418 | D14: =D6+D7+D8+D9+D10+D11+D12+D13 -> 2605 | E14: =E6+E7+E8+E9+E10+E11+E12+E13 -> 2605 | F14: =F6+F7+F8+F9+F10+F11+F12+F13 -> 2158 | G14: =G6+G7+G8+G9+G10+G11+G12+G13 -> 2188
A15: COST
A16: Interface 원가 | B16: =Inputs!$E$59*(Inputs_Yearly!$G$9+Inputs!$E$60*(1-Inputs_Yearly!$G$9))+Inputs!$E$61*(1-Inputs_Yearly!$G$9) -> 277 | C16: =Inputs!$E$59*(Inputs_Yearly!$I$9+Inputs!$E$60*(1-Inputs_Yearly!$I$9))+Inputs!$E$61*(1-Inputs_Yearly!$I$9) -> 244 | D16: =Inputs!$E$59*(Inputs_Yearly!$G$9+Inputs!$E$60*(1-Inputs_Yearly!$G$9))+Inputs!$E$61*(1-Inputs_Yearly!$G$9) -> 277 | E16: =Inputs!$E$59*(Inputs_Yearly!$I$9+Inputs!$E$60*(1-Inputs_Yearly!$I$9))+Inputs!$E$61*(1-Inputs_Yearly!$I$9) -> 244 | F16: =Inputs!$E$63 -> 70 | G16: =Inputs!$E$62 -> 130
A17: Installation · Calibration 원가 | B17: =Inputs_Yearly!$G$17 -> 60 | C17: =Inputs_Yearly!$I$17 -> 38 | D17: =Inputs_Yearly!$G$17 -> 60 | E17: =Inputs_Yearly!$I$17 -> 38 | F17: =Inputs_Yearly!$G$21 -> 95 | G17: =Inputs_Yearly!$G$17 -> 60
A18: 물류 | B18: =Inputs!$E$64 -> 25 | C18: =Inputs!$E$64 -> 25 | D18: =Inputs!$E$64 -> 25 | E18: =Inputs!$E$64 -> 25 | F18: =Inputs!$E$64 -> 25 | G18: =Inputs!$E$64 -> 25
A19: Robot BOM (Rental은 잔존가치 차감) | B19: =Inputs_Yearly!$G$13 -> 1180 | C19: =Inputs_Yearly!$I$13 -> 915 | D19: =Inputs_Yearly!$G$13*(1-Inputs!$E$75) -> 1003 | E19: =Inputs_Yearly!$I$13*(1-Inputs!$E$75) -> 777.75 | F19: =Inputs_Yearly!$G$13 -> 1180 | G19: =Inputs_Yearly!$G$13 -> 1180
A20: Rental 금융비용 (5년) | B20: =0 -> 0 | C20: =0 -> 0 | D20: =Inputs_Yearly!$G$13*(1+Inputs!$E$75)/2*Inputs!$E$76*5 -> 271.4 | E20: =Inputs_Yearly!$I$13*(1+Inputs!$E$75)/2*Inputs!$E$76*5 -> 210.45 | F20: =0 -> 0 | G20: =0 -> 0
A21: Warranty Reserve | B21: =Inputs!$E$65*Inputs!$E$37 -> 59.6 | C21: =Inputs!$E$65*Inputs!$E$37 -> 59.6 | D21: =Inputs!$E$65*Inputs_Yearly!$G$13 -> 47.2 | E21: =Inputs!$E$65*Inputs_Yearly!$I$13 -> 36.6 | F21: =Inputs!$E$65*Inputs!$E$37 -> 59.6 | G21: =Inputs!$E$65*Inputs!$E$37 -> 59.6
A22: Care Service 원가 (5년) | B22: =5*(Inputs_Yearly!$G$25*Inputs_Yearly!$G$29+Inputs!$E$66*Inputs!$E$67+Inputs!$E$68) -> 184 | C22: =5*(Inputs_Yearly!$I$25*Inputs_Yearly!$I$29+Inputs!$E$66*Inputs!$E$67+Inputs!$E$68) -> 134 | D22: =5*(Inputs_Yearly!$G$25*Inputs_Yearly!$G$29+Inputs!$E$66*Inputs!$E$67+Inputs!$E$68) -> 184 | E22: =5*(Inputs_Yearly!$I$25*Inputs_Yearly!$I$29+Inputs!$E$66*Inputs!$E$67+Inputs!$E$68) -> 134 | F22: =5*(Inputs_Yearly!$G$25*Inputs_Yearly!$G$29+Inputs!$E$66*Inputs!$E$67+Inputs!$E$68) -> 184 | G22: =5*(Inputs_Yearly!$G$25*Inputs_Yearly!$G$29+Inputs!$E$66*Inputs!$E$67+Inputs!$E$68) -> 184
A23: Consumables 원가 | B23: =B11*Inputs!$E$69 -> 44.1 | C23: =C11*Inputs!$E$69 -> 44.1 | D23: =(D11+5*Inputs!$E$44*Inputs!$E$45)*Inputs!$E$69 -> 53.55 | E23: =(E11+5*Inputs!$E$44*Inputs!$E$45)*Inputs!$E$69 -> 53.55 | F23: =F11*Inputs!$E$69 -> 44.1 | G23: =G11*Inputs!$E$69 -> 44.1
A24: Skill · Tool 원가 | B24: =Inputs!$E$53*Inputs!$E$52*Inputs!$E$70+Inputs!$E$55*Inputs!$E$54*Inputs!$E$71 -> 10.2 | C24: =Inputs!$E$53*Inputs!$E$52*Inputs!$E$70+Inputs!$E$55*Inputs!$E$54*Inputs!$E$71 -> 10.2 | D24: =Inputs!$E$53*Inputs!$E$52*Inputs!$E$70+Inputs!$E$55*Inputs!$E$54*Inputs!$E$71 -> 10.2 | E24: =Inputs!$E$53*Inputs!$E$52*Inputs!$E$70+Inputs!$E$55*Inputs!$E$54*Inputs!$E$71 -> 10.2 | F24: =Inputs!$E$53*Inputs!$E$52*Inputs!$E$70+Inputs!$E$55*Inputs!$E$54*Inputs!$E$71 -> 10.2 | G24: =Inputs!$E$53*Inputs!$E$52*Inputs!$E$70+Inputs!$E$55*Inputs!$E$54*Inputs!$E$71 -> 10.2
A25: 채널비용 (획득비용 · Partner 수수료 · 수주비용) | B25: =Inputs!$E$73 -> 150 | C25: =Inputs!$E$73 -> 150 | D25: =Inputs!$E$73 -> 150 | E25: =Inputs!$E$73 -> 150 | F25: =Inputs!$E$72*(Inputs!$E$36+Inputs!$E$37+Inputs!$E$39) -> 176 | G25: =Inputs!$E$74/(Inputs!$E$80*Inputs!$E$81) -> 25
A26: 5년 비용 | B26: =B16+B17+B18+B19+B20+B21+B22+B23+B24+B25 -> 1989.9 | C26: =C16+C17+C18+C19+C20+C21+C22+C23+C24+C25 -> 1619.9 | D26: =D16+D17+D18+D19+D20+D21+D22+D23+D24+D25 -> 2081.35 | E26: =E16+E17+E18+E19+E20+E21+E22+E23+E24+E25 -> 1679.55 | F26: =F16+F17+F18+F19+F20+F21+F22+F23+F24+F25 -> 1843.9 | G26: =G16+G17+G18+G19+G20+G21+G22+G23+G24+G25 -> 1717.9
A27: RESULT
A28: Year 0 매출 (INSTALL) | B28: =B6+B7+B8 -> 2020 | C28: =C6+C7+C8 -> 2020 | D28: =D6+D7+D8 -> 530 | E28: =E6+E7+E8 -> 530 | F28: =F6+F7+F8 -> 1760 | G28: =G6+G7+G8 -> 1790
A29: OPERATE 매출 (5년) | B29: =B9+B10+B11 -> 366 | C29: =C9+C10+C11 -> 366 | D29: =D9+D10+D11 -> 2043 | E29: =E9+E10+E11 -> 2043 | F29: =F9+F10+F11 -> 366 | G29: =G9+G10+G11 -> 366
A30: EXPAND 매출 (5년) | B30: =B12+B13 -> 32 | C30: =C12+C13 -> 32 | D30: =D12+D13 -> 32 | E30: =E12+E13 -> 32 | F30: =F12+F13 -> 32 | G30: =G12+G13 -> 32
A31: 5년 매출총이익 (채널비용 전) | B31: =B14-(B26-B25) -> 578.1 | C31: =C14-(C26-C25) -> 948.1 | D31: =D14-(D26-D25) -> 673.65 | E31: =E14-(E26-E25) -> 1075.45 | F31: =F14-(F26-F25) -> 490.1 | G31: =G14-(G26-G25) -> 495.1
A32: 5년 Lifetime Contribution | B32: =B14-B26 -> 428.1 | C32: =C14-C26 -> 798.1 | D32: =D14-D26 -> 523.65 | E32: =E14-E26 -> 925.45 | F32: =F14-F26 -> 314.1 | G32: =G14-G26 -> 470.1
A33: Contribution Margin | B33: =IF(B14=0,0,B32/B14) -> 0.17704715 | C33: =IF(C14=0,0,C32/C14) -> 0.33006617 | D33: =IF(D14=0,0,D32/D14) -> 0.20101727 | E33: =IF(E14=0,0,E32/E14) -> 0.35525912 | F33: =IF(F14=0,0,F32/F14) -> 0.14555144 | G33: =IF(G14=0,0,G32/G14) -> 0.21485375
A34: 5년 서비스 원가 (Care · Consumables · Warranty) | B34: =B22+B23+B21 -> 287.7 | C34: =C22+C23+C21 -> 237.7 | D34: =D22+D23+D21 -> 284.75 | E34: =E22+E23+E21 -> 224.15 | F34: =F22+F23+F21 -> 287.7 | G34: =G22+G23+G21 -> 287.7

Sheet Unit_Economics
A1: Unit Economics — Base (만원)
A3: Rental 월 원가 Build-up (Robot 1대, MH 보유 가정) | B3: Y3 원가 | C3: Y5 원가 | D3: 산식
A4: Robot BOM | B4: =Inputs_Yearly!$G$13 -> 1180 | C4: =Inputs_Yearly!$I$13 -> 915
A5: 감가 (잔존가치 차감, 60개월) | B5: =B4*(1-Inputs!$E$75)/Inputs!$E$41 -> 16.716667 | C5: =C4*(1-Inputs!$E$75)/Inputs!$E$41 -> 12.9625
A6: 금융비용 (평균잔액 × 금리 / 12) | B6: =B4*(1+Inputs!$E$75)/2*Inputs!$E$76/12 -> 4.5233333 | C6: =C4*(1+Inputs!$E$75)/2*Inputs!$E$76/12 -> 3.5075
A7: Care 원가 / 12 | B7: =(Inputs_Yearly!$G$25*Inputs_Yearly!$G$29+Inputs!$E$66*Inputs!$E$67+Inputs!$E$68)/12 -> 3.0666667 | C7: =(Inputs_Yearly!$I$25*Inputs_Yearly!$I$29+Inputs!$E$66*Inputs!$E$67+Inputs!$E$68)/12 -> 2.2333333
A8: Grip Kit 원가 / 12 | B8: =Inputs!$E$44*Inputs!$E$45*Inputs!$E$69/12 -> 0.525 | C8: =Inputs!$E$44*Inputs!$E$45*Inputs!$E$69/12 -> 0.525
A9: Failure Reserve | B9: =Inputs!$E$65*B4/Inputs!$E$41 -> 0.78666667 | C9: =Inputs!$E$65*C4/Inputs!$E$41 -> 0.61
A10: 월 원가 합계 | B10: =B5+B6+B7+B8+B9 -> 25.618333 | C10: =C5+C6+C7+C8+C9 -> 19.838333
A11: 월 Rental 요금 (가정) | B11: =Inputs!$E$40 -> 33 | C11: =Inputs!$E$40 -> 33
A12: 월 Contribution | B12: =B11-B10 -> 7.3816667 | C12: =C11-C10 -> 13.161667
A13: Contribution Margin | B13: =B12/B11 -> 0.22368687 | C13: =C12/C11 -> 0.39883838
A14: 마진 20% 확보 요금 | B14: =B10/0.8 -> 32.022917 | C14: =C10/0.8 -> 24.797917
A15: Payback (BOM ÷ (요금 − Care − Grip), 개월) | B15: =B4/(B11-B7-B8) -> 40.124681 | C15: =C4/(C11-C7-C8) -> 30.256269 | D15: 금융비용 제외 현금 회수
A16: Payback 허들 충족 최대 BOM | B16: =Inputs!$E$77*(B11-B7-B8) -> 1058.7 | C16: =Inputs!$E$77*(C11-C7-C8) -> 1088.7 | D16: Rental Partner 요구 Payback 기준
A18: Care Basic (Robot 1대·년) | B18: Y3 원가 | C18: Y5 원가 | D18: 산식
A19: Care 연 요금 | B19: =Inputs!$E$42 -> 48 | C19: =Inputs!$E$42 -> 48
A20: 정기 방문 원가 | B20: =Inputs_Yearly!$G$25*Inputs_Yearly!$G$29 -> 22 | C20: =Inputs_Yearly!$I$25*Inputs_Yearly!$I$29 -> 12
A21: 고장 방문 원가 | B21: =Inputs!$E$66*Inputs!$E$67 -> 10.8 | C21: =Inputs!$E$66*Inputs!$E$67 -> 10.8
A22: Cloud·Software | B22: =Inputs!$E$68 -> 4 | C22: =Inputs!$E$68 -> 4
A23: Care 원가 합계 | B23: =SUM(B20:B22) -> 36.8 | C23: =SUM(C20:C22) -> 26.8
A24: Care Contribution | B24: =B19-B23 -> 11.2 | C24: =C19-C23 -> 21.2
A25: Care Margin | B25: =B24/B19 -> 0.23333333 | C25: =C24/C19 -> 0.44166667
A27: Consumables (Robot 1대·년, 구매 고객) | B27: 연 매출 | C27: 원가 | D27: Contribution
A28: Grip Kit (List × 구매율) | B28: =Inputs!$E$44*Inputs!$E$45*Inputs!$E$50 -> 12.6 | C28: =B28*Inputs!$E$69 -> 4.41 | D28: =B28-C28 -> 8.19
A29: Cleaning Kit (List × 구매율) | B29: =Inputs!$E$46*Inputs!$E$47*Inputs!$E$50 -> 7 | C29: =B29*Inputs!$E$69 -> 2.45 | D29: =B29-C29 -> 4.55
A30: Protection Kit (List × 구매율) | B30: =Inputs!$E$48*Inputs!$E$49*Inputs!$E$50 -> 5.6 | C30: =B30*Inputs!$E$69 -> 1.96 | D30: =B30-C30 -> 3.64
A31: 합계 | B31: =SUM(B28:B30) -> 25.2 | C31: =SUM(C28:C30) -> 8.82 | D31: =SUM(D28:D30) -> 16.38
A33: Rental Partner 경제성 (Base, Y4~) | B33: 값 | D33: 산식
A34: Robot 매입가 (ASP × 공급가율) | B34: =Inputs!$E$37*Inputs!$E$56 -> 1311.2
A35: 월 순유입 (요금 − MH 서비스료) | B35: =Inputs!$E$40-Inputs!$E$57 -> 27
A36: 잔존가치 (매입가 × 잔존율) | B36: =B34*Inputs!$E$75 -> 196.68
A37: 월 IRR | B37: =RATE(Inputs!$E$41,B35,-B34,B36) -> 0.010276112 | D37: RATE(기간, 월 유입, −매입가, 잔존가치)
A38: 연 IRR (연체·해지 미반영) | B38: =(1+B37)^12-1 -> 0.13052719
A39: 단순 회수기간 (개월) | B39: =B34/B35 -> 48.562963 | D39: 매입가 ÷ 월 순유입
A40: Partner 요구 Payback (가정, 개월) | B40: =Inputs!$E$77 -> 36 | D40: 회수기간 > 요구치이면 매입가율 · 서비스료 · 기간 협의 필요
A42: Robot BOM 구성 (ASSUMPTION, 만원/대) | B42: Pilot (Y1) | C42: Y3 | D42: Y5
A43: 6축 Arm (가반 3~5kg, Controller 포함) | B43: 950 | C43: 600 | D43: 450 | E43: FAIRINO FR5 $6,999 · xArm 6 $8,399 · UR3e $23k~33k 공개가 → OEM · 국산 Partner
A44: Adaptive Hand (손가락 2~3 · 교체형 Pad · 힘/미끄럼 감지 · Quick Changer) | B44: 200 | C44: 120 | D44: 85 | E44: Robotiq 2F-85 약 $5,825 (2026 판매가) · Inspire RH56 $4,500~9,899 대비 자체 설계 목표가
A45: Rail · Carriage · Servo (Remodeling · New-build, 2.4~3.6m) | B45: 180 | C45: 150 | D45: 120 | E45: Belt 구동 7축 Rail. Retrofit은 Compact Mount
A46: Vision (Depth Camera 2대 + Mount) | B46: 110 | C46: 80 | D46: 60 | E46: Orbbec Gemini 335 $384~400 · RealSense D405 $514
A47: Compute (Edge GPU) | B47: 100 | C47: 80 | D47: 70 | E47: Edge AI Module 가정
A48: Safety (Zone Sensor · Safety Controller) | B48: 70 | C48: 60 | D48: 50 | E48: ToF/Radar Zone Sensor + Safety Relay 가정
A49: Robot Home (Dock) · Harness · Enclosure | B49: 70 | C49: 50 | D49: 45
A50: 조립 · 시험 (Pilot은 Opex 인건비 처리) | B50: 0 | C50: 40 | D50: 35
A51: 합계 | B51: =SUM(B43:B50) -> 1680 | C51: =SUM(C43:C50) -> 1180 | D51: =SUM(D43:D50) -> 915
A52: 검증: Inputs_Yearly Base BOM과 차이 (0이어야 함) | B52: =B51-Inputs_Yearly!$E$13 -> 0 | C52: =C51-Inputs_Yearly!$G$13 -> 0 | D52: =D51-Inputs_Yearly!$I$13 -> 0

Sheet Market
A1: Market Sizing — Bottom-up 4개 시장 (Base)
A2: 큰 TAM 대신 세대 수 × 적용률 × 단가. 아파트 재고는 기회 기반이지 구매시장 규모가 아님. 핵심 비율은 모두 ASSUMPTION (검증 계획 부록).
A3: 항목 | B3: 값 | C3: 단위 | D3: Tag | E3: 산식 / 출처
A4: 총주택 (2025) | B4: =Inputs!$E$5 -> 20181 | C4: 천호 | D4: FACT | E4: 국가데이터처 2025 인구주택총조사
A5: 아파트 비중 | B5: =Inputs!$E$6 -> 0.658 | C5: % | D5: FACT
A6: 아파트 수 (2025) | B6: =B4*B5 -> 13279.098 | C6: 천호 | D6: DERIVED | E6: 총주택 × 비중
A7: 교차검증 ①: 20년+ 아파트(2023) ÷ 교체주기 | B7: =Inputs!$E$10/Inputs!$E$15 -> 290.45455 | C7: 천/년 | D7: DERIVED
A8: 교차검증 ②: 매매거래 × 아파트 비중 × 교체율 + 비거래 교체 | B8: =Inputs!$E$11*Inputs!$E$16*Inputs!$E$17+Inputs!$E$18 -> 303.28 | C8: 천/년 | D8: DERIVED
A9: 연간 Kitchen 교체 세대 (설정) | B9: =Inputs!$E$19 -> 300 | C9: 천/년 | D9: ASSUMPTION | E9: ①·② 교차검증 후 설정
A10: Premium 비중 | B10: =Inputs!$E$20 -> 0.1 | C10: % | D10: ASSUMPTION
A11: Premium Kitchen 교체 세대 | B11: =B9*B10 -> 30 | C11: 천/년 | D11: DERIVED
A12: Remodeling 적용 가능률 | B12: =Inputs!$E$21 -> 0.6 | C12: % | D12: ASSUMPTION
A13: ① Remodeling 대상 세대 | B13: =B11*B12 -> 18 | C13: 천/년 | D13: DERIVED
A14: Remodeling 패키지 기대 매출/세대 | B14: =Inputs!$E$34+Inputs_Yearly!$I$45*(Inputs!$E$37+Inputs!$E$38) -> 1784.5 | C14: 만원 | D14: DERIVED | E14: Interface + Attach × (Robot + 설치)
A15: ① SAM Remodeling | B15: =B13*B14/10 -> 3212.1 | C15: 억원/년 | D15: DERIVED | E15: 천세대 × 만원 ÷ 10 = 억원
A16: Premium 세대 비중 (재고) | B16: =Inputs!$E$22 -> 0.1 | C16: % | D16: ASSUMPTION
A17: Premium 세대 식기세척기 보유율 | B17: =Inputs!$E$23 -> 0.6 | C17: % | D17: ASSUMPTION | E17: TO BE VALIDATED
A18: Retrofit 호환률 | B18: =Inputs!$E$24 -> 0.4 | C18: % | D18: ASSUMPTION | E18: 받은 평면 5종 중 2종 (표본 작음)
A19: Retrofit 호환 세대 Pool (재고) | B19: =B6*B16*B17*B18 -> 318.69835 | C19: 천세대 | D19: DERIVED | E19: 아파트 × Premium × 식세기 × 호환
A20: Retrofit 연간 전환율 | B20: =Inputs!$E$25 -> 0.005 | C20: % | D20: ASSUMPTION
A21: ② Retrofit 대상 세대 | B21: =B19*B20 -> 1.5934918 | C21: 천/년 | D21: DERIVED
A22: Retrofit 패키지 매출/세대 | B22: =Inputs!$E$36+Inputs!$E$37+Inputs!$E$39 -> 1760 | C22: 만원 | D22: DERIVED | E22: Interface Kit + Robot + 설치
A23: ② SAM Retrofit | B23: =B21*B22/10 -> 280.45455 | C23: 억원/년 | D23: DERIVED
A24: 연간 신규 아파트 입주 | B24: =Inputs!$E$26 -> 200 | C24: 천/년 | D24: DERIVED | E24: 2025 23.6만 · 2026E 18.3만
A25: Premium 단지 비중 | B25: =Inputs!$E$27 -> 0.15 | C25: % | D25: ASSUMPTION
A26: 신축 Premium 세대 | B26: =B24*B25 -> 30 | C26: 천/년 | D26: DERIVED
A27: Interface Option 선택률 | B27: =Inputs!$E$81 -> 0.1 | C27: % | D27: ASSUMPTION
A28: ③ New-build 대상 세대 | B28: =B26*B27 -> 3 | C28: 천/년 | D28: DERIVED
A29: New-build 패키지 기대 매출/세대 | B29: =Inputs!$E$35+Inputs!$E$82*(Inputs!$E$37+Inputs!$E$38) -> 612.5 | C29: 만원 | D29: DERIVED | E29: Option + 입주 Attach × (Robot + 설치)
A30: ③ SAM New-build | B30: =B28*B29/10 -> 183.75 | C30: 억원/년 | D30: DERIVED
A31: 구매 고객 ARPU (Care × 가입률 + Consumables × 구매율) | B31: =Inputs!$E$51*Inputs!$E$42+Inputs!$E$50*(Inputs!$E$44*Inputs!$E$45+Inputs!$E$46*Inputs!$E$47+Inputs!$E$48*Inputs!$E$49) -> 58.8 | C31: 만원/년 | D31: DERIVED
A32: ④ Installed Base 1,000대당 연 OPERATE 매출 (구매 고객) | B32: =B31*1000/10000 -> 5.88 | C32: 억원/년 | D32: DERIVED
A33: Y5 Installed Robot (Base Plan) | B33: =FM_Base!$G$28 -> 662.625 | C33: 대 | D33: TARGET | E33: FM_Base Y5
A34: ④ Y5 OPERATE 매출 (Base Plan) | B34: =FM_Base!$G$76/10000 -> 3.478281 | C34: 억원/년 | D34: TARGET | E34: FM_Base Y5 (Rental Partner 보유분은 서비스료만)
A35: 전체 패키지 단가 (Interface + Robot + 설치) | B35: =Inputs!$E$34+Inputs!$E$37+Inputs!$E$38 -> 2020 | C35: 만원 | D35: ASSUMPTION
A36: 참고 TAM: Premium 세대 (Remodeling + New-build) × 전체 패키지 | B36: =(B11+B26)*B35/10 -> 12120 | C36: 억원/년 | D36: DERIVED | E36: 본문 미사용 (참고)
A37: SAM 합계 (① + ② + ③) | B37: =B15+B23+B30 -> 3676.3045 | C37: 억원/년 | D37: DERIVED
A38: SOM: Y5 매출 (Base Plan) | B38: =FM_Base!$G$42/10000 -> 91.490638 | C38: 억원/년 | D38: TARGET | E38: FM_Base Y5
A39: SOM 세대 / SAM 세대 | B39: =FM_Base!$G$9/((B13+B21+B28)*1000) -> 0.024785899 | C39: % | D39: DERIVED

Sheet Sensitivity
A1: Sensitivity — Remodeling 구매 1세대 5년 Contribution (Base, Y3 원가, 직접판매)
A2: 각 행은 한 변수만 바꾼 파라미터 세트 (파란 글자 = 변경값). Contribution 수식은 Household 시트와 동일 구조.
A4: Case | B4: p_robot | C4: bom | D4: p_rr | E4: cac | F4: p_care | G4: visit_cost | H4: smr | I4: comm_cost | J4: corrective | K4: warranty | L4: cons_attach | M4: Contribution | N4: Δ vs Base
A5: Base | B5: =Inputs!$E$37 -> 1490 | C5: =Inputs_Yearly!$G$13 -> 1180 | D5: =Inputs!$E$34 -> 450 | E5: =Inputs!$E$73 -> 150 | F5: =Inputs!$E$42 -> 48 | G5: =Inputs_Yearly!$G$29 -> 11 | H5: =Inputs_Yearly!$G$9 -> 0.65 | I5: =Inputs_Yearly!$G$17 -> 60 | J5: =Inputs!$E$66 -> 0.6 | K5: =Inputs!$E$65 -> 0.04 | L5: =Inputs!$E$50 -> 0.7 | M5: =(D5+Inputs!$E$38+B5+5*F5+5*L5*(Inputs!$E$44*Inputs!$E$45+Inputs!$E$46*Inputs!$E$47+Inputs!$E$48*Inputs!$E$49)+Inputs!$E$53*Inputs!$E$52+Inputs!$E$55*Inputs!$E$54)-(Inputs!$E$59*(H5+Inputs!$E$60*(1-H5))+Inputs!$E$61*(1-H5)+I5+Inputs!$E$64+C5+K5*B5+5*(Inputs_Yearly!$G$25*G5+J5*Inputs!$E$67+Inputs!$E$68)+5*L5*(Inputs!$E$44*Inputs!$E$45+Inputs!$E$46*Inputs!$E$47+Inputs!$E$48*Inputs!$E$49)*Inputs!$E$69+Inputs!$E$53*Inputs!$E$52*Inputs!$E$70+Inputs!$E$55*Inputs!$E$54*Inputs!$E$71+E5) -> 428.1 | N5: =M5-$M$5 -> 0
A6: Robot ASP (WTP) — 불리 | B6: =Inputs!$E$37*0.8 -> 1192 | C6: =Inputs_Yearly!$G$13 -> 1180 | D6: =Inputs!$E$34 -> 450 | E6: =Inputs!$E$73 -> 150 | F6: =Inputs!$E$42 -> 48 | G6: =Inputs_Yearly!$G$29 -> 11 | H6: =Inputs_Yearly!$G$9 -> 0.65 | I6: =Inputs_Yearly!$G$17 -> 60 | J6: =Inputs!$E$66 -> 0.6 | K6: =Inputs!$E$65 -> 0.04 | L6: =Inputs!$E$50 -> 0.7 | M6: =(D6+Inputs!$E$38+B6+5*F6+5*L6*(Inputs!$E$44*Inputs!$E$45+Inputs!$E$46*Inputs!$E$47+Inputs!$E$48*Inputs!$E$49)+Inputs!$E$53*Inputs!$E$52+Inputs!$E$55*Inputs!$E$54)-(Inputs!$E$59*(H6+Inputs!$E$60*(1-H6))+Inputs!$E$61*(1-H6)+I6+Inputs!$E$64+C6+K6*B6+5*(Inputs_Yearly!$G$25*G6+J6*Inputs!$E$67+Inputs!$E$68)+5*L6*(Inputs!$E$44*Inputs!$E$45+Inputs!$E$46*Inputs!$E$47+Inputs!$E$48*Inputs!$E$49)*Inputs!$E$69+Inputs!$E$53*Inputs!$E$52*Inputs!$E$70+Inputs!$E$55*Inputs!$E$54*Inputs!$E$71+E6) -> 142.02 | N6: =M6-$M$5 -> -286.08
A7: Robot ASP (WTP) — 유리 | B7: =Inputs!$E$37*1.2 -> 1788 | C7: =Inputs_Yearly!$G$13 -> 1180 | D7: =Inputs!$E$34 -> 450 | E7: =Inputs!$E$73 -> 150 | F7: =Inputs!$E$42 -> 48 | G7: =Inputs_Yearly!$G$29 -> 11 | H7: =Inputs_Yearly!$G$9 -> 0.65 | I7: =Inputs_Yearly!$G$17 -> 60 | J7: =Inputs!$E$66 -> 0.6 | K7: =Inputs!$E$65 -> 0.04 | L7: =Inputs!$E$50 -> 0.7 | M7: =(D7+Inputs!$E$38+B7+5*F7+5*L7*(Inputs!$E$44*Inputs!$E$45+Inputs!$E$46*Inputs!$E$47+Inputs!$E$48*Inputs!$E$49)+Inputs!$E$53*Inputs!$E$52+Inputs!$E$55*Inputs!$E$54)-(Inputs!$E$59*(H7+Inputs!$E$60*(1-H7))+Inputs!$E$61*(1-H7)+I7+Inputs!$E$64+C7+K7*B7+5*(Inputs_Yearly!$G$25*G7+J7*Inputs!$E$67+Inputs!$E$68)+5*L7*(Inputs!$E$44*Inputs!$E$45+Inputs!$E$46*Inputs!$E$47+Inputs!$E$48*Inputs!$E$49)*Inputs!$E$69+Inputs!$E$53*Inputs!$E$52*Inputs!$E$70+Inputs!$E$55*Inputs!$E$54*Inputs!$E$71+E7) -> 714.18 | N7: =M7-$M$5 -> 286.08
A8: Robot BOM — 불리 | B8: =Inputs!$E$37 -> 1490 | C8: =Inputs_Yearly!$G$13*1.2 -> 1416 | D8: =Inputs!$E$34 -> 450 | E8: =Inputs!$E$73 -> 150 | F8: =Inputs!$E$42 -> 48 | G8: =Inputs_Yearly!$G$29 -> 11 | H8: =Inputs_Yearly!$G$9 -> 0.65 | I8: =Inputs_Yearly!$G$17 -> 60 | J8: =Inputs!$E$66 -> 0.6 | K8: =Inputs!$E$65 -> 0.04 | L8: =Inputs!$E$50 -> 0.7 | M8: =(D8+Inputs!$E$38+B8+5*F8+5*L8*(Inputs!$E$44*Inputs!$E$45+Inputs!$E$46*Inputs!$E$47+Inputs!$E$48*Inputs!$E$49)+Inputs!$E$53*Inputs!$E$52+Inputs!$E$55*Inputs!$E$54)-(Inputs!$E$59*(H8+Inputs!$E$60*(1-H8))+Inputs!$E$61*(1-H8)+I8+Inputs!$E$64+C8+K8*B8+5*(Inputs_Yearly!$G$25*G8+J8*Inputs!$E$67+Inputs!$E$68)+5*L8*(Inputs!$E$44*Inputs!$E$45+Inputs!$E$46*Inputs!$E$47+Inputs!$E$48*Inputs!$E$49)*Inputs!$E$69+Inputs!$E$53*Inputs!$E$52*Inputs!$E$70+Inputs!$E$55*Inputs!$E$54*Inputs!$E$71+E8) -> 192.1 | N8: =M8-$M$5 -> -236
A9: Robot BOM — 유리 | B9: =Inputs!$E$37 -> 1490 | C9: =Inputs_Yearly!$G$13*0.8 -> 944 | D9: =Inputs!$E$34 -> 450 | E9: =Inputs!$E$73 -> 150 | F9: =Inputs!$E$42 -> 48 | G9: =Inputs_Yearly!$G$29 -> 11 | H9: =Inputs_Yearly!$G$9 -> 0.65 | I9: =Inputs_Yearly!$G$17 -> 60 | J9: =Inputs!$E$66 -> 0.6 | K9: =Inputs!$E$65 -> 0.04 | L9: =Inputs!$E$50 -> 0.7 | M9: =(D9+Inputs!$E$38+B9+5*F9+5*L9*(Inputs!$E$44*Inputs!$E$45+Inputs!$E$46*Inputs!$E$47+Inputs!$E$48*Inputs!$E$49)+Inputs!$E$53*Inputs!$E$52+Inputs!$E$55*Inputs!$E$54)-(Inputs!$E$59*(H9+Inputs!$E$60*(1-H9))+Inputs!$E$61*(1-H9)+I9+Inputs!$E$64+C9+K9*B9+5*(Inputs_Yearly!$G$25*G9+J9*Inputs!$E$67+Inputs!$E$68)+5*L9*(Inputs!$E$44*Inputs!$E$45+Inputs!$E$46*Inputs!$E$47+Inputs!$E$48*Inputs!$E$49)*Inputs!$E$69+Inputs!$E$53*Inputs!$E$52*Inputs!$E$70+Inputs!$E$55*Inputs!$E$54*Inputs!$E$71+E9) -> 664.1 | N9: =M9-$M$5 -> 236
A10: Interface 가격 — 불리 | B10: =Inputs!$E$37 -> 1490 | C10: =Inputs_Yearly!$G$13 -> 1180 | D10: =Inputs!$E$34*0.8 -> 360 | E10: =Inputs!$E$73 -> 150 | F10: =Inputs!$E$42 -> 48 | G10: =Inputs_Yearly!$G$29 -> 11 | H10: =Inputs_Yearly!$G$9 -> 0.65 | I10: =Inputs_Yearly!$G$17 -> 60 | J10: =Inputs!$E$66 -> 0.6 | K10: =Inputs!$E$65 -> 0.04 | L10: =Inputs!$E$50 -> 0.7 | M10: =(D10+Inputs!$E$38+B10+5*F10+5*L10*(Inputs!$E$44*Inputs!$E$45+Inputs!$E$46*Inputs!$E$47+Inputs!$E$48*Inputs!$E$49)+Inputs!$E$53*Inputs!$E$52+Inputs!$E$55*Inputs!$E$54)-(Inputs!$E$59*(H10+Inputs!$E$60*(1-H10))+Inputs!$E$61*(1-H10)+I10+Inputs!$E$64+C10+K10*B10+5*(Inputs_Yearly!$G$25*G10+J10*Inputs!$E$67+Inputs!$E$68)+5*L10*(Inputs!$E$44*Inputs!$E$45+Inputs!$E$46*Inputs!$E$47+Inputs!$E$48*Inputs!$E$49)*Inputs!$E$69+Inputs!$E$53*Inputs!$E$52*Inputs!$E$70+Inputs!$E$55*Inputs!$E$54*Inputs!$E$71+E10) -> 338.1 | N10: =M10-$M$5 -> -90
A11: Interface 가격 — 유리 | B11: =Inputs!$E$37 -> 1490 | C11: =Inputs_Yearly!$G$13 -> 1180 | D11: =Inputs!$E$34*1.2 -> 540 | E11: =Inputs!$E$73 -> 150 | F11: =Inputs!$E$42 -> 48 | G11: =Inputs_Yearly!$G$29 -> 11 | H11: =Inputs_Yearly!$G$9 -> 0.65 | I11: =Inputs_Yearly!$G$17 -> 60 | J11: =Inputs!$E$66 -> 0.6 | K11: =Inputs!$E$65 -> 0.04 | L11: =Inputs!$E$50 -> 0.7 | M11: =(D11+Inputs!$E$38+B11+5*F11+5*L11*(Inputs!$E$44*Inputs!$E$45+Inputs!$E$46*Inputs!$E$47+Inputs!$E$48*Inputs!$E$49)+Inputs!$E$53*Inputs!$E$52+Inputs!$E$55*Inputs!$E$54)-(Inputs!$E$59*(H11+Inputs!$E$60*(1-H11))+Inputs!$E$61*(1-H11)+I11+Inputs!$E$64+C11+K11*B11+5*(Inputs_Yearly!$G$25*G11+J11*Inputs!$E$67+Inputs!$E$68)+5*L11*(Inputs!$E$44*Inputs!$E$45+Inputs!$E$46*Inputs!$E$47+Inputs!$E$48*Inputs!$E$49)*Inputs!$E$69+Inputs!$E$53*Inputs!$E$52*Inputs!$E$70+Inputs!$E$55*Inputs!$E$54*Inputs!$E$71+E11) -> 518.1 | N11: =M11-$M$5 -> 90
A12: 직접판매 획득비용 — 불리 | B12: =Inputs!$E$37 -> 1490 | C12: =Inputs_Yearly!$G$13 -> 1180 | D12: =Inputs!$E$34 -> 450 | E12: =Inputs!$E$73*1.5 -> 225 | F12: =Inputs!$E$42 -> 48 | G12: =Inputs_Yearly!$G$29 -> 11 | H12: =Inputs_Yearly!$G$9 -> 0.65 | I12: =Inputs_Yearly!$G$17 -> 60 | J12: =Inputs!$E$66 -> 0.6 | K12: =Inputs!$E$65 -> 0.04 | L12: =Inputs!$E$50 -> 0.7 | M12: =(D12+Inputs!$E$38+B12+5*F12+5*L12*(Inputs!$E$44*Inputs!$E$45+Inputs!$E$46*Inputs!$E$47+Inputs!$E$48*Inputs!$E$49)+Inputs!$E$53*Inputs!$E$52+Inputs!$E$55*Inputs!$E$54)-(Inputs!$E$59*(H12+Inputs!$E$60*(1-H12))+Inputs!$E$61*(1-H12)+I12+Inputs!$E$64+C12+K12*B12+5*(Inputs_Yearly!$G$25*G12+J12*Inputs!$E$67+Inputs!$E$68)+5*L12*(Inputs!$E$44*Inputs!$E$45+Inputs!$E$46*Inputs!$E$47+Inputs!$E$48*Inputs!$E$49)*Inputs!$E$69+Inputs!$E$53*Inputs!$E$52*Inputs!$E$70+Inputs!$E$55*Inputs!$E$54*Inputs!$E$71+E12) -> 353.1 | N12: =M12-$M$5 -> -75
A13: 직접판매 획득비용 — 유리 | B13: =Inputs!$E$37 -> 1490 | C13: =Inputs_Yearly!$G$13 -> 1180 | D13: =Inputs!$E$34 -> 450 | E13: =Inputs!$E$73*0.5 -> 75 | F13: =Inputs!$E$42 -> 48 | G13: =Inputs_Yearly!$G$29 -> 11 | H13: =Inputs_Yearly!$G$9 -> 0.65 | I13: =Inputs_Yearly!$G$17 -> 60 | J13: =Inputs!$E$66 -> 0.6 | K13: =Inputs!$E$65 -> 0.04 | L13: =Inputs!$E$50 -> 0.7 | M13: =(D13+Inputs!$E$38+B13+5*F13+5*L13*(Inputs!$E$44*Inputs!$E$45+Inputs!$E$46*Inputs!$E$47+Inputs!$E$48*Inputs!$E$49)+Inputs!$E$53*Inputs!$E$52+Inputs!$E$55*Inputs!$E$54)-(Inputs!$E$59*(H13+Inputs!$E$60*(1-H13))+Inputs!$E$61*(1-H13)+I13+Inputs!$E$64+C13+K13*B13+5*(Inputs_Yearly!$G$25*G13+J13*Inputs!$E$67+Inputs!$E$68)+5*L13*(Inputs!$E$44*Inputs!$E$45+Inputs!$E$46*Inputs!$E$47+Inputs!$E$48*Inputs!$E$49)*Inputs!$E$69+Inputs!$E$53*Inputs!$E$52*Inputs!$E$70+Inputs!$E$55*Inputs!$E$54*Inputs!$E$71+E13) -> 503.1 | N13: =M13-$M$5 -> 75
A14: Failure Rate — 불리 | B14: =Inputs!$E$37 -> 1490 | C14: =Inputs_Yearly!$G$13 -> 1180 | D14: =Inputs!$E$34 -> 450 | E14: =Inputs!$E$73 -> 150 | F14: =Inputs!$E$42 -> 48 | G14: =Inputs_Yearly!$G$29 -> 11 | H14: =Inputs_Yearly!$G$9 -> 0.65 | I14: =Inputs_Yearly!$G$17 -> 60 | J14: =1.2 -> 1.2 | K14: =0.06 -> 0.06 | L14: =Inputs!$E$50 -> 0.7 | M14: =(D14+Inputs!$E$38+B14+5*F14+5*L14*(Inputs!$E$44*Inputs!$E$45+Inputs!$E$46*Inputs!$E$47+Inputs!$E$48*Inputs!$E$49)+Inputs!$E$53*Inputs!$E$52+Inputs!$E$55*Inputs!$E$54)-(Inputs!$E$59*(H14+Inputs!$E$60*(1-H14))+Inputs!$E$61*(1-H14)+I14+Inputs!$E$64+C14+K14*B14+5*(Inputs_Yearly!$G$25*G14+J14*Inputs!$E$67+Inputs!$E$68)+5*L14*(Inputs!$E$44*Inputs!$E$45+Inputs!$E$46*Inputs!$E$47+Inputs!$E$48*Inputs!$E$49)*Inputs!$E$69+Inputs!$E$53*Inputs!$E$52*Inputs!$E$70+Inputs!$E$55*Inputs!$E$54*Inputs!$E$71+E14) -> 344.3 | N14: =M14-$M$5 -> -83.8
A15: Failure Rate — 유리 | B15: =Inputs!$E$37 -> 1490 | C15: =Inputs_Yearly!$G$13 -> 1180 | D15: =Inputs!$E$34 -> 450 | E15: =Inputs!$E$73 -> 150 | F15: =Inputs!$E$42 -> 48 | G15: =Inputs_Yearly!$G$29 -> 11 | H15: =Inputs_Yearly!$G$9 -> 0.65 | I15: =Inputs_Yearly!$G$17 -> 60 | J15: =0.3 -> 0.3 | K15: =0.025 -> 0.025 | L15: =Inputs!$E$50 -> 0.7 | M15: =(D15+Inputs!$E$38+B15+5*F15+5*L15*(Inputs!$E$44*Inputs!$E$45+Inputs!$E$46*Inputs!$E$47+Inputs!$E$48*Inputs!$E$49)+Inputs!$E$53*Inputs!$E$52+Inputs!$E$55*Inputs!$E$54)-(Inputs!$E$59*(H15+Inputs!$E$60*(1-H15))+Inputs!$E$61*(1-H15)+I15+Inputs!$E$64+C15+K15*B15+5*(Inputs_Yearly!$G$25*G15+J15*Inputs!$E$67+Inputs!$E$68)+5*L15*(Inputs!$E$44*Inputs!$E$45+Inputs!$E$46*Inputs!$E$47+Inputs!$E$48*Inputs!$E$49)*Inputs!$E$69+Inputs!$E$53*Inputs!$E$52*Inputs!$E$70+Inputs!$E$55*Inputs!$E$54*Inputs!$E$71+E15) -> 477.45 | N15: =M15-$M$5 -> 49.35
A16: Care 요금 — 불리 | B16: =Inputs!$E$37 -> 1490 | C16: =Inputs_Yearly!$G$13 -> 1180 | D16: =Inputs!$E$34 -> 450 | E16: =Inputs!$E$73 -> 150 | F16: =Inputs!$E$42*0.8 -> 38.4 | G16: =Inputs_Yearly!$G$29 -> 11 | H16: =Inputs_Yearly!$G$9 -> 0.65 | I16: =Inputs_Yearly!$G$17 -> 60 | J16: =Inputs!$E$66 -> 0.6 | K16: =Inputs!$E$65 -> 0.04 | L16: =Inputs!$E$50 -> 0.7 | M16: =(D16+Inputs!$E$38+B16+5*F16+5*L16*(Inputs!$E$44*Inputs!$E$45+Inputs!$E$46*Inputs!$E$47+Inputs!$E$48*Inputs!$E$49)+Inputs!$E$53*Inputs!$E$52+Inputs!$E$55*Inputs!$E$54)-(Inputs!$E$59*(H16+Inputs!$E$60*(1-H16))+Inputs!$E$61*(1-H16)+I16+Inputs!$E$64+C16+K16*B16+5*(Inputs_Yearly!$G$25*G16+J16*Inputs!$E$67+Inputs!$E$68)+5*L16*(Inputs!$E$44*Inputs!$E$45+Inputs!$E$46*Inputs!$E$47+Inputs!$E$48*Inputs!$E$49)*Inputs!$E$69+Inputs!$E$53*Inputs!$E$52*Inputs!$E$70+Inputs!$E$55*Inputs!$E$54*Inputs!$E$71+E16) -> 380.1 | N16: =M16-$M$5 -> -48
A17: Care 요금 — 유리 | B17: =Inputs!$E$37 -> 1490 | C17: =Inputs_Yearly!$G$13 -> 1180 | D17: =Inputs!$E$34 -> 450 | E17: =Inputs!$E$73 -> 150 | F17: =Inputs!$E$42*1.2 -> 57.6 | G17: =Inputs_Yearly!$G$29 -> 11 | H17: =Inputs_Yearly!$G$9 -> 0.65 | I17: =Inputs_Yearly!$G$17 -> 60 | J17: =Inputs!$E$66 -> 0.6 | K17: =Inputs!$E$65 -> 0.04 | L17: =Inputs!$E$50 -> 0.7 | M17: =(D17+Inputs!$E$38+B17+5*F17+5*L17*(Inputs!$E$44*Inputs!$E$45+Inputs!$E$46*Inputs!$E$47+Inputs!$E$48*Inputs!$E$49)+Inputs!$E$53*Inputs!$E$52+Inputs!$E$55*Inputs!$E$54)-(Inputs!$E$59*(H17+Inputs!$E$60*(1-H17))+Inputs!$E$61*(1-H17)+I17+Inputs!$E$64+C17+K17*B17+5*(Inputs_Yearly!$G$25*G17+J17*Inputs!$E$67+Inputs!$E$68)+5*L17*(Inputs!$E$44*Inputs!$E$45+Inputs!$E$46*Inputs!$E$47+Inputs!$E$48*Inputs!$E$49)*Inputs!$E$69+Inputs!$E$53*Inputs!$E$52*Inputs!$E$70+Inputs!$E$55*Inputs!$E$54*Inputs!$E$71+E17) -> 476.1 | N17: =M17-$M$5 -> 48
A18: Care 방문 원가 — 불리 | B18: =Inputs!$E$37 -> 1490 | C18: =Inputs_Yearly!$G$13 -> 1180 | D18: =Inputs!$E$34 -> 450 | E18: =Inputs!$E$73 -> 150 | F18: =Inputs!$E$42 -> 48 | G18: =Inputs_Yearly!$G$29*1.3 -> 14.3 | H18: =Inputs_Yearly!$G$9 -> 0.65 | I18: =Inputs_Yearly!$G$17 -> 60 | J18: =Inputs!$E$66 -> 0.6 | K18: =Inputs!$E$65 -> 0.04 | L18: =Inputs!$E$50 -> 0.7 | M18: =(D18+Inputs!$E$38+B18+5*F18+5*L18*(Inputs!$E$44*Inputs!$E$45+Inputs!$E$46*Inputs!$E$47+Inputs!$E$48*Inputs!$E$49)+Inputs!$E$53*Inputs!$E$52+Inputs!$E$55*Inputs!$E$54)-(Inputs!$E$59*(H18+Inputs!$E$60*(1-H18))+Inputs!$E$61*(1-H18)+I18+Inputs!$E$64+C18+K18*B18+5*(Inputs_Yearly!$G$25*G18+J18*Inputs!$E$67+Inputs!$E$68)+5*L18*(Inputs!$E$44*Inputs!$E$45+Inputs!$E$46*Inputs!$E$47+Inputs!$E$48*Inputs!$E$49)*Inputs!$E$69+Inputs!$E$53*Inputs!$E$52*Inputs!$E$70+Inputs!$E$55*Inputs!$E$54*Inputs!$E$71+E18) -> 395.1 | N18: =M18-$M$5 -> -33
A19: Care 방문 원가 — 유리 | B19: =Inputs!$E$37 -> 1490 | C19: =Inputs_Yearly!$G$13 -> 1180 | D19: =Inputs!$E$34 -> 450 | E19: =Inputs!$E$73 -> 150 | F19: =Inputs!$E$42 -> 48 | G19: =Inputs_Yearly!$G$29*0.7 -> 7.7 | H19: =Inputs_Yearly!$G$9 -> 0.65 | I19: =Inputs_Yearly!$G$17 -> 60 | J19: =Inputs!$E$66 -> 0.6 | K19: =Inputs!$E$65 -> 0.04 | L19: =Inputs!$E$50 -> 0.7 | M19: =(D19+Inputs!$E$38+B19+5*F19+5*L19*(Inputs!$E$44*Inputs!$E$45+Inputs!$E$46*Inputs!$E$47+Inputs!$E$48*Inputs!$E$49)+Inputs!$E$53*Inputs!$E$52+Inputs!$E$55*Inputs!$E$54)-(Inputs!$E$59*(H19+Inputs!$E$60*(1-H19))+Inputs!$E$61*(1-H19)+I19+Inputs!$E$64+C19+K19*B19+5*(Inputs_Yearly!$G$25*G19+J19*Inputs!$E$67+Inputs!$E$68)+5*L19*(Inputs!$E$44*Inputs!$E$45+Inputs!$E$46*Inputs!$E$47+Inputs!$E$48*Inputs!$E$49)*Inputs!$E$69+Inputs!$E$53*Inputs!$E$52*Inputs!$E$70+Inputs!$E$55*Inputs!$E$54*Inputs!$E$71+E19) -> 461.1 | N19: =M19-$M$5 -> 33
A20: Interface 표준부품 사용률 — 불리 | B20: =Inputs!$E$37 -> 1490 | C20: =Inputs_Yearly!$G$13 -> 1180 | D20: =Inputs!$E$34 -> 450 | E20: =Inputs!$E$73 -> 150 | F20: =Inputs!$E$42 -> 48 | G20: =Inputs_Yearly!$G$29 -> 11 | H20: =Inputs_Yearly!$G$9-0.15 -> 0.5 | I20: =Inputs_Yearly!$G$17 -> 60 | J20: =Inputs!$E$66 -> 0.6 | K20: =Inputs!$E$65 -> 0.04 | L20: =Inputs!$E$50 -> 0.7 | M20: =(D20+Inputs!$E$38+B20+5*F20+5*L20*(Inputs!$E$44*Inputs!$E$45+Inputs!$E$46*Inputs!$E$47+Inputs!$E$48*Inputs!$E$49)+Inputs!$E$53*Inputs!$E$52+Inputs!$E$55*Inputs!$E$54)-(Inputs!$E$59*(H20+Inputs!$E$60*(1-H20))+Inputs!$E$61*(1-H20)+I20+Inputs!$E$64+C20+K20*B20+5*(Inputs_Yearly!$G$25*G20+J20*Inputs!$E$67+Inputs!$E$68)+5*L20*(Inputs!$E$44*Inputs!$E$45+Inputs!$E$46*Inputs!$E$47+Inputs!$E$48*Inputs!$E$49)*Inputs!$E$69+Inputs!$E$53*Inputs!$E$52*Inputs!$E$70+Inputs!$E$55*Inputs!$E$54*Inputs!$E$71+E20) -> 395.1 | N20: =M20-$M$5 -> -33
A21: Interface 표준부품 사용률 — 유리 | B21: =Inputs!$E$37 -> 1490 | C21: =Inputs_Yearly!$G$13 -> 1180 | D21: =Inputs!$E$34 -> 450 | E21: =Inputs!$E$73 -> 150 | F21: =Inputs!$E$42 -> 48 | G21: =Inputs_Yearly!$G$29 -> 11 | H21: =Inputs_Yearly!$G$9+0.15 -> 0.8 | I21: =Inputs_Yearly!$G$17 -> 60 | J21: =Inputs!$E$66 -> 0.6 | K21: =Inputs!$E$65 -> 0.04 | L21: =Inputs!$E$50 -> 0.7 | M21: =(D21+Inputs!$E$38+B21+5*F21+5*L21*(Inputs!$E$44*Inputs!$E$45+Inputs!$E$46*Inputs!$E$47+Inputs!$E$48*Inputs!$E$49)+Inputs!$E$53*Inputs!$E$52+Inputs!$E$55*Inputs!$E$54)-(Inputs!$E$59*(H21+Inputs!$E$60*(1-H21))+Inputs!$E$61*(1-H21)+I21+Inputs!$E$64+C21+K21*B21+5*(Inputs_Yearly!$G$25*G21+J21*Inputs!$E$67+Inputs!$E$68)+5*L21*(Inputs!$E$44*Inputs!$E$45+Inputs!$E$46*Inputs!$E$47+Inputs!$E$48*Inputs!$E$49)*Inputs!$E$69+Inputs!$E$53*Inputs!$E$52*Inputs!$E$70+Inputs!$E$55*Inputs!$E$54*Inputs!$E$71+E21) -> 461.1 | N21: =M21-$M$5 -> 33
A22: 설치 · Calibration 원가 — 불리 | B22: =Inputs!$E$37 -> 1490 | C22: =Inputs_Yearly!$G$13 -> 1180 | D22: =Inputs!$E$34 -> 450 | E22: =Inputs!$E$73 -> 150 | F22: =Inputs!$E$42 -> 48 | G22: =Inputs_Yearly!$G$29 -> 11 | H22: =Inputs_Yearly!$G$9 -> 0.65 | I22: =Inputs_Yearly!$G$17*1.5 -> 90 | J22: =Inputs!$E$66 -> 0.6 | K22: =Inputs!$E$65 -> 0.04 | L22: =Inputs!$E$50 -> 0.7 | M22: =(D22+Inputs!$E$38+B22+5*F22+5*L22*(Inputs!$E$44*Inputs!$E$45+Inputs!$E$46*Inputs!$E$47+Inputs!$E$48*Inputs!$E$49)+Inputs!$E$53*Inputs!$E$52+Inputs!$E$55*Inputs!$E$54)-(Inputs!$E$59*(H22+Inputs!$E$60*(1-H22))+Inputs!$E$61*(1-H22)+I22+Inputs!$E$64+C22+K22*B22+5*(Inputs_Yearly!$G$25*G22+J22*Inputs!$E$67+Inputs!$E$68)+5*L22*(Inputs!$E$44*Inputs!$E$45+Inputs!$E$46*Inputs!$E$47+Inputs!$E$48*Inputs!$E$49)*Inputs!$E$69+Inputs!$E$53*Inputs!$E$52*Inputs!$E$70+Inputs!$E$55*Inputs!$E$54*Inputs!$E$71+E22) -> 398.1 | N22: =M22-$M$5 -> -30
A23: 설치 · Calibration 원가 — 유리 | B23: =Inputs!$E$37 -> 1490 | C23: =Inputs_Yearly!$G$13 -> 1180 | D23: =Inputs!$E$34 -> 450 | E23: =Inputs!$E$73 -> 150 | F23: =Inputs!$E$42 -> 48 | G23: =Inputs_Yearly!$G$29 -> 11 | H23: =Inputs_Yearly!$G$9 -> 0.65 | I23: =Inputs_Yearly!$G$17*0.5 -> 30 | J23: =Inputs!$E$66 -> 0.6 | K23: =Inputs!$E$65 -> 0.04 | L23: =Inputs!$E$50 -> 0.7 | M23: =(D23+Inputs!$E$38+B23+5*F23+5*L23*(Inputs!$E$44*Inputs!$E$45+Inputs!$E$46*Inputs!$E$47+Inputs!$E$48*Inputs!$E$49)+Inputs!$E$53*Inputs!$E$52+Inputs!$E$55*Inputs!$E$54)-(Inputs!$E$59*(H23+Inputs!$E$60*(1-H23))+Inputs!$E$61*(1-H23)+I23+Inputs!$E$64+C23+K23*B23+5*(Inputs_Yearly!$G$25*G23+J23*Inputs!$E$67+Inputs!$E$68)+5*L23*(Inputs!$E$44*Inputs!$E$45+Inputs!$E$46*Inputs!$E$47+Inputs!$E$48*Inputs!$E$49)*Inputs!$E$69+Inputs!$E$53*Inputs!$E$52*Inputs!$E$70+Inputs!$E$55*Inputs!$E$54*Inputs!$E$71+E23) -> 458.1 | N23: =M23-$M$5 -> 30
A24: Consumables 구매율 — 불리 | B24: =Inputs!$E$37 -> 1490 | C24: =Inputs_Yearly!$G$13 -> 1180 | D24: =Inputs!$E$34 -> 450 | E24: =Inputs!$E$73 -> 150 | F24: =Inputs!$E$42 -> 48 | G24: =Inputs_Yearly!$G$29 -> 11 | H24: =Inputs_Yearly!$G$9 -> 0.65 | I24: =Inputs_Yearly!$G$17 -> 60 | J24: =Inputs!$E$66 -> 0.6 | K24: =Inputs!$E$65 -> 0.04 | L24: =0.5 -> 0.5 | M24: =(D24+Inputs!$E$38+B24+5*F24+5*L24*(Inputs!$E$44*Inputs!$E$45+Inputs!$E$46*Inputs!$E$47+Inputs!$E$48*Inputs!$E$49)+Inputs!$E$53*Inputs!$E$52+Inputs!$E$55*Inputs!$E$54)-(Inputs!$E$59*(H24+Inputs!$E$60*(1-H24))+Inputs!$E$61*(1-H24)+I24+Inputs!$E$64+C24+K24*B24+5*(Inputs_Yearly!$G$25*G24+J24*Inputs!$E$67+Inputs!$E$68)+5*L24*(Inputs!$E$44*Inputs!$E$45+Inputs!$E$46*Inputs!$E$47+Inputs!$E$48*Inputs!$E$49)*Inputs!$E$69+Inputs!$E$53*Inputs!$E$52*Inputs!$E$70+Inputs!$E$55*Inputs!$E$54*Inputs!$E$71+E24) -> 404.7 | N24: =M24-$M$5 -> -23.4
A25: Consumables 구매율 — 유리 | B25: =Inputs!$E$37 -> 1490 | C25: =Inputs_Yearly!$G$13 -> 1180 | D25: =Inputs!$E$34 -> 450 | E25: =Inputs!$E$73 -> 150 | F25: =Inputs!$E$42 -> 48 | G25: =Inputs_Yearly!$G$29 -> 11 | H25: =Inputs_Yearly!$G$9 -> 0.65 | I25: =Inputs_Yearly!$G$17 -> 60 | J25: =Inputs!$E$66 -> 0.6 | K25: =Inputs!$E$65 -> 0.04 | L25: =0.9 -> 0.9 | M25: =(D25+Inputs!$E$38+B25+5*F25+5*L25*(Inputs!$E$44*Inputs!$E$45+Inputs!$E$46*Inputs!$E$47+Inputs!$E$48*Inputs!$E$49)+Inputs!$E$53*Inputs!$E$52+Inputs!$E$55*Inputs!$E$54)-(Inputs!$E$59*(H25+Inputs!$E$60*(1-H25))+Inputs!$E$61*(1-H25)+I25+Inputs!$E$64+C25+K25*B25+5*(Inputs_Yearly!$G$25*G25+J25*Inputs!$E$67+Inputs!$E$68)+5*L25*(Inputs!$E$44*Inputs!$E$45+Inputs!$E$46*Inputs!$E$47+Inputs!$E$48*Inputs!$E$49)*Inputs!$E$69+Inputs!$E$53*Inputs!$E$52*Inputs!$E$70+Inputs!$E$55*Inputs!$E$54*Inputs!$E$71+E25) -> 451.5 | N25: =M25-$M$5 -> 23.4
A28: 회사 Y5 Contribution 민감도 (Base, 만원) — STATIC SNAPSHOT: model.py sens_company() 결과. 입력 변경 시 model.py 재실행 필요
A29: 변수 (불리 ↔ 유리) | B29: 불리 Δ | C29: 유리 Δ
A30: Base Y5 Contribution | B30: 230691.8
A31: Customer WTP (Robot ASP · Interface ±20%) | B31: -142696.2 | C31: 142696.2
A32: Robot BOM ±20% | B32: -81695.7 | C32: 81695.7
A33: Partner 경유 Remodeling ±30% | B33: -46636.7 | C33: 46636.7
A34: Retrofit 물량 0 ↔ 2배 | B34: -33169.3 | C34: 33169.3
A35: Robot Attach Rate 65% ↔ 95% | B35: -30175 | C35: 15087.5
A36: Rental 비중 60% ↔ 20% | B36: -13965.8 | C36: 13965.8
A37: Failure Rate 1.2 ↔ 0.3회 | B37: -16468.6 | C37: 11378.9
A38: Interface 표준부품 사용률 -15pp/+10pp | B38: -13200 | C38: 8800
A39: 설치 · Calibration 원가 ±50% | B39: -9384.1 | C39: 9384.1
A40: 신축 Option 선택률 5% ↔ 15% | B40: -7675.2 | C40: 7675.2
A41: Care 방문 원가 ±30% | B41: -1296.7 | C41: 1296.7

Sheet Budget_24M
A1: 24개월 자금 계획 (만원) — 팀 계획 · 사용처 · TIPS 과제 편성 · 재원 · Seed 범위
A2: 팀 · 지출 표의 파란 값이 Inputs_Yearly Y1~Y2 지출의 원천 (model.py TEAM · COSTS). Founder 2인은 TIPS 요건 기준의 자리이며 인물 정보는 비어 있음. 모든 값 ASSUMPTION, 정부지원 규정은 FACT (2026 공고, 선정 미확정).
A4: Key | B4: 역할 | C4: 구분 | D4: 시작 월 | E4: 인당 연 인건비 | F4: FTE 비율 | G4: TIPS 참여율 | H4: Lean 포함 | I4: Y1 인월 | J4: Y2 인월 | K4: Y1 인건비 | L4: Y2 인건비 | M4: TIPS 인건비 Y1 | N4: TIPS 인건비 Y2
A5: F1 | B5: 대표 · 사업 총괄 [Founder 정보 필요] | C5: Founder | D5: 1 | E5: 6000 | F5: 1 | G5: 0.5 | H5: 예 | I5: =IF(D5<=12,13-D5,0)*F5 -> 12 | J5: =IF(D5<=13,12,MAX(0,25-D5))*F5 -> 12 | K5: =E5*I5/12 -> 6000 | L5: =E5*J5/12 -> 6000 | M5: =IF(OR(C5="R&D",C5="Founder"),K5*G5,0) -> 3000 | N5: =IF(OR(C5="R&D",C5="Founder"),L5*G5,0) -> 3000
A6: F2 | B6: 공동창업자 · 기술 총괄 [Founder 정보 필요] | C6: Founder | D6: 1 | E6: 6000 | F6: 1 | G6: 0.6 | H6: 예 | I6: =IF(D6<=12,13-D6,0)*F6 -> 12 | J6: =IF(D6<=13,12,MAX(0,25-D6))*F6 -> 12 | K6: =E6*I6/12 -> 6000 | L6: =E6*J6/12 -> 6000 | M6: =IF(OR(C6="R&D",C6="Founder"),K6*G6,0) -> 3600 | N6: =IF(OR(C6="R&D",C6="Founder"),L6*G6,0) -> 3600
A7: E1 | B7: Manipulation · 제어 리드 | C7: R&D | D7: 1 | E7: 9600 | F7: 1 | G7: 0.5 | H7: 예 | I7: =IF(D7<=12,13-D7,0)*F7 -> 12 | J7: =IF(D7<=13,12,MAX(0,25-D7))*F7 -> 12 | K7: =E7*I7/12 -> 9600 | L7: =E7*J7/12 -> 9600 | M7: =IF(OR(C7="R&D",C7="Founder"),K7*G7,0) -> 4800 | N7: =IF(OR(C7="R&D",C7="Founder"),L7*G7,0) -> 4800
A8: E2 | B8: Perception · ML 리드 | C8: R&D | D8: 2 | E8: 9600 | F8: 1 | G8: 0.5 | H8: 예 | I8: =IF(D8<=12,13-D8,0)*F8 -> 11 | J8: =IF(D8<=13,12,MAX(0,25-D8))*F8 -> 12 | K8: =E8*I8/12 -> 8800 | L8: =E8*J8/12 -> 9600 | M8: =IF(OR(C8="R&D",C8="Founder"),K8*G8,0) -> 4400 | N8: =IF(OR(C8="R&D",C8="Founder"),L8*G8,0) -> 4800
A9: E3 | B9: Hand · 기구 리드 (메카트로닉스) | C9: R&D | D9: 2 | E9: 9600 | F9: 1 | G9: 0.6 | H9: 예 | I9: =IF(D9<=12,13-D9,0)*F9 -> 11 | J9: =IF(D9<=13,12,MAX(0,25-D9))*F9 -> 12 | K9: =E9*I9/12 -> 8800 | L9: =E9*J9/12 -> 9600 | M9: =IF(OR(C9="R&D",C9="Founder"),K9*G9,0) -> 5280 | N9: =IF(OR(C9="R&D",C9="Founder"),L9*G9,0) -> 5760
A10: E4 | B10: 임베디드 · 전기 · 안전 | C10: R&D | D10: 4 | E10: 7800 | F10: 1 | G10: 0.5 | H10: 예 | I10: =IF(D10<=12,13-D10,0)*F10 -> 9 | J10: =IF(D10<=13,12,MAX(0,25-D10))*F10 -> 12 | K10: =E10*I10/12 -> 5850 | L10: =E10*J10/12 -> 7800 | M10: =IF(OR(C10="R&D",C10="Founder"),K10*G10,0) -> 2925 | N10: =IF(OR(C10="R&D",C10="Founder"),L10*G10,0) -> 3900
A11: E5 | B11: Robot SW · 통합 (Motion · Skill) | C11: R&D | D11: 6 | E11: 7800 | F11: 1 | G11: 0.5 | H11: 예 | I11: =IF(D11<=12,13-D11,0)*F11 -> 7 | J11: =IF(D11<=13,12,MAX(0,25-D11))*F11 -> 12 | K11: =E11*I11/12 -> 4550 | L11: =E11*J11/12 -> 7800 | M11: =IF(OR(C11="R&D",C11="Founder"),K11*G11,0) -> 2275 | N11: =IF(OR(C11="R&D",C11="Founder"),L11*G11,0) -> 3900
A12: B1 | B12: 제품 · 사업개발 (고객 검증 · 파트너) | C12: 사업 | D12: 7 | E12: 7200 | F12: 1 | G12: 0 | H12: 예 | I12: =IF(D12<=12,13-D12,0)*F12 -> 6 | J12: =IF(D12<=13,12,MAX(0,25-D12))*F12 -> 12 | K12: =E12*I12/12 -> 3600 | L12: =E12*J12/12 -> 7200 | M12: =IF(OR(C12="R&D",C12="Founder"),K12*G12,0) -> 0 | N12: =IF(OR(C12="R&D",C12="Founder"),L12*G12,0) -> 0
A13: E6 | B13: Hand 센싱 (Grip Force · Slip) | C13: R&D | D13: 10 | E13: 7800 | F13: 1 | G13: 0.5 | H13: 아니오 | I13: =IF(D13<=12,13-D13,0)*F13 -> 3 | J13: =IF(D13<=13,12,MAX(0,25-D13))*F13 -> 12 | K13: =E13*I13/12 -> 1950 | L13: =E13*J13/12 -> 7800 | M13: =IF(OR(C13="R&D",C13="Founder"),K13*G13,0) -> 975 | N13: =IF(OR(C13="R&D",C13="Founder"),L13*G13,0) -> 3900
A14: O1 | B14: 경영지원 (재무 · 과제 관리, 0.5 FTE) | C14: 경영지원 | D14: 10 | E14: 5400 | F14: 0.5 | G14: 0 | H14: 예 | I14: =IF(D14<=12,13-D14,0)*F14 -> 1.5 | J14: =IF(D14<=13,12,MAX(0,25-D14))*F14 -> 6 | K14: =E14*I14/12 -> 675 | L14: =E14*J14/12 -> 2700 | M14: =IF(OR(C14="R&D",C14="Founder"),K14*G14,0) -> 0 | N14: =IF(OR(C14="R&D",C14="Founder"),L14*G14,0) -> 0
A15: E7 | B15: 시험 · 신뢰성 (Test · QA) | C15: R&D | D15: 13 | E15: 7800 | F15: 1 | G15: 0.4 | H15: 예 (M19 시작) | I15: =IF(D15<=12,13-D15,0)*F15 -> 0 | J15: =IF(D15<=13,12,MAX(0,25-D15))*F15 -> 12 | K15: =E15*I15/12 -> 0 | L15: =E15*J15/12 -> 7800 | M15: =IF(OR(C15="R&D",C15="Founder"),K15*G15,0) -> 0 | N15: =IF(OR(C15="R&D",C15="Founder"),L15*G15,0) -> 3120
A16: S1 | B16: 설치 · Commissioning 엔지니어 | C16: 현장 | D16: 13 | E16: 6600 | F16: 1 | G16: 0 | H16: 예 | I16: =IF(D16<=12,13-D16,0)*F16 -> 0 | J16: =IF(D16<=13,12,MAX(0,25-D16))*F16 -> 12 | K16: =E16*I16/12 -> 0 | L16: =E16*J16/12 -> 6600 | M16: =IF(OR(C16="R&D",C16="Founder"),K16*G16,0) -> 0 | N16: =IF(OR(C16="R&D",C16="Founder"),L16*G16,0) -> 0
... A18: S2 | B18: 현장 서비스 Technician | C18: 현장 | D18: 19 | E18: 5400 | F18: 1 | G18: 0 | H18: 아니오 | I18: =IF(D18<=12,13-D18,0)*F18 -> 0 | J18: =IF(D18<=13,12,MAX(0,25-D18))*F18 -> 6 | K18: =E18*I18/12 -> 0 | L18: =E18*J18/12 -> 2700 | M18: =IF(OR(C18="R&D",C18="Founder"),K18*G18,0) -> 0 | N18: =IF(OR(C18="R&D",C18="Founder"),L18*G18,0) -> 0
B19: 합계 | I19: =SUM(I5:I18) -> 84.5 | J19: =SUM(J5:J18) -> 153 | K19: =SUM(K5:K18) -> 55825 | L19: =SUM(L5:L18) -> 97050 | M19: =SUM(M5:M18) -> 27255 | N19: =SUM(N5:N18) -> 39120
B20: 평균 FTE (인월 ÷ 12) | I20: =I19/12 -> 7.0416667 | J20: =J19/12 -> 12.75
B21: 검증: FM_Base 인건비 − 팀 계획 (0이어야 함) | K21: =FM_Base!$C$67-K19 -> 0 | L21: =FM_Base!$D$67-L19 -> 0
B23: B. 인건비 외 사용처 (Spec 33 항목) | E23: Y1 | F23: Y2 | G23: 합계 | H23: TIPS 비율 Y1 | I23: TIPS 비율 Y2 | J23: TIPS 편성 Y1 | K23: TIPS 편성 Y2 | L23: TIPS 비목
A24: robot_hw | B24: Robot Hardware — R&D 로봇 셀 (Arm · Vision · Compute) Y1 3식 + Y2 1식 | E24: 4800 | F24: 1600 | G24: =E24+F24 -> 6400 | H24: 0.8 | I24: 0.8 | J24: =E24*H24 -> 3840 | K24: =F24*I24 -> 1280 | L24: 연구재료비
A25: hand_proto | B25: Hand Prototype — 상용 Gripper 비교군 구매 · 자체 Hand v1~v3 가공 · 센서 · Pad 금형 | E25: 6000 | F25: 4000 | G25: =E25+F25 -> 10000 | H25: 0.9 | I25: 0.9 | J25: =E25*H25 -> 5400 | K25: =F25*I25 -> 3600 | L25: 연구재료비
A26: mockup | B26: Kitchen Mock-up — 실물 크기 목업 3종 (Remodeling · ㄱ자 · Retrofit) · 식기세척기 3모델 · 재구성 | E26: 5000 | F26: 2500 | G26: =E26+F26 -> 7500 | H26: 0.8 | I26: 0.8 | J26: =E26*H26 -> 4000 | K26: =F26*I26 -> 2000 | L26: 연구재료비
A27: swdata | B27: Software · Data — GPU · Cloud · Annotation · SW License | E27: 2500 | F27: 3000 | G27: =E27+F27 -> 5500 | H27: 0.8 | I27: 0.8 | J27: =E27*H27 -> 2000 | K27: =F27*I27 -> 2400 | L27: 연구활동비
A28: pilot | B28: Pilot — 가정 실증 운영 (설치 파트너 · 보험 · 모니터링). 실증 하드웨어는 원가로 별도 | E28: 0 | F28: 3500 | G28: =E28+F28 -> 3500 | H28: 0 | I28: 0 | J28: =E28*H28 -> 0 | K28: =F28*I28 -> 0 | L28: -
A29: custval | B29: Customer · Partner — 고객 인터뷰 · 정리 시간 기록 · WTP 조사 (n≥300) · 예약금 Test · 파트너 개발 · 전시 | E29: 2000 | F29: 4000 | G29: =E29+F29 -> 6000 | H29: 0 | I29: 0 | J29: =E29*H29 -> 0 | K29: =F29*I29 -> 0 | L29: -
A30: cert | B30: Certification — 안전 Gap 분석 (IEC 63682 초안 · ISO 13482) · EMC/전기안전 사전시험 · 식품접촉 소재 시험 | E30: 1500 | F30: 4500 | G30: =E30+F30 -> 6000 | H30: 1 | I30: 0.45 | J30: =E30*H30 -> 1500 | K30: =F30*I30 -> 2025 | L30: 연구활동비
A31: ip | B31: IP — 선행기술조사 · 국내 출원 5건 · PCT 1건 | E31: 1500 | F31: 3000 | G31: =E31+F31 -> 4500 | H31: 0.8 | I31: 0.8 | J31: =E31*H31 -> 1200 | K31: =F31*I31 -> 2400 | L31: 연구활동비
A32: space | B32: Space — 실험실 · 목업 공간 (약 50평) 임차 · 관리 | E32: 4800 | F32: 4800 | G32: =E32+F32 -> 9600 | H32: 0 | I32: 0 | J32: =E32*H32 -> 0 | K32: =F32*I32 -> 0 | L32: 간접비 일부
A33: ga | B33: Operating — 법무 · 회계 · 보험 · 사무 · 출장 · 채용 | E33: 4000 | F33: 5000 | G33: =E33+F33 -> 9000 | H33: 0 | I33: 0 | J33: =E33*H33 -> 0 | K33: =F33*I33 -> 0 | L33: 간접비 일부
B34: 인건비 외 합계 | E34: =SUM(E24:E33) -> 32100 | F34: =SUM(F24:F33) -> 35900 | G34: =SUM(G24:G33) -> 68000 | J34: =SUM(J24:J33) -> 17940 | K34: =SUM(K24:K33) -> 13705
B35: 예비비 (인건비 외 × 10%) | E35: =E34*0.1 -> 3210 | F35: =F34*0.1 -> 3590 | G35: =E35+F35 -> 6800
B36: 연구수당 (TIPS 현금 인건비 × 5%) | E36: =SUMIF($C$5:$C$18,"R&D",M$5:M$18)*0.05 -> 1032.75 | F36: =SUMIF($C$5:$C$18,"R&D",N$5:N$18)*0.05 -> 1626 | G36: =E36+F36 -> 2658.75
B37: 검증: FM_Base 기타 운영비 − (인건비 외 + 예비비 + 연구수당) (0이어야 함) | E37: =FM_Base!$C$68-(E34+E35+E36) -> 0 | F37: =FM_Base!$D$68-(F34+F35+F36) -> 0
B39: C. TIPS 과제 편성 (비목) | E39: 1차년도 | F39: 2차년도 | G39: 합계 | L39: 근거
B40: 인건비 (현금) | E40: =SUMIF($C$5:$C$18,"R&D",M$5:M$18) -> 20655 | F40: =SUMIF($C$5:$C$18,"R&D",N$5:N$18) -> 32520 | G40: =E40+F40 -> 53175 | L40: R&D 인원 × 참여율
B41: 인건비 (현물) | E41: =SUMIF($C$5:$C$18,"Founder",M$5:M$18) -> 6600 | F41: =SUMIF($C$5:$C$18,"Founder",N$5:N$18) -> 6600 | G41: =E41+F41 -> 13200 | L41: Founder 2인 × 참여율
B42: 연구재료비 | E42: =SUMIF($L$24:$L$33,"연구재료비",J$24:J$33) -> 13240 | F42: =SUMIF($L$24:$L$33,"연구재료비",K$24:K$33) -> 6880 | G42: =E42+F42 -> 20120 | L42: Robot HW · Hand · Mock-up × 편성 비율
B43: 연구활동비 | E43: =SUMIF($L$24:$L$33,"연구활동비",J$24:J$33) -> 4700 | F43: =SUMIF($L$24:$L$33,"연구활동비",K$24:K$33) -> 6825 | G43: =E43+F43 -> 11525 | L43: SW · Data · 인증 사전시험 · IP × 편성 비율
B44: 연구수당 | E44: =E36 -> 1032.75 | F44: =F36 -> 1626 | G44: =E44+F44 -> 2658.75 | L44: 현금 인건비 × 5%
B45: 직접비 합계 | E45: =SUM(E40:E44) -> 46227.75 | F45: =SUM(F40:F44) -> 54451 | G45: =SUM(G40:G44) -> 100678.75
B46: 간접비 (연차 총액 − 직접비, 직접비 비례 배분) | E46: =G47*E45/G45-E45 -> 2749.4175 | F46: =G47*F45/G45-F45 -> 3238.4992 | G46: =E46+F46 -> 5987.9167
B47: TIPS 과제 총 연구개발비 (= 정부지원금 ÷ 정부 비율 상한) | E47: =E45+E46 -> 48977.167 | F47: =F45+F46 -> 57689.499 | G47: =Inputs!$E$84/Inputs!$E$86 -> 106666.67
B48: 정부지원금 (선정 시) | G48: =Inputs!$E$84 -> 80000 | L48: FACT (2026 공고 최대)
B49: 기관부담 (= 총액 − 정부지원금) | G49: =G47-Inputs!$E$84 -> 26666.667
B50: 기관부담 중 현물 (Founder 인건비) | G50: =G41 -> 13200
B51: 기관부담 중 현금 | G51: =G47-Inputs!$E$84-G41 -> 13466.667 | L51: Seed 자금으로 부담
B52: 현금 비율 하한 충족 (1 = 예) | G52: =IF((G47-Inputs!$E$84-G41)/(G47-Inputs!$E$84)>=Inputs!$E$87-0.0001,1,0) -> 1 | L52: 기관부담 중 현금 ≥ tips_cash_ratio
B53: 간접비율 (간접비 ÷ 현금 직접비) | G53: =G46/(G45-G41) -> 0.068449957 | L53: 협약 기준 확인 필요 (ASSUMPTION)
B55: D. 재원 · Seed 범위 (24개월) | E55: Y1 | F55: Y2 | G55: 합계 | L55: 비고
B56: 회사 전체 지출 (= −FM_Base 현금흐름) | E56: =-FM_Base!$C$71 -> 92167.75 | F56: =-FM_Base!$D$71 -> 141970.9 | G56: =E56+F56 -> 234138.65
B57: 그중 실증 순비용 (지출 − Opex) | E57: =E56-FM_Base!$C$69 -> 0 | F57: =F56-FM_Base!$D$69 -> 3804.8985 | G57: =E57+F57 -> 3804.8985
B58: TIPS 정부지원금 (선정 시, 연차 배분) | E58: =E47*Inputs!$E$86 -> 36732.876 | F58: =F47*Inputs!$E$86 -> 43267.124 | G58: =E58+F58 -> 80000
B59: Buffer (Y2 월평균 지출 × 3개월, Series A 협상 기간) | G59: =F56/12*3 -> 35492.725
B60: Seed 필요액 — Base (지출 − 정부지원금 + Buffer) | G60: =G56-G58+G59 -> 189631.37
B61: Seed 필요액 — Lean (팀 축소 · 목업/실증/인증 축소) — STATIC | G61: 137770.1 | L61: model.py budget24('lean')
B62: Seed 필요액 — TIPS 미선정 시 Lean 범위 단독 — STATIC | G62: 215241.1 | L62: 연구수당 제외 · 정부지원 0
B63: TIPS 운영사 선투자 요건 (수도권, FACT) | G63: 20000 | L63: Seed 라운드의 일부로 충족

Sheet Sources
A1: FACT Sources (조회일 2026-10-07~08, 검색 결과 기준 — 외부 제출 전 원문 재확인 필요)
A3: 항목 | B3: 값 | C3: 기준 | D3: Source
A4: 총주택 / 아파트 비중 / 준공 20년·30년 이상 비중 / 미거주 주택 | B4: 2,018.1만호 / 65.8% / 56.0%·30.6% / 172.2만호 | C4: 2025.11.1 기준 | D4: 국가데이터처, 2025 인구주택총조사 결과 (2026.7.28 발표) — 보도: https://www.newsis.com/view/NISX20260728_0003726109 , https://www.fnnews.com/news/202607281048203456
A5: 아파트 수 / 준공 20년 이상 아파트 (2023) | B5: 1,263만호 / 639만호 (50.7%) | C5: 2023 주택총조사 | D5: 통계청 주택총조사 인용 보도: https://www.smarttoday.co.kr/ko-kr/articles/49322
A6: 2025 주택 준공 / 인허가 / 착공 / 공동주택 분양 | B6: 34만2,399호 (−17.8%) / 37만9,834호 / 27만2,685호 (−10.1%) / 19만8,373호 (−14.1%) | C6: 2025 연간 | D6: 국토교통부, '25년 12월 주택통계 (2026.1.30): https://www.korea.kr/briefing/pressReleaseView.do?newsId=156742136 , https://www.m-economynews.com/news/article.html?no=64226
A7: 아파트 인허가 (2025) | B7: 34만6,773가구 (2024: 39만7,904) | C7: 2025 연간 | D7: 국토교통부 주택통계 인용 보도: https://www.newsis.com/view/NISX20260129_0003495426
A8: 아파트 입주 물량 | B8: 2025 23만6,263가구 / 2026 예정 18만3,124가구 | C8: 부동산114 REPS | D8: https://v.daum.net/v/GCidIvCEQs
A9: 주택 매매거래 (2025) | B9: 72.6만호 (+13%, 10년 평균 88.5만호) | C9: 2025 연간, 한국부동산원 자료 | D9: KB주택시장리뷰 2026년 2월호: https://kbthink.com/realestate/insights/research/260213-3.html
A10: 국내 리모델링 시장 전망 (건축물 전체, 비주거 포함) | B10: 2025년 37조원 → 2030년 44조원 (리모델링 23.3조 + 유지보수 13.8조, 2025) | C10: 한국건설산업연구원 전망치 | D10: https://m.ekn.kr/view.php?key=523568
A11: 한샘 리하우스 스타일패키지 (전체 리모델링) | B11: 30평대 평당 100만원대 → 약 3,000만원 | C11: 2019 보도 (가격 시점 오래됨) | D11: https://www.dailian.co.kr/news/view/1008108/
A12: 프리미엄 Kitchen 동향 (한샘 키친바흐·빌트인 가전 연계) | B12: 국내 프리미엄 키친 시장 약 90%가 수입·고가 맞춤 / 키친바흐 매출 +17% (2025.6 기준) / 밀레 연계 부엌 매출 +173% (2024 대비) | C12: 회사 발표 인용 보도 | D12: https://www.heraldk.com/article/2025072318143590645 , https://www.heraldk.com/article/2026062223520679105
A13: 한샘 리하우스 부문 매출 | B13: 2025 1Q 1,147억원 (−4.3%) | C13: 분기 실적 | D13: https://newstomato.com/ReadNews.aspx?no=1284742
A14: 신축 유상옵션 비용 비중 | B14: 분양가상한제 단지 7곳 평균 분양가 대비 9.7% | C14: 수도권 분양 단지 보도 | D14: https://www.etoday.co.kr/news/view/2392578
... A55: 2026 TIPS 접수 방식 | B55: 공고 접수 기간 2026.1.26~12.31 · 일반트랙 분기 단위 평가 (운용사 해설) — 남은 차수 일정은 운영사 확인 | C55: 공고 요약 · 운용사 해설 | D55: https://www.venturesquare.net/announcement/1035119 , https://zuzu.network/resource/blog/2026-different-tips-required/
