Workbook

Sheet README
B1: ARKI Robotics — TIPS IR Financial Model (Draft v4, 2026-10)
B3: 목적: TIPS IR 덱의 모든 사업 수치를 하나의 수식 모델로 관리. 단위는 별도 표기가 없으면 만원 (KRW 10,000). 억원 = 만원 / 10,000.
B4: 주의: 실적·계약·고객·Partner 데이터 없음. 모든 수치는 FACT / DERIVED / ASSUMPTION / TARGET Tag로 구분.
B6: Color code
B7: 파란 글자 = 입력값 (Inputs, Inputs_Yearly에서만 수정) · 검은 글자 = 수식 · 녹색 글자 = 다른 Sheet 참조 · 노란 바탕 = 핵심 가정 (WTP·BOM·Volume)
B8: Tag
B9: FACT = 공식 통계·공개자료 확인값 · DERIVED = FACT 기반 계산값 · ASSUMPTION = 현재 사업가설 · TARGET = TIPS 과제 · 이후 목표
B10: Sheets
B11: Inputs: 단일값 가정 (시나리오별 Conservative / Base / Upside 열)
B12: Inputs_Yearly: 연도별 가정 (Volume, BOM, Standard Module 사용률, 인원 등)
B13: FM_Conservative / FM_Base / FM_Upside: 5개년 Bottom-up 손익 (각 Sheet가 해당 시나리오 열을 참조)
B14: Scenario_Summary: 3개 시나리오 요약 (억원)
... B23: 재현: python3 ARKI/source/model.py → python3 ARKI/source/xlsx_model.py (LibreOffice 재계산 후 model.py와 교차검증)

Sheet Scenario_Summary
A1: Scenario Summary (억원 · 세대 · 대)
A2: 각 셀은 FM Sheet 참조. 억원 = 만원 / 10,000. Upside는 가격 인상 없이 Partner·표준화·설치원가·Installed Base로 차이.
A4: Conservative | B4: 단위 | C4: Y1 | D4: Y2 | E4: Y3 | F4: Y4 | G4: Y5
A5: 매출 | B5: 억원 | C5: =FM_Conservative!$C$41/10000 -> 0 | D5: =FM_Conservative!$D$41/10000 -> 0.14508 | E5: =FM_Conservative!$E$41/10000 -> 3.609345 | F5: =FM_Conservative!$F$41/10000 -> 13.79455 | G5: =FM_Conservative!$G$41/10000 -> 27.786233
A6: 매출총이익 | B6: 억원 | C6: =FM_Conservative!$C$59/10000 -> 0 | D6: =FM_Conservative!$D$59/10000 -> -0.32554485 | E6: =FM_Conservative!$E$59/10000 -> 0.16499805 | F6: =FM_Conservative!$F$59/10000 -> 1.1136167 | G6: =FM_Conservative!$G$59/10000 -> 3.9891288
A7: 매출총이익률 | B7: % | C7: =FM_Conservative!$C$60 -> 0 | D7: =FM_Conservative!$D$60 -> -2.2438989 | E7: =FM_Conservative!$E$60 -> 0.045714125 | F7: =FM_Conservative!$F$60 -> 0.080728743 | G7: =FM_Conservative!$G$60 -> 0.14356494
A8: Contribution | B8: 억원 | C8: =FM_Conservative!$C$65/10000 -> 0 | D8: =FM_Conservative!$D$65/10000 -> -0.37954485 | E8: =FM_Conservative!$E$65/10000 -> -0.36630195 | F8: =FM_Conservative!$F$65/10000 -> -0.74418328 | G8: =FM_Conservative!$G$65/10000 -> 0.29962884
A9: Opex | B9: 억원 | C9: =FM_Conservative!$C$68/10000 -> 6.69 | D9: =FM_Conservative!$D$68/10000 -> 8.7 | E9: =FM_Conservative!$E$68/10000 -> 30.5 | F9: =FM_Conservative!$F$68/10000 -> 43.9 | G9: =FM_Conservative!$G$68/10000 -> 56.7
A10: 영업이익 (근사) | B10: 억원 | C10: =FM_Conservative!$C$69/10000 -> -6.69 | D10: =FM_Conservative!$D$69/10000 -> -9.0795448 | E10: =FM_Conservative!$E$69/10000 -> -30.866302 | F10: =FM_Conservative!$F$69/10000 -> -44.644183 | G10: =FM_Conservative!$G$69/10000 -> -56.400371
A11: 누적 현금흐름 | B11: 억원 | C11: =FM_Conservative!$C$71/10000 -> -6.69 | D11: =FM_Conservative!$D$71/10000 -> -15.89307 | E11: =FM_Conservative!$E$71/10000 -> -47.539334 | F11: =FM_Conservative!$F$71/10000 -> -92.011393 | G11: =FM_Conservative!$G$71/10000 -> -148.23964
A12: Kitchen 설치 | B12: 세대 | C12: =FM_Conservative!$C$8 -> 0 | D12: =FM_Conservative!$D$8 -> 3 | E12: =FM_Conservative!$E$8 -> 30 | F12: =FM_Conservative!$F$8 -> 95 | G12: =FM_Conservative!$G$8 -> 190
A13: Robot 설치 | B13: 대 | C13: =FM_Conservative!$C$13 -> 0 | D13: =FM_Conservative!$D$13 -> 3 | E13: =FM_Conservative!$E$13 -> 22.5 | F13: =FM_Conservative!$F$13 -> 71.625 | G13: =FM_Conservative!$G$13 -> 144.04375
A14: Installed Robot (기말) | B14: 대 | C14: =FM_Conservative!$C$27 -> 0 | D14: =FM_Conservative!$D$27 -> 3 | E14: =FM_Conservative!$E$27 -> 25.5 | F14: =FM_Conservative!$F$27 -> 97.125 | G14: =FM_Conservative!$G$27 -> 241.16875
A15: 신축 Backlog | B15: 세대 | C15: =FM_Conservative!$C$28 -> 0 | D15: =FM_Conservative!$D$28 -> 0 | E15: =FM_Conservative!$E$28 -> 0 | F15: =FM_Conservative!$F$28 -> 48 | G15: =FM_Conservative!$G$28 -> 144
A16: Robot + Recurring + Upgrade 비중 | B16: % | C16: =FM_Conservative!$C$75 -> 0 | D16: =FM_Conservative!$D$75 -> 0.70223325 | E16: =FM_Conservative!$E$75 -> 0.61765916 | F16: =FM_Conservative!$F$75 -> 0.68299076 | G16: =FM_Conservative!$G$75 -> 0.68501128
A18: Base | B18: 단위 | C18: Y1 | D18: Y2 | E18: Y3 | F18: Y4 | G18: Y5
A19: 매출 | B19: 억원 | C19: =FM_Base!$C$41/10000 -> 0 | D19: =FM_Base!$D$41/10000 -> 0.260511 | E19: =FM_Base!$E$41/10000 -> 7.4234195 | F19: =FM_Base!$F$41/10000 -> 32.472507 | G19: =FM_Base!$G$41/10000 -> 77.544078
A20: 매출총이익 | B20: 억원 | C20: =FM_Base!$C$59/10000 -> 0 | D20: =FM_Base!$D$59/10000 -> -0.19508235 | E20: =FM_Base!$E$59/10000 -> 1.8194202 | F20: =FM_Base!$F$59/10000 -> 9.8175725 | G20: =FM_Base!$G$59/10000 -> 27.872179
A21: 매출총이익률 | B21: % | C21: =FM_Base!$C$60 -> 0 | D21: =FM_Base!$D$60 -> -0.74884496 | E21: =FM_Base!$E$60 -> 0.24509192 | F21: =FM_Base!$F$60 -> 0.30233491 | G21: =FM_Base!$G$60 -> 0.35943659
A22: Contribution | B22: 억원 | C22: =FM_Base!$C$65/10000 -> 0 | D22: =FM_Base!$D$65/10000 -> -0.24008235 | E22: =FM_Base!$E$65/10000 -> 0.81252018 | F22: =FM_Base!$F$65/10000 -> 6.3477225 | G22: =FM_Base!$G$65/10000 -> 20.304879
A23: Opex | B23: 억원 | C23: =FM_Base!$C$68/10000 -> 6.69 | D23: =FM_Base!$D$68/10000 -> 8.7 | E23: =FM_Base!$E$68/10000 -> 30.5 | F23: =FM_Base!$F$68/10000 -> 43.9 | G23: =FM_Base!$G$68/10000 -> 56.7
A24: 영업이익 (근사) | B24: 억원 | C24: =FM_Base!$C$69/10000 -> -6.69 | D24: =FM_Base!$D$69/10000 -> -8.9400824 | E24: =FM_Base!$E$69/10000 -> -29.68748 | F24: =FM_Base!$F$69/10000 -> -37.552278 | G24: =FM_Base!$G$69/10000 -> -36.395121
A25: 누적 현금흐름 | B25: 억원 | C25: =FM_Base!$C$71/10000 -> -6.69 | D25: =FM_Base!$D$71/10000 -> -15.74949 | E25: =FM_Base!$E$71/10000 -> -46.756403 | F25: =FM_Base!$F$71/10000 -> -84.037233 | G25: =FM_Base!$G$71/10000 -> -120.16091
A26: Kitchen 설치 | B26: 세대 | C26: =FM_Base!$C$8 -> 0 | D26: =FM_Base!$D$8 -> 3 | E26: =FM_Base!$E$8 -> 50 | F26: =FM_Base!$F$8 -> 180 | G26: =FM_Base!$G$8 -> 480
A27: Robot 설치 | B27: 대 | C27: =FM_Base!$C$13 -> 0 | D27: =FM_Base!$D$13 -> 3 | E27: =FM_Base!$E$13 -> 42.5 | F27: =FM_Base!$F$13 -> 153.75 | G27: =FM_Base!$G$13 -> 363.375
A28: Installed Robot (기말) | B28: 대 | C28: =FM_Base!$C$27 -> 0 | D28: =FM_Base!$D$27 -> 3 | E28: =FM_Base!$E$27 -> 45.5 | F28: =FM_Base!$F$27 -> 199.25 | G28: =FM_Base!$G$27 -> 562.625
A29: 신축 Backlog | B29: 세대 | C29: =FM_Base!$C$28 -> 0 | D29: =FM_Base!$D$28 -> 0 | E29: =FM_Base!$E$28 -> 80 | F29: =FM_Base!$F$28 -> 240 | G29: =FM_Base!$G$28 -> 400
A30: Robot + Recurring + Upgrade 비중 | B30: % | C30: =FM_Base!$C$75 -> 0 | D30: =FM_Base!$D$75 -> 0.69483054 | E30: =FM_Base!$E$75 -> 0.65110418 | F30: =FM_Base!$F$75 -> 0.71268002 | G30: =FM_Base!$G$75 -> 0.70768883
A32: Upside | B32: 단위 | C32: Y1 | D32: Y2 | E32: Y3 | F32: Y4 | G32: Y5
A33: 매출 | B33: 억원 | C33: =FM_Upside!$C$41/10000 -> 0 | D33: =FM_Upside!$D$41/10000 -> 0.307701 | E33: =FM_Upside!$E$41/10000 -> 9.6346287 | F33: =FM_Upside!$F$41/10000 -> 50.093412 | G33: =FM_Upside!$G$41/10000 -> 133.9515
A34: 매출총이익 | B34: 억원 | C34: =FM_Upside!$C$59/10000 -> 0 | D34: =FM_Upside!$D$59/10000 -> -0.13195176 | E34: =FM_Upside!$E$59/10000 -> 2.809274 | F34: =FM_Upside!$F$59/10000 -> 17.648547 | G34: =FM_Upside!$G$59/10000 -> 56.239078
A35: 매출총이익률 | B35: % | C35: =FM_Upside!$C$60 -> 0 | D35: =FM_Upside!$D$60 -> -0.42883111 | E35: =FM_Upside!$E$60 -> 0.29158093 | F35: =FM_Upside!$F$60 -> 0.35231273 | G35: =FM_Upside!$G$60 -> 0.41984656
A36: Contribution | B36: 억원 | C36: =FM_Upside!$C$65/10000 -> 0 | D36: =FM_Upside!$D$65/10000 -> -0.17395176 | E36: =FM_Upside!$E$65/10000 -> 1.437459 | F36: =FM_Upside!$F$65/10000 -> 12.675237 | G36: =FM_Upside!$G$65/10000 -> 44.822778
A37: Opex | B37: 억원 | C37: =FM_Upside!$C$68/10000 -> 6.69 | D37: =FM_Upside!$D$68/10000 -> 8.7 | E37: =FM_Upside!$E$68/10000 -> 30.5 | F37: =FM_Upside!$F$68/10000 -> 43.9 | G37: =FM_Upside!$G$68/10000 -> 56.7
A38: 영업이익 (근사) | B38: 억원 | C38: =FM_Upside!$C$69/10000 -> -6.69 | D38: =FM_Upside!$D$69/10000 -> -8.8739518 | E38: =FM_Upside!$E$69/10000 -> -29.062541 | F38: =FM_Upside!$F$69/10000 -> -31.224763 | G38: =FM_Upside!$G$69/10000 -> -11.877222
A39: 누적 현금흐름 | B39: 억원 | C39: =FM_Upside!$C$71/10000 -> -6.69 | D39: =FM_Upside!$D$71/10000 -> -15.679242 | E39: =FM_Upside!$E$71/10000 -> -46.358304 | F39: =FM_Upside!$F$71/10000 -> -77.257331 | G39: =FM_Upside!$G$71/10000 -> -88.808816
A40: Kitchen 설치 | B40: 세대 | C40: =FM_Upside!$C$8 -> 0 | D40: =FM_Upside!$D$8 -> 3 | E40: =FM_Upside!$E$8 -> 65 | F40: =FM_Upside!$F$8 -> 280 | G40: =FM_Upside!$G$8 -> 862
A41: Robot 설치 | B41: 대 | C41: =FM_Upside!$C$13 -> 0 | D41: =FM_Upside!$D$13 -> 3 | E41: =FM_Upside!$E$13 -> 55.25 | F41: =FM_Upside!$F$13 -> 239.17 | G41: =FM_Upside!$G$13 -> 633.1696
A42: Installed Robot (기말) | B42: 대 | C42: =FM_Upside!$C$27 -> 0 | D42: =FM_Upside!$D$27 -> 3 | E42: =FM_Upside!$E$27 -> 58.25 | F42: =FM_Upside!$F$27 -> 297.42 | G42: =FM_Upside!$G$27 -> 930.5896
A43: 신축 Backlog | B43: 세대 | C43: =FM_Upside!$C$28 -> 0 | D43: =FM_Upside!$D$28 -> 0 | E43: =FM_Upside!$E$28 -> 192 | F43: =FM_Upside!$F$28 -> 480 | G43: =FM_Upside!$G$28 -> 672
A44: Robot + Recurring + Upgrade 비중 | B44: % | C44: =FM_Upside!$C$75 -> 0 | D44: =FM_Upside!$D$75 -> 0.68995876 | E44: =FM_Upside!$E$75 -> 0.65053142 | F44: =FM_Upside!$F$75 -> 0.71027408 | G44: =FM_Upside!$G$75 -> 0.70556988

Sheet Inputs
A1: Inputs — 단일값 가정 (만원 기준)
A3: Key | B3: 항목 | C3: 단위 | D3: Conservative | E3: Base | F3: Upside | G3: Tag | H3: Source / Note
A4: MARKET
A5: m_housing_total | B5: 총주택 (2025.11.1 기준) | C5: 천호 | D5: 20181 | E5: 20181 | F5: 20181 | G5: FACT | H5: 국가데이터처, 2025 인구주택총조사 등록센서스 결과 (2026.7.28 발표)
A6: m_apt_share | B6: 아파트 비중 (총주택 대비) | C6: % | D6: 0.658 | E6: 0.658 | F6: 0.658 | G6: FACT | H6: 국가데이터처, 2025 인구주택총조사
A7: m_house_20y_share | B7: 준공 20년 이상 주택 비중 | C7: % | D7: 0.56 | E7: 0.56 | F7: 0.56 | G7: FACT | H7: 국가데이터처, 2025 인구주택총조사
A8: m_house_30y_share | B8: 준공 30년 이상 주택 비중 | C8: % | D8: 0.306 | E8: 0.306 | F8: 0.306 | G8: FACT | H8: 국가데이터처, 2025 인구주택총조사
A9: m_apt_2023 | B9: 아파트 수 (2023) | C9: 천호 | D9: 12630 | E9: 12630 | F9: 12630 | G9: FACT | H9: 통계청, 2023 주택총조사 (보도 인용)
A10: m_apt_20y_2023 | B10: 준공 20년 이상 아파트 (2023) | C10: 천호 | D10: 6390 | E10: 6390 | F10: 6390 | G10: FACT | H10: 통계청, 2023 주택총조사 (보도 인용)
A11: m_txn_2025 | B11: 주택 매매거래 (2025, 전체 주택) | C11: 천호 | D11: 726 | E11: 726 | F11: 726 | G11: FACT | H11: KB주택시장리뷰 2026.2 (한국부동산원 자료)
A12: m_completion_2025 | B12: 주택 준공 (2025 연간, 전체 주택) | C12: 천호 | D12: 342.4 | E12: 342.4 | F12: 342.4 | G12: FACT | H12: 국토교통부, 2025년 12월 주택통계
A13: m_movein_2025 | B13: 아파트 입주 (2025) | C13: 천호 | D13: 236.3 | E13: 236.3 | F13: 236.3 | G13: FACT | H13: 부동산114 REPS
A14: m_movein_2026e | B14: 아파트 입주 예정 (2026) | C14: 천호 | D14: 183.1 | E14: 183.1 | F14: 183.1 | G14: FACT | H14: 부동산114 REPS (예정 물량)
A15: a_replace_cycle | B15: Kitchen 교체주기 (노후 아파트) | C15: 년 | D15: 22 | E15: 22 | F15: 22 | G15: ASSUMPTION | H15: 교차검증용 가정. Seed 기간 견적·인터뷰로 검증
A16: a_txn_apt_share | B16: 매매거래 중 아파트 비중 | C16: % | D16: 0.7 | E16: 0.7 | F16: 0.7 | G16: ASSUMPTION | H16: 부동산원 월별 아파트 거래 비중 확인 필요
... A23: a_premium_project | B23: Premium 단지 비중 (신축) | C23: % | D23: 0.15 | E23: 0.15 | F23: 0.15 | G23: ASSUMPTION | H23: 브랜드·분양가 기준 정의 필요
A24: VALUE
A25: f_helper_rate | B25: 가사서비스 시간당 요금 (플랫폼 4시간 59,900~64,900원) | C25: 만원/h | D25: 1.5 | E25: 1.5 | F25: 1.5 | G25: FACT | H25: 가사서비스 플랫폼 공개 요금 (2025, 보도·앱 정보)
A26: a_cleanup_min | B26: Clean-up 시간 (식사 후 정리, 일) | C26: 분/일 | D26: 40 | E26: 40 | F26: 40 | G26: ASSUMPTION | H26: Time-diary(n=30)로 검증
A27: a_auto_share | B27: V1 자동화 가능 비중 | C27: % | D27: 0.6 | E27: 0.6 | F27: 0.6 | G27: ASSUMPTION | H27: 식기 이동·식세기·수납만. 행주·싱크 세척 제외
A28: fx | B28: 환율 (Benchmark 환산용) | C28: 원/USD | D28: 1400 | E28: 1400 | F28: 1400 | G28: ASSUMPTION | H28: 부품 Benchmark 환산 전용
A29: PRICE
A30: p_rr | B30: Robot-ready Kitchen 증분가 (구축) | C30: 만원/세대 | D30: 400 | E30: 450 | F30: 450 | G30: ASSUMPTION | H30: 기존 Kitchen 공사비 위 증분. 시스템에어컨 유상옵션(500~1,000만원) 대비 하단
A31: p_rr_new | B31: Robot-ready Option 공급가 (신축, ARKI 매출) | C31: 만원/세대 | D31: 200 | E31: 220 | F31: 220 | G31: ASSUMPTION | H31: 건설사·가구사 마진 별도. 분양 고객가 약 300만원 가정
A32: p_robot | B32: Robot Module ASP (구매) | C32: 만원/대 | D32: 1290 | E32: 1490 | F32: 1490 | G32: ASSUMPTION | H32: Upside는 가격 인상 없음. WTP 검증 대상 1순위
A33: p_comm | B33: 설치·Calibration·Safety Check | C33: 만원/대 | D33: 80 | E33: 80 | F33: 80 | G33: ASSUMPTION
A34: p_rent | B34: Robot Rental 월 요금 (Care Basic·Grip Kit 포함, 60개월) | C34: 만원/월 | D34: 29 | E34: 33 | F34: 33 | G34: ASSUMPTION | H34: 원가 Build-up(감가·금융·Care·Grip·Reserve)+마진
A35: rent_months | B35: Rental 계약기간 | C35: 개월 | D35: 60 | E35: 60 | F35: 60 | G35: ASSUMPTION
A36: p_care | B36: Care Basic 연 요금 (구매 고객) | C36: 만원/년 | D36: 42 | E36: 48 | F36: 48 | G36: ASSUMPTION | H36: 정기점검·Calibration·원격진단·SW Update·A/S 공임
A37: p_care_plus | B37: Care Plus 연 요금 (Kit 정기교체 포함) | C37: 만원/년 | D37: 72 | E37: 72 | F37: 72 | G37: ASSUMPTION | H37: 옵션 상품. 재무 Base에는 미반영
A38: p_grip | B38: Grip Kit (Finger Pad·Food-contact Tip·Suction Cup) | C38: 만원/Kit | D38: 4.5 | E38: 4.5 | F38: 4.5 | G38: ASSUMPTION | H38: 분기 교체 가정
A39: n_grip | B39: Grip Kit 교체 횟수 | C39: 회/년 | D39: 4 | E39: 4 | F39: 4 | G39: ASSUMPTION | H39: Replacement Cycle 검증 대상
A40: p_clean | B40: Cleaning Kit (Brush·Wiper·Cleaning Pad) | C40: 만원/Kit | D40: 2.5 | E40: 2.5 | F40: 2.5 | G40: ASSUMPTION
A41: n_clean | B41: Cleaning Kit 교체 횟수 | C41: 회/년 | D41: 4 | E41: 4 | F41: 4 | G41: ASSUMPTION
A42: p_protect | B42: Protection Kit (Sensor Cover·Sleeve·Seal) | C42: 만원/Kit | D42: 4 | E42: 4 | F42: 4 | G42: ASSUMPTION
A43: n_protect | B43: Protection Kit 교체 횟수 | C43: 회/년 | D43: 2 | E43: 2 | F43: 2 | G43: ASSUMPTION
A44: cons_attach | B44: Consumables 구매율 | C44: % | D44: 0.55 | E44: 0.7 | F44: 0.7 | G44: ASSUMPTION
A45: care_attach | B45: Care 가입률 (구매 고객) | C45: % | D45: 0.55 | E45: 0.7 | F45: 0.7 | G45: ASSUMPTION
A46: p_sw | B46: Software Skill Pack (설치 다음 해) | C46: 만원 | D46: 60 | E46: 60 | F46: 60 | G46: ASSUMPTION | H46: V2 기능 (재료 투입 보조 등) 출시 전제
A47: sw_attach | B47: Software Skill 구매율 | C47: % | D47: 0.1 | E47: 0.2 | F47: 0.2 | G47: ASSUMPTION
A48: p_tool | B48: End-effector / Tool 추가 (설치 2년 후) | C48: 만원 | D48: 80 | E48: 80 | F48: 80 | G48: ASSUMPTION | H48: FUTURE CONCEPT 제품
A49: tool_attach | B49: Tool 구매율 | C49: % | D49: 0.15 | E49: 0.25 | F49: 0.25 | G49: ASSUMPTION
A50: wholesale | B50: Rental Partner 공급가율 (Robot ASP 대비) | C50: % | D50: 0.88 | E50: 0.88 | F50: 0.88 | G50: ASSUMPTION | H50: Y4부터 Rental Partner가 자산 보유
A51: partner_fee | B51: Rental Partner → ARKI Care·Grip 서비스료 | C51: 만원/월 | D51: 6 | E51: 6 | F51: 6 | G51: ASSUMPTION
A52: COST
A53: kit_std_cost | B53: Kitchen Module 원가 (100% 표준부품 기준) | C53: 만원/세대 | D53: 200 | E53: 200 | F53: 200 | G53: ASSUMPTION | H53: 하부 보강 프레임·Rail Interface·식세기 상향 하우징·Robot Garage·전원/통신·수납 Rack
A54: custom_factor | B54: Custom 부품 원가 배수 | C54: x | D54: 1.6 | E54: 1.6 | F54: 1.6 | G54: ASSUMPTION
A55: design_cost | B55: Design·Site Adjustment 원가 (100% Custom 시) | C55: 만원/세대 | D55: 100 | E55: 100 | F55: 100 | G55: ASSUMPTION
A56: kit_new_cost | B56: Robot-ready Option 원가 (신축, 공장 생산) | C56: 만원/세대 | D56: 145 | E56: 130 | F56: 120 | G56: ASSUMPTION
A57: logistics | B57: 물류 (프로젝트당) | C57: 만원/세대 | D57: 25 | E57: 25 | F57: 25 | G57: ASSUMPTION
A58: warranty | B58: Warranty Reserve (Robot 매출 대비) | C58: % | D58: 0.05 | E58: 0.04 | F58: 0.035 | G58: ASSUMPTION | H58: 1년 무상 A/S
A59: corrective | B59: 고장 방문 (Failure Rate) | C59: 회/대·년 | D59: 0.9 | E59: 0.6 | F59: 0.5 | G59: ASSUMPTION
A60: corr_cost | B60: 고장 방문 1회 원가 (소부품 포함) | C60: 만원/회 | D60: 18 | E60: 18 | F60: 18 | G60: ASSUMPTION
A61: cloud | B61: Cloud·Software 운영비 | C61: 만원/대·년 | D61: 4 | E61: 4 | F61: 4 | G61: ASSUMPTION
A62: cons_cogs | B62: Consumables 원가율 (물류 포함) | C62: % | D62: 0.4 | E62: 0.35 | F62: 0.32 | G62: ASSUMPTION
A63: sw_cogs | B63: Software 원가율 | C63: % | D63: 0.1 | E63: 0.1 | F63: 0.1 | G63: ASSUMPTION
A64: tool_cogs | B64: Tool 원가율 | C64: % | D64: 0.45 | E64: 0.45 | F64: 0.45 | G64: ASSUMPTION
A65: partner_margin | B65: Kitchen·Interior Partner 수수료 (Partner 경유 패키지) | C65: % | D65: 0.12 | E65: 0.1 | F65: 0.09 | G65: ASSUMPTION
A66: cac | B66: 직접판매 획득비용 (상담·설계·Demo) | C66: 만원/세대 | D66: 180 | E66: 150 | F66: 140 | G66: ASSUMPTION
A67: bd_new | B67: 신축 Project 수주비용 (Spec·견본주택) | C67: 만원/Project | D67: 2000 | E67: 2000 | F67: 2000 | G67: ASSUMPTION
A68: residual | B68: Rental 자산 잔존가치 (60개월 후) | C68: % | D68: 0.15 | E68: 0.15 | F68: 0.15 | G68: ASSUMPTION | H68: Refurbish 재배치
A69: fin_rate | B69: Rental 자산 금융비용 | C69: %/년 | D69: 0.08 | E69: 0.08 | F69: 0.08 | G69: ASSUMPTION | H69: 캐피탈 조달금리+Spread 가정
A70: payback_hurdle | B70: Rental Partner 요구 Payback | C70: 개월 | D70: 36 | E70: 36 | F70: 36 | G70: ASSUMPTION | H70: 렌탈·캐피탈사 협의로 검증
A71: VOLUME
A72: later_attach | B72: Robot-ready Only 세대의 연간 후속 Attach | C72: %/년 | D72: 0.05 | E72: 0.1 | F72: 0.12 | G72: ASSUMPTION
A73: hh_project | B73: Project당 세대수 | C73: 세대 | D73: 800 | E73: 800 | F73: 800 | G73: ASSUMPTION
A74: option_rate | B74: 신축 Robot-ready Option 선택률 | C74: % | D74: 0.06 | E74: 0.1 | F74: 0.12 | G74: ASSUMPTION
A75: new_attach | B75: 신축 입주 시 Robot Attach | C75: % | D75: 0.15 | E75: 0.25 | F75: 0.3 | G75: ASSUMPTION
A76: OPEX
A77: loaded | B77: 인당 연 인건비 (4대보험·퇴직급여 포함) | C77: 만원/년 | D77: 8500 | E77: 8500 | F77: 8500 | G77: ASSUMPTION | H77: 평균 연봉 약 7,100만원 × 1.2
A78: FUNDING
A79: tips | B79: TIPS R&D 정부지원금 (일반 트랙 최대) | C79: 만원 | D79: 80000 | E79: 80000 | F79: 80000 | G79: FACT | H79: 중소벤처기업부 공고 제2026-40호 (2026.1.26) 팁스 창업기업 지원계획. 선정 미확정
A80: tips_months | B80: TIPS R&D 기간 (최대) | C80: 개월 | D80: 24 | E80: 24 | F80: 24 | G80: FACT | H80: 공고 제2026-40호
A81: tips_gov_ratio | B81: 정부지원연구개발비 비율 상한 (총 연구개발비 대비) | C81: % | D81: 0.75 | E81: 0.75 | F81: 0.75 | G81: FACT | H81: 공고 제2026-40호 (사본 · 운용사 정리 기준: 정부 75% 이내, 기관부담 25% 이상)
A82: tips_cash_ratio | B82: 기관부담연구개발비 중 현금 최소 비율 | C82: % | D82: 0.1 | E82: 0.1 | F82: 0.1 | G82: FACT | H82: 공고 제2026-40호 (사본 · 운용사 정리 기준)
A83: op_invest | B83: 운영사 투자 (요청액, TIPS 추천 전제) | C83: 만원 | D83: 30000 | E83: 30000 | F83: 30000 | G83: ASSUMPTION | H83: 요건: 수도권 2억원 이상 · 비수도권 1억원 이상 (2026). 조건 (형태 · 기업가치 · 지분)은 협의
A84: followon | B84: 후속 투자 (M12 목표, 공동투자 · Pre-A) | C84: 만원 | D84: 50000 | E84: 50000 | F84: 50000 | G84: TARGET | H84: M9 · M12 점검 결과 기반
A85: biz_link | B85: 비R&D 연계 (창업사업화 · 해외마케팅) 각 최대 (선정 뒤 별도 신청, 기본안 미반영) | C85: 만원 | D85: 15000 | E85: 15000 | F85: 15000 | G85: FACT | H85: 공고 제2026-40호: 각 10개월 최대 1.5억원, 합산 3억원, 정부 70% 이내

Sheet Inputs_Yearly
A1: Inputs_Yearly — 연도별 가정
A3: Key | B3: 항목 | C3: 단위 | D3: Scenario | E3: Y1 | F3: Y2 | G3: Y3 | H3: Y4 | I3: Y5 | J3: Tag | K3: Source / Note
A4: realization | B4: 가격 실현율 (Y2 Pilot 할인) | C4: % | D4: Conservative | E4: 1 | F4: 0.3 | G4: 1 | H4: 1 | I4: 1 | J4: ASSUMPTION | K4: Pilot은 할인 유료
A5: realization | B5: 가격 실현율 (Y2 Pilot 할인) | C5: % | D5: Base | E5: 1 | F5: 0.5 | G5: 1 | H5: 1 | I5: 1 | J5: ASSUMPTION | K5: Pilot은 할인 유료
A6: realization | B6: 가격 실현율 (Y2 Pilot 할인) | C6: % | D6: Upside | E6: 1 | F6: 0.6 | G6: 1 | H6: 1 | I6: 1 | J6: ASSUMPTION | K6: Pilot은 할인 유료
A8: smr | B8: Standard Module 사용률 | C8: % | D8: Conservative | E8: 0.4 | F8: 0.45 | G8: 0.55 | H8: 0.62 | I8: 0.65 | J8: TARGET | K8: Seed 종료 시 65% 이상 (Kill Criteria: M18 60% 미만)
A9: smr | B9: Standard Module 사용률 | C9: % | D9: Base | E9: 0.4 | F9: 0.5 | G9: 0.65 | H9: 0.75 | I9: 0.8 | J9: TARGET | K9: Seed 종료 시 65% 이상 (Kill Criteria: M18 60% 미만)
A10: smr | B10: Standard Module 사용률 | C10: % | D10: Upside | E10: 0.4 | F10: 0.55 | G10: 0.7 | H10: 0.8 | I10: 0.85 | J10: TARGET | K10: Seed 종료 시 65% 이상 (Kill Criteria: M18 60% 미만)
A12: bom | B12: Robot Module BOM | C12: 만원/대 | D12: Conservative | E12: 1600 | F12: 1500 | G12: 1300 | H12: 1180 | I12: 1080 | J12: ASSUMPTION | K12: A4 부품 Benchmark 기반. 수량·국산화·전용 Arm으로 하락 가정
A13: bom | B13: Robot Module BOM | C13: 만원/대 | D13: Base | E13: 1600 | F13: 1450 | G13: 1150 | H13: 1000 | I13: 900 | J13: ASSUMPTION | K13: A4 부품 Benchmark 기반. 수량·국산화·전용 Arm으로 하락 가정
A14: bom | B14: Robot Module BOM | C14: 만원/대 | D14: Upside | E14: 1600 | F14: 1400 | G14: 1080 | H14: 920 | I14: 800 | J14: ASSUMPTION | K14: A4 부품 Benchmark 기반. 수량·국산화·전용 Arm으로 하락 가정
A16: comm_cost | B16: 설치·Calibration 원가 (ARKI 인력) | C16: 만원/대 | D16: Conservative | E16: 120 | F16: 100 | G16: 75 | H16: 62 | I16: 55 | J16: ASSUMPTION | K16: 설치시간 TARGET과 연동
A17: comm_cost | B17: 설치·Calibration 원가 (ARKI 인력) | C17: 만원/대 | D17: Base | E17: 120 | F17: 90 | G17: 60 | H17: 45 | I17: 38 | J17: ASSUMPTION | K17: 설치시간 TARGET과 연동
A18: comm_cost | B18: 설치·Calibration 원가 (ARKI 인력) | C18: 만원/대 | D18: Upside | E18: 120 | F18: 85 | G18: 52 | H18: 38 | I18: 30 | J18: ASSUMPTION | K18: 설치시간 TARGET과 연동
... A38: attach | B38: Robot Attach Rate (구축, 설치 시점) | C38: % | D38: Upside | E38: 1 | F38: 1 | G38: 0.85 | H38: 0.85 | I38: 0.85 | J38: ASSUMPTION | K38: 나머지는 Robot-ready Only
A40: rental_share | B40: Rental 선택 비중 | C40: % | D40: Conservative | E40: 0 | F40: 0.3 | G40: 0.3 | H40: 0.35 | I40: 0.35 | J40: ASSUMPTION
A41: rental_share | B41: Rental 선택 비중 | C41: % | D41: Base | E41: 0 | F41: 0.3 | G41: 0.3 | H41: 0.4 | I41: 0.4 | J41: ASSUMPTION
A42: rental_share | B42: Rental 선택 비중 | C42: % | D42: Upside | E42: 0 | F42: 0.3 | G42: 0.3 | H42: 0.45 | I42: 0.45 | J42: ASSUMPTION
A44: partner_rental | B44: Rental 자산 보유 주체 (0 = ARKI Pilot, 1 = Rental Partner) | C44: flag | D44: Conservative | E44: 0 | F44: 0 | G44: 0 | H44: 1 | I44: 1 | J44: ASSUMPTION
A45: partner_rental | B45: Rental 자산 보유 주체 (0 = ARKI Pilot, 1 = Rental Partner) | C45: flag | D45: Base | E45: 0 | F45: 0 | G45: 0 | H45: 1 | I45: 1 | J45: ASSUMPTION
A46: partner_rental | B46: Rental 자산 보유 주체 (0 = ARKI Pilot, 1 = Rental Partner) | C46: flag | D46: Upside | E46: 0 | F46: 0 | G46: 0 | H46: 1 | I46: 1 | J46: ASSUMPTION
A48: projects | B48: 신축 Robot-ready Option 계약 Project | C48: 개 | D48: Conservative | E48: 0 | F48: 0 | G48: 0 | H48: 1 | I48: 2 | J48: TARGET | K48: 계약 2년 후 입주·설치
A49: projects | B49: 신축 Robot-ready Option 계약 Project | C49: 개 | D49: Base | E49: 0 | F49: 0 | G49: 1 | H49: 2 | I49: 3 | J49: TARGET | K49: 계약 2년 후 입주·설치
A50: projects | B50: 신축 Robot-ready Option 계약 Project | C50: 개 | D50: Upside | E50: 0 | F50: 0 | G50: 2 | H50: 3 | I50: 4 | J50: TARGET | K50: 계약 2년 후 입주·설치
A52: fte | B52: 평균 인원 | C52: 명 | D52: Conservative | E52: 4.4 | F52: 7 | G52: 20 | H52: 32 | I52: 42 | J52: ASSUMPTION | K52: Y1~Y2 = TIPS 기간 (대표 + 신규 연구원 4명 → Y2 실증 엔지니어 · 사업개발 추가, TIPS_TEAM). Y3부터 후속 투자 전제
A53: fte | B53: 평균 인원 | C53: 명 | D53: Base | E53: 4.4 | F53: 7 | G53: 20 | H53: 32 | I53: 42 | J53: ASSUMPTION | K53: Y1~Y2 = TIPS 기간 (대표 + 신규 연구원 4명 → Y2 실증 엔지니어 · 사업개발 추가, TIPS_TEAM). Y3부터 후속 투자 전제
A54: fte | B54: 평균 인원 | C54: 명 | D54: Upside | E54: 4.4 | F54: 7 | G54: 20 | H54: 32 | I54: 42 | J54: ASSUMPTION | K54: Y1~Y2 = TIPS 기간 (대표 + 신규 연구원 4명 → Y2 실증 엔지니어 · 사업개발 추가, TIPS_TEAM). Y3부터 후속 투자 전제
A56: proto | B56: Robot·Kitchen Prototype (H/W) | C56: 만원 | D56: Conservative | E56: 12000 | F56: 4000 | G56: 30000 | H56: 35000 | I56: 40000 | J56: ASSUMPTION | K56: Y1 시제품 1차 2식 + 실물 크기 목업 주방 2식 · Y2 2차 개선 부품 (실증 3세대 하드웨어는 원가에 반영)
A57: proto | B57: Robot·Kitchen Prototype (H/W) | C57: 만원 | D57: Base | E57: 12000 | F57: 4000 | G57: 30000 | H57: 35000 | I57: 40000 | J57: ASSUMPTION | K57: Y1 시제품 1차 2식 + 실물 크기 목업 주방 2식 · Y2 2차 개선 부품 (실증 3세대 하드웨어는 원가에 반영)
A58: proto | B58: Robot·Kitchen Prototype (H/W) | C58: 만원 | D58: Upside | E58: 12000 | F58: 4000 | G58: 30000 | H58: 35000 | I58: 40000 | J58: ASSUMPTION | K58: Y1 시제품 1차 2식 + 실물 크기 목업 주방 2식 · Y2 2차 개선 부품 (실증 3세대 하드웨어는 원가에 반영)
A60: swdata | B60: Vision·Software·Data (GPU·Cloud·Annotation) | C60: 만원 | D60: Conservative | E60: 2000 | F60: 3000 | G60: 10000 | H60: 15000 | I60: 20000 | J60: ASSUMPTION
A61: swdata | B61: Vision·Software·Data (GPU·Cloud·Annotation) | C61: 만원 | D61: Base | E61: 2000 | F61: 3000 | G61: 10000 | H61: 15000 | I61: 20000 | J61: ASSUMPTION
A62: swdata | B62: Vision·Software·Data (GPU·Cloud·Annotation) | C62: 만원 | D62: Upside | E62: 2000 | F62: 3000 | G62: 10000 | H62: 15000 | I62: 20000 | J62: ASSUMPTION
A64: space | B64: Full-scale Mock-up·공간 | C64: 만원 | D64: Conservative | E64: 6000 | F64: 4000 | G64: 10000 | H64: 12000 | I64: 15000 | J64: ASSUMPTION | K64: Y1~Y2: 목업 공간 약 30평 임차 + 목업 시공
A65: space | B65: Full-scale Mock-up·공간 | C65: 만원 | D65: Base | E65: 6000 | F65: 4000 | G65: 10000 | H65: 12000 | I65: 15000 | J65: ASSUMPTION | K65: Y1~Y2: 목업 공간 약 30평 임차 + 목업 시공
A66: space | B66: Full-scale Mock-up·공간 | C66: 만원 | D66: Upside | E66: 6000 | F66: 4000 | G66: 10000 | H66: 12000 | I66: 15000 | J66: ASSUMPTION | K66: Y1~Y2: 목업 공간 약 30평 임차 + 목업 시공
A68: cert_ip | B68: Safety·Certification·IP | C68: 만원 | D68: Conservative | E68: 2500 | F68: 6000 | G68: 20000 | H68: 10000 | I68: 10000 | J68: ASSUMPTION | K68: Y1 선행기술조사 · 특허 출원 2건 / Y2 공인시험 · 안전 사전시험 · 특허 3건 / Y3 본인증
A69: cert_ip | B69: Safety·Certification·IP | C69: 만원 | D69: Base | E69: 2500 | F69: 6000 | G69: 20000 | H69: 10000 | I69: 10000 | J69: ASSUMPTION | K69: Y1 선행기술조사 · 특허 출원 2건 / Y2 공인시험 · 안전 사전시험 · 특허 3건 / Y3 본인증
A70: cert_ip | B70: Safety·Certification·IP | C70: 만원 | D70: Upside | E70: 2500 | F70: 6000 | G70: 20000 | H70: 10000 | I70: 10000 | J70: ASSUMPTION | K70: Y1 선행기술조사 · 특허 출원 2건 / Y2 공인시험 · 안전 사전시험 · 특허 3건 / Y3 본인증
A72: research | B72: Pilot·Customer Validation | C72: 만원 | D72: Conservative | E72: 2000 | F72: 3500 | G72: 5000 | H72: 5000 | I72: 5000 | J72: ASSUMPTION | K72: Y1 인터뷰 50명 · 정리 시간 기록 30세대 / Y2 지불의사 조사 n≥300 · 실증 가정 지원
A73: research | B73: Pilot·Customer Validation | C73: 만원 | D73: Base | E73: 2000 | F73: 3500 | G73: 5000 | H73: 5000 | I73: 5000 | J73: ASSUMPTION | K73: Y1 인터뷰 50명 · 정리 시간 기록 30세대 / Y2 지불의사 조사 n≥300 · 실증 가정 지원
A74: research | B74: Pilot·Customer Validation | C74: 만원 | D74: Upside | E74: 2000 | F74: 3500 | G74: 5000 | H74: 5000 | I74: 5000 | J74: ASSUMPTION | K74: Y1 인터뷰 50명 · 정리 시간 기록 30세대 / Y2 지불의사 조사 n≥300 · 실증 가정 지원
A76: mkt | B76: Marketing·Partner Enablement | C76: 만원 | D76: Conservative | E76: 0 | F76: 1000 | G76: 30000 | H76: 50000 | I76: 70000 | J76: ASSUMPTION
A77: mkt | B77: Marketing·Partner Enablement | C77: 만원 | D77: Base | E77: 0 | F77: 1000 | G77: 30000 | H77: 50000 | I77: 70000 | J77: ASSUMPTION
A78: mkt | B78: Marketing·Partner Enablement | C78: 만원 | D78: Upside | E78: 0 | F78: 1000 | G78: 30000 | H78: 50000 | I78: 70000 | J78: ASSUMPTION
A80: ga | B80: G&A (법무·회계·보험·사무) | C80: 만원 | D80: Conservative | E80: 5000 | F80: 6000 | G80: 30000 | H80: 40000 | I80: 50000 | J80: ASSUMPTION
A81: ga | B81: G&A (법무·회계·보험·사무) | C81: 만원 | D81: Base | E81: 5000 | F81: 6000 | G81: 30000 | H81: 40000 | I81: 50000 | J81: ASSUMPTION
A82: ga | B82: G&A (법무·회계·보험·사무) | C82: 만원 | D82: Upside | E82: 5000 | F82: 6000 | G82: 30000 | H82: 40000 | I82: 50000 | J82: ASSUMPTION

Sheet FM_Conservative
A1: 5-Year Bottom-up Model — Conservative (만원)
A2: 모든 입력은 Inputs / Inputs_Yearly의 Conservative 열·행을 참조 (녹색). 영업이익은 이자·세금 제외 근사.
A3: 항목 | B3: 단위 | C3: Y1 | D3: Y2 | E3: Y3 | F3: Y4 | G3: Y5 | H3: 5Y 합계
A4: VOLUME
A5: 구축 직접판매 Kitchen | B5: 세대 | C5: =Inputs_Yearly!$E$28 -> 0 | D5: =Inputs_Yearly!$F$28 -> 3 | E5: =Inputs_Yearly!$G$28 -> 20 | F5: =Inputs_Yearly!$H$28 -> 35 | G5: =Inputs_Yearly!$I$28 -> 40 | H5: =SUM(C5:G5) -> 98
A6: 구축 Partner 경유 Kitchen | B6: 세대 | C6: =Inputs_Yearly!$E$32 -> 0 | D6: =Inputs_Yearly!$F$32 -> 0 | E6: =Inputs_Yearly!$G$32 -> 10 | F6: =Inputs_Yearly!$H$32 -> 60 | G6: =Inputs_Yearly!$I$32 -> 150 | H6: =SUM(C6:G6) -> 220
A7: 신축 Robot-ready 설치 (계약 2년 후) | B7: 세대 | C7: =0 -> 0 | D7: =0 -> 0 | E7: =Inputs_Yearly!$E$48*Inputs!$D$73*Inputs!$D$74 -> 0 | F7: =Inputs_Yearly!$F$48*Inputs!$D$73*Inputs!$D$74 -> 0 | G7: =Inputs_Yearly!$G$48*Inputs!$D$73*Inputs!$D$74 -> 0 | H7: =SUM(C7:G7) -> 0
A8: Kitchen 설치 합계 | B8: 세대 | C8: =C5+C6+C7 -> 0 | D8: =D5+D6+D7 -> 3 | E8: =E5+E6+E7 -> 30 | F8: =F5+F6+F7 -> 95 | G8: =G5+G6+G7 -> 190 | H8: =SUM(C8:G8) -> 318
A9: Robot Attach Rate (구축) | B9: % | C9: =Inputs_Yearly!$E$36 -> 1 | D9: =Inputs_Yearly!$F$36 -> 1 | E9: =Inputs_Yearly!$G$36 -> 0.75 | F9: =Inputs_Yearly!$H$36 -> 0.75 | G9: =Inputs_Yearly!$I$36 -> 0.75
A10: Robot-ready Only 세대 후속 Attach | B10: 대 | C10: =0*Inputs!$D$72 -> 0 | D10: =C20*Inputs!$D$72 -> 0 | E10: =D20*Inputs!$D$72 -> 0 | F10: =E20*Inputs!$D$72 -> 0.375 | G10: =F20*Inputs!$D$72 -> 1.54375 | H10: =SUM(C10:G10) -> 1.91875
A11: Robot 설치 — 구축 | B11: 대 | C11: =(C5+C6)*C9 -> 0 | D11: =(D5+D6)*D9 -> 3 | E11: =(E5+E6)*E9 -> 22.5 | F11: =(F5+F6)*F9 -> 71.25 | G11: =(G5+G6)*G9 -> 142.5 | H11: =SUM(C11:G11) -> 239.25
A12: Robot 설치 — 신축 입주 | B12: 대 | C12: =C7*Inputs!$D$75 -> 0 | D12: =D7*Inputs!$D$75 -> 0 | E12: =E7*Inputs!$D$75 -> 0 | F12: =F7*Inputs!$D$75 -> 0 | G12: =G7*Inputs!$D$75 -> 0 | H12: =SUM(C12:G12) -> 0
A13: Robot 설치 합계 | B13: 대 | C13: =C11+C12+C10 -> 0 | D13: =D11+D12+D10 -> 3 | E13: =E11+E12+E10 -> 22.5 | F13: =F11+F12+F10 -> 71.625 | G13: =G11+G12+G10 -> 144.04375 | H13: =SUM(C13:G13) -> 241.16875
A14: Rental 비중 | B14: % | C14: =Inputs_Yearly!$E$40 -> 0 | D14: =Inputs_Yearly!$F$40 -> 0.3 | E14: =Inputs_Yearly!$G$40 -> 0.3 | F14: =Inputs_Yearly!$H$40 -> 0.35 | G14: =Inputs_Yearly!$I$40 -> 0.35
A15: Rental Partner 보유 Flag | B15: flag | C15: =Inputs_Yearly!$E$44 -> 0 | D15: =Inputs_Yearly!$F$44 -> 0 | E15: =Inputs_Yearly!$G$44 -> 0 | F15: =Inputs_Yearly!$H$44 -> 1 | G15: =Inputs_Yearly!$I$44 -> 1
A16: Rental 설치 | B16: 대 | C16: =C13*C14 -> 0 | D16: =D13*D14 -> 0.9 | E16: =E13*E14 -> 6.75 | F16: =F13*F14 -> 25.06875 | G16: =G13*G14 -> 50.415312 | H16: =SUM(C16:G16) -> 83.134062
A17: 구매 설치 | B17: 대 | C17: =C13-C16 -> 0 | D17: =D13-D16 -> 2.1 | E17: =E13-E16 -> 15.75 | F17: =F13-F16 -> 46.55625 | G17: =G13-G16 -> 93.628438 | H17: =SUM(C17:G17) -> 158.03469
A18: Rental — ARKI 보유 (Pilot) | B18: 대 | C18: =C16*(1-C15) -> 0 | D18: =D16*(1-D15) -> 0.9 | E18: =E16*(1-E15) -> 6.75 | F18: =F16*(1-F15) -> 0 | G18: =G16*(1-G15) -> 0 | H18: =SUM(C18:G18) -> 7.65
A19: Rental — Partner 보유 | B19: 대 | C19: =C16*C15 -> 0 | D19: =D16*D15 -> 0 | E19: =E16*E15 -> 0 | F19: =F16*F15 -> 25.06875 | G19: =G16*G15 -> 50.415312 | H19: =SUM(C19:G19) -> 75.484062
A20: Robot-ready Only 누적 (기말) | B20: 세대 | C20: =0+(C5+C6)*(1-C9)+C7*(1-Inputs!$D$75)-C10 -> 0 | D20: =C20+(D5+D6)*(1-D9)+D7*(1-Inputs!$D$75)-D10 -> 0 | E20: =D20+(E5+E6)*(1-E9)+E7*(1-Inputs!$D$75)-E10 -> 7.5 | F20: =E20+(F5+F6)*(1-F9)+F7*(1-Inputs!$D$75)-F10 -> 30.875 | G20: =F20+(G5+G6)*(1-G9)+G7*(1-Inputs!$D$75)-G10 -> 76.83125
A21: 구매 Robot 누적 (기말) | B21: 대 | C21: =0+C17 -> 0 | D21: =C21+D17 -> 2.1 | E21: =D21+E17 -> 17.85 | F21: =E21+F17 -> 64.40625 | G21: =F21+G17 -> 158.03469
A22: 구매 Robot 평균 가동 | B22: 대 | C22: =0+C17/2 -> 0 | D22: =C21+D17/2 -> 1.05 | E22: =D21+E17/2 -> 9.975 | F22: =E21+F17/2 -> 41.128125 | G22: =F21+G17/2 -> 111.22047
A23: ARKI Rental 누적 (기말) | B23: 대 | C23: =0+C18 -> 0 | D23: =C23+D18 -> 0.9 | E23: =D23+E18 -> 7.65 | F23: =E23+F18 -> 7.65 | G23: =F23+G18 -> 7.65
A24: ARKI Rental 평균 가동 | B24: 대 | C24: =0+C18/2 -> 0 | D24: =C23+D18/2 -> 0.45 | E24: =D23+E18/2 -> 4.275 | F24: =E23+F18/2 -> 7.65 | G24: =F23+G18/2 -> 7.65
A25: Partner Rental 누적 (기말) | B25: 대 | C25: =0+C19 -> 0 | D25: =C25+D19 -> 0 | E25: =D25+E19 -> 0 | F25: =E25+F19 -> 25.06875 | G25: =F25+G19 -> 75.484062
A26: Partner Rental 평균 가동 | B26: 대 | C26: =0+C19/2 -> 0 | D26: =C25+D19/2 -> 0 | E26: =D25+E19/2 -> 0 | F26: =E25+F19/2 -> 12.534375 | G26: =F25+G19/2 -> 50.276406
A27: Installed Robot (기말) | B27: 대 | C27: =C21+C23+C25 -> 0 | D27: =D21+D23+D25 -> 3 | E27: =E21+E23+E25 -> 25.5 | F27: =F21+F23+F25 -> 97.125 | G27: =G21+G23+G25 -> 241.16875
A28: 신축 계약 Backlog (미설치 세대) | B28: 세대 | C28: =Inputs_Yearly!$E$48*Inputs!$D$73*Inputs!$D$74 -> 0 | D28: =(Inputs_Yearly!$F$48+Inputs_Yearly!$E$48)*Inputs!$D$73*Inputs!$D$74 -> 0 | E28: =(Inputs_Yearly!$G$48+Inputs_Yearly!$F$48)*Inputs!$D$73*Inputs!$D$74 -> 0 | F28: =(Inputs_Yearly!$H$48+Inputs_Yearly!$G$48)*Inputs!$D$73*Inputs!$D$74 -> 48 | G28: =(Inputs_Yearly!$I$48+Inputs_Yearly!$H$48)*Inputs!$D$73*Inputs!$D$74 -> 144
A29: REVENUE (만원)
A30: 가격 실현율 | B30: % | C30: =Inputs_Yearly!$E$4 -> 1 | D30: =Inputs_Yearly!$F$4 -> 0.3 | E30: =Inputs_Yearly!$G$4 -> 1 | F30: =Inputs_Yearly!$H$4 -> 1 | G30: =Inputs_Yearly!$I$4 -> 1
A31: Consumables 연 List (구매 고객) | B31: 만원/대 | C31: =Inputs!$D$38*Inputs!$D$39+Inputs!$D$40*Inputs!$D$41+Inputs!$D$42*Inputs!$D$43 -> 36 | D31: =Inputs!$D$38*Inputs!$D$39+Inputs!$D$40*Inputs!$D$41+Inputs!$D$42*Inputs!$D$43 -> 36 | E31: =Inputs!$D$38*Inputs!$D$39+Inputs!$D$40*Inputs!$D$41+Inputs!$D$42*Inputs!$D$43 -> 36 | F31: =Inputs!$D$38*Inputs!$D$39+Inputs!$D$40*Inputs!$D$41+Inputs!$D$42*Inputs!$D$43 -> 36 | G31: =Inputs!$D$38*Inputs!$D$39+Inputs!$D$40*Inputs!$D$41+Inputs!$D$42*Inputs!$D$43 -> 36
A32: Consumables 연 List (Rental, Grip 제외) | B32: 만원/대 | C32: =Inputs!$D$40*Inputs!$D$41+Inputs!$D$42*Inputs!$D$43 -> 18 | D32: =Inputs!$D$40*Inputs!$D$41+Inputs!$D$42*Inputs!$D$43 -> 18 | E32: =Inputs!$D$40*Inputs!$D$41+Inputs!$D$42*Inputs!$D$43 -> 18 | F32: =Inputs!$D$40*Inputs!$D$41+Inputs!$D$42*Inputs!$D$43 -> 18 | G32: =Inputs!$D$40*Inputs!$D$41+Inputs!$D$42*Inputs!$D$43 -> 18
A33: Grip Kit 연 List | B33: 만원/대 | C33: =Inputs!$D$38*Inputs!$D$39 -> 18 | D33: =Inputs!$D$38*Inputs!$D$39 -> 18 | E33: =Inputs!$D$38*Inputs!$D$39 -> 18 | F33: =Inputs!$D$38*Inputs!$D$39 -> 18 | G33: =Inputs!$D$38*Inputs!$D$39 -> 18
A34: A. Kitchen Build (Robot-ready) | B34: 만원 | C34: =(C5+C6)*Inputs!$D$30*C30+C7*Inputs!$D$31 -> 0 | D34: =(D5+D6)*Inputs!$D$30*D30+D7*Inputs!$D$31 -> 360 | E34: =(E5+E6)*Inputs!$D$30*E30+E7*Inputs!$D$31 -> 12000 | F34: =(F5+F6)*Inputs!$D$30*F30+F7*Inputs!$D$31 -> 38000 | G34: =(G5+G6)*Inputs!$D$30*G30+G7*Inputs!$D$31 -> 76000 | H34: =SUM(C34:G34) -> 126360
A35: A. 설치·Calibration | B35: 만원 | C35: =C13*Inputs!$D$33*C30 -> 0 | D35: =D13*Inputs!$D$33*D30 -> 72 | E35: =E13*Inputs!$D$33*E30 -> 1800 | F35: =F13*Inputs!$D$33*F30 -> 5730 | G35: =G13*Inputs!$D$33*G30 -> 11523.5 | H35: =SUM(C35:G35) -> 19125.5
A36: A. Robot Hardware (구매 + Rental Partner 공급) | B36: 만원 | C36: =C17*Inputs!$D$32*C30+C19*Inputs!$D$32*Inputs!$D$50 -> 0 | D36: =D17*Inputs!$D$32*D30+D19*Inputs!$D$32*Inputs!$D$50 -> 812.7 | E36: =E17*Inputs!$D$32*E30+E19*Inputs!$D$32*Inputs!$D$50 -> 20317.5 | F36: =F17*Inputs!$D$32*F30+F19*Inputs!$D$32*Inputs!$D$50 -> 88515.607 | G36: =G17*Inputs!$D$32*G30+G19*Inputs!$D$32*Inputs!$D$50 -> 178012.15 | H36: =SUM(C36:G36) -> 287657.95
A37: B. Rental (ARKI 보유) | B37: 만원 | C37: =C24*Inputs!$D$34*12 -> 0 | D37: =D24*Inputs!$D$34*12 -> 156.6 | E37: =E24*Inputs!$D$34*12 -> 1487.7 | F37: =F24*Inputs!$D$34*12 -> 2662.2 | G37: =G24*Inputs!$D$34*12 -> 2662.2 | H37: =SUM(C37:G37) -> 6968.7
A38: B. Care (구매 고객 + Partner 서비스료) | B38: 만원 | C38: =C22*Inputs!$D$45*Inputs!$D$36+C26*Inputs!$D$51*12 -> 0 | D38: =D22*Inputs!$D$45*Inputs!$D$36+D26*Inputs!$D$51*12 -> 24.255 | E38: =E22*Inputs!$D$45*Inputs!$D$36+E26*Inputs!$D$51*12 -> 230.4225 | F38: =F22*Inputs!$D$45*Inputs!$D$36+F26*Inputs!$D$51*12 -> 1852.5347 | G38: =G22*Inputs!$D$45*Inputs!$D$36+G26*Inputs!$D$51*12 -> 6189.0941 | H38: =SUM(C38:G38) -> 8296.3063
A39: B. Consumables | B39: 만원 | C39: =C22*Inputs!$D$44*C31+(C24+C26)*Inputs!$D$44*C32 -> 0 | D39: =D22*Inputs!$D$44*D31+(D24+D26)*Inputs!$D$44*D32 -> 25.245 | E39: =E22*Inputs!$D$44*E31+(E24+E26)*Inputs!$D$44*E32 -> 239.8275 | F39: =F22*Inputs!$D$44*F31+(F24+F26)*Inputs!$D$44*F32 -> 1014.1622 | G39: =G22*Inputs!$D$44*G31+(G24+G26)*Inputs!$D$44*G32 -> 2775.6367 | H39: =SUM(C39:G39) -> 4054.8714
A40: C. Upgrade (Software Skill + Tool) | B40: 만원 | C40: =0*Inputs!$D$47*Inputs!$D$46+0*Inputs!$D$49*Inputs!$D$48 -> 0 | D40: =C13*Inputs!$D$47*Inputs!$D$46+0*Inputs!$D$49*Inputs!$D$48 -> 0 | E40: =D13*Inputs!$D$47*Inputs!$D$46+C13*Inputs!$D$49*Inputs!$D$48 -> 18 | F40: =E13*Inputs!$D$47*Inputs!$D$46+D13*Inputs!$D$49*Inputs!$D$48 -> 171 | G40: =F13*Inputs!$D$47*Inputs!$D$46+E13*Inputs!$D$49*Inputs!$D$48 -> 699.75 | H40: =SUM(C40:G40) -> 888.75
A41: 매출 합계 | B41: 만원 | C41: =SUM(C34:C40) -> 0 | D41: =SUM(D34:D40) -> 1450.8 | E41: =SUM(E34:E40) -> 36093.45 | F41: =SUM(F34:F40) -> 137945.5 | G41: =SUM(G34:G40) -> 277862.33 | H41: =SUM(C41:G41) -> 453352.08
A42: COGS (만원)
A43: Standard Module 사용률 | B43: % | C43: =Inputs_Yearly!$E$8 -> 0.4 | D43: =Inputs_Yearly!$F$8 -> 0.45 | E43: =Inputs_Yearly!$G$8 -> 0.55 | F43: =Inputs_Yearly!$H$8 -> 0.62 | G43: =Inputs_Yearly!$I$8 -> 0.65
A44: Kitchen Module 원가/세대 | B44: 만원 | C44: =Inputs!$D$53*(C43+Inputs!$D$54*(1-C43))+Inputs!$D$55*(1-C43) -> 332 | D44: =Inputs!$D$53*(D43+Inputs!$D$54*(1-D43))+Inputs!$D$55*(1-D43) -> 321 | E44: =Inputs!$D$53*(E43+Inputs!$D$54*(1-E43))+Inputs!$D$55*(1-E43) -> 299 | F44: =Inputs!$D$53*(F43+Inputs!$D$54*(1-F43))+Inputs!$D$55*(1-F43) -> 283.6 | G44: =Inputs!$D$53*(G43+Inputs!$D$54*(1-G43))+Inputs!$D$55*(1-G43) -> 277
A45: Robot BOM/대 | B45: 만원 | C45: =Inputs_Yearly!$E$12 -> 1600 | D45: =Inputs_Yearly!$F$12 -> 1500 | E45: =Inputs_Yearly!$G$12 -> 1300 | F45: =Inputs_Yearly!$H$12 -> 1180 | G45: =Inputs_Yearly!$I$12 -> 1080
A46: Care 원가/대·년 | B46: 만원 | C46: =Inputs_Yearly!$E$20*Inputs_Yearly!$E$24+Inputs!$D$59*Inputs!$D$60+Inputs!$D$61 -> 50.2 | D46: =Inputs_Yearly!$F$20*Inputs_Yearly!$F$24+Inputs!$D$59*Inputs!$D$60+Inputs!$D$61 -> 48.2 | E46: =Inputs_Yearly!$G$20*Inputs_Yearly!$G$24+Inputs!$D$59*Inputs!$D$60+Inputs!$D$61 -> 45.2 | F46: =Inputs_Yearly!$H$20*Inputs_Yearly!$H$24+Inputs!$D$59*Inputs!$D$60+Inputs!$D$61 -> 42.2 | G46: =Inputs_Yearly!$I$20*Inputs_Yearly!$I$24+Inputs!$D$59*Inputs!$D$60+Inputs!$D$61 -> 40.2
A47: Kitchen Module 원가 | B47: 만원 | C47: =(C5+C6)*C44+C7*Inputs!$D$56 -> 0 | D47: =(D5+D6)*D44+D7*Inputs!$D$56 -> 963 | E47: =(E5+E6)*E44+E7*Inputs!$D$56 -> 8970 | F47: =(F5+F6)*F44+F7*Inputs!$D$56 -> 26942 | G47: =(G5+G6)*G44+G7*Inputs!$D$56 -> 52630 | H47: =SUM(C47:G47) -> 89505
A48: 물류 | B48: 만원 | C48: =(C5+C6+C7)*Inputs!$D$57 -> 0 | D48: =(D5+D6+D7)*Inputs!$D$57 -> 75 | E48: =(E5+E6+E7)*Inputs!$D$57 -> 750 | F48: =(F5+F6+F7)*Inputs!$D$57 -> 2375 | G48: =(G5+G6+G7)*Inputs!$D$57 -> 4750 | H48: =SUM(C48:G48) -> 7950
A49: Robot BOM (판매분) | B49: 만원 | C49: =(C17+C19)*C45 -> 0 | D49: =(D17+D19)*D45 -> 3150 | E49: =(E17+E19)*E45 -> 20475 | F49: =(F17+F19)*F45 -> 84517.5 | G49: =(G17+G19)*G45 -> 155567.25 | H49: =SUM(C49:G49) -> 263709.75
A50: 설치·Calibration 원가 | B50: 만원 | C50: =C13*Inputs_Yearly!$E$16 -> 0 | D50: =D13*Inputs_Yearly!$F$16 -> 300 | E50: =E13*Inputs_Yearly!$G$16 -> 1687.5 | F50: =F13*Inputs_Yearly!$H$16 -> 4440.75 | G50: =G13*Inputs_Yearly!$I$16 -> 7922.4062 | H50: =SUM(C50:G50) -> 14350.656
A51: Warranty Reserve | B51: 만원 | C51: =Inputs!$D$58*C36 -> 0 | D51: =Inputs!$D$58*D36 -> 40.635 | E51: =Inputs!$D$58*E36 -> 1015.875 | F51: =Inputs!$D$58*F36 -> 4425.7804 | G51: =Inputs!$D$58*G36 -> 8900.6074 | H51: =SUM(C51:G51) -> 14382.898
A52: Rental 자산 취득 (ARKI 보유) | B52: 만원 | C52: =C18*C45 -> 0 | D52: =D18*D45 -> 1350 | E52: =E18*E45 -> 8775 | F52: =F18*F45 -> 0 | G52: =G18*G45 -> 0 | H52: =SUM(C52:G52) -> 10125
A53: Rental 자산 누적 취득 | B53: 만원 | C53: =0+C52 -> 0 | D53: =C53+D52 -> 1350 | E53: =D53+E52 -> 10125 | F53: =E53+F52 -> 10125 | G53: =F53+G52 -> 10125
A54: Rental 자산 감가상각 | B54: 만원 | C54: =0*(1-Inputs!$D$68)/5+C52*(1-Inputs!$D$68)/5*0.5 -> 0 | D54: =C53*(1-Inputs!$D$68)/5+D52*(1-Inputs!$D$68)/5*0.5 -> 114.75 | E54: =D53*(1-Inputs!$D$68)/5+E52*(1-Inputs!$D$68)/5*0.5 -> 975.375 | F54: =E53*(1-Inputs!$D$68)/5+F52*(1-Inputs!$D$68)/5*0.5 -> 1721.25 | G54: =F53*(1-Inputs!$D$68)/5+G52*(1-Inputs!$D$68)/5*0.5 -> 1721.25 | H54: =SUM(C54:G54) -> 4532.625
A55: Care Service 원가 | B55: 만원 | C55: =(C22*Inputs!$D$45+C24+C26)*C46 -> 0 | D55: =(D22*Inputs!$D$45+D24+D26)*D46 -> 49.5255 | E55: =(E22*Inputs!$D$45+E24+E26)*E46 -> 441.2085 | F55: =(F22*Inputs!$D$45+F24+F26)*F46 -> 1806.3644 | G55: =(G22*Inputs!$D$45+G24+G26)*G46 -> 4787.7261 | H55: =SUM(C55:G55) -> 7084.8245
A56: Consumables 원가 (Rental Grip 포함) | B56: 만원 | C56: =C39*Inputs!$D$62+(C24+C26)*C33*Inputs!$D$62 -> 0 | D56: =D39*Inputs!$D$62+(D24+D26)*D33*Inputs!$D$62 -> 13.338 | E56: =E39*Inputs!$D$62+(E24+E26)*E33*Inputs!$D$62 -> 126.711 | F56: =F39*Inputs!$D$62+(F24+F26)*F33*Inputs!$D$62 -> 550.99238 | G56: =G39*Inputs!$D$62+(G24+G26)*G33*Inputs!$D$62 -> 1527.3248 | H56: =SUM(C56:G56) -> 2218.3662
A57: Upgrade 원가 | B57: 만원 | C57: =0*Inputs!$D$47*Inputs!$D$46*Inputs!$D$63+0*Inputs!$D$49*Inputs!$D$48*Inputs!$D$64 -> 0 | D57: =C13*Inputs!$D$47*Inputs!$D$46*Inputs!$D$63+0*Inputs!$D$49*Inputs!$D$48*Inputs!$D$64 -> 0 | E57: =D13*Inputs!$D$47*Inputs!$D$46*Inputs!$D$63+C13*Inputs!$D$49*Inputs!$D$48*Inputs!$D$64 -> 1.8 | F57: =E13*Inputs!$D$47*Inputs!$D$46*Inputs!$D$63+D13*Inputs!$D$49*Inputs!$D$48*Inputs!$D$64 -> 29.7 | G57: =F13*Inputs!$D$47*Inputs!$D$46*Inputs!$D$63+E13*Inputs!$D$49*Inputs!$D$48*Inputs!$D$64 -> 164.475 | H57: =SUM(C57:G57) -> 195.975
A58: COGS 합계 | B58: 만원 | C58: =C47+C48+C49+C50+C51+C54+C55+C56+C57 -> 0 | D58: =D47+D48+D49+D50+D51+D54+D55+D56+D57 -> 4706.2485 | E58: =E47+E48+E49+E50+E51+E54+E55+E56+E57 -> 34443.469 | F58: =F47+F48+F49+F50+F51+F54+F55+F56+F57 -> 126809.34 | G58: =G47+G48+G49+G50+G51+G54+G55+G56+G57 -> 237971.04 | H58: =SUM(C58:G58) -> 403930.09
A59: 매출총이익 | B59: 만원 | C59: =C41-C58 -> 0 | D59: =D41-D58 -> -3255.4485 | E59: =E41-E58 -> 1649.9805 | F59: =F41-F58 -> 11136.167 | G59: =G41-G58 -> 39891.288 | H59: =SUM(C59:G59) -> 49421.988
A60: 매출총이익률 | B60: % | C60: =IF(C41=0,0,C59/C41) -> 0 | D60: =IF(D41=0,0,D59/D41) -> -2.2438989 | E60: =IF(E41=0,0,E59/E41) -> 0.045714125 | F60: =IF(F41=0,0,F59/F41) -> 0.080728743 | G60: =IF(G41=0,0,G59/G41) -> 0.14356494
A61: CHANNEL · OPEX (만원)
A62: Partner 수수료 | B62: 만원 | C62: =Inputs!$D$65*C6*(Inputs!$D$30*C30+C9*(Inputs!$D$32+Inputs!$D$33)*C30) -> 0 | D62: =Inputs!$D$65*D6*(Inputs!$D$30*D30+D9*(Inputs!$D$32+Inputs!$D$33)*D30) -> 0 | E62: =Inputs!$D$65*E6*(Inputs!$D$30*E30+E9*(Inputs!$D$32+Inputs!$D$33)*E30) -> 1713 | F62: =Inputs!$D$65*F6*(Inputs!$D$30*F30+F9*(Inputs!$D$32+Inputs!$D$33)*F30) -> 10278 | G62: =Inputs!$D$65*G6*(Inputs!$D$30*G30+G9*(Inputs!$D$32+Inputs!$D$33)*G30) -> 25695 | H62: =SUM(C62:G62) -> 37686
A63: 직접판매 획득비용 | B63: 만원 | C63: =C5*Inputs!$D$66 -> 0 | D63: =D5*Inputs!$D$66 -> 540 | E63: =E5*Inputs!$D$66 -> 3600 | F63: =F5*Inputs!$D$66 -> 6300 | G63: =G5*Inputs!$D$66 -> 7200 | H63: =SUM(C63:G63) -> 17640
A64: 신축 Project 수주비용 | B64: 만원 | C64: =Inputs_Yearly!$E$48*Inputs!$D$67 -> 0 | D64: =Inputs_Yearly!$F$48*Inputs!$D$67 -> 0 | E64: =Inputs_Yearly!$G$48*Inputs!$D$67 -> 0 | F64: =Inputs_Yearly!$H$48*Inputs!$D$67 -> 2000 | G64: =Inputs_Yearly!$I$48*Inputs!$D$67 -> 4000 | H64: =SUM(C64:G64) -> 6000
A65: Contribution (매출총이익 − 채널·변동 판매비) | B65: 만원 | C65: =C59-C62-C63-C64 -> 0 | D65: =D59-D62-D63-D64 -> -3795.4485 | E65: =E59-E62-E63-E64 -> -3663.0195 | F65: =F59-F62-F63-F64 -> -7441.8328 | G65: =G59-G62-G63-G64 -> 2996.2884 | H65: =SUM(C65:G65) -> -11904.012
A66: 인건비 | B66: 만원 | C66: =Inputs_Yearly!$E$52*Inputs!$D$77 -> 37400 | D66: =Inputs_Yearly!$F$52*Inputs!$D$77 -> 59500 | E66: =Inputs_Yearly!$G$52*Inputs!$D$77 -> 170000 | F66: =Inputs_Yearly!$H$52*Inputs!$D$77 -> 272000 | G66: =Inputs_Yearly!$I$52*Inputs!$D$77 -> 357000 | H66: =SUM(C66:G66) -> 895900
A67: 기타 운영비 (Prototype·SW·공간·인증/IP·검증·Marketing·G&A) | B67: 만원 | C67: =Inputs_Yearly!$E$56+Inputs_Yearly!$E$60+Inputs_Yearly!$E$64+Inputs_Yearly!$E$68+Inputs_Yearly!$E$72+Inputs_Yearly!$E$76+Inputs_Yearly!$E$80 -> 29500 | D67: =Inputs_Yearly!$F$56+Inputs_Yearly!$F$60+Inputs_Yearly!$F$64+Inputs_Yearly!$F$68+Inputs_Yearly!$F$72+Inputs_Yearly!$F$76+Inputs_Yearly!$F$80 -> 27500 | E67: =Inputs_Yearly!$G$56+Inputs_Yearly!$G$60+Inputs_Yearly!$G$64+Inputs_Yearly!$G$68+Inputs_Yearly!$G$72+Inputs_Yearly!$G$76+Inputs_Yearly!$G$80 -> 135000 | F67: =Inputs_Yearly!$H$56+Inputs_Yearly!$H$60+Inputs_Yearly!$H$64+Inputs_Yearly!$H$68+Inputs_Yearly!$H$72+Inputs_Yearly!$H$76+Inputs_Yearly!$H$80 -> 167000 | G67: =Inputs_Yearly!$I$56+Inputs_Yearly!$I$60+Inputs_Yearly!$I$64+Inputs_Yearly!$I$68+Inputs_Yearly!$I$72+Inputs_Yearly!$I$76+Inputs_Yearly!$I$80 -> 210000 | H67: =SUM(C67:G67) -> 569000
A68: Opex 합계 | B68: 만원 | C68: =C66+C67 -> 66900 | D68: =D66+D67 -> 87000 | E68: =E66+E67 -> 305000 | F68: =F66+F67 -> 439000 | G68: =G66+G67 -> 567000 | H68: =SUM(C68:G68) -> 1464900
A69: 영업이익 (근사) | B69: 만원 | C69: =C65-C68 -> -66900 | D69: =D65-D68 -> -90795.448 | E69: =E65-E68 -> -308663.02 | F69: =F65-F68 -> -446441.83 | G69: =G65-G68 -> -564003.71 | H69: =SUM(C69:G69) -> -1476804
A70: 현금흐름 (영업이익 + 감가 − Rental 자산) | B70: 만원 | C70: =C69+C54-C52 -> -66900 | D70: =D69+D54-D52 -> -92030.698 | E70: =E69+E54-E52 -> -316462.64 | F70: =F69+F54-F52 -> -444720.58 | G70: =G69+G54-G52 -> -562282.46 | H70: =SUM(C70:G70) -> -1482396.4
A71: 누적 현금흐름 | B71: 만원 | C71: =0+C70 -> -66900 | D71: =C71+D70 -> -158930.7 | E71: =D71+E70 -> -475393.34 | F71: =E71+F70 -> -920113.93 | G71: =F71+G70 -> -1482396.4
A72: MIX
A73: Build 매출 (Kitchen + 설치) | B73: 만원 | C73: =C34+C35 -> 0 | D73: =D34+D35 -> 432 | E73: =E34+E35 -> 13800 | F73: =F34+F35 -> 43730 | G73: =G34+G35 -> 87523.5 | H73: =SUM(C73:G73) -> 145485.5
A74: Recurring 매출 (Rental + Care + Consumables) | B74: 만원 | C74: =C37+C38+C39 -> 0 | D74: =D37+D38+D39 -> 206.1 | E74: =E37+E38+E39 -> 1957.95 | F74: =F37+F38+F39 -> 5528.8969 | G74: =G37+G38+G39 -> 11626.931 | H74: =SUM(C74:G74) -> 19319.878
A75: Robot + Recurring + Upgrade 비중 | B75: % | C75: =IF(C41=0,0,(C36+C74+C40)/C41) -> 0 | D75: =IF(D41=0,0,(D36+D74+D40)/D41) -> 0.70223325 | E75: =IF(E41=0,0,(E36+E74+E40)/E41) -> 0.61765916 | F75: =IF(F41=0,0,(F36+F74+F40)/F41) -> 0.68299076 | G75: =IF(G41=0,0,(G36+G74+G40)/G41) -> 0.68501128

Sheet FM_Base
A1: 5-Year Bottom-up Model — Base (만원)
A2: 모든 입력은 Inputs / Inputs_Yearly의 Base 열·행을 참조 (녹색). 영업이익은 이자·세금 제외 근사.
A3: 항목 | B3: 단위 | C3: Y1 | D3: Y2 | E3: Y3 | F3: Y4 | G3: Y5 | H3: 5Y 합계
A4: VOLUME
A5: 구축 직접판매 Kitchen | B5: 세대 | C5: =Inputs_Yearly!$E$29 -> 0 | D5: =Inputs_Yearly!$F$29 -> 3 | E5: =Inputs_Yearly!$G$29 -> 30 | F5: =Inputs_Yearly!$H$29 -> 50 | G5: =Inputs_Yearly!$I$29 -> 60 | H5: =SUM(C5:G5) -> 143
A6: 구축 Partner 경유 Kitchen | B6: 세대 | C6: =Inputs_Yearly!$E$33 -> 0 | D6: =Inputs_Yearly!$F$33 -> 0 | E6: =Inputs_Yearly!$G$33 -> 20 | F6: =Inputs_Yearly!$H$33 -> 130 | G6: =Inputs_Yearly!$I$33 -> 340 | H6: =SUM(C6:G6) -> 490
A7: 신축 Robot-ready 설치 (계약 2년 후) | B7: 세대 | C7: =0 -> 0 | D7: =0 -> 0 | E7: =Inputs_Yearly!$E$49*Inputs!$E$73*Inputs!$E$74 -> 0 | F7: =Inputs_Yearly!$F$49*Inputs!$E$73*Inputs!$E$74 -> 0 | G7: =Inputs_Yearly!$G$49*Inputs!$E$73*Inputs!$E$74 -> 80 | H7: =SUM(C7:G7) -> 80
A8: Kitchen 설치 합계 | B8: 세대 | C8: =C5+C6+C7 -> 0 | D8: =D5+D6+D7 -> 3 | E8: =E5+E6+E7 -> 50 | F8: =F5+F6+F7 -> 180 | G8: =G5+G6+G7 -> 480 | H8: =SUM(C8:G8) -> 713
A9: Robot Attach Rate (구축) | B9: % | C9: =Inputs_Yearly!$E$37 -> 1 | D9: =Inputs_Yearly!$F$37 -> 1 | E9: =Inputs_Yearly!$G$37 -> 0.85 | F9: =Inputs_Yearly!$H$37 -> 0.85 | G9: =Inputs_Yearly!$I$37 -> 0.85
A10: Robot-ready Only 세대 후속 Attach | B10: 대 | C10: =0*Inputs!$E$72 -> 0 | D10: =C20*Inputs!$E$72 -> 0 | E10: =D20*Inputs!$E$72 -> 0 | F10: =E20*Inputs!$E$72 -> 0.75 | G10: =F20*Inputs!$E$72 -> 3.375 | H10: =SUM(C10:G10) -> 4.125
A11: Robot 설치 — 구축 | B11: 대 | C11: =(C5+C6)*C9 -> 0 | D11: =(D5+D6)*D9 -> 3 | E11: =(E5+E6)*E9 -> 42.5 | F11: =(F5+F6)*F9 -> 153 | G11: =(G5+G6)*G9 -> 340 | H11: =SUM(C11:G11) -> 538.5
A12: Robot 설치 — 신축 입주 | B12: 대 | C12: =C7*Inputs!$E$75 -> 0 | D12: =D7*Inputs!$E$75 -> 0 | E12: =E7*Inputs!$E$75 -> 0 | F12: =F7*Inputs!$E$75 -> 0 | G12: =G7*Inputs!$E$75 -> 20 | H12: =SUM(C12:G12) -> 20
A13: Robot 설치 합계 | B13: 대 | C13: =C11+C12+C10 -> 0 | D13: =D11+D12+D10 -> 3 | E13: =E11+E12+E10 -> 42.5 | F13: =F11+F12+F10 -> 153.75 | G13: =G11+G12+G10 -> 363.375 | H13: =SUM(C13:G13) -> 562.625
A14: Rental 비중 | B14: % | C14: =Inputs_Yearly!$E$41 -> 0 | D14: =Inputs_Yearly!$F$41 -> 0.3 | E14: =Inputs_Yearly!$G$41 -> 0.3 | F14: =Inputs_Yearly!$H$41 -> 0.4 | G14: =Inputs_Yearly!$I$41 -> 0.4
A15: Rental Partner 보유 Flag | B15: flag | C15: =Inputs_Yearly!$E$45 -> 0 | D15: =Inputs_Yearly!$F$45 -> 0 | E15: =Inputs_Yearly!$G$45 -> 0 | F15: =Inputs_Yearly!$H$45 -> 1 | G15: =Inputs_Yearly!$I$45 -> 1
A16: Rental 설치 | B16: 대 | C16: =C13*C14 -> 0 | D16: =D13*D14 -> 0.9 | E16: =E13*E14 -> 12.75 | F16: =F13*F14 -> 61.5 | G16: =G13*G14 -> 145.35 | H16: =SUM(C16:G16) -> 220.5
A17: 구매 설치 | B17: 대 | C17: =C13-C16 -> 0 | D17: =D13-D16 -> 2.1 | E17: =E13-E16 -> 29.75 | F17: =F13-F16 -> 92.25 | G17: =G13-G16 -> 218.025 | H17: =SUM(C17:G17) -> 342.125
A18: Rental — ARKI 보유 (Pilot) | B18: 대 | C18: =C16*(1-C15) -> 0 | D18: =D16*(1-D15) -> 0.9 | E18: =E16*(1-E15) -> 12.75 | F18: =F16*(1-F15) -> 0 | G18: =G16*(1-G15) -> 0 | H18: =SUM(C18:G18) -> 13.65
A19: Rental — Partner 보유 | B19: 대 | C19: =C16*C15 -> 0 | D19: =D16*D15 -> 0 | E19: =E16*E15 -> 0 | F19: =F16*F15 -> 61.5 | G19: =G16*G15 -> 145.35 | H19: =SUM(C19:G19) -> 206.85
A20: Robot-ready Only 누적 (기말) | B20: 세대 | C20: =0+(C5+C6)*(1-C9)+C7*(1-Inputs!$E$75)-C10 -> 0 | D20: =C20+(D5+D6)*(1-D9)+D7*(1-Inputs!$E$75)-D10 -> 0 | E20: =D20+(E5+E6)*(1-E9)+E7*(1-Inputs!$E$75)-E10 -> 7.5 | F20: =E20+(F5+F6)*(1-F9)+F7*(1-Inputs!$E$75)-F10 -> 33.75 | G20: =F20+(G5+G6)*(1-G9)+G7*(1-Inputs!$E$75)-G10 -> 150.375
A21: 구매 Robot 누적 (기말) | B21: 대 | C21: =0+C17 -> 0 | D21: =C21+D17 -> 2.1 | E21: =D21+E17 -> 31.85 | F21: =E21+F17 -> 124.1 | G21: =F21+G17 -> 342.125
A22: 구매 Robot 평균 가동 | B22: 대 | C22: =0+C17/2 -> 0 | D22: =C21+D17/2 -> 1.05 | E22: =D21+E17/2 -> 16.975 | F22: =E21+F17/2 -> 77.975 | G22: =F21+G17/2 -> 233.1125
A23: ARKI Rental 누적 (기말) | B23: 대 | C23: =0+C18 -> 0 | D23: =C23+D18 -> 0.9 | E23: =D23+E18 -> 13.65 | F23: =E23+F18 -> 13.65 | G23: =F23+G18 -> 13.65
A24: ARKI Rental 평균 가동 | B24: 대 | C24: =0+C18/2 -> 0 | D24: =C23+D18/2 -> 0.45 | E24: =D23+E18/2 -> 7.275 | F24: =E23+F18/2 -> 13.65 | G24: =F23+G18/2 -> 13.65
A25: Partner Rental 누적 (기말) | B25: 대 | C25: =0+C19 -> 0 | D25: =C25+D19 -> 0 | E25: =D25+E19 -> 0 | F25: =E25+F19 -> 61.5 | G25: =F25+G19 -> 206.85
A26: Partner Rental 평균 가동 | B26: 대 | C26: =0+C19/2 -> 0 | D26: =C25+D19/2 -> 0 | E26: =D25+E19/2 -> 0 | F26: =E25+F19/2 -> 30.75 | G26: =F25+G19/2 -> 134.175
A27: Installed Robot (기말) | B27: 대 | C27: =C21+C23+C25 -> 0 | D27: =D21+D23+D25 -> 3 | E27: =E21+E23+E25 -> 45.5 | F27: =F21+F23+F25 -> 199.25 | G27: =G21+G23+G25 -> 562.625
A28: 신축 계약 Backlog (미설치 세대) | B28: 세대 | C28: =Inputs_Yearly!$E$49*Inputs!$E$73*Inputs!$E$74 -> 0 | D28: =(Inputs_Yearly!$F$49+Inputs_Yearly!$E$49)*Inputs!$E$73*Inputs!$E$74 -> 0 | E28: =(Inputs_Yearly!$G$49+Inputs_Yearly!$F$49)*Inputs!$E$73*Inputs!$E$74 -> 80 | F28: =(Inputs_Yearly!$H$49+Inputs_Yearly!$G$49)*Inputs!$E$73*Inputs!$E$74 -> 240 | G28: =(Inputs_Yearly!$I$49+Inputs_Yearly!$H$49)*Inputs!$E$73*Inputs!$E$74 -> 400
A29: REVENUE (만원)
A30: 가격 실현율 | B30: % | C30: =Inputs_Yearly!$E$5 -> 1 | D30: =Inputs_Yearly!$F$5 -> 0.5 | E30: =Inputs_Yearly!$G$5 -> 1 | F30: =Inputs_Yearly!$H$5 -> 1 | G30: =Inputs_Yearly!$I$5 -> 1
A31: Consumables 연 List (구매 고객) | B31: 만원/대 | C31: =Inputs!$E$38*Inputs!$E$39+Inputs!$E$40*Inputs!$E$41+Inputs!$E$42*Inputs!$E$43 -> 36 | D31: =Inputs!$E$38*Inputs!$E$39+Inputs!$E$40*Inputs!$E$41+Inputs!$E$42*Inputs!$E$43 -> 36 | E31: =Inputs!$E$38*Inputs!$E$39+Inputs!$E$40*Inputs!$E$41+Inputs!$E$42*Inputs!$E$43 -> 36 | F31: =Inputs!$E$38*Inputs!$E$39+Inputs!$E$40*Inputs!$E$41+Inputs!$E$42*Inputs!$E$43 -> 36 | G31: =Inputs!$E$38*Inputs!$E$39+Inputs!$E$40*Inputs!$E$41+Inputs!$E$42*Inputs!$E$43 -> 36
A32: Consumables 연 List (Rental, Grip 제외) | B32: 만원/대 | C32: =Inputs!$E$40*Inputs!$E$41+Inputs!$E$42*Inputs!$E$43 -> 18 | D32: =Inputs!$E$40*Inputs!$E$41+Inputs!$E$42*Inputs!$E$43 -> 18 | E32: =Inputs!$E$40*Inputs!$E$41+Inputs!$E$42*Inputs!$E$43 -> 18 | F32: =Inputs!$E$40*Inputs!$E$41+Inputs!$E$42*Inputs!$E$43 -> 18 | G32: =Inputs!$E$40*Inputs!$E$41+Inputs!$E$42*Inputs!$E$43 -> 18
A33: Grip Kit 연 List | B33: 만원/대 | C33: =Inputs!$E$38*Inputs!$E$39 -> 18 | D33: =Inputs!$E$38*Inputs!$E$39 -> 18 | E33: =Inputs!$E$38*Inputs!$E$39 -> 18 | F33: =Inputs!$E$38*Inputs!$E$39 -> 18 | G33: =Inputs!$E$38*Inputs!$E$39 -> 18
A34: A. Kitchen Build (Robot-ready) | B34: 만원 | C34: =(C5+C6)*Inputs!$E$30*C30+C7*Inputs!$E$31 -> 0 | D34: =(D5+D6)*Inputs!$E$30*D30+D7*Inputs!$E$31 -> 675 | E34: =(E5+E6)*Inputs!$E$30*E30+E7*Inputs!$E$31 -> 22500 | F34: =(F5+F6)*Inputs!$E$30*F30+F7*Inputs!$E$31 -> 81000 | G34: =(G5+G6)*Inputs!$E$30*G30+G7*Inputs!$E$31 -> 197600 | H34: =SUM(C34:G34) -> 301775
A35: A. 설치·Calibration | B35: 만원 | C35: =C13*Inputs!$E$33*C30 -> 0 | D35: =D13*Inputs!$E$33*D30 -> 120 | E35: =E13*Inputs!$E$33*E30 -> 3400 | F35: =F13*Inputs!$E$33*F30 -> 12300 | G35: =G13*Inputs!$E$33*G30 -> 29070 | H35: =SUM(C35:G35) -> 44890
A36: A. Robot Hardware (구매 + Rental Partner 공급) | B36: 만원 | C36: =C17*Inputs!$E$32*C30+C19*Inputs!$E$32*Inputs!$E$50 -> 0 | D36: =D17*Inputs!$E$32*D30+D19*Inputs!$E$32*Inputs!$E$50 -> 1564.5 | E36: =E17*Inputs!$E$32*E30+E19*Inputs!$E$32*Inputs!$E$50 -> 44327.5 | F36: =F17*Inputs!$E$32*F30+F19*Inputs!$E$32*Inputs!$E$50 -> 218091.3 | G36: =G17*Inputs!$E$32*G30+G19*Inputs!$E$32*Inputs!$E$50 -> 515440.17 | H36: =SUM(C36:G36) -> 779423.47
A37: B. Rental (ARKI 보유) | B37: 만원 | C37: =C24*Inputs!$E$34*12 -> 0 | D37: =D24*Inputs!$E$34*12 -> 178.2 | E37: =E24*Inputs!$E$34*12 -> 2880.9 | F37: =F24*Inputs!$E$34*12 -> 5405.4 | G37: =G24*Inputs!$E$34*12 -> 5405.4 | H37: =SUM(C37:G37) -> 13869.9
A38: B. Care (구매 고객 + Partner 서비스료) | B38: 만원 | C38: =C22*Inputs!$E$45*Inputs!$E$36+C26*Inputs!$E$51*12 -> 0 | D38: =D22*Inputs!$E$45*Inputs!$E$36+D26*Inputs!$E$51*12 -> 35.28 | E38: =E22*Inputs!$E$45*Inputs!$E$36+E26*Inputs!$E$51*12 -> 570.36 | F38: =F22*Inputs!$E$45*Inputs!$E$36+F26*Inputs!$E$51*12 -> 4833.96 | G38: =G22*Inputs!$E$45*Inputs!$E$36+G26*Inputs!$E$51*12 -> 17493.18 | H38: =SUM(C38:G38) -> 22932.78
A39: B. Consumables | B39: 만원 | C39: =C22*Inputs!$E$44*C31+(C24+C26)*Inputs!$E$44*C32 -> 0 | D39: =D22*Inputs!$E$44*D31+(D24+D26)*Inputs!$E$44*D32 -> 32.13 | E39: =E22*Inputs!$E$44*E31+(E24+E26)*Inputs!$E$44*E32 -> 519.435 | F39: =F22*Inputs!$E$44*F31+(F24+F26)*Inputs!$E$44*F32 -> 2524.41 | G39: =G22*Inputs!$E$44*G31+(G24+G26)*Inputs!$E$44*G32 -> 7737.03 | H39: =SUM(C39:G39) -> 10813.005
A40: C. Upgrade (Software Skill + Tool) | B40: 만원 | C40: =0*Inputs!$E$47*Inputs!$E$46+0*Inputs!$E$49*Inputs!$E$48 -> 0 | D40: =C13*Inputs!$E$47*Inputs!$E$46+0*Inputs!$E$49*Inputs!$E$48 -> 0 | E40: =D13*Inputs!$E$47*Inputs!$E$46+C13*Inputs!$E$49*Inputs!$E$48 -> 36 | F40: =E13*Inputs!$E$47*Inputs!$E$46+D13*Inputs!$E$49*Inputs!$E$48 -> 570 | G40: =F13*Inputs!$E$47*Inputs!$E$46+E13*Inputs!$E$49*Inputs!$E$48 -> 2695 | H40: =SUM(C40:G40) -> 3301
A41: 매출 합계 | B41: 만원 | C41: =SUM(C34:C40) -> 0 | D41: =SUM(D34:D40) -> 2605.11 | E41: =SUM(E34:E40) -> 74234.195 | F41: =SUM(F34:F40) -> 324725.07 | G41: =SUM(G34:G40) -> 775440.78 | H41: =SUM(C41:G41) -> 1177005.2
A42: COGS (만원)
A43: Standard Module 사용률 | B43: % | C43: =Inputs_Yearly!$E$9 -> 0.4 | D43: =Inputs_Yearly!$F$9 -> 0.5 | E43: =Inputs_Yearly!$G$9 -> 0.65 | F43: =Inputs_Yearly!$H$9 -> 0.75 | G43: =Inputs_Yearly!$I$9 -> 0.8
A44: Kitchen Module 원가/세대 | B44: 만원 | C44: =Inputs!$E$53*(C43+Inputs!$E$54*(1-C43))+Inputs!$E$55*(1-C43) -> 332 | D44: =Inputs!$E$53*(D43+Inputs!$E$54*(1-D43))+Inputs!$E$55*(1-D43) -> 310 | E44: =Inputs!$E$53*(E43+Inputs!$E$54*(1-E43))+Inputs!$E$55*(1-E43) -> 277 | F44: =Inputs!$E$53*(F43+Inputs!$E$54*(1-F43))+Inputs!$E$55*(1-F43) -> 255 | G44: =Inputs!$E$53*(G43+Inputs!$E$54*(1-G43))+Inputs!$E$55*(1-G43) -> 244
A45: Robot BOM/대 | B45: 만원 | C45: =Inputs_Yearly!$E$13 -> 1600 | D45: =Inputs_Yearly!$F$13 -> 1450 | E45: =Inputs_Yearly!$G$13 -> 1150 | F45: =Inputs_Yearly!$H$13 -> 1000 | G45: =Inputs_Yearly!$I$13 -> 900
A46: Care 원가/대·년 | B46: 만원 | C46: =Inputs_Yearly!$E$21*Inputs_Yearly!$E$25+Inputs!$E$59*Inputs!$E$60+Inputs!$E$61 -> 44.8 | D46: =Inputs_Yearly!$F$21*Inputs_Yearly!$F$25+Inputs!$E$59*Inputs!$E$60+Inputs!$E$61 -> 40.8 | E46: =Inputs_Yearly!$G$21*Inputs_Yearly!$G$25+Inputs!$E$59*Inputs!$E$60+Inputs!$E$61 -> 36.8 | F46: =Inputs_Yearly!$H$21*Inputs_Yearly!$H$25+Inputs!$E$59*Inputs!$E$60+Inputs!$E$61 -> 28.3 | G46: =Inputs_Yearly!$I$21*Inputs_Yearly!$I$25+Inputs!$E$59*Inputs!$E$60+Inputs!$E$61 -> 26.8
A47: Kitchen Module 원가 | B47: 만원 | C47: =(C5+C6)*C44+C7*Inputs!$E$56 -> 0 | D47: =(D5+D6)*D44+D7*Inputs!$E$56 -> 930 | E47: =(E5+E6)*E44+E7*Inputs!$E$56 -> 13850 | F47: =(F5+F6)*F44+F7*Inputs!$E$56 -> 45900 | G47: =(G5+G6)*G44+G7*Inputs!$E$56 -> 108000 | H47: =SUM(C47:G47) -> 168680
A48: 물류 | B48: 만원 | C48: =(C5+C6+C7)*Inputs!$E$57 -> 0 | D48: =(D5+D6+D7)*Inputs!$E$57 -> 75 | E48: =(E5+E6+E7)*Inputs!$E$57 -> 1250 | F48: =(F5+F6+F7)*Inputs!$E$57 -> 4500 | G48: =(G5+G6+G7)*Inputs!$E$57 -> 12000 | H48: =SUM(C48:G48) -> 17825
A49: Robot BOM (판매분) | B49: 만원 | C49: =(C17+C19)*C45 -> 0 | D49: =(D17+D19)*D45 -> 3045 | E49: =(E17+E19)*E45 -> 34212.5 | F49: =(F17+F19)*F45 -> 153750 | G49: =(G17+G19)*G45 -> 327037.5 | H49: =SUM(C49:G49) -> 518045
A50: 설치·Calibration 원가 | B50: 만원 | C50: =C13*Inputs_Yearly!$E$17 -> 0 | D50: =D13*Inputs_Yearly!$F$17 -> 270 | E50: =E13*Inputs_Yearly!$G$17 -> 2550 | F50: =F13*Inputs_Yearly!$H$17 -> 6918.75 | G50: =G13*Inputs_Yearly!$I$17 -> 13808.25 | H50: =SUM(C50:G50) -> 23547
A51: Warranty Reserve | B51: 만원 | C51: =Inputs!$E$58*C36 -> 0 | D51: =Inputs!$E$58*D36 -> 62.58 | E51: =Inputs!$E$58*E36 -> 1773.1 | F51: =Inputs!$E$58*F36 -> 8723.652 | G51: =Inputs!$E$58*G36 -> 20617.607 | H51: =SUM(C51:G51) -> 31176.939
A52: Rental 자산 취득 (ARKI 보유) | B52: 만원 | C52: =C18*C45 -> 0 | D52: =D18*D45 -> 1305 | E52: =E18*E45 -> 14662.5 | F52: =F18*F45 -> 0 | G52: =G18*G45 -> 0 | H52: =SUM(C52:G52) -> 15967.5
A53: Rental 자산 누적 취득 | B53: 만원 | C53: =0+C52 -> 0 | D53: =C53+D52 -> 1305 | E53: =D53+E52 -> 15967.5 | F53: =E53+F52 -> 15967.5 | G53: =F53+G52 -> 15967.5
A54: Rental 자산 감가상각 | B54: 만원 | C54: =0*(1-Inputs!$E$68)/5+C52*(1-Inputs!$E$68)/5*0.5 -> 0 | D54: =C53*(1-Inputs!$E$68)/5+D52*(1-Inputs!$E$68)/5*0.5 -> 110.925 | E54: =D53*(1-Inputs!$E$68)/5+E52*(1-Inputs!$E$68)/5*0.5 -> 1468.1625 | F54: =E53*(1-Inputs!$E$68)/5+F52*(1-Inputs!$E$68)/5*0.5 -> 2714.475 | G54: =F53*(1-Inputs!$E$68)/5+G52*(1-Inputs!$E$68)/5*0.5 -> 2714.475 | H54: =SUM(C54:G54) -> 7008.0375
A55: Care Service 원가 | B55: 만원 | C55: =(C22*Inputs!$E$45+C24+C26)*C46 -> 0 | D55: =(D22*Inputs!$E$45+D24+D26)*D46 -> 48.348 | E55: =(E22*Inputs!$E$45+E24+E26)*E46 -> 704.996 | F55: =(F22*Inputs!$E$45+F24+F26)*F46 -> 2801.2047 | G55: =(G22*Inputs!$E$45+G24+G26)*G46 -> 8334.9005 | H55: =SUM(C55:G55) -> 11889.449
A56: Consumables 원가 (Rental Grip 포함) | B56: 만원 | C56: =C39*Inputs!$E$62+(C24+C26)*C33*Inputs!$E$62 -> 0 | D56: =D39*Inputs!$E$62+(D24+D26)*D33*Inputs!$E$62 -> 14.0805 | E56: =E39*Inputs!$E$62+(E24+E26)*E33*Inputs!$E$62 -> 227.63475 | F56: =F39*Inputs!$E$62+(F24+F26)*F33*Inputs!$E$62 -> 1163.2635 | G56: =G39*Inputs!$E$62+(G24+G26)*G33*Inputs!$E$62 -> 3639.258 | H56: =SUM(C56:G56) -> 5044.2368
A57: Upgrade 원가 | B57: 만원 | C57: =0*Inputs!$E$47*Inputs!$E$46*Inputs!$E$63+0*Inputs!$E$49*Inputs!$E$48*Inputs!$E$64 -> 0 | D57: =C13*Inputs!$E$47*Inputs!$E$46*Inputs!$E$63+0*Inputs!$E$49*Inputs!$E$48*Inputs!$E$64 -> 0 | E57: =D13*Inputs!$E$47*Inputs!$E$46*Inputs!$E$63+C13*Inputs!$E$49*Inputs!$E$48*Inputs!$E$64 -> 3.6 | F57: =E13*Inputs!$E$47*Inputs!$E$46*Inputs!$E$63+D13*Inputs!$E$49*Inputs!$E$48*Inputs!$E$64 -> 78 | G57: =F13*Inputs!$E$47*Inputs!$E$46*Inputs!$E$63+E13*Inputs!$E$49*Inputs!$E$48*Inputs!$E$64 -> 567 | H57: =SUM(C57:G57) -> 648.6
A58: COGS 합계 | B58: 만원 | C58: =C47+C48+C49+C50+C51+C54+C55+C56+C57 -> 0 | D58: =D47+D48+D49+D50+D51+D54+D55+D56+D57 -> 4555.9335 | E58: =E47+E48+E49+E50+E51+E54+E55+E56+E57 -> 56039.993 | F58: =F47+F48+F49+F50+F51+F54+F55+F56+F57 -> 226549.35 | G58: =G47+G48+G49+G50+G51+G54+G55+G56+G57 -> 496718.99 | H58: =SUM(C58:G58) -> 783864.26
A59: 매출총이익 | B59: 만원 | C59: =C41-C58 -> 0 | D59: =D41-D58 -> -1950.8235 | E59: =E41-E58 -> 18194.202 | F59: =F41-F58 -> 98175.725 | G59: =G41-G58 -> 278721.79 | H59: =SUM(C59:G59) -> 393140.89
A60: 매출총이익률 | B60: % | C60: =IF(C41=0,0,C59/C41) -> 0 | D60: =IF(D41=0,0,D59/D41) -> -0.74884496 | E60: =IF(E41=0,0,E59/E41) -> 0.24509192 | F60: =IF(F41=0,0,F59/F41) -> 0.30233491 | G60: =IF(G41=0,0,G59/G41) -> 0.35943659
A61: CHANNEL · OPEX (만원)
A62: Partner 수수료 | B62: 만원 | C62: =Inputs!$E$65*C6*(Inputs!$E$30*C30+C9*(Inputs!$E$32+Inputs!$E$33)*C30) -> 0 | D62: =Inputs!$E$65*D6*(Inputs!$E$30*D30+D9*(Inputs!$E$32+Inputs!$E$33)*D30) -> 0 | E62: =Inputs!$E$65*E6*(Inputs!$E$30*E30+E9*(Inputs!$E$32+Inputs!$E$33)*E30) -> 3569 | F62: =Inputs!$E$65*F6*(Inputs!$E$30*F30+F9*(Inputs!$E$32+Inputs!$E$33)*F30) -> 23198.5 | G62: =Inputs!$E$65*G6*(Inputs!$E$30*G30+G9*(Inputs!$E$32+Inputs!$E$33)*G30) -> 60673 | H62: =SUM(C62:G62) -> 87440.5
A63: 직접판매 획득비용 | B63: 만원 | C63: =C5*Inputs!$E$66 -> 0 | D63: =D5*Inputs!$E$66 -> 450 | E63: =E5*Inputs!$E$66 -> 4500 | F63: =F5*Inputs!$E$66 -> 7500 | G63: =G5*Inputs!$E$66 -> 9000 | H63: =SUM(C63:G63) -> 21450
A64: 신축 Project 수주비용 | B64: 만원 | C64: =Inputs_Yearly!$E$49*Inputs!$E$67 -> 0 | D64: =Inputs_Yearly!$F$49*Inputs!$E$67 -> 0 | E64: =Inputs_Yearly!$G$49*Inputs!$E$67 -> 2000 | F64: =Inputs_Yearly!$H$49*Inputs!$E$67 -> 4000 | G64: =Inputs_Yearly!$I$49*Inputs!$E$67 -> 6000 | H64: =SUM(C64:G64) -> 12000
A65: Contribution (매출총이익 − 채널·변동 판매비) | B65: 만원 | C65: =C59-C62-C63-C64 -> 0 | D65: =D59-D62-D63-D64 -> -2400.8235 | E65: =E59-E62-E63-E64 -> 8125.2018 | F65: =F59-F62-F63-F64 -> 63477.225 | G65: =G59-G62-G63-G64 -> 203048.79 | H65: =SUM(C65:G65) -> 272250.39
A66: 인건비 | B66: 만원 | C66: =Inputs_Yearly!$E$53*Inputs!$E$77 -> 37400 | D66: =Inputs_Yearly!$F$53*Inputs!$E$77 -> 59500 | E66: =Inputs_Yearly!$G$53*Inputs!$E$77 -> 170000 | F66: =Inputs_Yearly!$H$53*Inputs!$E$77 -> 272000 | G66: =Inputs_Yearly!$I$53*Inputs!$E$77 -> 357000 | H66: =SUM(C66:G66) -> 895900
A67: 기타 운영비 (Prototype·SW·공간·인증/IP·검증·Marketing·G&A) | B67: 만원 | C67: =Inputs_Yearly!$E$57+Inputs_Yearly!$E$61+Inputs_Yearly!$E$65+Inputs_Yearly!$E$69+Inputs_Yearly!$E$73+Inputs_Yearly!$E$77+Inputs_Yearly!$E$81 -> 29500 | D67: =Inputs_Yearly!$F$57+Inputs_Yearly!$F$61+Inputs_Yearly!$F$65+Inputs_Yearly!$F$69+Inputs_Yearly!$F$73+Inputs_Yearly!$F$77+Inputs_Yearly!$F$81 -> 27500 | E67: =Inputs_Yearly!$G$57+Inputs_Yearly!$G$61+Inputs_Yearly!$G$65+Inputs_Yearly!$G$69+Inputs_Yearly!$G$73+Inputs_Yearly!$G$77+Inputs_Yearly!$G$81 -> 135000 | F67: =Inputs_Yearly!$H$57+Inputs_Yearly!$H$61+Inputs_Yearly!$H$65+Inputs_Yearly!$H$69+Inputs_Yearly!$H$73+Inputs_Yearly!$H$77+Inputs_Yearly!$H$81 -> 167000 | G67: =Inputs_Yearly!$I$57+Inputs_Yearly!$I$61+Inputs_Yearly!$I$65+Inputs_Yearly!$I$69+Inputs_Yearly!$I$73+Inputs_Yearly!$I$77+Inputs_Yearly!$I$81 -> 210000 | H67: =SUM(C67:G67) -> 569000
A68: Opex 합계 | B68: 만원 | C68: =C66+C67 -> 66900 | D68: =D66+D67 -> 87000 | E68: =E66+E67 -> 305000 | F68: =F66+F67 -> 439000 | G68: =G66+G67 -> 567000 | H68: =SUM(C68:G68) -> 1464900
A69: 영업이익 (근사) | B69: 만원 | C69: =C65-C68 -> -66900 | D69: =D65-D68 -> -89400.823 | E69: =E65-E68 -> -296874.8 | F69: =F65-F68 -> -375522.78 | G69: =G65-G68 -> -363951.21 | H69: =SUM(C69:G69) -> -1192649.6
A70: 현금흐름 (영업이익 + 감가 − Rental 자산) | B70: 만원 | C70: =C69+C54-C52 -> -66900 | D70: =D69+D54-D52 -> -90594.898 | E70: =E69+E54-E52 -> -310069.14 | F70: =F69+F54-F52 -> -372808.3 | G70: =G69+G54-G52 -> -361236.74 | H70: =SUM(C70:G70) -> -1201609.1
A71: 누적 현금흐름 | B71: 만원 | C71: =0+C70 -> -66900 | D71: =C71+D70 -> -157494.9 | E71: =D71+E70 -> -467564.03 | F71: =E71+F70 -> -840372.33 | G71: =F71+G70 -> -1201609.1
A72: MIX
A73: Build 매출 (Kitchen + 설치) | B73: 만원 | C73: =C34+C35 -> 0 | D73: =D34+D35 -> 795 | E73: =E34+E35 -> 25900 | F73: =F34+F35 -> 93300 | G73: =G34+G35 -> 226670 | H73: =SUM(C73:G73) -> 346665
A74: Recurring 매출 (Rental + Care + Consumables) | B74: 만원 | C74: =C37+C38+C39 -> 0 | D74: =D37+D38+D39 -> 245.61 | E74: =E37+E38+E39 -> 3970.695 | F74: =F37+F38+F39 -> 12763.77 | G74: =G37+G38+G39 -> 30635.61 | H74: =SUM(C74:G74) -> 47615.685
A75: Robot + Recurring + Upgrade 비중 | B75: % | C75: =IF(C41=0,0,(C36+C74+C40)/C41) -> 0 | D75: =IF(D41=0,0,(D36+D74+D40)/D41) -> 0.69483054 | E75: =IF(E41=0,0,(E36+E74+E40)/E41) -> 0.65110418 | F75: =IF(F41=0,0,(F36+F74+F40)/F41) -> 0.71268002 | G75: =IF(G41=0,0,(G36+G74+G40)/G41) -> 0.70768883

Sheet FM_Upside
A1: 5-Year Bottom-up Model — Upside (만원)
A2: 모든 입력은 Inputs / Inputs_Yearly의 Upside 열·행을 참조 (녹색). 영업이익은 이자·세금 제외 근사.
A3: 항목 | B3: 단위 | C3: Y1 | D3: Y2 | E3: Y3 | F3: Y4 | G3: Y5 | H3: 5Y 합계
A4: VOLUME
A5: 구축 직접판매 Kitchen | B5: 세대 | C5: =Inputs_Yearly!$E$30 -> 0 | D5: =Inputs_Yearly!$F$30 -> 3 | E5: =Inputs_Yearly!$G$30 -> 35 | F5: =Inputs_Yearly!$H$30 -> 60 | G5: =Inputs_Yearly!$I$30 -> 70 | H5: =SUM(C5:G5) -> 168
A6: 구축 Partner 경유 Kitchen | B6: 세대 | C6: =Inputs_Yearly!$E$34 -> 0 | D6: =Inputs_Yearly!$F$34 -> 0 | E6: =Inputs_Yearly!$G$34 -> 30 | F6: =Inputs_Yearly!$H$34 -> 220 | G6: =Inputs_Yearly!$I$34 -> 600 | H6: =SUM(C6:G6) -> 850
A7: 신축 Robot-ready 설치 (계약 2년 후) | B7: 세대 | C7: =0 -> 0 | D7: =0 -> 0 | E7: =Inputs_Yearly!$E$50*Inputs!$F$73*Inputs!$F$74 -> 0 | F7: =Inputs_Yearly!$F$50*Inputs!$F$73*Inputs!$F$74 -> 0 | G7: =Inputs_Yearly!$G$50*Inputs!$F$73*Inputs!$F$74 -> 192 | H7: =SUM(C7:G7) -> 192
A8: Kitchen 설치 합계 | B8: 세대 | C8: =C5+C6+C7 -> 0 | D8: =D5+D6+D7 -> 3 | E8: =E5+E6+E7 -> 65 | F8: =F5+F6+F7 -> 280 | G8: =G5+G6+G7 -> 862 | H8: =SUM(C8:G8) -> 1210
A9: Robot Attach Rate (구축) | B9: % | C9: =Inputs_Yearly!$E$38 -> 1 | D9: =Inputs_Yearly!$F$38 -> 1 | E9: =Inputs_Yearly!$G$38 -> 0.85 | F9: =Inputs_Yearly!$H$38 -> 0.85 | G9: =Inputs_Yearly!$I$38 -> 0.85
A10: Robot-ready Only 세대 후속 Attach | B10: 대 | C10: =0*Inputs!$F$72 -> 0 | D10: =C20*Inputs!$F$72 -> 0 | E10: =D20*Inputs!$F$72 -> 0 | F10: =E20*Inputs!$F$72 -> 1.17 | G10: =F20*Inputs!$F$72 -> 6.0696 | H10: =SUM(C10:G10) -> 7.2396
A11: Robot 설치 — 구축 | B11: 대 | C11: =(C5+C6)*C9 -> 0 | D11: =(D5+D6)*D9 -> 3 | E11: =(E5+E6)*E9 -> 55.25 | F11: =(F5+F6)*F9 -> 238 | G11: =(G5+G6)*G9 -> 569.5 | H11: =SUM(C11:G11) -> 865.75
A12: Robot 설치 — 신축 입주 | B12: 대 | C12: =C7*Inputs!$F$75 -> 0 | D12: =D7*Inputs!$F$75 -> 0 | E12: =E7*Inputs!$F$75 -> 0 | F12: =F7*Inputs!$F$75 -> 0 | G12: =G7*Inputs!$F$75 -> 57.6 | H12: =SUM(C12:G12) -> 57.6
A13: Robot 설치 합계 | B13: 대 | C13: =C11+C12+C10 -> 0 | D13: =D11+D12+D10 -> 3 | E13: =E11+E12+E10 -> 55.25 | F13: =F11+F12+F10 -> 239.17 | G13: =G11+G12+G10 -> 633.1696 | H13: =SUM(C13:G13) -> 930.5896
A14: Rental 비중 | B14: % | C14: =Inputs_Yearly!$E$42 -> 0 | D14: =Inputs_Yearly!$F$42 -> 0.3 | E14: =Inputs_Yearly!$G$42 -> 0.3 | F14: =Inputs_Yearly!$H$42 -> 0.45 | G14: =Inputs_Yearly!$I$42 -> 0.45
A15: Rental Partner 보유 Flag | B15: flag | C15: =Inputs_Yearly!$E$46 -> 0 | D15: =Inputs_Yearly!$F$46 -> 0 | E15: =Inputs_Yearly!$G$46 -> 0 | F15: =Inputs_Yearly!$H$46 -> 1 | G15: =Inputs_Yearly!$I$46 -> 1
A16: Rental 설치 | B16: 대 | C16: =C13*C14 -> 0 | D16: =D13*D14 -> 0.9 | E16: =E13*E14 -> 16.575 | F16: =F13*F14 -> 107.6265 | G16: =G13*G14 -> 284.92632 | H16: =SUM(C16:G16) -> 410.02782
A17: 구매 설치 | B17: 대 | C17: =C13-C16 -> 0 | D17: =D13-D16 -> 2.1 | E17: =E13-E16 -> 38.675 | F17: =F13-F16 -> 131.5435 | G17: =G13-G16 -> 348.24328 | H17: =SUM(C17:G17) -> 520.56178
A18: Rental — ARKI 보유 (Pilot) | B18: 대 | C18: =C16*(1-C15) -> 0 | D18: =D16*(1-D15) -> 0.9 | E18: =E16*(1-E15) -> 16.575 | F18: =F16*(1-F15) -> 0 | G18: =G16*(1-G15) -> 0 | H18: =SUM(C18:G18) -> 17.475
A19: Rental — Partner 보유 | B19: 대 | C19: =C16*C15 -> 0 | D19: =D16*D15 -> 0 | E19: =E16*E15 -> 0 | F19: =F16*F15 -> 107.6265 | G19: =G16*G15 -> 284.92632 | H19: =SUM(C19:G19) -> 392.55282
A20: Robot-ready Only 누적 (기말) | B20: 세대 | C20: =0+(C5+C6)*(1-C9)+C7*(1-Inputs!$F$75)-C10 -> 0 | D20: =C20+(D5+D6)*(1-D9)+D7*(1-Inputs!$F$75)-D10 -> 0 | E20: =D20+(E5+E6)*(1-E9)+E7*(1-Inputs!$F$75)-E10 -> 9.75 | F20: =E20+(F5+F6)*(1-F9)+F7*(1-Inputs!$F$75)-F10 -> 50.58 | G20: =F20+(G5+G6)*(1-G9)+G7*(1-Inputs!$F$75)-G10 -> 279.4104
A21: 구매 Robot 누적 (기말) | B21: 대 | C21: =0+C17 -> 0 | D21: =C21+D17 -> 2.1 | E21: =D21+E17 -> 40.775 | F21: =E21+F17 -> 172.3185 | G21: =F21+G17 -> 520.56178
A22: 구매 Robot 평균 가동 | B22: 대 | C22: =0+C17/2 -> 0 | D22: =C21+D17/2 -> 1.05 | E22: =D21+E17/2 -> 21.4375 | F22: =E21+F17/2 -> 106.54675 | G22: =F21+G17/2 -> 346.44014
A23: ARKI Rental 누적 (기말) | B23: 대 | C23: =0+C18 -> 0 | D23: =C23+D18 -> 0.9 | E23: =D23+E18 -> 17.475 | F23: =E23+F18 -> 17.475 | G23: =F23+G18 -> 17.475
A24: ARKI Rental 평균 가동 | B24: 대 | C24: =0+C18/2 -> 0 | D24: =C23+D18/2 -> 0.45 | E24: =D23+E18/2 -> 9.1875 | F24: =E23+F18/2 -> 17.475 | G24: =F23+G18/2 -> 17.475
A25: Partner Rental 누적 (기말) | B25: 대 | C25: =0+C19 -> 0 | D25: =C25+D19 -> 0 | E25: =D25+E19 -> 0 | F25: =E25+F19 -> 107.6265 | G25: =F25+G19 -> 392.55282
A26: Partner Rental 평균 가동 | B26: 대 | C26: =0+C19/2 -> 0 | D26: =C25+D19/2 -> 0 | E26: =D25+E19/2 -> 0 | F26: =E25+F19/2 -> 53.81325 | G26: =F25+G19/2 -> 250.08966
A27: Installed Robot (기말) | B27: 대 | C27: =C21+C23+C25 -> 0 | D27: =D21+D23+D25 -> 3 | E27: =E21+E23+E25 -> 58.25 | F27: =F21+F23+F25 -> 297.42 | G27: =G21+G23+G25 -> 930.5896
A28: 신축 계약 Backlog (미설치 세대) | B28: 세대 | C28: =Inputs_Yearly!$E$50*Inputs!$F$73*Inputs!$F$74 -> 0 | D28: =(Inputs_Yearly!$F$50+Inputs_Yearly!$E$50)*Inputs!$F$73*Inputs!$F$74 -> 0 | E28: =(Inputs_Yearly!$G$50+Inputs_Yearly!$F$50)*Inputs!$F$73*Inputs!$F$74 -> 192 | F28: =(Inputs_Yearly!$H$50+Inputs_Yearly!$G$50)*Inputs!$F$73*Inputs!$F$74 -> 480 | G28: =(Inputs_Yearly!$I$50+Inputs_Yearly!$H$50)*Inputs!$F$73*Inputs!$F$74 -> 672
A29: REVENUE (만원)
A30: 가격 실현율 | B30: % | C30: =Inputs_Yearly!$E$6 -> 1 | D30: =Inputs_Yearly!$F$6 -> 0.6 | E30: =Inputs_Yearly!$G$6 -> 1 | F30: =Inputs_Yearly!$H$6 -> 1 | G30: =Inputs_Yearly!$I$6 -> 1
A31: Consumables 연 List (구매 고객) | B31: 만원/대 | C31: =Inputs!$F$38*Inputs!$F$39+Inputs!$F$40*Inputs!$F$41+Inputs!$F$42*Inputs!$F$43 -> 36 | D31: =Inputs!$F$38*Inputs!$F$39+Inputs!$F$40*Inputs!$F$41+Inputs!$F$42*Inputs!$F$43 -> 36 | E31: =Inputs!$F$38*Inputs!$F$39+Inputs!$F$40*Inputs!$F$41+Inputs!$F$42*Inputs!$F$43 -> 36 | F31: =Inputs!$F$38*Inputs!$F$39+Inputs!$F$40*Inputs!$F$41+Inputs!$F$42*Inputs!$F$43 -> 36 | G31: =Inputs!$F$38*Inputs!$F$39+Inputs!$F$40*Inputs!$F$41+Inputs!$F$42*Inputs!$F$43 -> 36
A32: Consumables 연 List (Rental, Grip 제외) | B32: 만원/대 | C32: =Inputs!$F$40*Inputs!$F$41+Inputs!$F$42*Inputs!$F$43 -> 18 | D32: =Inputs!$F$40*Inputs!$F$41+Inputs!$F$42*Inputs!$F$43 -> 18 | E32: =Inputs!$F$40*Inputs!$F$41+Inputs!$F$42*Inputs!$F$43 -> 18 | F32: =Inputs!$F$40*Inputs!$F$41+Inputs!$F$42*Inputs!$F$43 -> 18 | G32: =Inputs!$F$40*Inputs!$F$41+Inputs!$F$42*Inputs!$F$43 -> 18
A33: Grip Kit 연 List | B33: 만원/대 | C33: =Inputs!$F$38*Inputs!$F$39 -> 18 | D33: =Inputs!$F$38*Inputs!$F$39 -> 18 | E33: =Inputs!$F$38*Inputs!$F$39 -> 18 | F33: =Inputs!$F$38*Inputs!$F$39 -> 18 | G33: =Inputs!$F$38*Inputs!$F$39 -> 18
A34: A. Kitchen Build (Robot-ready) | B34: 만원 | C34: =(C5+C6)*Inputs!$F$30*C30+C7*Inputs!$F$31 -> 0 | D34: =(D5+D6)*Inputs!$F$30*D30+D7*Inputs!$F$31 -> 810 | E34: =(E5+E6)*Inputs!$F$30*E30+E7*Inputs!$F$31 -> 29250 | F34: =(F5+F6)*Inputs!$F$30*F30+F7*Inputs!$F$31 -> 126000 | G34: =(G5+G6)*Inputs!$F$30*G30+G7*Inputs!$F$31 -> 343740 | H34: =SUM(C34:G34) -> 499800
A35: A. 설치·Calibration | B35: 만원 | C35: =C13*Inputs!$F$33*C30 -> 0 | D35: =D13*Inputs!$F$33*D30 -> 144 | E35: =E13*Inputs!$F$33*E30 -> 4420 | F35: =F13*Inputs!$F$33*F30 -> 19133.6 | G35: =G13*Inputs!$F$33*G30 -> 50653.568 | H35: =SUM(C35:G35) -> 74351.168
A36: A. Robot Hardware (구매 + Rental Partner 공급) | B36: 만원 | C36: =C17*Inputs!$F$32*C30+C19*Inputs!$F$32*Inputs!$F$50 -> 0 | D36: =D17*Inputs!$F$32*D30+D19*Inputs!$F$32*Inputs!$F$50 -> 1877.4 | E36: =E17*Inputs!$F$32*E30+E19*Inputs!$F$32*Inputs!$F$50 -> 57625.75 | F36: =F17*Inputs!$F$32*F30+F19*Inputs!$F$32*Inputs!$F$50 -> 337119.68 | G36: =G17*Inputs!$F$32*G30+G19*Inputs!$F$32*Inputs!$F$50 -> 892477.88 | H36: =SUM(C36:G36) -> 1289100.7
A37: B. Rental (ARKI 보유) | B37: 만원 | C37: =C24*Inputs!$F$34*12 -> 0 | D37: =D24*Inputs!$F$34*12 -> 178.2 | E37: =E24*Inputs!$F$34*12 -> 3638.25 | F37: =F24*Inputs!$F$34*12 -> 6920.1 | G37: =G24*Inputs!$F$34*12 -> 6920.1 | H37: =SUM(C37:G37) -> 17656.65
A38: B. Care (구매 고객 + Partner 서비스료) | B38: 만원 | C38: =C22*Inputs!$F$45*Inputs!$F$36+C26*Inputs!$F$51*12 -> 0 | D38: =D22*Inputs!$F$45*Inputs!$F$36+D26*Inputs!$F$51*12 -> 35.28 | E38: =E22*Inputs!$F$45*Inputs!$F$36+E26*Inputs!$F$51*12 -> 720.3 | F38: =F22*Inputs!$F$45*Inputs!$F$36+F26*Inputs!$F$51*12 -> 7454.5248 | G38: =G22*Inputs!$F$45*Inputs!$F$36+G26*Inputs!$F$51*12 -> 29646.844 | H38: =SUM(C38:G38) -> 37856.949
A39: B. Consumables | B39: 만원 | C39: =C22*Inputs!$F$44*C31+(C24+C26)*Inputs!$F$44*C32 -> 0 | D39: =D22*Inputs!$F$44*D31+(D24+D26)*Inputs!$F$44*D32 -> 32.13 | E39: =E22*Inputs!$F$44*E31+(E24+E26)*Inputs!$F$44*E32 -> 655.9875 | F39: =F22*Inputs!$F$44*F31+(F24+F26)*Inputs!$F$44*F32 -> 3583.2101 | G39: =G22*Inputs!$F$44*G31+(G24+G26)*Inputs!$F$44*G32 -> 12101.606 | H39: =SUM(C39:G39) -> 16372.934
A40: C. Upgrade (Software Skill + Tool) | B40: 만원 | C40: =0*Inputs!$F$47*Inputs!$F$46+0*Inputs!$F$49*Inputs!$F$48 -> 0 | D40: =C13*Inputs!$F$47*Inputs!$F$46+0*Inputs!$F$49*Inputs!$F$48 -> 0 | E40: =D13*Inputs!$F$47*Inputs!$F$46+C13*Inputs!$F$49*Inputs!$F$48 -> 36 | F40: =E13*Inputs!$F$47*Inputs!$F$46+D13*Inputs!$F$49*Inputs!$F$48 -> 723 | G40: =F13*Inputs!$F$47*Inputs!$F$46+E13*Inputs!$F$49*Inputs!$F$48 -> 3975.04 | H40: =SUM(C40:G40) -> 4734.04
A41: 매출 합계 | B41: 만원 | C41: =SUM(C34:C40) -> 0 | D41: =SUM(D34:D40) -> 3077.01 | E41: =SUM(E34:E40) -> 96346.288 | F41: =SUM(F34:F40) -> 500934.12 | G41: =SUM(G34:G40) -> 1339515 | H41: =SUM(C41:G41) -> 1939872.5
A42: COGS (만원)
A43: Standard Module 사용률 | B43: % | C43: =Inputs_Yearly!$E$10 -> 0.4 | D43: =Inputs_Yearly!$F$10 -> 0.55 | E43: =Inputs_Yearly!$G$10 -> 0.7 | F43: =Inputs_Yearly!$H$10 -> 0.8 | G43: =Inputs_Yearly!$I$10 -> 0.85
A44: Kitchen Module 원가/세대 | B44: 만원 | C44: =Inputs!$F$53*(C43+Inputs!$F$54*(1-C43))+Inputs!$F$55*(1-C43) -> 332 | D44: =Inputs!$F$53*(D43+Inputs!$F$54*(1-D43))+Inputs!$F$55*(1-D43) -> 299 | E44: =Inputs!$F$53*(E43+Inputs!$F$54*(1-E43))+Inputs!$F$55*(1-E43) -> 266 | F44: =Inputs!$F$53*(F43+Inputs!$F$54*(1-F43))+Inputs!$F$55*(1-F43) -> 244 | G44: =Inputs!$F$53*(G43+Inputs!$F$54*(1-G43))+Inputs!$F$55*(1-G43) -> 233
A45: Robot BOM/대 | B45: 만원 | C45: =Inputs_Yearly!$E$14 -> 1600 | D45: =Inputs_Yearly!$F$14 -> 1400 | E45: =Inputs_Yearly!$G$14 -> 1080 | F45: =Inputs_Yearly!$H$14 -> 920 | G45: =Inputs_Yearly!$I$14 -> 800
A46: Care 원가/대·년 | B46: 만원 | C46: =Inputs_Yearly!$E$22*Inputs_Yearly!$E$26+Inputs!$F$59*Inputs!$F$60+Inputs!$F$61 -> 43 | D46: =Inputs_Yearly!$F$22*Inputs_Yearly!$F$26+Inputs!$F$59*Inputs!$F$60+Inputs!$F$61 -> 37 | E46: =Inputs_Yearly!$G$22*Inputs_Yearly!$G$26+Inputs!$F$59*Inputs!$F$60+Inputs!$F$61 -> 28 | F46: =Inputs_Yearly!$H$22*Inputs_Yearly!$H$26+Inputs!$F$59*Inputs!$F$60+Inputs!$F$61 -> 22.6 | G46: =Inputs_Yearly!$I$22*Inputs_Yearly!$I$26+Inputs!$F$59*Inputs!$F$60+Inputs!$F$61 -> 20
A47: Kitchen Module 원가 | B47: 만원 | C47: =(C5+C6)*C44+C7*Inputs!$F$56 -> 0 | D47: =(D5+D6)*D44+D7*Inputs!$F$56 -> 897 | E47: =(E5+E6)*E44+E7*Inputs!$F$56 -> 17290 | F47: =(F5+F6)*F44+F7*Inputs!$F$56 -> 68320 | G47: =(G5+G6)*G44+G7*Inputs!$F$56 -> 179150 | H47: =SUM(C47:G47) -> 265657
A48: 물류 | B48: 만원 | C48: =(C5+C6+C7)*Inputs!$F$57 -> 0 | D48: =(D5+D6+D7)*Inputs!$F$57 -> 75 | E48: =(E5+E6+E7)*Inputs!$F$57 -> 1625 | F48: =(F5+F6+F7)*Inputs!$F$57 -> 7000 | G48: =(G5+G6+G7)*Inputs!$F$57 -> 21550 | H48: =SUM(C48:G48) -> 30250
A49: Robot BOM (판매분) | B49: 만원 | C49: =(C17+C19)*C45 -> 0 | D49: =(D17+D19)*D45 -> 2940 | E49: =(E17+E19)*E45 -> 41769 | F49: =(F17+F19)*F45 -> 220036.4 | G49: =(G17+G19)*G45 -> 506535.68 | H49: =SUM(C49:G49) -> 771281.08
A50: 설치·Calibration 원가 | B50: 만원 | C50: =C13*Inputs_Yearly!$E$18 -> 0 | D50: =D13*Inputs_Yearly!$F$18 -> 255 | E50: =E13*Inputs_Yearly!$G$18 -> 2873 | F50: =F13*Inputs_Yearly!$H$18 -> 9088.46 | G50: =G13*Inputs_Yearly!$I$18 -> 18995.088 | H50: =SUM(C50:G50) -> 31211.548
A51: Warranty Reserve | B51: 만원 | C51: =Inputs!$F$58*C36 -> 0 | D51: =Inputs!$F$58*D36 -> 65.709 | E51: =Inputs!$F$58*E36 -> 2016.9012 | F51: =Inputs!$F$58*F36 -> 11799.189 | G51: =Inputs!$F$58*G36 -> 31236.726 | H51: =SUM(C51:G51) -> 45118.525
A52: Rental 자산 취득 (ARKI 보유) | B52: 만원 | C52: =C18*C45 -> 0 | D52: =D18*D45 -> 1260 | E52: =E18*E45 -> 17901 | F52: =F18*F45 -> 0 | G52: =G18*G45 -> 0 | H52: =SUM(C52:G52) -> 19161
A53: Rental 자산 누적 취득 | B53: 만원 | C53: =0+C52 -> 0 | D53: =C53+D52 -> 1260 | E53: =D53+E52 -> 19161 | F53: =E53+F52 -> 19161 | G53: =F53+G52 -> 19161
A54: Rental 자산 감가상각 | B54: 만원 | C54: =0*(1-Inputs!$F$68)/5+C52*(1-Inputs!$F$68)/5*0.5 -> 0 | D54: =C53*(1-Inputs!$F$68)/5+D52*(1-Inputs!$F$68)/5*0.5 -> 107.1 | E54: =D53*(1-Inputs!$F$68)/5+E52*(1-Inputs!$F$68)/5*0.5 -> 1735.785 | F54: =E53*(1-Inputs!$F$68)/5+F52*(1-Inputs!$F$68)/5*0.5 -> 3257.37 | G54: =F53*(1-Inputs!$F$68)/5+G52*(1-Inputs!$F$68)/5*0.5 -> 3257.37 | H54: =SUM(C54:G54) -> 8357.625
A55: Care Service 원가 | B55: 만원 | C55: =(C22*Inputs!$F$45+C24+C26)*C46 -> 0 | D55: =(D22*Inputs!$F$45+D24+D26)*D46 -> 43.845 | E55: =(E22*Inputs!$F$45+E24+E26)*E46 -> 677.425 | F55: =(F22*Inputs!$F$45+F24+F26)*F46 -> 3296.684 | G55: =(G22*Inputs!$F$45+G24+G26)*G46 -> 10201.455 | H55: =SUM(C55:G55) -> 14219.409
A56: Consumables 원가 (Rental Grip 포함) | B56: 만원 | C56: =C39*Inputs!$F$62+(C24+C26)*C33*Inputs!$F$62 -> 0 | D56: =D39*Inputs!$F$62+(D24+D26)*D33*Inputs!$F$62 -> 12.8736 | E56: =E39*Inputs!$F$62+(E24+E26)*E33*Inputs!$F$62 -> 262.836 | F56: =F39*Inputs!$F$62+(F24+F26)*F33*Inputs!$F$62 -> 1557.2475 | G56: =G39*Inputs!$F$62+(G24+G26)*G33*Inputs!$F$62 -> 5413.6864 | H56: =SUM(C56:G56) -> 7246.6436
A57: Upgrade 원가 | B57: 만원 | C57: =0*Inputs!$F$47*Inputs!$F$46*Inputs!$F$63+0*Inputs!$F$49*Inputs!$F$48*Inputs!$F$64 -> 0 | D57: =C13*Inputs!$F$47*Inputs!$F$46*Inputs!$F$63+0*Inputs!$F$49*Inputs!$F$48*Inputs!$F$64 -> 0 | E57: =D13*Inputs!$F$47*Inputs!$F$46*Inputs!$F$63+C13*Inputs!$F$49*Inputs!$F$48*Inputs!$F$64 -> 3.6 | F57: =E13*Inputs!$F$47*Inputs!$F$46*Inputs!$F$63+D13*Inputs!$F$49*Inputs!$F$48*Inputs!$F$64 -> 93.3 | G57: =F13*Inputs!$F$47*Inputs!$F$46*Inputs!$F$63+E13*Inputs!$F$49*Inputs!$F$48*Inputs!$F$64 -> 784.254 | H57: =SUM(C57:G57) -> 881.154
A58: COGS 합계 | B58: 만원 | C58: =C47+C48+C49+C50+C51+C54+C55+C56+C57 -> 0 | D58: =D47+D48+D49+D50+D51+D54+D55+D56+D57 -> 4396.5276 | E58: =E47+E48+E49+E50+E51+E54+E55+E56+E57 -> 68253.547 | F58: =F47+F48+F49+F50+F51+F54+F55+F56+F57 -> 324448.65 | G58: =G47+G48+G49+G50+G51+G54+G55+G56+G57 -> 777124.26 | H58: =SUM(C58:G58) -> 1174223
A59: 매출총이익 | B59: 만원 | C59: =C41-C58 -> 0 | D59: =D41-D58 -> -1319.5176 | E59: =E41-E58 -> 28092.74 | F59: =F41-F58 -> 176485.47 | G59: =G41-G58 -> 562390.78 | H59: =SUM(C59:G59) -> 765649.47
A60: 매출총이익률 | B60: % | C60: =IF(C41=0,0,C59/C41) -> 0 | D60: =IF(D41=0,0,D59/D41) -> -0.42883111 | E60: =IF(E41=0,0,E59/E41) -> 0.29158093 | F60: =IF(F41=0,0,F59/F41) -> 0.35231273 | G60: =IF(G41=0,0,G59/G41) -> 0.41984656
A61: CHANNEL · OPEX (만원)
A62: Partner 수수료 | B62: 만원 | C62: =Inputs!$F$65*C6*(Inputs!$F$30*C30+C9*(Inputs!$F$32+Inputs!$F$33)*C30) -> 0 | D62: =Inputs!$F$65*D6*(Inputs!$F$30*D30+D9*(Inputs!$F$32+Inputs!$F$33)*D30) -> 0 | E62: =Inputs!$F$65*E6*(Inputs!$F$30*E30+E9*(Inputs!$F$32+Inputs!$F$33)*E30) -> 4818.15 | F62: =Inputs!$F$65*F6*(Inputs!$F$30*F30+F9*(Inputs!$F$32+Inputs!$F$33)*F30) -> 35333.1 | G62: =Inputs!$F$65*G6*(Inputs!$F$30*G30+G9*(Inputs!$F$32+Inputs!$F$33)*G30) -> 96363 | H62: =SUM(C62:G62) -> 136514.25
A63: 직접판매 획득비용 | B63: 만원 | C63: =C5*Inputs!$F$66 -> 0 | D63: =D5*Inputs!$F$66 -> 420 | E63: =E5*Inputs!$F$66 -> 4900 | F63: =F5*Inputs!$F$66 -> 8400 | G63: =G5*Inputs!$F$66 -> 9800 | H63: =SUM(C63:G63) -> 23520
A64: 신축 Project 수주비용 | B64: 만원 | C64: =Inputs_Yearly!$E$50*Inputs!$F$67 -> 0 | D64: =Inputs_Yearly!$F$50*Inputs!$F$67 -> 0 | E64: =Inputs_Yearly!$G$50*Inputs!$F$67 -> 4000 | F64: =Inputs_Yearly!$H$50*Inputs!$F$67 -> 6000 | G64: =Inputs_Yearly!$I$50*Inputs!$F$67 -> 8000 | H64: =SUM(C64:G64) -> 18000
A65: Contribution (매출총이익 − 채널·변동 판매비) | B65: 만원 | C65: =C59-C62-C63-C64 -> 0 | D65: =D59-D62-D63-D64 -> -1739.5176 | E65: =E59-E62-E63-E64 -> 14374.59 | F65: =F59-F62-F63-F64 -> 126752.37 | G65: =G59-G62-G63-G64 -> 448227.78 | H65: =SUM(C65:G65) -> 587615.22
A66: 인건비 | B66: 만원 | C66: =Inputs_Yearly!$E$54*Inputs!$F$77 -> 37400 | D66: =Inputs_Yearly!$F$54*Inputs!$F$77 -> 59500 | E66: =Inputs_Yearly!$G$54*Inputs!$F$77 -> 170000 | F66: =Inputs_Yearly!$H$54*Inputs!$F$77 -> 272000 | G66: =Inputs_Yearly!$I$54*Inputs!$F$77 -> 357000 | H66: =SUM(C66:G66) -> 895900
A67: 기타 운영비 (Prototype·SW·공간·인증/IP·검증·Marketing·G&A) | B67: 만원 | C67: =Inputs_Yearly!$E$58+Inputs_Yearly!$E$62+Inputs_Yearly!$E$66+Inputs_Yearly!$E$70+Inputs_Yearly!$E$74+Inputs_Yearly!$E$78+Inputs_Yearly!$E$82 -> 29500 | D67: =Inputs_Yearly!$F$58+Inputs_Yearly!$F$62+Inputs_Yearly!$F$66+Inputs_Yearly!$F$70+Inputs_Yearly!$F$74+Inputs_Yearly!$F$78+Inputs_Yearly!$F$82 -> 27500 | E67: =Inputs_Yearly!$G$58+Inputs_Yearly!$G$62+Inputs_Yearly!$G$66+Inputs_Yearly!$G$70+Inputs_Yearly!$G$74+Inputs_Yearly!$G$78+Inputs_Yearly!$G$82 -> 135000 | F67: =Inputs_Yearly!$H$58+Inputs_Yearly!$H$62+Inputs_Yearly!$H$66+Inputs_Yearly!$H$70+Inputs_Yearly!$H$74+Inputs_Yearly!$H$78+Inputs_Yearly!$H$82 -> 167000 | G67: =Inputs_Yearly!$I$58+Inputs_Yearly!$I$62+Inputs_Yearly!$I$66+Inputs_Yearly!$I$70+Inputs_Yearly!$I$74+Inputs_Yearly!$I$78+Inputs_Yearly!$I$82 -> 210000 | H67: =SUM(C67:G67) -> 569000
A68: Opex 합계 | B68: 만원 | C68: =C66+C67 -> 66900 | D68: =D66+D67 -> 87000 | E68: =E66+E67 -> 305000 | F68: =F66+F67 -> 439000 | G68: =G66+G67 -> 567000 | H68: =SUM(C68:G68) -> 1464900
A69: 영업이익 (근사) | B69: 만원 | C69: =C65-C68 -> -66900 | D69: =D65-D68 -> -88739.518 | E69: =E65-E68 -> -290625.41 | F69: =F65-F68 -> -312247.63 | G69: =G65-G68 -> -118772.22 | H69: =SUM(C69:G69) -> -877284.78
A70: 현금흐름 (영업이익 + 감가 − Rental 자산) | B70: 만원 | C70: =C69+C54-C52 -> -66900 | D70: =D69+D54-D52 -> -89892.418 | E70: =E69+E54-E52 -> -306790.62 | F70: =F69+F54-F52 -> -308990.26 | G70: =G69+G54-G52 -> -115514.85 | H70: =SUM(C70:G70) -> -888088.16
A71: 누적 현금흐름 | B71: 만원 | C71: =0+C70 -> -66900 | D71: =C71+D70 -> -156792.42 | E71: =D71+E70 -> -463583.04 | F71: =E71+F70 -> -772573.31 | G71: =F71+G70 -> -888088.16
A72: MIX
A73: Build 매출 (Kitchen + 설치) | B73: 만원 | C73: =C34+C35 -> 0 | D73: =D34+D35 -> 954 | E73: =E34+E35 -> 33670 | F73: =F34+F35 -> 145133.6 | G73: =G34+G35 -> 394393.57 | H73: =SUM(C73:G73) -> 574151.17
A74: Recurring 매출 (Rental + Care + Consumables) | B74: 만원 | C74: =C37+C38+C39 -> 0 | D74: =D37+D38+D39 -> 245.61 | E74: =E37+E38+E39 -> 5014.5375 | F74: =F37+F38+F39 -> 17957.835 | G74: =G37+G38+G39 -> 48668.55 | H74: =SUM(C74:G74) -> 71886.533
A75: Robot + Recurring + Upgrade 비중 | B75: % | C75: =IF(C41=0,0,(C36+C74+C40)/C41) -> 0 | D75: =IF(D41=0,0,(D36+D74+D40)/D41) -> 0.68995876 | E75: =IF(E41=0,0,(E36+E74+E40)/E41) -> 0.65053142 | F75: =IF(F41=0,0,(F36+F74+F40)/F41) -> 0.71027408 | G75: =IF(G41=0,0,(G36+G74+G40)/G41) -> 0.70556988

Sheet Household
A1: Household Economics — 구축 Premium 1세대, 5년, 직접판매, Base (만원)
A2: 기대값 기준 (Software·Tool은 구매율 반영). 구매 모델은 Care 가입 세대 기준. Y3 / Y5 = 해당 연도의 원가 수준을 5년간 적용.
A4: 항목 | B4: 구매 · Y3 원가 | C4: 구매 · Y5 원가 | D4: Rental · Y3 원가 | E4: Rental · Y5 원가 | F4: 산식
A5: REVENUE
A6: Robot-ready Kitchen 증분 | B6: =Inputs!$E$30 -> 450 | C6: =Inputs!$E$30 -> 450 | D6: =Inputs!$E$30 -> 450 | E6: =Inputs!$E$30 -> 450 | F6: Year 0
A7: 설치·Calibration | B7: =Inputs!$E$33 -> 80 | C7: =Inputs!$E$33 -> 80 | D7: =Inputs!$E$33 -> 80 | E7: =Inputs!$E$33 -> 80 | F7: Year 0
A8: Robot Module (구매) | B8: =Inputs!$E$32 -> 1490 | C8: =Inputs!$E$32 -> 1490 | D8: =0 -> 0 | E8: =0 -> 0 | F8: Year 0
A9: Rental (60개월) | B9: =0 -> 0 | C9: =0 -> 0 | D9: =Inputs!$E$34*Inputs!$E$35 -> 1980 | E9: =Inputs!$E$34*Inputs!$E$35 -> 1980 | F9: 월 요금 × 60
A10: Care Basic (5년) | B10: =5*Inputs!$E$36 -> 240 | C10: =5*Inputs!$E$36 -> 240 | D10: =0 -> 0 | E10: =0 -> 0 | F10: Rental은 요금에 포함
A11: Consumables (5년, 구매율 반영) | B11: =5*Inputs!$E$44*(Inputs!$E$38*Inputs!$E$39+Inputs!$E$40*Inputs!$E$41+Inputs!$E$42*Inputs!$E$43) -> 126 | C11: =5*Inputs!$E$44*(Inputs!$E$38*Inputs!$E$39+Inputs!$E$40*Inputs!$E$41+Inputs!$E$42*Inputs!$E$43) -> 126 | D11: =5*Inputs!$E$44*(Inputs!$E$40*Inputs!$E$41+Inputs!$E$42*Inputs!$E$43) -> 63 | E11: =5*Inputs!$E$44*(Inputs!$E$40*Inputs!$E$41+Inputs!$E$42*Inputs!$E$43) -> 63 | F11: Rental은 Grip Kit 포함
A12: Software Skill (기대값) | B12: =Inputs!$E$47*Inputs!$E$46 -> 12 | C12: =Inputs!$E$47*Inputs!$E$46 -> 12 | D12: =Inputs!$E$47*Inputs!$E$46 -> 12 | E12: =Inputs!$E$47*Inputs!$E$46 -> 12
A13: Tool / End-effector (기대값) | B13: =Inputs!$E$49*Inputs!$E$48 -> 20 | C13: =Inputs!$E$49*Inputs!$E$48 -> 20 | D13: =Inputs!$E$49*Inputs!$E$48 -> 20 | E13: =Inputs!$E$49*Inputs!$E$48 -> 20
A14: 5년 매출 | B14: =B6+B7+B8+B9+B10+B11+B12+B13 -> 2418 | C14: =C6+C7+C8+C9+C10+C11+C12+C13 -> 2418 | D14: =D6+D7+D8+D9+D10+D11+D12+D13 -> 2605 | E14: =E6+E7+E8+E9+E10+E11+E12+E13 -> 2605
A15: COST
A16: Kitchen Module 원가 | B16: =Inputs!$E$53*(Inputs_Yearly!$G$9+Inputs!$E$54*(1-Inputs_Yearly!$G$9))+Inputs!$E$55*(1-Inputs_Yearly!$G$9) -> 277 | C16: =Inputs!$E$53*(Inputs_Yearly!$I$9+Inputs!$E$54*(1-Inputs_Yearly!$I$9))+Inputs!$E$55*(1-Inputs_Yearly!$I$9) -> 244 | D16: =Inputs!$E$53*(Inputs_Yearly!$G$9+Inputs!$E$54*(1-Inputs_Yearly!$G$9))+Inputs!$E$55*(1-Inputs_Yearly!$G$9) -> 277 | E16: =Inputs!$E$53*(Inputs_Yearly!$I$9+Inputs!$E$54*(1-Inputs_Yearly!$I$9))+Inputs!$E$55*(1-Inputs_Yearly!$I$9) -> 244 | F16: Standard Module 사용률 연동
A17: 설치·Calibration 원가 | B17: =Inputs_Yearly!$G$17 -> 60 | C17: =Inputs_Yearly!$I$17 -> 38 | D17: =Inputs_Yearly!$G$17 -> 60 | E17: =Inputs_Yearly!$I$17 -> 38
A18: 물류 | B18: =Inputs!$E$57 -> 25 | C18: =Inputs!$E$57 -> 25 | D18: =Inputs!$E$57 -> 25 | E18: =Inputs!$E$57 -> 25
A19: Robot BOM (Rental은 잔존가치 차감) | B19: =Inputs_Yearly!$G$13 -> 1150 | C19: =Inputs_Yearly!$I$13 -> 900 | D19: =Inputs_Yearly!$G$13*(1-Inputs!$E$68) -> 977.5 | E19: =Inputs_Yearly!$I$13*(1-Inputs!$E$68) -> 765
A20: Rental 금융비용 (5년) | B20: =0 -> 0 | C20: =0 -> 0 | D20: =Inputs_Yearly!$G$13*(1+Inputs!$E$68)/2*Inputs!$E$69*5 -> 264.5 | E20: =Inputs_Yearly!$I$13*(1+Inputs!$E$68)/2*Inputs!$E$69*5 -> 207 | F20: 평균잔액 × 금리
A21: Warranty Reserve | B21: =Inputs!$E$58*Inputs!$E$32 -> 59.6 | C21: =Inputs!$E$58*Inputs!$E$32 -> 59.6 | D21: =Inputs!$E$58*Inputs_Yearly!$G$13 -> 46 | E21: =Inputs!$E$58*Inputs_Yearly!$I$13 -> 36
A22: Care Service 원가 (5년) | B22: =5*(Inputs_Yearly!$G$21*Inputs_Yearly!$G$25+Inputs!$E$59*Inputs!$E$60+Inputs!$E$61) -> 184 | C22: =5*(Inputs_Yearly!$I$21*Inputs_Yearly!$I$25+Inputs!$E$59*Inputs!$E$60+Inputs!$E$61) -> 134 | D22: =5*(Inputs_Yearly!$G$21*Inputs_Yearly!$G$25+Inputs!$E$59*Inputs!$E$60+Inputs!$E$61) -> 184 | E22: =5*(Inputs_Yearly!$I$21*Inputs_Yearly!$I$25+Inputs!$E$59*Inputs!$E$60+Inputs!$E$61) -> 134
A23: Consumables 원가 | B23: =B11*Inputs!$E$62 -> 44.1 | C23: =C11*Inputs!$E$62 -> 44.1 | D23: =(D11+5*Inputs!$E$38*Inputs!$E$39)*Inputs!$E$62 -> 53.55 | E23: =(E11+5*Inputs!$E$38*Inputs!$E$39)*Inputs!$E$62 -> 53.55
A24: Upgrade 원가 | B24: =Inputs!$E$47*Inputs!$E$46*Inputs!$E$63+Inputs!$E$49*Inputs!$E$48*Inputs!$E$64 -> 10.2 | C24: =Inputs!$E$47*Inputs!$E$46*Inputs!$E$63+Inputs!$E$49*Inputs!$E$48*Inputs!$E$64 -> 10.2 | D24: =Inputs!$E$47*Inputs!$E$46*Inputs!$E$63+Inputs!$E$49*Inputs!$E$48*Inputs!$E$64 -> 10.2 | E24: =Inputs!$E$47*Inputs!$E$46*Inputs!$E$63+Inputs!$E$49*Inputs!$E$48*Inputs!$E$64 -> 10.2
A25: 직접판매 획득비용 | B25: =Inputs!$E$66 -> 150 | C25: =Inputs!$E$66 -> 150 | D25: =Inputs!$E$66 -> 150 | E25: =Inputs!$E$66 -> 150
A26: 5년 비용 | B26: =B16+B17+B18+B19+B20+B21+B22+B23+B24+B25 -> 1959.9 | C26: =C16+C17+C18+C19+C20+C21+C22+C23+C24+C25 -> 1604.9 | D26: =D16+D17+D18+D19+D20+D21+D22+D23+D24+D25 -> 2047.75 | E26: =E16+E17+E18+E19+E20+E21+E22+E23+E24+E25 -> 1662.75
A27: RESULT
A28: Year 0 매출 | B28: =B6+B7+B8 -> 2020 | C28: =C6+C7+C8 -> 2020 | D28: =D6+D7 -> 530 | E28: =E6+E7 -> 530
A29: 5년 매출총이익 (획득비용 전) | B29: =B14-(B26-B25) -> 608.1 | C29: =C14-(C26-C25) -> 963.1 | D29: =D14-(D26-D25) -> 707.25 | E29: =E14-(E26-E25) -> 1092.25
A30: 5년 Lifetime Contribution | B30: =B14-B26 -> 458.1 | C30: =C14-C26 -> 813.1 | D30: =D14-D26 -> 557.25 | E30: =E14-E26 -> 942.25
A31: Contribution Margin | B31: =IF(B14=0,0,B30/B14) -> 0.18945409 | C31: =IF(C14=0,0,C30/C14) -> 0.33626964 | D31: =IF(D14=0,0,D30/D14) -> 0.21391555 | E31: =IF(E14=0,0,E30/E14) -> 0.36170825
A32: Recurring 매출 (Rental·Care·Consumables) | B32: =B10+B11 -> 366 | C32: =C10+C11 -> 366 | D32: =D9+D11 -> 2043 | E32: =E9+E11 -> 2043

Sheet Unit_Economics
A1: Unit Economics — Base (만원)
A3: Rental 월 원가 Build-up (Robot 1대, ARKI 보유 가정) | B3: Y3 원가 | C3: Y5 원가 | D3: 산식
A4: Robot BOM | B4: =Inputs_Yearly!$G$13 -> 1150 | C4: =Inputs_Yearly!$I$13 -> 900
A5: 감가 (잔존가치 차감, 60개월) | B5: =B4*(1-Inputs!$E$68)/Inputs!$E$35 -> 16.291667 | C5: =C4*(1-Inputs!$E$68)/Inputs!$E$35 -> 12.75
A6: 금융비용 (평균잔액 × 금리 / 12) | B6: =B4*(1+Inputs!$E$68)/2*Inputs!$E$69/12 -> 4.4083333 | C6: =C4*(1+Inputs!$E$68)/2*Inputs!$E$69/12 -> 3.45
A7: Care 원가 / 12 | B7: =(Inputs_Yearly!$G$21*Inputs_Yearly!$G$25+Inputs!$E$59*Inputs!$E$60+Inputs!$E$61)/12 -> 3.0666667 | C7: =(Inputs_Yearly!$I$21*Inputs_Yearly!$I$25+Inputs!$E$59*Inputs!$E$60+Inputs!$E$61)/12 -> 2.2333333
A8: Grip Kit 원가 / 12 | B8: =Inputs!$E$38*Inputs!$E$39*Inputs!$E$62/12 -> 0.525 | C8: =Inputs!$E$38*Inputs!$E$39*Inputs!$E$62/12 -> 0.525
A9: Failure Reserve | B9: =Inputs!$E$58*B4/Inputs!$E$35 -> 0.76666667 | C9: =Inputs!$E$58*C4/Inputs!$E$35 -> 0.6
A10: 월 원가 합계 | B10: =B5+B6+B7+B8+B9 -> 25.058333 | C10: =C5+C6+C7+C8+C9 -> 19.558333
A11: 월 Rental 요금 (가정) | B11: =Inputs!$E$34 -> 33 | C11: =Inputs!$E$34 -> 33
A12: 월 Contribution | B12: =B11-B10 -> 7.9416667 | C12: =C11-C10 -> 13.441667
A13: Contribution Margin | B13: =B12/B11 -> 0.24065657 | C13: =C12/C11 -> 0.40732323
A14: 마진 20% 확보 요금 | B14: =B10/0.8 -> 31.322917 | C14: =C10/0.8 -> 24.447917
A15: Payback (BOM ÷ (요금 − Care − Grip), 개월) | B15: =B4/(B11-B7-B8) -> 39.104562 | C15: =C4/(C11-C7-C8) -> 29.760265 | D15: 금융비용 제외 현금 회수
A16: Payback 허들 충족 최대 BOM | B16: =Inputs!$E$70*(B11-B7-B8) -> 1058.7 | C16: =Inputs!$E$70*(C11-C7-C8) -> 1088.7 | D16: Rental Partner 요구 Payback 기준
A18: Care Basic (Robot 1대·년) | B18: Y3 원가 | C18: Y5 원가 | D18: 산식
A19: Care 연 요금 | B19: =Inputs!$E$36 -> 48 | C19: =Inputs!$E$36 -> 48
A20: 정기 방문 원가 | B20: =Inputs_Yearly!$G$21*Inputs_Yearly!$G$25 -> 22 | C20: =Inputs_Yearly!$I$21*Inputs_Yearly!$I$25 -> 12
A21: 고장 방문 원가 | B21: =Inputs!$E$59*Inputs!$E$60 -> 10.8 | C21: =Inputs!$E$59*Inputs!$E$60 -> 10.8
A22: Cloud·Software | B22: =Inputs!$E$61 -> 4 | C22: =Inputs!$E$61 -> 4
A23: Care 원가 합계 | B23: =SUM(B20:B22) -> 36.8 | C23: =SUM(C20:C22) -> 26.8
A24: Care Contribution | B24: =B19-B23 -> 11.2 | C24: =C19-C23 -> 21.2
A25: Care Margin | B25: =B24/B19 -> 0.23333333 | C25: =C24/C19 -> 0.44166667
A27: Consumables (Robot 1대·년, 구매 고객) | B27: 연 매출 | C27: 원가 | D27: Contribution
A28: Grip Kit (List × 구매율) | B28: =Inputs!$E$38*Inputs!$E$39*Inputs!$E$44 -> 12.6 | C28: =B28*Inputs!$E$62 -> 4.41 | D28: =B28-C28 -> 8.19
A29: Cleaning Kit (List × 구매율) | B29: =Inputs!$E$40*Inputs!$E$41*Inputs!$E$44 -> 7 | C29: =B29*Inputs!$E$62 -> 2.45 | D29: =B29-C29 -> 4.55
A30: Protection Kit (List × 구매율) | B30: =Inputs!$E$42*Inputs!$E$43*Inputs!$E$44 -> 5.6 | C30: =B30*Inputs!$E$62 -> 1.96 | D30: =B30-C30 -> 3.64
A31: 합계 | B31: =SUM(B28:B30) -> 25.2 | C31: =SUM(C28:C30) -> 8.82 | D31: =SUM(D28:D30) -> 16.38
A33: Rental Partner 경제성 (Base, Y4~) | B33: 값 | D33: 산식
A34: Robot 매입가 (ASP × 공급가율) | B34: =Inputs!$E$32*Inputs!$E$50 -> 1311.2
A35: 월 순유입 (요금 − ARKI 서비스료) | B35: =Inputs!$E$34-Inputs!$E$51 -> 27
A36: 잔존가치 (매입가 × 잔존율) | B36: =B34*Inputs!$E$68 -> 196.68
A37: 월 IRR | B37: =RATE(Inputs!$E$35,B35,-B34,B36) -> 0.010276112 | D37: RATE(기간, 월 유입, −매입가, 잔존가치)
A38: 연 IRR (연체·해지 미반영) | B38: =(1+B37)^12-1 -> 0.13052719
A40: Robot BOM 구성 (ASSUMPTION, 만원/대) | B40: Pilot (Y1) | C40: Y3 | D40: Y5
A41: 6축 Arm (가반 3~5kg, Controller 포함) | B41: 950 | C41: 600 | D41: 450 | E41: FAIRINO FR5 $6,999 · xArm 6 $8,399 공개가 → OEM·국산 Partner·전용 Arm
A42: Linear Rail · Carriage · Servo (2.4~3.6m) | B42: 180 | C42: 150 | D42: 120 | E42: Belt 구동 7축 Rail. 소형 KK Module $73~245는 참고만
A43: End-effector Set (Gripper + Suction + Tool Changer) | B43: 120 | C43: 90 | D43: 70 | E43: Robotiq 2F-85 $4,999 대비 저가 전동 Gripper + 자체 Finger
A44: Vision (Depth Camera 2대 + Mount) | B44: 110 | C44: 80 | D44: 60 | E44: Orbbec Gemini 335 $384~400 · RealSense D405 $514
A45: Compute (Edge GPU) | B45: 100 | C45: 80 | D45: 70 | E45: Edge AI Module 가정
A46: Safety (Zone Sensor·Safety Controller) | B46: 70 | C46: 60 | D46: 50 | E46: ToF/Radar Zone Sensor + Safety Relay 가정
A47: Garage Door · Harness · Enclosure | B47: 70 | C47: 50 | D47: 45
A48: 조립·시험 (Pilot은 Opex 인건비 처리) | B48: 0 | C48: 40 | D48: 35
A49: 합계 | B49: =SUM(B41:B48) -> 1600 | C49: =SUM(C41:C48) -> 1150 | D49: =SUM(D41:D48) -> 900
A50: 검증: Inputs_Yearly Base BOM과 차이 (0이어야 함) | B50: =B49-Inputs_Yearly!$E$13 -> 0 | C50: =C49-Inputs_Yearly!$G$13 -> 0 | D50: =D49-Inputs_Yearly!$I$13 -> 0

Sheet Market
A1: Market Sizing — Bottom-up (Base)
A3: 항목 | B3: 값 | C3: 단위 | D3: Tag | E3: 산식 / 출처
A4: 총주택 (2025) | B4: =Inputs!$E$5 -> 20181 | C4: 천호 | D4: FACT | E4: 국가데이터처 2025 인구주택총조사
A5: 아파트 비중 | B5: =Inputs!$E$6 -> 0.658 | C5: % | D5: FACT
A6: 아파트 수 (2025) | B6: =B4*B5 -> 13279.098 | C6: 천호 | D6: DERIVED | E6: 총주택 × 비중
A7: 교차검증 ①: 20년+ 아파트(2023) ÷ 교체주기 | B7: =Inputs!$E$10/Inputs!$E$15 -> 290.45455 | C7: 천/년 | D7: DERIVED
A8: 교차검증 ②: 매매거래 × 아파트 비중 × 교체율 + 비거래 교체 | B8: =Inputs!$E$11*Inputs!$E$16*Inputs!$E$17+Inputs!$E$18 -> 303.28 | C8: 천/년 | D8: DERIVED
A9: 연간 Kitchen 교체 세대 (설정) | B9: =Inputs!$E$19 -> 300 | C9: 천/년 | D9: ASSUMPTION | E9: ①·② 교차검증 후 설정
A10: Premium 비중 | B10: =Inputs!$E$20 -> 0.1 | C10: % | D10: ASSUMPTION
A11: Premium Kitchen 교체 세대 | B11: =B9*B10 -> 30 | C11: 천/년 | D11: DERIVED
A12: Robot-ready 적용 가능률 | B12: =Inputs!$E$21 -> 0.6 | C12: % | D12: ASSUMPTION
A13: 구축 SAM 세대 | B13: =B11*B12 -> 18 | C13: 천/년 | D13: DERIVED
A14: 구축 패키지 기대 매출/세대 | B14: =Inputs!$E$30+Inputs_Yearly!$I$37*(Inputs!$E$32+Inputs!$E$33) -> 1784.5 | C14: 만원 | D14: DERIVED | E14: Robot-ready + Attach × (Robot + 설치)
A15: 연간 신규 아파트 입주 | B15: =Inputs!$E$22 -> 200 | C15: 천/년 | D15: DERIVED | E15: 2025 23.6만 · 2026E 18.3만
A16: Premium 단지 비중 | B16: =Inputs!$E$23 -> 0.15 | C16: % | D16: ASSUMPTION
A17: 신축 Premium 세대 | B17: =B15*B16 -> 30 | C17: 천/년 | D17: DERIVED
A18: Robot-ready Option 선택률 | B18: =Inputs!$E$74 -> 0.1 | C18: % | D18: ASSUMPTION
A19: 신축 SAM 세대 | B19: =B17*B18 -> 3 | C19: 천/년 | D19: DERIVED
A20: 신축 패키지 기대 매출/세대 | B20: =Inputs!$E$31+Inputs!$E$75*(Inputs!$E$32+Inputs!$E$33) -> 612.5 | C20: 만원 | D20: DERIVED
A21: 전체 패키지 단가 (Robot-ready + Robot + 설치) | B21: =Inputs!$E$30+Inputs!$E$32+Inputs!$E$33 -> 2020 | C21: 만원 | D21: ASSUMPTION
A22: TAM: Premium 세대 (구축+신축) × 전체 패키지 | B22: =(B11+B17)*B21/10 -> 12120 | C22: 억원/년 | D22: DERIVED | E22: 천세대 × 만원 ÷ 10 = 억원
A23: SAM 구축 | B23: =B13*B14/10 -> 3212.1 | C23: 억원/년 | D23: DERIVED
A24: SAM 신축 | B24: =B19*B20/10 -> 183.75 | C24: 억원/년 | D24: DERIVED
A25: SAM 합계 | B25: =B23+B24 -> 3395.85 | C25: 억원/년 | D25: DERIVED
A26: SOM: Y5 매출 (Base Plan) | B26: =FM_Base!$G$41/10000 -> 77.544078 | C26: 억원/년 | D26: TARGET | E26: FM_Base Y5
A27: SOM 세대 / SAM 세대 | B27: =FM_Base!$G$8/((B13+B19)*1000) -> 0.022857143 | C27: % | D27: DERIVED

Sheet Sensitivity
A1: Sensitivity — 구축 구매 1세대 5년 Contribution (Base, Y3 원가, 직접판매)
A2: 각 행은 한 변수만 바꾼 파라미터 세트 (파란 글자 = 변경값). Contribution 수식은 Household 시트와 동일 구조.
A4: Case | B4: p_robot | C4: bom | D4: p_rr | E4: cac | F4: p_care | G4: visit_cost | H4: smr | I4: comm_cost | J4: corrective | K4: warranty | L4: cons_attach | M4: Contribution | N4: Δ vs Base
A5: Base | B5: =Inputs!$E$32 -> 1490 | C5: =Inputs_Yearly!$G$13 -> 1150 | D5: =Inputs!$E$30 -> 450 | E5: =Inputs!$E$66 -> 150 | F5: =Inputs!$E$36 -> 48 | G5: =Inputs_Yearly!$G$25 -> 11 | H5: =Inputs_Yearly!$G$9 -> 0.65 | I5: =Inputs_Yearly!$G$17 -> 60 | J5: =Inputs!$E$59 -> 0.6 | K5: =Inputs!$E$58 -> 0.04 | L5: =Inputs!$E$44 -> 0.7 | M5: =(D5+Inputs!$E$33+B5+5*F5+5*L5*(Inputs!$E$38*Inputs!$E$39+Inputs!$E$40*Inputs!$E$41+Inputs!$E$42*Inputs!$E$43)+Inputs!$E$47*Inputs!$E$46+Inputs!$E$49*Inputs!$E$48)-(Inputs!$E$53*(H5+Inputs!$E$54*(1-H5))+Inputs!$E$55*(1-H5)+I5+Inputs!$E$57+C5+K5*B5+5*(Inputs_Yearly!$G$21*G5+J5*Inputs!$E$60+Inputs!$E$61)+5*L5*(Inputs!$E$38*Inputs!$E$39+Inputs!$E$40*Inputs!$E$41+Inputs!$E$42*Inputs!$E$43)*Inputs!$E$62+Inputs!$E$47*Inputs!$E$46*Inputs!$E$63+Inputs!$E$49*Inputs!$E$48*Inputs!$E$64+E5) -> 458.1 | N5: =M5-$M$5 -> 0
A6: Robot ASP (WTP) — 불리 | B6: =Inputs!$E$32*0.8 -> 1192 | C6: =Inputs_Yearly!$G$13 -> 1150 | D6: =Inputs!$E$30 -> 450 | E6: =Inputs!$E$66 -> 150 | F6: =Inputs!$E$36 -> 48 | G6: =Inputs_Yearly!$G$25 -> 11 | H6: =Inputs_Yearly!$G$9 -> 0.65 | I6: =Inputs_Yearly!$G$17 -> 60 | J6: =Inputs!$E$59 -> 0.6 | K6: =Inputs!$E$58 -> 0.04 | L6: =Inputs!$E$44 -> 0.7 | M6: =(D6+Inputs!$E$33+B6+5*F6+5*L6*(Inputs!$E$38*Inputs!$E$39+Inputs!$E$40*Inputs!$E$41+Inputs!$E$42*Inputs!$E$43)+Inputs!$E$47*Inputs!$E$46+Inputs!$E$49*Inputs!$E$48)-(Inputs!$E$53*(H6+Inputs!$E$54*(1-H6))+Inputs!$E$55*(1-H6)+I6+Inputs!$E$57+C6+K6*B6+5*(Inputs_Yearly!$G$21*G6+J6*Inputs!$E$60+Inputs!$E$61)+5*L6*(Inputs!$E$38*Inputs!$E$39+Inputs!$E$40*Inputs!$E$41+Inputs!$E$42*Inputs!$E$43)*Inputs!$E$62+Inputs!$E$47*Inputs!$E$46*Inputs!$E$63+Inputs!$E$49*Inputs!$E$48*Inputs!$E$64+E6) -> 172.02 | N6: =M6-$M$5 -> -286.08
A7: Robot ASP (WTP) — 유리 | B7: =Inputs!$E$32*1.2 -> 1788 | C7: =Inputs_Yearly!$G$13 -> 1150 | D7: =Inputs!$E$30 -> 450 | E7: =Inputs!$E$66 -> 150 | F7: =Inputs!$E$36 -> 48 | G7: =Inputs_Yearly!$G$25 -> 11 | H7: =Inputs_Yearly!$G$9 -> 0.65 | I7: =Inputs_Yearly!$G$17 -> 60 | J7: =Inputs!$E$59 -> 0.6 | K7: =Inputs!$E$58 -> 0.04 | L7: =Inputs!$E$44 -> 0.7 | M7: =(D7+Inputs!$E$33+B7+5*F7+5*L7*(Inputs!$E$38*Inputs!$E$39+Inputs!$E$40*Inputs!$E$41+Inputs!$E$42*Inputs!$E$43)+Inputs!$E$47*Inputs!$E$46+Inputs!$E$49*Inputs!$E$48)-(Inputs!$E$53*(H7+Inputs!$E$54*(1-H7))+Inputs!$E$55*(1-H7)+I7+Inputs!$E$57+C7+K7*B7+5*(Inputs_Yearly!$G$21*G7+J7*Inputs!$E$60+Inputs!$E$61)+5*L7*(Inputs!$E$38*Inputs!$E$39+Inputs!$E$40*Inputs!$E$41+Inputs!$E$42*Inputs!$E$43)*Inputs!$E$62+Inputs!$E$47*Inputs!$E$46*Inputs!$E$63+Inputs!$E$49*Inputs!$E$48*Inputs!$E$64+E7) -> 744.18 | N7: =M7-$M$5 -> 286.08
A8: Robot BOM — 불리 | B8: =Inputs!$E$32 -> 1490 | C8: =Inputs_Yearly!$G$13*1.2 -> 1380 | D8: =Inputs!$E$30 -> 450 | E8: =Inputs!$E$66 -> 150 | F8: =Inputs!$E$36 -> 48 | G8: =Inputs_Yearly!$G$25 -> 11 | H8: =Inputs_Yearly!$G$9 -> 0.65 | I8: =Inputs_Yearly!$G$17 -> 60 | J8: =Inputs!$E$59 -> 0.6 | K8: =Inputs!$E$58 -> 0.04 | L8: =Inputs!$E$44 -> 0.7 | M8: =(D8+Inputs!$E$33+B8+5*F8+5*L8*(Inputs!$E$38*Inputs!$E$39+Inputs!$E$40*Inputs!$E$41+Inputs!$E$42*Inputs!$E$43)+Inputs!$E$47*Inputs!$E$46+Inputs!$E$49*Inputs!$E$48)-(Inputs!$E$53*(H8+Inputs!$E$54*(1-H8))+Inputs!$E$55*(1-H8)+I8+Inputs!$E$57+C8+K8*B8+5*(Inputs_Yearly!$G$21*G8+J8*Inputs!$E$60+Inputs!$E$61)+5*L8*(Inputs!$E$38*Inputs!$E$39+Inputs!$E$40*Inputs!$E$41+Inputs!$E$42*Inputs!$E$43)*Inputs!$E$62+Inputs!$E$47*Inputs!$E$46*Inputs!$E$63+Inputs!$E$49*Inputs!$E$48*Inputs!$E$64+E8) -> 228.1 | N8: =M8-$M$5 -> -230
A9: Robot BOM — 유리 | B9: =Inputs!$E$32 -> 1490 | C9: =Inputs_Yearly!$G$13*0.8 -> 920 | D9: =Inputs!$E$30 -> 450 | E9: =Inputs!$E$66 -> 150 | F9: =Inputs!$E$36 -> 48 | G9: =Inputs_Yearly!$G$25 -> 11 | H9: =Inputs_Yearly!$G$9 -> 0.65 | I9: =Inputs_Yearly!$G$17 -> 60 | J9: =Inputs!$E$59 -> 0.6 | K9: =Inputs!$E$58 -> 0.04 | L9: =Inputs!$E$44 -> 0.7 | M9: =(D9+Inputs!$E$33+B9+5*F9+5*L9*(Inputs!$E$38*Inputs!$E$39+Inputs!$E$40*Inputs!$E$41+Inputs!$E$42*Inputs!$E$43)+Inputs!$E$47*Inputs!$E$46+Inputs!$E$49*Inputs!$E$48)-(Inputs!$E$53*(H9+Inputs!$E$54*(1-H9))+Inputs!$E$55*(1-H9)+I9+Inputs!$E$57+C9+K9*B9+5*(Inputs_Yearly!$G$21*G9+J9*Inputs!$E$60+Inputs!$E$61)+5*L9*(Inputs!$E$38*Inputs!$E$39+Inputs!$E$40*Inputs!$E$41+Inputs!$E$42*Inputs!$E$43)*Inputs!$E$62+Inputs!$E$47*Inputs!$E$46*Inputs!$E$63+Inputs!$E$49*Inputs!$E$48*Inputs!$E$64+E9) -> 688.1 | N9: =M9-$M$5 -> 230
A10: Robot-ready 증분가 — 불리 | B10: =Inputs!$E$32 -> 1490 | C10: =Inputs_Yearly!$G$13 -> 1150 | D10: =Inputs!$E$30*0.8 -> 360 | E10: =Inputs!$E$66 -> 150 | F10: =Inputs!$E$36 -> 48 | G10: =Inputs_Yearly!$G$25 -> 11 | H10: =Inputs_Yearly!$G$9 -> 0.65 | I10: =Inputs_Yearly!$G$17 -> 60 | J10: =Inputs!$E$59 -> 0.6 | K10: =Inputs!$E$58 -> 0.04 | L10: =Inputs!$E$44 -> 0.7 | M10: =(D10+Inputs!$E$33+B10+5*F10+5*L10*(Inputs!$E$38*Inputs!$E$39+Inputs!$E$40*Inputs!$E$41+Inputs!$E$42*Inputs!$E$43)+Inputs!$E$47*Inputs!$E$46+Inputs!$E$49*Inputs!$E$48)-(Inputs!$E$53*(H10+Inputs!$E$54*(1-H10))+Inputs!$E$55*(1-H10)+I10+Inputs!$E$57+C10+K10*B10+5*(Inputs_Yearly!$G$21*G10+J10*Inputs!$E$60+Inputs!$E$61)+5*L10*(Inputs!$E$38*Inputs!$E$39+Inputs!$E$40*Inputs!$E$41+Inputs!$E$42*Inputs!$E$43)*Inputs!$E$62+Inputs!$E$47*Inputs!$E$46*Inputs!$E$63+Inputs!$E$49*Inputs!$E$48*Inputs!$E$64+E10) -> 368.1 | N10: =M10-$M$5 -> -90
A11: Robot-ready 증분가 — 유리 | B11: =Inputs!$E$32 -> 1490 | C11: =Inputs_Yearly!$G$13 -> 1150 | D11: =Inputs!$E$30*1.2 -> 540 | E11: =Inputs!$E$66 -> 150 | F11: =Inputs!$E$36 -> 48 | G11: =Inputs_Yearly!$G$25 -> 11 | H11: =Inputs_Yearly!$G$9 -> 0.65 | I11: =Inputs_Yearly!$G$17 -> 60 | J11: =Inputs!$E$59 -> 0.6 | K11: =Inputs!$E$58 -> 0.04 | L11: =Inputs!$E$44 -> 0.7 | M11: =(D11+Inputs!$E$33+B11+5*F11+5*L11*(Inputs!$E$38*Inputs!$E$39+Inputs!$E$40*Inputs!$E$41+Inputs!$E$42*Inputs!$E$43)+Inputs!$E$47*Inputs!$E$46+Inputs!$E$49*Inputs!$E$48)-(Inputs!$E$53*(H11+Inputs!$E$54*(1-H11))+Inputs!$E$55*(1-H11)+I11+Inputs!$E$57+C11+K11*B11+5*(Inputs_Yearly!$G$21*G11+J11*Inputs!$E$60+Inputs!$E$61)+5*L11*(Inputs!$E$38*Inputs!$E$39+Inputs!$E$40*Inputs!$E$41+Inputs!$E$42*Inputs!$E$43)*Inputs!$E$62+Inputs!$E$47*Inputs!$E$46*Inputs!$E$63+Inputs!$E$49*Inputs!$E$48*Inputs!$E$64+E11) -> 548.1 | N11: =M11-$M$5 -> 90
A12: 직접판매 획득비용 — 불리 | B12: =Inputs!$E$32 -> 1490 | C12: =Inputs_Yearly!$G$13 -> 1150 | D12: =Inputs!$E$30 -> 450 | E12: =Inputs!$E$66*1.5 -> 225 | F12: =Inputs!$E$36 -> 48 | G12: =Inputs_Yearly!$G$25 -> 11 | H12: =Inputs_Yearly!$G$9 -> 0.65 | I12: =Inputs_Yearly!$G$17 -> 60 | J12: =Inputs!$E$59 -> 0.6 | K12: =Inputs!$E$58 -> 0.04 | L12: =Inputs!$E$44 -> 0.7 | M12: =(D12+Inputs!$E$33+B12+5*F12+5*L12*(Inputs!$E$38*Inputs!$E$39+Inputs!$E$40*Inputs!$E$41+Inputs!$E$42*Inputs!$E$43)+Inputs!$E$47*Inputs!$E$46+Inputs!$E$49*Inputs!$E$48)-(Inputs!$E$53*(H12+Inputs!$E$54*(1-H12))+Inputs!$E$55*(1-H12)+I12+Inputs!$E$57+C12+K12*B12+5*(Inputs_Yearly!$G$21*G12+J12*Inputs!$E$60+Inputs!$E$61)+5*L12*(Inputs!$E$38*Inputs!$E$39+Inputs!$E$40*Inputs!$E$41+Inputs!$E$42*Inputs!$E$43)*Inputs!$E$62+Inputs!$E$47*Inputs!$E$46*Inputs!$E$63+Inputs!$E$49*Inputs!$E$48*Inputs!$E$64+E12) -> 383.1 | N12: =M12-$M$5 -> -75
A13: 직접판매 획득비용 — 유리 | B13: =Inputs!$E$32 -> 1490 | C13: =Inputs_Yearly!$G$13 -> 1150 | D13: =Inputs!$E$30 -> 450 | E13: =Inputs!$E$66*0.5 -> 75 | F13: =Inputs!$E$36 -> 48 | G13: =Inputs_Yearly!$G$25 -> 11 | H13: =Inputs_Yearly!$G$9 -> 0.65 | I13: =Inputs_Yearly!$G$17 -> 60 | J13: =Inputs!$E$59 -> 0.6 | K13: =Inputs!$E$58 -> 0.04 | L13: =Inputs!$E$44 -> 0.7 | M13: =(D13+Inputs!$E$33+B13+5*F13+5*L13*(Inputs!$E$38*Inputs!$E$39+Inputs!$E$40*Inputs!$E$41+Inputs!$E$42*Inputs!$E$43)+Inputs!$E$47*Inputs!$E$46+Inputs!$E$49*Inputs!$E$48)-(Inputs!$E$53*(H13+Inputs!$E$54*(1-H13))+Inputs!$E$55*(1-H13)+I13+Inputs!$E$57+C13+K13*B13+5*(Inputs_Yearly!$G$21*G13+J13*Inputs!$E$60+Inputs!$E$61)+5*L13*(Inputs!$E$38*Inputs!$E$39+Inputs!$E$40*Inputs!$E$41+Inputs!$E$42*Inputs!$E$43)*Inputs!$E$62+Inputs!$E$47*Inputs!$E$46*Inputs!$E$63+Inputs!$E$49*Inputs!$E$48*Inputs!$E$64+E13) -> 533.1 | N13: =M13-$M$5 -> 75
A14: Failure Rate — 불리 | B14: =Inputs!$E$32 -> 1490 | C14: =Inputs_Yearly!$G$13 -> 1150 | D14: =Inputs!$E$30 -> 450 | E14: =Inputs!$E$66 -> 150 | F14: =Inputs!$E$36 -> 48 | G14: =Inputs_Yearly!$G$25 -> 11 | H14: =Inputs_Yearly!$G$9 -> 0.65 | I14: =Inputs_Yearly!$G$17 -> 60 | J14: =1.2 -> 1.2 | K14: =0.06 -> 0.06 | L14: =Inputs!$E$44 -> 0.7 | M14: =(D14+Inputs!$E$33+B14+5*F14+5*L14*(Inputs!$E$38*Inputs!$E$39+Inputs!$E$40*Inputs!$E$41+Inputs!$E$42*Inputs!$E$43)+Inputs!$E$47*Inputs!$E$46+Inputs!$E$49*Inputs!$E$48)-(Inputs!$E$53*(H14+Inputs!$E$54*(1-H14))+Inputs!$E$55*(1-H14)+I14+Inputs!$E$57+C14+K14*B14+5*(Inputs_Yearly!$G$21*G14+J14*Inputs!$E$60+Inputs!$E$61)+5*L14*(Inputs!$E$38*Inputs!$E$39+Inputs!$E$40*Inputs!$E$41+Inputs!$E$42*Inputs!$E$43)*Inputs!$E$62+Inputs!$E$47*Inputs!$E$46*Inputs!$E$63+Inputs!$E$49*Inputs!$E$48*Inputs!$E$64+E14) -> 374.3 | N14: =M14-$M$5 -> -83.8
A15: Failure Rate — 유리 | B15: =Inputs!$E$32 -> 1490 | C15: =Inputs_Yearly!$G$13 -> 1150 | D15: =Inputs!$E$30 -> 450 | E15: =Inputs!$E$66 -> 150 | F15: =Inputs!$E$36 -> 48 | G15: =Inputs_Yearly!$G$25 -> 11 | H15: =Inputs_Yearly!$G$9 -> 0.65 | I15: =Inputs_Yearly!$G$17 -> 60 | J15: =0.3 -> 0.3 | K15: =0.025 -> 0.025 | L15: =Inputs!$E$44 -> 0.7 | M15: =(D15+Inputs!$E$33+B15+5*F15+5*L15*(Inputs!$E$38*Inputs!$E$39+Inputs!$E$40*Inputs!$E$41+Inputs!$E$42*Inputs!$E$43)+Inputs!$E$47*Inputs!$E$46+Inputs!$E$49*Inputs!$E$48)-(Inputs!$E$53*(H15+Inputs!$E$54*(1-H15))+Inputs!$E$55*(1-H15)+I15+Inputs!$E$57+C15+K15*B15+5*(Inputs_Yearly!$G$21*G15+J15*Inputs!$E$60+Inputs!$E$61)+5*L15*(Inputs!$E$38*Inputs!$E$39+Inputs!$E$40*Inputs!$E$41+Inputs!$E$42*Inputs!$E$43)*Inputs!$E$62+Inputs!$E$47*Inputs!$E$46*Inputs!$E$63+Inputs!$E$49*Inputs!$E$48*Inputs!$E$64+E15) -> 507.45 | N15: =M15-$M$5 -> 49.35
A16: Care 요금 — 불리 | B16: =Inputs!$E$32 -> 1490 | C16: =Inputs_Yearly!$G$13 -> 1150 | D16: =Inputs!$E$30 -> 450 | E16: =Inputs!$E$66 -> 150 | F16: =Inputs!$E$36*0.8 -> 38.4 | G16: =Inputs_Yearly!$G$25 -> 11 | H16: =Inputs_Yearly!$G$9 -> 0.65 | I16: =Inputs_Yearly!$G$17 -> 60 | J16: =Inputs!$E$59 -> 0.6 | K16: =Inputs!$E$58 -> 0.04 | L16: =Inputs!$E$44 -> 0.7 | M16: =(D16+Inputs!$E$33+B16+5*F16+5*L16*(Inputs!$E$38*Inputs!$E$39+Inputs!$E$40*Inputs!$E$41+Inputs!$E$42*Inputs!$E$43)+Inputs!$E$47*Inputs!$E$46+Inputs!$E$49*Inputs!$E$48)-(Inputs!$E$53*(H16+Inputs!$E$54*(1-H16))+Inputs!$E$55*(1-H16)+I16+Inputs!$E$57+C16+K16*B16+5*(Inputs_Yearly!$G$21*G16+J16*Inputs!$E$60+Inputs!$E$61)+5*L16*(Inputs!$E$38*Inputs!$E$39+Inputs!$E$40*Inputs!$E$41+Inputs!$E$42*Inputs!$E$43)*Inputs!$E$62+Inputs!$E$47*Inputs!$E$46*Inputs!$E$63+Inputs!$E$49*Inputs!$E$48*Inputs!$E$64+E16) -> 410.1 | N16: =M16-$M$5 -> -48
A17: Care 요금 — 유리 | B17: =Inputs!$E$32 -> 1490 | C17: =Inputs_Yearly!$G$13 -> 1150 | D17: =Inputs!$E$30 -> 450 | E17: =Inputs!$E$66 -> 150 | F17: =Inputs!$E$36*1.2 -> 57.6 | G17: =Inputs_Yearly!$G$25 -> 11 | H17: =Inputs_Yearly!$G$9 -> 0.65 | I17: =Inputs_Yearly!$G$17 -> 60 | J17: =Inputs!$E$59 -> 0.6 | K17: =Inputs!$E$58 -> 0.04 | L17: =Inputs!$E$44 -> 0.7 | M17: =(D17+Inputs!$E$33+B17+5*F17+5*L17*(Inputs!$E$38*Inputs!$E$39+Inputs!$E$40*Inputs!$E$41+Inputs!$E$42*Inputs!$E$43)+Inputs!$E$47*Inputs!$E$46+Inputs!$E$49*Inputs!$E$48)-(Inputs!$E$53*(H17+Inputs!$E$54*(1-H17))+Inputs!$E$55*(1-H17)+I17+Inputs!$E$57+C17+K17*B17+5*(Inputs_Yearly!$G$21*G17+J17*Inputs!$E$60+Inputs!$E$61)+5*L17*(Inputs!$E$38*Inputs!$E$39+Inputs!$E$40*Inputs!$E$41+Inputs!$E$42*Inputs!$E$43)*Inputs!$E$62+Inputs!$E$47*Inputs!$E$46*Inputs!$E$63+Inputs!$E$49*Inputs!$E$48*Inputs!$E$64+E17) -> 506.1 | N17: =M17-$M$5 -> 48
A18: 방문 원가 — 불리 | B18: =Inputs!$E$32 -> 1490 | C18: =Inputs_Yearly!$G$13 -> 1150 | D18: =Inputs!$E$30 -> 450 | E18: =Inputs!$E$66 -> 150 | F18: =Inputs!$E$36 -> 48 | G18: =Inputs_Yearly!$G$25*1.3 -> 14.3 | H18: =Inputs_Yearly!$G$9 -> 0.65 | I18: =Inputs_Yearly!$G$17 -> 60 | J18: =Inputs!$E$59 -> 0.6 | K18: =Inputs!$E$58 -> 0.04 | L18: =Inputs!$E$44 -> 0.7 | M18: =(D18+Inputs!$E$33+B18+5*F18+5*L18*(Inputs!$E$38*Inputs!$E$39+Inputs!$E$40*Inputs!$E$41+Inputs!$E$42*Inputs!$E$43)+Inputs!$E$47*Inputs!$E$46+Inputs!$E$49*Inputs!$E$48)-(Inputs!$E$53*(H18+Inputs!$E$54*(1-H18))+Inputs!$E$55*(1-H18)+I18+Inputs!$E$57+C18+K18*B18+5*(Inputs_Yearly!$G$21*G18+J18*Inputs!$E$60+Inputs!$E$61)+5*L18*(Inputs!$E$38*Inputs!$E$39+Inputs!$E$40*Inputs!$E$41+Inputs!$E$42*Inputs!$E$43)*Inputs!$E$62+Inputs!$E$47*Inputs!$E$46*Inputs!$E$63+Inputs!$E$49*Inputs!$E$48*Inputs!$E$64+E18) -> 425.1 | N18: =M18-$M$5 -> -33
A19: 방문 원가 — 유리 | B19: =Inputs!$E$32 -> 1490 | C19: =Inputs_Yearly!$G$13 -> 1150 | D19: =Inputs!$E$30 -> 450 | E19: =Inputs!$E$66 -> 150 | F19: =Inputs!$E$36 -> 48 | G19: =Inputs_Yearly!$G$25*0.7 -> 7.7 | H19: =Inputs_Yearly!$G$9 -> 0.65 | I19: =Inputs_Yearly!$G$17 -> 60 | J19: =Inputs!$E$59 -> 0.6 | K19: =Inputs!$E$58 -> 0.04 | L19: =Inputs!$E$44 -> 0.7 | M19: =(D19+Inputs!$E$33+B19+5*F19+5*L19*(Inputs!$E$38*Inputs!$E$39+Inputs!$E$40*Inputs!$E$41+Inputs!$E$42*Inputs!$E$43)+Inputs!$E$47*Inputs!$E$46+Inputs!$E$49*Inputs!$E$48)-(Inputs!$E$53*(H19+Inputs!$E$54*(1-H19))+Inputs!$E$55*(1-H19)+I19+Inputs!$E$57+C19+K19*B19+5*(Inputs_Yearly!$G$21*G19+J19*Inputs!$E$60+Inputs!$E$61)+5*L19*(Inputs!$E$38*Inputs!$E$39+Inputs!$E$40*Inputs!$E$41+Inputs!$E$42*Inputs!$E$43)*Inputs!$E$62+Inputs!$E$47*Inputs!$E$46*Inputs!$E$63+Inputs!$E$49*Inputs!$E$48*Inputs!$E$64+E19) -> 491.1 | N19: =M19-$M$5 -> 33
A20: Standard Module 사용률 — 불리 | B20: =Inputs!$E$32 -> 1490 | C20: =Inputs_Yearly!$G$13 -> 1150 | D20: =Inputs!$E$30 -> 450 | E20: =Inputs!$E$66 -> 150 | F20: =Inputs!$E$36 -> 48 | G20: =Inputs_Yearly!$G$25 -> 11 | H20: =Inputs_Yearly!$G$9-0.15 -> 0.5 | I20: =Inputs_Yearly!$G$17 -> 60 | J20: =Inputs!$E$59 -> 0.6 | K20: =Inputs!$E$58 -> 0.04 | L20: =Inputs!$E$44 -> 0.7 | M20: =(D20+Inputs!$E$33+B20+5*F20+5*L20*(Inputs!$E$38*Inputs!$E$39+Inputs!$E$40*Inputs!$E$41+Inputs!$E$42*Inputs!$E$43)+Inputs!$E$47*Inputs!$E$46+Inputs!$E$49*Inputs!$E$48)-(Inputs!$E$53*(H20+Inputs!$E$54*(1-H20))+Inputs!$E$55*(1-H20)+I20+Inputs!$E$57+C20+K20*B20+5*(Inputs_Yearly!$G$21*G20+J20*Inputs!$E$60+Inputs!$E$61)+5*L20*(Inputs!$E$38*Inputs!$E$39+Inputs!$E$40*Inputs!$E$41+Inputs!$E$42*Inputs!$E$43)*Inputs!$E$62+Inputs!$E$47*Inputs!$E$46*Inputs!$E$63+Inputs!$E$49*Inputs!$E$48*Inputs!$E$64+E20) -> 425.1 | N20: =M20-$M$5 -> -33
A21: Standard Module 사용률 — 유리 | B21: =Inputs!$E$32 -> 1490 | C21: =Inputs_Yearly!$G$13 -> 1150 | D21: =Inputs!$E$30 -> 450 | E21: =Inputs!$E$66 -> 150 | F21: =Inputs!$E$36 -> 48 | G21: =Inputs_Yearly!$G$25 -> 11 | H21: =Inputs_Yearly!$G$9+0.15 -> 0.8 | I21: =Inputs_Yearly!$G$17 -> 60 | J21: =Inputs!$E$59 -> 0.6 | K21: =Inputs!$E$58 -> 0.04 | L21: =Inputs!$E$44 -> 0.7 | M21: =(D21+Inputs!$E$33+B21+5*F21+5*L21*(Inputs!$E$38*Inputs!$E$39+Inputs!$E$40*Inputs!$E$41+Inputs!$E$42*Inputs!$E$43)+Inputs!$E$47*Inputs!$E$46+Inputs!$E$49*Inputs!$E$48)-(Inputs!$E$53*(H21+Inputs!$E$54*(1-H21))+Inputs!$E$55*(1-H21)+I21+Inputs!$E$57+C21+K21*B21+5*(Inputs_Yearly!$G$21*G21+J21*Inputs!$E$60+Inputs!$E$61)+5*L21*(Inputs!$E$38*Inputs!$E$39+Inputs!$E$40*Inputs!$E$41+Inputs!$E$42*Inputs!$E$43)*Inputs!$E$62+Inputs!$E$47*Inputs!$E$46*Inputs!$E$63+Inputs!$E$49*Inputs!$E$48*Inputs!$E$64+E21) -> 491.1 | N21: =M21-$M$5 -> 33
A22: 설치 원가 — 불리 | B22: =Inputs!$E$32 -> 1490 | C22: =Inputs_Yearly!$G$13 -> 1150 | D22: =Inputs!$E$30 -> 450 | E22: =Inputs!$E$66 -> 150 | F22: =Inputs!$E$36 -> 48 | G22: =Inputs_Yearly!$G$25 -> 11 | H22: =Inputs_Yearly!$G$9 -> 0.65 | I22: =Inputs_Yearly!$G$17*1.5 -> 90 | J22: =Inputs!$E$59 -> 0.6 | K22: =Inputs!$E$58 -> 0.04 | L22: =Inputs!$E$44 -> 0.7 | M22: =(D22+Inputs!$E$33+B22+5*F22+5*L22*(Inputs!$E$38*Inputs!$E$39+Inputs!$E$40*Inputs!$E$41+Inputs!$E$42*Inputs!$E$43)+Inputs!$E$47*Inputs!$E$46+Inputs!$E$49*Inputs!$E$48)-(Inputs!$E$53*(H22+Inputs!$E$54*(1-H22))+Inputs!$E$55*(1-H22)+I22+Inputs!$E$57+C22+K22*B22+5*(Inputs_Yearly!$G$21*G22+J22*Inputs!$E$60+Inputs!$E$61)+5*L22*(Inputs!$E$38*Inputs!$E$39+Inputs!$E$40*Inputs!$E$41+Inputs!$E$42*Inputs!$E$43)*Inputs!$E$62+Inputs!$E$47*Inputs!$E$46*Inputs!$E$63+Inputs!$E$49*Inputs!$E$48*Inputs!$E$64+E22) -> 428.1 | N22: =M22-$M$5 -> -30
A23: 설치 원가 — 유리 | B23: =Inputs!$E$32 -> 1490 | C23: =Inputs_Yearly!$G$13 -> 1150 | D23: =Inputs!$E$30 -> 450 | E23: =Inputs!$E$66 -> 150 | F23: =Inputs!$E$36 -> 48 | G23: =Inputs_Yearly!$G$25 -> 11 | H23: =Inputs_Yearly!$G$9 -> 0.65 | I23: =Inputs_Yearly!$G$17*0.5 -> 30 | J23: =Inputs!$E$59 -> 0.6 | K23: =Inputs!$E$58 -> 0.04 | L23: =Inputs!$E$44 -> 0.7 | M23: =(D23+Inputs!$E$33+B23+5*F23+5*L23*(Inputs!$E$38*Inputs!$E$39+Inputs!$E$40*Inputs!$E$41+Inputs!$E$42*Inputs!$E$43)+Inputs!$E$47*Inputs!$E$46+Inputs!$E$49*Inputs!$E$48)-(Inputs!$E$53*(H23+Inputs!$E$54*(1-H23))+Inputs!$E$55*(1-H23)+I23+Inputs!$E$57+C23+K23*B23+5*(Inputs_Yearly!$G$21*G23+J23*Inputs!$E$60+Inputs!$E$61)+5*L23*(Inputs!$E$38*Inputs!$E$39+Inputs!$E$40*Inputs!$E$41+Inputs!$E$42*Inputs!$E$43)*Inputs!$E$62+Inputs!$E$47*Inputs!$E$46*Inputs!$E$63+Inputs!$E$49*Inputs!$E$48*Inputs!$E$64+E23) -> 488.1 | N23: =M23-$M$5 -> 30
A24: Consumables 구매율 — 불리 | B24: =Inputs!$E$32 -> 1490 | C24: =Inputs_Yearly!$G$13 -> 1150 | D24: =Inputs!$E$30 -> 450 | E24: =Inputs!$E$66 -> 150 | F24: =Inputs!$E$36 -> 48 | G24: =Inputs_Yearly!$G$25 -> 11 | H24: =Inputs_Yearly!$G$9 -> 0.65 | I24: =Inputs_Yearly!$G$17 -> 60 | J24: =Inputs!$E$59 -> 0.6 | K24: =Inputs!$E$58 -> 0.04 | L24: =0.5 -> 0.5 | M24: =(D24+Inputs!$E$33+B24+5*F24+5*L24*(Inputs!$E$38*Inputs!$E$39+Inputs!$E$40*Inputs!$E$41+Inputs!$E$42*Inputs!$E$43)+Inputs!$E$47*Inputs!$E$46+Inputs!$E$49*Inputs!$E$48)-(Inputs!$E$53*(H24+Inputs!$E$54*(1-H24))+Inputs!$E$55*(1-H24)+I24+Inputs!$E$57+C24+K24*B24+5*(Inputs_Yearly!$G$21*G24+J24*Inputs!$E$60+Inputs!$E$61)+5*L24*(Inputs!$E$38*Inputs!$E$39+Inputs!$E$40*Inputs!$E$41+Inputs!$E$42*Inputs!$E$43)*Inputs!$E$62+Inputs!$E$47*Inputs!$E$46*Inputs!$E$63+Inputs!$E$49*Inputs!$E$48*Inputs!$E$64+E24) -> 434.7 | N24: =M24-$M$5 -> -23.4
A25: Consumables 구매율 — 유리 | B25: =Inputs!$E$32 -> 1490 | C25: =Inputs_Yearly!$G$13 -> 1150 | D25: =Inputs!$E$30 -> 450 | E25: =Inputs!$E$66 -> 150 | F25: =Inputs!$E$36 -> 48 | G25: =Inputs_Yearly!$G$25 -> 11 | H25: =Inputs_Yearly!$G$9 -> 0.65 | I25: =Inputs_Yearly!$G$17 -> 60 | J25: =Inputs!$E$59 -> 0.6 | K25: =Inputs!$E$58 -> 0.04 | L25: =0.9 -> 0.9 | M25: =(D25+Inputs!$E$33+B25+5*F25+5*L25*(Inputs!$E$38*Inputs!$E$39+Inputs!$E$40*Inputs!$E$41+Inputs!$E$42*Inputs!$E$43)+Inputs!$E$47*Inputs!$E$46+Inputs!$E$49*Inputs!$E$48)-(Inputs!$E$53*(H25+Inputs!$E$54*(1-H25))+Inputs!$E$55*(1-H25)+I25+Inputs!$E$57+C25+K25*B25+5*(Inputs_Yearly!$G$21*G25+J25*Inputs!$E$60+Inputs!$E$61)+5*L25*(Inputs!$E$38*Inputs!$E$39+Inputs!$E$40*Inputs!$E$41+Inputs!$E$42*Inputs!$E$43)*Inputs!$E$62+Inputs!$E$47*Inputs!$E$46*Inputs!$E$63+Inputs!$E$49*Inputs!$E$48*Inputs!$E$64+E25) -> 481.5 | N25: =M25-$M$5 -> 23.4
A28: 회사 Y5 Contribution 민감도 (Base, 만원) — STATIC SNAPSHOT: model.py sens_company() 결과. 입력 변경 시 model.py 재실행 필요
A29: 변수 (불리 ↔ 유리) | B29: 불리 Δ | C29: 유리 Δ
A30: Base Y5 Contribution | B30: 203048.8
A31: Customer WTP (Robot ASP·증분가 ±20%) | B31: -123292.3 | C31: 123292.3
A32: Robot BOM ±20% | B32: -65950.4 | C32: 65950.4
A33: Partner 경유 Kitchen ±30% | B33: -47955 | C33: 47955
A34: Robot Attach Rate 65% ↔ 95% | B34: -31322.8 | C34: 15661.4
A35: Failure Rate 0.3 ↔ 1.2회 | B35: -13667.6 | C35: 9411
A36: Rental 비중 20% ↔ 60% | B36: -11409.8 | C36: 11409.8
A37: Standard Module 사용률 -15pp/+10pp | B37: -13200 | C37: 8800
A38: 신축 Option 선택률 5% ↔ 15% | B38: -7825.2 | C38: 7825.2
A39: 설치 원가 ±50% | B39: -6904.1 | C39: 6904.1
A40: Service 원가 (방문) ±30% | B40: -1119.6 | C40: 1119.6

Sheet TIPS_Budget
A1: TIPS 기간 24개월 자금 계획 (만원) — 회사 전체 지출 · TIPS 과제 예산 · 재원
A3: A. 회사 전체 지출 (FM_Base 연동) | B3: Y1 | C3: Y2 | D3: 합계 | E3: 산식
A4: 인건비 | B4: =FM_Base!$C$66 -> 37400 | C4: =FM_Base!$D$66 -> 59500 | D4: =B4+C4 -> 96900 | E4: 평균 인원 × 인당 인건비
A5: 그 밖의 운영비 (시제품 · 공간 · SW · 시험 · 특허 · 고객 검증 · 관리) | B5: =FM_Base!$C$67 -> 29500 | C5: =FM_Base!$D$67 -> 27500 | D5: =B5+C5 -> 57000 | E5: Inputs_Yearly
A6: 실증 · 판매 관련 순비용 (실증 매출총손실 · 획득비용 · Rental 자산 − 감가) | B6: =-FM_Base!$C$70-FM_Base!$C$68 -> 0 | C6: =-FM_Base!$D$70-FM_Base!$D$68 -> 3594.8985 | D6: =B6+C6 -> 3594.8985 | E6: −현금흐름 − Opex
A7: 회사 전체 지출 합계 (= −현금흐름) | B7: =SUM(B4:B6) -> 66900 | C7: =SUM(C4:C6) -> 90594.898 | D7: =SUM(D4:D6) -> 157494.9
A9: B. TIPS 과제 예산 (비목 · 내용 · 현금/현물) | B9: 1차년도 | C9: 2차년도 | D9: 합계 | E9: 근거
A10: 인건비 — 신규 연구원 5명 (참여율 50~80%) [현금] | B10: 23233.3 | C10: 31450 | D10: =B10+C10 -> 54683.3 | E10: model.py TIPS_TEAM · TIPS_OTHER · TIPS_YEAR (ASSUMPTION)
A11: 인건비 — 대표 (과제책임자, 참여율 50%) [현물] | B11: 4250 | C11: 4250 | D11: =B11+C11 -> 8500 | E11: model.py TIPS_TEAM · TIPS_OTHER · TIPS_YEAR (ASSUMPTION)
A12: 연구재료비 — 시제품 1차 2식 · 실물 크기 목업 주방 2식 (Y1) / 실증용 하드웨어 · 2차 개선 부품 (Y2) [현금] | B12: 12000 | C12: 6500 | D12: =B12+C12 -> 18500 | E12: model.py TIPS_TEAM · TIPS_OTHER · TIPS_YEAR (ASSUMPTION)
A13: 연구활동비 — 외주 가공 · SW · 연구실 운영 · 특허 2건 (Y1) / 공인시험 · 안전 사전시험 · 특허 3건 (Y2) [현금] | B13: 6000 | C13: 9200 | D13: =B13+C13 -> 15200 | E13: model.py TIPS_TEAM · TIPS_OTHER · TIPS_YEAR (ASSUMPTION)
A14: 연구수당 — 참여 연구원 (인건비 대비 약 5%) [현금] | B14: 1400 | C14: 1800 | D14: =B14+C14 -> 3200 | E14: model.py TIPS_TEAM · TIPS_OTHER · TIPS_YEAR (ASSUMPTION)
A15: 간접비 — 연구개발 지원 · 성과활용 (직접비 대비) [현금] | B15: 3116.7 | C15: 3466.7 | D15: =B15+C15 -> 6583.4 | E15: model.py TIPS_TEAM · TIPS_OTHER · TIPS_YEAR (ASSUMPTION)
A16: TIPS 과제 예산 합계 | B16: =SUM(B10:B15) -> 50000 | C16: =SUM(C10:C15) -> 56666.7 | D16: =SUM(D10:D15) -> 106666.7
A17: 정부지원금 (Inputs) | D17: =Inputs!$E$79 -> 80000
A18: 정부지원 비율 (= 정부지원금 / 과제 합계) | D18: =Inputs!$E$79/D16 -> 0.74999977 | E18: 상한 = Inputs tips_gov_ratio
A19: 정부지원 비율 상한 충족 (1 = 예) | D19: =IF(Inputs!$E$79/D16<=Inputs!$E$81+0.0001,1,0) -> 1
A20: 민간부담 (= 과제 합계 − 정부지원금) | D20: =D16-Inputs!$E$79 -> 26666.7
A21: 민간부담 중 현물 | D21: =D11 -> 8500 | E21: 대표 인건비 참여분
A22: 민간부담 중 현금 | D22: =D16-Inputs!$E$79-(D11) -> 18166.7
A23: 민간 현금 비율 하한 충족 (1 = 예) | D23: =IF((D16-Inputs!$E$79-(D11))/(D16-Inputs!$E$79)>=Inputs!$E$82-0.0001,1,0) -> 1 | E23: 기관부담 중 현금 ≥ Inputs tips_cash_ratio
A25: C. 재원 vs 지출 (24개월) | D25: 금액 | E25: 비고
A26: TIPS R&D 정부지원금 (선정 시) | D26: =Inputs!$E$79 -> 80000 | E26: FACT (2026 공고 최대) · 선정 미확정
A27: 운영사 투자 (요청) | D27: =Inputs!$E$83 -> 30000 | E27: ASSUMPTION
A28: 후속 투자 (M12 목표) | D28: =Inputs!$E$84 -> 50000 | E28: TARGET
A29: 재원 합계 | D29: =SUM(D26:D28) -> 160000
A30: 회사 전체 지출 (A) | D30: =D7 -> 157494.9
A31: 여유 (재원 − 지출) | D31: =D29-D7 -> 2505.1015
A32: 과제 밖 지출 (A − B) | D32: =D7-D16 -> 50828.198 | E32: 인건비 일부 · 관리 · 고객 조사 · 실증 순비용
A33: 회사 부담 필요액 (A − 정부지원금) | D33: =D7-Inputs!$E$79 -> 77494.898 | E33: 운영사 투자 + 후속 투자로 충당
A34: 후속 투자 없을 때 자금 지속 (개월) — STATIC: model.py tips_plan() | D34: 17.7 | E34: 정부지원금 연차 초 지급 · 월 지출 균등 가정

Sheet Sources
A1: FACT Sources (조회일 2026-10-07, 검색 결과 기준 — 외부 제출 전 원문 재확인 필요)
A3: 항목 | B3: 값 | C3: 기준 | D3: Source
A4: 총주택 / 아파트 비중 / 준공 20년·30년 이상 비중 / 미거주 주택 | B4: 2,018.1만호 / 65.8% / 56.0%·30.6% / 172.2만호 | C4: 2025.11.1 기준 | D4: 국가데이터처, 2025 인구주택총조사 결과 (2026.7.28 발표) — 보도: https://www.newsis.com/view/NISX20260728_0003726109 , https://www.fnnews.com/news/202607281048203456
A5: 아파트 수 / 준공 20년 이상 아파트 (2023) | B5: 1,263만호 / 639만호 (50.7%) | C5: 2023 주택총조사 | D5: 통계청 주택총조사 인용 보도: https://www.smarttoday.co.kr/ko-kr/articles/49322
A6: 2025 주택 준공 / 인허가 / 착공 / 공동주택 분양 | B6: 34만2,399호 (−17.8%) / 37만9,834호 / 27만2,685호 (−10.1%) / 19만8,373호 (−14.1%) | C6: 2025 연간 | D6: 국토교통부, '25년 12월 주택통계 (2026.1.30): https://www.korea.kr/briefing/pressReleaseView.do?newsId=156742136 , https://www.m-economynews.com/news/article.html?no=64226
A7: 아파트 인허가 (2025) | B7: 34만6,773가구 (2024: 39만7,904) | C7: 2025 연간 | D7: 국토교통부 주택통계 인용 보도: https://www.newsis.com/view/NISX20260129_0003495426
A8: 아파트 입주 물량 | B8: 2025 23만6,263가구 / 2026 예정 18만3,124가구 | C8: 부동산114 REPS | D8: https://v.daum.net/v/GCidIvCEQs
A9: 주택 매매거래 (2025) | B9: 72.6만호 (+13%, 10년 평균 88.5만호) | C9: 2025 연간, 한국부동산원 자료 | D9: KB주택시장리뷰 2026년 2월호: https://kbthink.com/realestate/insights/research/260213-3.html
A10: 국내 리모델링 시장 전망 (건축물 전체, 비주거 포함) | B10: 2025년 37조원 → 2030년 44조원 (리모델링 23.3조 + 유지보수 13.8조, 2025) | C10: 한국건설산업연구원 전망치 | D10: https://m.ekn.kr/view.php?key=523568
A11: 한샘 리하우스 스타일패키지 (전체 리모델링) | B11: 30평대 평당 100만원대 → 약 3,000만원 | C11: 2019 보도 (가격 시점 오래됨) | D11: https://www.dailian.co.kr/news/view/1008108/
A12: 프리미엄 Kitchen 동향 (한샘 키친바흐·빌트인 가전 연계) | B12: 국내 프리미엄 키친 시장 약 90%가 수입·고가 맞춤 / 키친바흐 매출 +17% (2025.6 기준) / 밀레 연계 부엌 매출 +173% (2024 대비) | C12: 회사 발표 인용 보도 | D12: https://www.heraldk.com/article/2025072318143590645 , https://www.heraldk.com/article/2026062223520679105
A13: 한샘 리하우스 부문 매출 | B13: 2025 1Q 1,147억원 (−4.3%) | C13: 분기 실적 | D13: https://newstomato.com/ReadNews.aspx?no=1284742
A14: 신축 유상옵션 비용 비중 | B14: 분양가상한제 단지 7곳 평균 분양가 대비 9.7% | C14: 수도권 분양 단지 보도 | D14: https://www.etoday.co.kr/news/view/2392578
... A35: 가정용 로봇 인증 동향 | B35: 반려로봇 KS 인증 도입 (2026.4, 정부) | C35: 보도 | D35: https://news.mtn.co.kr/news-detail/2026042014042480949
